Workbook

Sheet Inputs
A2: AVESTA — Case Inputs | J2: Selected consumption and bill
A3: Edit the yellow cells. Location is fixed at Cairo. Initial values are the previous El Mo3alem example, not new measurements. | J3: Input status | L3: =IF(OR(C10<=0,COUNT(C10)=0),"Enter billing days",IF(AND(C6<>"Bill only",OR(C7<0,COUNT(C7)=0)),"Enter consumption",IF(AND(C6<>"Consumption only",OR(C8<0,COUNT(C8)=0)),"Enter bill amount",IF(AND(C6="Bill only",C66<>1),"Bill does not give a unique consumption",IF(AND(C14="Specified",OR(C15<=0,COUNT(C15)=0)),"Enter a positive area",IF(AND(C17="Known",OR(C18<0,C18>1,COUNT(C18)=0)),"Check daytime share",IF(AND(C20="Known",OR(C21<=0,COUNT(C21)=0)),"Enter a positive critical load","Ready for indicative calculation"))))))) -> Ready for indicative calculation
J4: Selected monthly use (kWh) | L4: =IF(L3<>"Ready for indicative calculation","Not available",IF(C6="Bill only",SUM(G50:G63),C7)) -> 2421
A5: Case name | C5: El Mo3alem shop — example | J5: Average consumption (kWh/day) | L5: =IF(ISNUMBER(L4),L4/C10,"Not available") -> 80.7
A6: Input mode | C6: Bill and consumption | J6: Active daytime energy share | L6: =IF(C17="Known",C18,'Assumptions and Catalog'!$C$13/24) -> 0.5
A7: Monthly consumption (kWh) | C7: 2421 | E7: Monthly use, not the cumulative meter reading | J7: Reference official bill (EGP) | L7: =IF(ISNUMBER(L4),IF(Inputs!$C$9="Residential",IF(L4<='Assumptions and Catalog'!$C$50,L4*'Assumptions and Catalog'!$H$50+'Assumptions and Catalog'!$E$50+'Assumptions and Catalog'!$F$50,IF(L4<='Assumptions and Catalog'!$C$51,L4*'Assumptions and Catalog'!$H$51+'Assumptions and Catalog'!$E$51+'Assumptions and Catalog'!$F$51,IF(L4<='Assumptions and Catalog'!$C$52,L4*'Assumptions and Catalog'!$H$52+'Assumptions and Catalog'!$E$52+'Assumptions and Catalog'!$F$52,IF(L4<='Assumptions and Catalog'!$C$53,L4*'Assumptions and Catalog'!$H$53+'Assumptions and Catalog'!$E$53+'Assumptions and Catalog'!$F$53,IF(L4<='Assumptions and Catalog'!$C$54,L4*'Assumptions and Catalog'!$H$54+'Assumptions and Catalog'!$E$54+'Assumptions and Catalog'!$F$54,IF(L4<='Assumptions and Catalog'!$C$55,L4*'Assumptions and Catalog'!$H$55+'Assumptions and Catalog'!$E$55+'Assumptions and Catalog'!$F$55,IF(L4<='Assumptions and Catalog'!$C$56,L4*'Assumptions and Catalog'!$H$56+'Assumptions and Catalog'!$E$56+'Assumptions and Catalog'!$F$56,IF(L4<='Assumptions and Catalog'!$C$57,L4*'Assumptions and Catalog'!$H$57+'Assumptions and Catalog'!$E$57+'Assumptions and Catalog'!$F$57,"Out of range")))))))),IF(L4<='Assumptions and Catalog'!$C$60,L4*'Assumptions and Catalog'!$H$60+'Assumptions and Catalog'!$E$60+'Assumptions and Catalog'!$F$60,IF(L4<='Assumptions and Catalog'!$C$61,L4*'Assumptions and Catalog'!$H$61+'Assumptions and Catalog'!$E$61+'Assumptions and Catalog'!$F$61,IF(L4<='Assumptions and Catalog'!$C$62,L4*'Assumptions and Catalog'!$H$62+'Assumptions and Catalog'!$E$62+'Assumptions and Catalog'!$F$62,IF(L4<='Assumptions and Catalog'!$C$63,L4*'Assumptions and Catalog'!$H$63+'Assumptions and Catalog'!$E$63+'Assumptions and Catalog'!$F$63,IF(L4<='Assumptions and Catalog'!$C$64,L4*'Assumptions and Catalog'!$H$64+'Assumptions and Catalog'!$E$64+'Assumptions and Catalog'!$F$64,IF(L4<='Assumptions and Catalog'!$C$65,L4*'Assumptions and Catalog'!$H$65+'Assumptions and Catalog'!$E$65+'Assumptions and Catalog'!$F$65,"Out of range"))))))),"Not available") -> 6867.22
A8: Monthly bill amount (EGP) | C8: 8279 | E8: Consumption bill, not a prepaid top-up | J8: Paid less official bill (EGP) | L8: =IF(AND(C6="Bill and consumption",ISNUMBER(L7)),C8-L7,"Not available") -> 1411.78
A9: Tariff category | C9: Commercial | J9: Active pricing basis | L9: =IF(AND(C6="Bill and consumption",C7>0,C11="Actual flat rate"),"Actual flat rate","Official") -> Official
A10: Billing period days | C10: 30 | J10: Actual average (EGP/kWh) | L10: =IF(AND(C6="Bill and consumption",C7>0),C8/C7,"Not available") -> 3.4196613
A11: Pricing basis | C11: Official | E11: Actual flat rate is available only with both bill amount and consumption | J11: Official average (EGP/kWh) | L11: =IF(AND(ISNUMBER(L4),L4>0),L7/L4,"Not available") -> 2.8365221
J12: Average rate difference (EGP/kWh) | L12: =IF(AND(ISNUMBER(L10),ISNUMBER(L11)),L10-L11,"Not available") -> 0.5831392
J13: Selected baseline bill (EGP) | L13: =IF(ISNUMBER(L4),IF(L9="Actual flat rate",L4*L10,L7),"Not available") -> 6867.22
A14: Available installation area | C14: Unspecified | J14: Reference-data status | L14: ="Reference tariffs and prices: verify before commercial use" -> Reference tariffs and prices: verify before commercial use
A15: Available area (m2) | C15: 50 | E15: Usable installation area after obstacles; unspecified area sets no cap
A17: Energy distribution | C17: Constant load
A18: Daytime energy share | C18: 0.5 | E18: Share of energy, not appliance count; night share is calculated
A20: Critical load | C20: Unknown
A21: Critical load (kW) | C21: 4 | E21: When unknown, no customer-specific backup hours are calculated
A39: Enter the case inputs, review assumptions, then choose equipment and quantities on the Scenarios sheet.
A40: Actual flat rate spreads the paid bill over kWh; it may differ from the marginal cost of avoided electricity.
A41: One representative day/night cycle per month with constant daily load. This is not an hourly simulation.
A47: Inverse-bill calculations — audit detail
A49: Tariff | B49: Above | C49: Up to | D49: Candidate kWh | E49: Candidate bill | F49: Valid solution 1/0 | G49: Accepted kWh
A50: ='Assumptions and Catalog'!$A$50 -> Residential | B50: ='Assumptions and Catalog'!$B$50 -> -1 | C50: ='Assumptions and Catalog'!$C$50 -> 0 | D50: =IF('Assumptions and Catalog'!$H$50=0,0,($C$8-'Assumptions and Catalog'!$E$50-'Assumptions and Catalog'!$F$50)/'Assumptions and Catalog'!$H$50) -> 0 | E50: =D50*'Assumptions and Catalog'!$H$50+'Assumptions and Catalog'!$E$50+'Assumptions and Catalog'!$F$50 -> 9 | F50: =IF(AND(A50=$C$9,D50>B50,D50<=C50,D50>=0,ABS(E50-$C$8)<='Assumptions and Catalog'!$C$25),1,0) -> 0 | G50: =IF(F50=1,D50,0) -> 0
A51: ='Assumptions and Catalog'!$A$51 -> Residential | B51: ='Assumptions and Catalog'!$B$51 -> 0 | C51: ='Assumptions and Catalog'!$C$51 -> 50 | D51: =IF('Assumptions and Catalog'!$H$51=0,0,($C$8-'Assumptions and Catalog'!$E$51-'Assumptions and Catalog'!$F$51)/'Assumptions and Catalog'!$H$51) -> 12173.529 | E51: =D51*'Assumptions and Catalog'!$H$51+'Assumptions and Catalog'!$E$51+'Assumptions and Catalog'!$F$51 -> 8279 | F51: =IF(AND(A51=$C$9,D51>B51,D51<=C51,D51>=0,ABS(E51-$C$8)<='Assumptions and Catalog'!$C$25),1,0) -> 0 | G51: =IF(F51=1,D51,0) -> 0
A52: ='Assumptions and Catalog'!$A$52 -> Residential | B52: ='Assumptions and Catalog'!$B$52 -> 50 | C52: ='Assumptions and Catalog'!$C$52 -> 100 | D52: =IF('Assumptions and Catalog'!$H$52=0,0,($C$8-'Assumptions and Catalog'!$E$52-'Assumptions and Catalog'!$F$52)/'Assumptions and Catalog'!$H$52) -> 9524.7126 | E52: =D52*'Assumptions and Catalog'!$H$52+'Assumptions and Catalog'!$E$52+'Assumptions and Catalog'!$F$52 -> 8279 | F52: =IF(AND(A52=$C$9,D52>B52,D52<=C52,D52>=0,ABS(E52-$C$8)<='Assumptions and Catalog'!$C$25),1,0) -> 0 | G52: =IF(F52=1,D52,0) -> 0
A53: ='Assumptions and Catalog'!$A$53 -> Residential | B53: ='Assumptions and Catalog'!$B$53 -> 100 | C53: ='Assumptions and Catalog'!$C$53 -> 200 | D53: =IF('Assumptions and Catalog'!$H$53=0,0,($C$8-'Assumptions and Catalog'!$E$53-'Assumptions and Catalog'!$F$53)/'Assumptions and Catalog'!$H$53) -> 8273 | E53: =D53*'Assumptions and Catalog'!$H$53+'Assumptions and Catalog'!$E$53+'Assumptions and Catalog'!$F$53 -> 8279 | F53: =IF(AND(A53=$C$9,D53>B53,D53<=C53,D53>=0,ABS(E53-$C$8)<='Assumptions and Catalog'!$C$25),1,0) -> 0 | G53: =IF(F53=1,D53,0) -> 0
A54: ='Assumptions and Catalog'!$A$54 -> Residential | B54: ='Assumptions and Catalog'!$B$54 -> 200 | C54: ='Assumptions and Catalog'!$C$54 -> 350 | D54: =IF('Assumptions and Catalog'!$H$54=0,0,($C$8-'Assumptions and Catalog'!$E$54-'Assumptions and Catalog'!$F$54)/'Assumptions and Catalog'!$H$54) -> 4863.5838 | E54: =D54*'Assumptions and Catalog'!$H$54+'Assumptions and Catalog'!$E$54+'Assumptions and Catalog'!$F$54 -> 8279 | F54: =IF(AND(A54=$C$9,D54>B54,D54<=C54,D54>=0,ABS(E54-$C$8)<='Assumptions and Catalog'!$C$25),1,0) -> 0 | G54: =IF(F54=1,D54,0) -> 0
A55: ='Assumptions and Catalog'!$A$55 -> Residential | B55: ='Assumptions and Catalog'!$B$55 -> 350 | C55: ='Assumptions and Catalog'!$C$55 -> 650 | D55: =IF('Assumptions and Catalog'!$H$55=0,0,($C$8-'Assumptions and Catalog'!$E$55-'Assumptions and Catalog'!$F$55)/'Assumptions and Catalog'!$H$55) -> 3930.0459 | E55: =D55*'Assumptions and Catalog'!$H$55+'Assumptions and Catalog'!$E$55+'Assumptions and Catalog'!$F$55 -> 8279 | F55: =IF(AND(A55=$C$9,D55>B55,D55<=C55,D55>=0,ABS(E55-$C$8)<='Assumptions and Catalog'!$C$25),1,0) -> 0 | G55: =IF(F55=1,D55,0) -> 0
A56: ='Assumptions and Catalog'!$A$56 -> Residential | B56: ='Assumptions and Catalog'!$B$56 -> 650 | C56: ='Assumptions and Catalog'!$C$56 -> 1000 | D56: =IF('Assumptions and Catalog'!$H$56=0,0,($C$8-'Assumptions and Catalog'!$E$56-'Assumptions and Catalog'!$F$56)/'Assumptions and Catalog'!$H$56) -> 3512.3404 | E56: =D56*'Assumptions and Catalog'!$H$56+'Assumptions and Catalog'!$E$56+'Assumptions and Catalog'!$F$56 -> 8279 | F56: =IF(AND(A56=$C$9,D56>B56,D56<=C56,D56>=0,ABS(E56-$C$8)<='Assumptions and Catalog'!$C$25),1,0) -> 0 | G56: =IF(F56=1,D56,0) -> 0
A57: ='Assumptions and Catalog'!$A$57 -> Residential | B57: ='Assumptions and Catalog'!$B$57 -> 1000 | C57: ='Assumptions and Catalog'!$C$57 -> 10000000 | D57: =IF('Assumptions and Catalog'!$H$57=0,0,($C$8-'Assumptions and Catalog'!$E$57-'Assumptions and Catalog'!$F$57)/'Assumptions and Catalog'!$H$57) -> 2850.8651 | E57: =D57*'Assumptions and Catalog'!$H$57+'Assumptions and Catalog'!$E$57+'Assumptions and Catalog'!$F$57 -> 8279 | F57: =IF(AND(A57=$C$9,D57>B57,D57<=C57,D57>=0,ABS(E57-$C$8)<='Assumptions and Catalog'!$C$25),1,0) -> 0 | G57: =IF(F57=1,D57,0) -> 0
A58: ='Assumptions and Catalog'!$A$60 -> Commercial | B58: ='Assumptions and Catalog'!$B$60 -> -1 | C58: ='Assumptions and Catalog'!$C$60 -> 0 | D58: =IF('Assumptions and Catalog'!$H$60=0,0,($C$8-'Assumptions and Catalog'!$E$60-'Assumptions and Catalog'!$F$60)/'Assumptions and Catalog'!$H$60) -> 0 | E58: =D58*'Assumptions and Catalog'!$H$60+'Assumptions and Catalog'!$E$60+'Assumptions and Catalog'!$F$60 -> 9 | F58: =IF(AND(A58=$C$9,D58>B58,D58<=C58,D58>=0,ABS(E58-$C$8)<='Assumptions and Catalog'!$C$25),1,0) -> 0 | G58: =IF(F58=1,D58,0) -> 0
A59: ='Assumptions and Catalog'!$A$61 -> Commercial | B59: ='Assumptions and Catalog'!$B$61 -> 0 | C59: ='Assumptions and Catalog'!$C$61 -> 100 | D59: =IF('Assumptions and Catalog'!$H$61=0,0,($C$8-'Assumptions and Catalog'!$E$61-'Assumptions and Catalog'!$F$61)/'Assumptions and Catalog'!$H$61) -> 5014.5455 | E59: =D59*'Assumptions and Catalog'!$H$61+'Assumptions and Catalog'!$E$61+'Assumptions and Catalog'!$F$61 -> 8279 | F59: =IF(AND(A59=$C$9,D59>B59,D59<=C59,D59>=0,ABS(E59-$C$8)<='Assumptions and Catalog'!$C$25),1,0) -> 0 | G59: =IF(F59=1,D59,0) -> 0
A60: ='Assumptions and Catalog'!$A$62 -> Commercial | B60: ='Assumptions and Catalog'!$B$62 -> 100 | C60: ='Assumptions and Catalog'!$C$62 -> 250 | D60: =IF('Assumptions and Catalog'!$H$62=0,0,($C$8-'Assumptions and Catalog'!$E$62-'Assumptions and Catalog'!$F$62)/'Assumptions and Catalog'!$H$62) -> 3773.516 | E60: =D60*'Assumptions and Catalog'!$H$62+'Assumptions and Catalog'!$E$62+'Assumptions and Catalog'!$F$62 -> 8279 | F60: =IF(AND(A60=$C$9,D60>B60,D60<=C60,D60>=0,ABS(E60-$C$8)<='Assumptions and Catalog'!$C$25),1,0) -> 0 | G60: =IF(F60=1,D60,0) -> 0
A61: ='Assumptions and Catalog'!$A$63 -> Commercial | B61: ='Assumptions and Catalog'!$B$63 -> 250 | C61: ='Assumptions and Catalog'!$C$63 -> 600 | D61: =IF('Assumptions and Catalog'!$H$63=0,0,($C$8-'Assumptions and Catalog'!$E$63-'Assumptions and Catalog'!$F$63)/'Assumptions and Catalog'!$H$63) -> 3093.2584 | E61: =D61*'Assumptions and Catalog'!$H$63+'Assumptions and Catalog'!$E$63+'Assumptions and Catalog'!$F$63 -> 8279 | F61: =IF(AND(A61=$C$9,D61>B61,D61<=C61,D61>=0,ABS(E61-$C$8)<='Assumptions and Catalog'!$C$25),1,0) -> 0 | G61: =IF(F61=1,D61,0) -> 0
A62: ='Assumptions and Catalog'!$A$64 -> Commercial | B62: ='Assumptions and Catalog'!$B$64 -> 600 | C62: ='Assumptions and Catalog'!$C$64 -> 1000 | D62: =IF('Assumptions and Catalog'!$H$64=0,0,($C$8-'Assumptions and Catalog'!$E$64-'Assumptions and Catalog'!$F$64)/'Assumptions and Catalog'!$H$64) -> 3001.444 | E62: =D62*'Assumptions and Catalog'!$H$64+'Assumptions and Catalog'!$E$64+'Assumptions and Catalog'!$F$64 -> 8279 | F62: =IF(AND(A62=$C$9,D62>B62,D62<=C62,D62>=0,ABS(E62-$C$8)<='Assumptions and Catalog'!$C$25),1,0) -> 0 | G62: =IF(F62=1,D62,0) -> 0
A63: ='Assumptions and Catalog'!$A$65 -> Commercial | B63: ='Assumptions and Catalog'!$B$65 -> 1000 | C63: ='Assumptions and Catalog'!$C$65 -> 10000000 | D63: =IF('Assumptions and Catalog'!$H$65=0,0,($C$8-'Assumptions and Catalog'!$E$65-'Assumptions and Catalog'!$F$65)/'Assumptions and Catalog'!$H$65) -> 2921.6312 | E63: =D63*'Assumptions and Catalog'!$H$65+'Assumptions and Catalog'!$E$65+'Assumptions and Catalog'!$F$65 -> 8279 | F63: =IF(AND(A63=$C$9,D63>B63,D63<=C63,D63>=0,ABS(E63-$C$8)<='Assumptions and Catalog'!$C$25),1,0) -> 1 | G63: =IF(F63=1,D63,0) -> 2921.6312
A66: Accepted solution count | C66: =SUM(F50:F63) -> 1

Sheet Assumptions and Catalog
A2: AVESTA — Assumptions and Catalog
A3: Yellow cells are editable. Equipment prices and limits are illustrative, not supplier quotes or manufacturer specifications.
A6: Study period | B6: years | C6: 10 | D6: 1 to 20
A7: Nominal discount rate | B7: % | C7: 0.1 | D7: Illustrative assumption; approval needed
A8: Tariff and fee escalation | B8: % per year | C8: 0 | D8: Flat by default; applies to all bill components
A9: Maintenance cost escalation | B9: % per year | C9: 0 | D9: Assumed cost escalation
A10: Annual PV degradation | B10: % per year | C10: 0.005 | D10: Assumption
A11: Charge efficiency | B11: % | C11: 0.975 | D11: AC input to stored energy
A12: Discharge efficiency | B12: % | C12: 0.975 | D12: Stored energy to AC load
A13: Daytime duration | B13: hours/day | C13: 12 | D13: Not PSH; used only to split daily load
A14: PV charging window | B14: hours/day | C14: 6 | D14: Approximate power window, not hourly simulation
A15: Grid charging window | B15: hours/day | C15: 8 | D15: Battery-only scenario
A16: Installation area multiplier | B16: times panel area | C16: 1.5 | D16: Includes assumed installation clearances
A17: Installation and BOS | B17: % of equipment | C17: 0.1 | D17: Applied once to PV, battery and inverter
... A26: Battery auxiliary consumption | B26: kWh/day | C26: 0 | D26: Not estimated; enter standby consumption
A29: Cairo seasonal solar production - experimental
A31: Annual-average PV yield (derived) | B31: kWh/kWp/day | C31: ='Solar Production'!D32 -> 4.9818356 | D31: Derived summary only. Monthly calculations use Solar Production.
A33: Monthly yield from Solar Production replaces the fixed daily average in this trial.
A34: Edit tilt and compass azimuth on Solar Production. PVGIS losses are already included.
A35: Source: JRC PVGIS 5.3 / SARAH3, 2005-2023; retrieved 26 October 2026.
A36: https://re.jrc.ec.europa.eu/pvg_tools/en/
A46: Editable reference tariff bands
A47: Tariffs from prior project files; current applicability could not be confirmed from the regulator link. Verify before commercial use.
A49: Type | B49: Above kWh | C49: Up to kWh | D49: Energy rate | E49: Energy intercept | F49: Service fee (EGP) | G49: Stamp/kWh | H49: Marginal rate incl. stamp
A50: Residential | B50: -1 | C50: 0 | D50: 0 | E50: 0 | F50: 9 | G50: 0 | H50: =D50+G50 -> 0
A51: Residential | B51: 0 | C51: 50 | D51: 0.68 | E51: 0 | F51: 1 | G51: 0 | H51: =D51+G51 -> 0.68
A52: Residential | B52: 50 | C52: 100 | D52: 0.87 | E52: =C51*D51-C51*D52 -> -9.5 | F52: 2 | G52: 0 | H52: =D52+G52 -> 0.87
A53: Residential | B53: 100 | C53: 200 | D53: 1 | E53: 0 | F53: 6 | G53: 0 | H53: =D53+G53 -> 1
A54: Residential | B54: 200 | C54: 350 | D54: 1.73 | E54: =C53*D53-C53*D54 -> -146 | F54: 11 | G54: 0 | H54: =D54+G54 -> 1.73
A55: Residential | B55: 350 | C55: 650 | D55: 2.18 | E55: =C54*D54+E54-C54*D55 -> -303.5 | F55: 15 | G55: 0 | H55: =D55+G55 -> 2.18
A56: Residential | B56: 650 | C56: 1000 | D56: 2.35 | E56: 0 | F56: 25 | G56: 0 | H56: =D56+G56 -> 2.35
A57: Residential | B57: 1000 | C57: 10000000 | D57: 2.89 | E57: 0 | F57: 40 | G57: 0 | H57: =D57+G57 -> 2.89
A60: Commercial | B60: -1 | C60: 0 | D60: 0 | E60: 0 | F60: 9 | G60: 0 | H60: =D60+G60 -> 0
A61: Commercial | B61: 0 | C61: 100 | D61: 1.62 | E61: 0 | F61: 5 | G61: 0.03 | H61: =D61+G61 -> 1.65
A62: Commercial | B62: 100 | C62: 250 | D62: 2.16 | E62: 0 | F62: 15 | G62: 0.03 | H62: =D62+G62 -> 2.19
A63: Commercial | B63: 250 | C63: 600 | D63: 2.64 | E63: 0 | F63: 20 | G63: 0.03 | H63: =D63+G63 -> 2.67
A64: Commercial | B64: 600 | C64: 1000 | D64: 2.74 | E64: =C63*D63-C63*D64 -> -60 | F64: 25 | G64: 0.03 | H64: =D64+G64 -> 2.77
A65: Commercial | B65: 1000 | C65: 10000000 | D65: 2.79 | E65: 0 | F65: 40 | G65: 0.03 | H65: =D65+G65 -> 2.82
A67: Residential rates: prior project model; service fees require confirmation. Commercial: prior El Mo3alem presentation (April 2026).
A68: https://www.egyptera.org/ar/TarrifApril2026.aspx — verification on 19 October 2026 returned 404. Annual stamp excluded.
A71: Example panels — replace with supplier specifications
A72: ID | B72: Name | C72: Wp | D72: Panel area (m2) | E72: Panel price (EGP)
A73: PV550 | B73: Example panel 550 | C73: 550 | D73: 2.6 | E73: 4400
A74: PV670 | B74: Example panel 670 | C74: 670 | D74: 2.7 | E74: 5360
A77: Example batteries — confirm real compatibility
A78: ID | B78: Description | C78: Nominal kWh | D78: Usable fraction | E78: Charge kW | F78: Discharge kW | G78: Price (EGP) | H78: Compatibility group
A79: BAT10 | B79: Example battery 10 | C79: 10 | D79: 0.8 | E79: 5 | F79: 5 | G79: 136400 | H79: LV
A80: BAT16 | B80: Example battery 16 | C80: 16 | D80: 0.8 | E80: 8 | F80: 8 | G80: 218240 | H80: LV
A81: BAT32 | B81: Example battery 32 | C81: 32 | D81: 0.8 | E81: 10 | F81: 10 | G81: 436480 | H81: LV
A84: Example inverters — not product recommendations
A85: ID | B85: Description | C85: AC kW | D85: PV limit kWp | E85: Charge kW | F85: Backup 1/0 | G85: Price (EGP) | H85: Compatibility group | I85: Phases
A86: GRID10 | B86: Grid-tied solar 10 | C86: 10 | D86: 13 | E86: 0 | F86: 0 | G86: 60000 | H86: NONE | I86: 3
A87: HYB5 | B87: Hybrid 5 | C87: 5 | D87: 6.5 | E87: 5 | F87: 1 | G87: 30000 | H87: LV | I87: 1
A88: HYB12 | B88: Hybrid 12 | C88: 12 | D88: 15.6 | E88: 10 | F88: 1 | G88: 72000 | H88: LV | I88: 3
A89: HYB20 | B89: Hybrid 20 | C89: 20 | D89: 26 | E89: 15 | F89: 1 | G89: 120000 | H89: LV | I89: 3
A92: Example prices from the prior presentation: PV 8,000 EGP/kWp, battery 13,640 EGP/kWh, inverter 6,000 EGP/kW.
A93: Power, area and compatibility limits are illustrative. They are not certified AVESTA specifications and exclude load starting currents.
A100: Formula reference
A101: Each distinct calculation is explained once. Repeated monthly and scenario formulas use the same rule. Cell references point to the working formulas.
A103: Calculation | B103: Equation / rule | D103: Parameters and units | G103: Purpose and workbook location
A104: 1. Consumption and tariff
A105: Input validity | B105: Ready only when the selected inputs are numeric and within their permitted ranges. | D105: Days > 0. Consumption and bill >= 0 when required. Specified roof and known critical load > 0. Day share is 0 to 1. Bill-only requires exactly one valid solution. | G105: Stops unavailable or ambiguous inputs from being treated as a valid case. Inputs!C25.
A106: Tariff marginal rate | B106: m = energy rate + stamp rate | D106: m: EGP/kWh. Energy rate: column D. Stamp rate: column G in the tariff table. | G106: Combines variable charges for the selected band. Assumptions and Catalog!H50:H65.
A107: Tariff band intercept | B107: b = previous upper limit × previous rate + previous intercept - previous upper limit × new rate | D107: b: fixed energy adjustment in EGP. Used only for the continuous bands. Other bands use their entered intercept, including full-consumption resets. | G107: Preserves the specific tariff's band rules. Assumptions and Catalog!E52, E54:E55 and E64.
A108: Official monthly bill | B108: T(E) = E × m + b + fee, using the first band whose upper limit contains E | D108: E: monthly kWh. m: marginal EGP/kWh. b: energy intercept, EGP. fee: service charge, EGP. Tariff type selects the residential or commercial table. | G108: Computes the actual piecewise bill instead of multiplying all consumption by an average price. Inputs!C29 and Scenarios!M:N monthly blocks.
A109: Inverse bill candidate | B109: E_candidate = (Paid - b - fee) / m; use 0 when m = 0 | D109: Paid, b and fee: EGP. m: EGP/kWh. Each tariff band is tested separately. The zero-rate band's candidate still has to pass the bill check. | G109: Estimates monthly consumption when only the bill is known. Inputs!D50:D63.
A110: Inverse bill validation | B110: Valid = 1 if type matches, lower < E_candidate <= upper, E_candidate >= 0 and ABS(candidate bill - Paid) <= tolerance; otherwise 0 | D110: Candidate bill = E_candidate × m + b + fee. Tolerance: Assumptions and Catalog!C25, EGP. Bounds and tariff type come from the selected band. | G110: Rejects candidates that do not belong to the band or do not reproduce the bill. Inputs!E50:F63.
A111: Accepted consumption | B111: Solution count = SUM(valid flags). E_month = SUM(valid candidates) only if count = 1; otherwise use entered kWh when that input mode applies | D111: Valid candidates: candidate kWh where flag = 1, else 0. Invalid inputs return an unavailable message. | G111: Avoids silently selecting a solution when bill inversion is ambiguous. Inputs!G50:G63, C66 and C26.
A112: Daily consumption | B112: E_day = E_month / period days | D112: E_month: accepted monthly kWh. Period days: Inputs!C10. E_day: kWh/day. | G112: Normalizes the entered billing period to a constant daily load used throughout the forecast. Inputs!C27.
A113: Day and night split | B113: Day share = entered share if known, else daylight hours / 24. Day load = E_day × day share. Night load = E_day - day load | D113: Day and night loads: kWh/day. Daylight hours: Assumptions and Catalog!C13. Share is a fraction of energy, not appliance count. | G113: Separates direct solar demand from demand that may use stored energy. Inputs!C28; Scenarios!D:E monthly blocks.
A114: Actual and official average prices | B114: p_actual = Paid / E_month; p_official = T(E_month) / E_month; price gap = p_actual - p_official | D114: Prices: EGP/kWh. Actual price requires both bill and positive consumption. Official average also requires positive consumption. | G114: Shows the difference between the paid average and the tariff-based average. Inputs!C32:C34.
A115: Bill difference | B115: Bill gap = Paid - T(E_month) | D115: Paid and official bill: EGP for the entered month. Available only when both bill and consumption were supplied. | G115: Shows how much more or less was paid than the reference tariff calculation. Inputs!C30.
A116: Selected pricing basis | B116: B(E) = E × p_actual in Actual flat mode; otherwise B(E) = T(E) | D116: Actual flat mode is accepted only with both bill and positive consumption. B(E): EGP for any monthly import E. | G116: Uses the chosen price basis consistently for baseline and post-installation bills. Inputs!C31, C35; Scenarios!M, N and Q monthly blocks. A paid average is not necessarily an avoidable marginal price.
A117: 2. Equipment, area and initial investment
A118: Catalog lookup | B118: Specification = INDEX(catalog data, MATCH(selected model ID, catalog IDs, 0), specification column) | D118: Model IDs: Scenarios!C39:E43. Catalogs: Assumptions and Catalog rows 73:74, 79:81 and 86:89. | G118: Retrieves the chosen equipment's capacity, power, area, price and compatibility. Used throughout Scenarios!C51:E70.
A119: Installed PV capacity | B119: P_PV = panel count × panel Wp / 1000 | D119: P_PV: kWp. Panel rating: Wp. Battery-only sets PV capacity to zero. | G119: Determines solar generation and checks the inverter PV limit. Scenarios!C51:E51; summary row 7.
A120: Battery nominal and usable capacity | B120: C_nom = battery count × unit kWh. C_usable = C_nom × usable fraction | D120: Capacities: kWh stored internally. Usable fraction: catalog value from 0 to 1. Solar-only sets nominal battery capacity to zero. | G120: Distinguishes purchased capacity from usable storage before reserve and losses. Scenarios!C52:E52 and C55:E55; summary row 8.
A121: Inverter ratings and support | B121: P_inv, PV_limit and backup flag = selected inverter catalog values | D121: P_inv: AC kW. PV_limit: allowed PV kWp. Backup flag: 1 supported, 0 unsupported; solar-only forces 0. | G121: Supplies the inverter limits and backup eligibility. Scenarios!C53:E54 and C58:E58; summary row 9.
A122: Charge and discharge power limits | B122: P_ch = MIN(count × battery charge kW, inverter charge kW). P_dis = MIN(count × battery discharge kW, inverter AC kW) | D122: P_ch and P_dis: kW at the model's AC boundary. Battery count and ratings come from the selected configuration. | G122: Limits charging, discharge and backup by both battery and inverter ratings. Scenarios!C56:E57.
A123: Installation area | B123: Area = (P_PV × 1000 / panel Wp) × panel area × spacing factor | D123: Area and panel area: m2. Spacing factor: Assumptions and Catalog!C16. Parenthesis recovers the active panel count. | G123: Checks whether the chosen array fits a specified roof. An unspecified roof does not constrain sizing. Scenarios!C59:E59; summary row 10.
A124: Equipment costs | B124: PV cost = active panel count × panel price. Battery cost = active battery count × battery price. Inverter cost = catalog inverter price | D124: Costs: EGP. Active counts are recovered from installed capacities, so inactive scenario equipment is excluded. | G124: Builds the equipment subtotal from the selected models and quantities. Scenarios!C60:E62.
A125: BOS and initial investment | B125: BOS = (PV cost + battery cost + inverter cost) × BOS rate. CAPEX = equipment subtotal + BOS | D125: BOS: installation and balance of system cost, EGP. BOS rate: Assumptions and Catalog!C17. CAPEX: upfront EGP. | G125: Calculates the year-zero investment without adding installation twice. Scenarios!C63:E64; summary row 11.
A126: Battery compatibility | B126: Compatible if nominal battery capacity = 0 OR battery group = inverter group | D126: Compatibility group: catalog text, such as LV. This is a catalog-group check, not a complete electrical design check. | G126: Flags incompatible selections before interpreting the results. Scenarios!C66:E66.
A127: Configuration validity | B127: Valid = 1 when inputs are ready, PV <= inverter PV limit, specified roof fits, compatibility passes, counts are nonnegative integers, reserve is 0 to 1, efficiencies are > 0 and <= 1, and study years are 1 to 20 | D127: Limits and flags come from the input, assumptions and sizing cells. All conditions must pass. | G127: Gates reported financial results and backup runtime. Scenarios!C65:E65 and C6:E6.
A128: Roof status | B128: Unspecified roof: fit not verified. Specified roof: compare required area <= available area | D128: Both areas: m2. Available area: Inputs!C15, used only when Inputs!C14 is Specified. | G128: Separates an unconstrained estimate from a layout that fits the supplied area. Scenarios!C26:E26.
A129: Year-one maintenance | B129: OM_1 = CAPEX × annual maintenance rate | D129: OM_1: EGP/year. Maintenance rate: Assumptions and Catalog!C18. | G129: Provides the recurring operating-cost base used in annual net savings. Scenarios!C70:E70.
A130: 3. Monthly solar and battery energy
A131: Monthly calculation scope | B131: Solar-only: rows 161:400. Battery-only: rows 411:650. Solar + battery: rows 661:900. Each block has 12 months × 20 years. | D131: Unless stated otherwise, references below are in Scenarios. y is study year starting at 1. n is calendar days in the month. Monthly energy is kWh. | G131: Explains repeated formulas once. The study horizon controls financial inclusion; monthly physical calculations remain available for all 20 years.
A132: Calendar month length | B132: n = DAY(DATE(first forecast year + y - 1, month + 1, 0)) | D132: First forecast year: Assumptions and Catalog!C24. Month: 1 to 12. n includes leap years. | G132: Converts constant daily energy into the correct monthly quantity. Scenarios monthly column C.
A133: Solar generation | B133: E_PV = P_PV × Y_daily × n × (1 - d_PV)^(y - 1) | D133: P_PV: installed kWp. Y_daily: Assumptions and Catalog!C31, kWh/kWp/day. d_PV: annual PV degradation at C10. | G133: Monthly Cairo yield uses Solar Production with annual degradation. PVGIS losses are included. Inverter-specific hourly clipping is not modeled.
A134: Direct solar use | B134: E_direct = MIN(E_PV, day load × n) | D134: E_PV: monthly solar generation. Day load: kWh/day from the consumption split. | G134: Limits directly consumed solar to estimated daytime energy demand. Scenarios monthly column G. This is an aggregate energy estimate.
A135: Battery age | B135: Age = y - replacement year if replacement year > 0 and y >= replacement year; otherwise Age = y - 1 | D135: Age: years. Battery replacement year: Assumptions and Catalog!C19. A replacement resets age to zero once. | G135: Resets capacity degradation in the replacement year. Scenarios monthly column R. The annual model applies fresh capacity for that year and books replacement cost at year-end.
A136: Capacity available for cycling | B136: C_cycle = C_usable × (1 - reserve fraction) × (1 - d_batt)^Age | D136: C_cycle: stored kWh per modeled daily cycle. Reserve: Scenarios row 44. d_batt: Assumptions and Catalog!C23. | G136: Excludes reserved energy and accounts for battery capacity degradation. Scenarios monthly column P.
A137: Combined system battery delivery | B137: E_dis = MIN(night load × n, C_cycle × eta_dis × n, (E_PV - E_direct) × eta_ch × eta_dis, P_ch × h_PV × eta_ch × eta_dis × n, P_dis × (24 - h_day) × n) | D137: E_dis: AC kWh/month. eta_ch / eta_dis: C11 / C12. h_PV: PV charge window C14, hours/day. h_day: daylight hours C13. P_ch / P_dis: kW. C_cycle: stored kWh. | G137: Uses the smallest of night demand, usable storage, solar surplus, charging-power and discharging-power limits. Scenarios!I661:I900.
A138: Battery-only grid-cycle delivery | B138: E_dis = n × MIN(daily target, E_day, C_cycle × eta_dis, P_dis × (24 - h_grid), P_ch × h_grid × eta_ch × eta_dis) in Grid cycle mode; otherwise 0 | D138: Daily target: Scenarios!D46, AC kWh/day. h_grid: Assumptions and Catalog!C15, hours/day. Other symbols are defined above. | G138: Limits grid-charged battery cycling. Backup mode does not perform a daily cycle. Solar-only delivery is always 0. Scenarios!I411:I650 and I161:I400.
A139: Charging energy | B139: E_charge = E_dis / (eta_ch × eta_dis) | D139: E_charge: AC kWh/month required to deliver E_dis. eta_ch and eta_dis: charging and discharging efficiencies. | G139: Includes both losses and charges only enough to support modeled discharge. Scenarios monthly column H.
A140: Unused solar | B140: E_surplus = MAX(E_PV - E_direct - E_charge, 0) for solar scenarios; battery-only excludes grid charging from this subtraction | D140: All energies: kWh/month. E_charge is solar charging only for the combined system. | G140: Identifies solar energy not used onsite. It earns no export income in this model. Scenarios monthly column J.
A141: Battery conversion losses | B141: E_loss = E_charge - E_dis | D141: E_loss: kWh/month. Charge and discharge are measured at the AC boundaries. | G141: Quantifies energy lost in storage conversion. Scenarios monthly column K.
A142: Auxiliary energy | B142: E_aux = auxiliary kWh/day × n when a battery is installed; otherwise 0 | D142: Auxiliary consumption: Assumptions and Catalog!C26. Solar-only always uses 0. | G142: Adds battery standby/auxiliary energy to grid demand. Embedded in monthly columns L and S.
... A148: Year-one energy and bill summaries | B148: PV generation = SUM(first 12 monthly PV values). Baseline bill, system bill and bill savings = their respective first-year monthly sums | D148: Energy: kWh/year. Bills: EGP/year. Baseline is shared because all scenarios serve the same load. | G148: Presents comparable first-year totals. Scenarios!C12:E15. System bill and savings are gated by configuration validity.
...

Sheet Scenarios
A2: AVESTA — Scenario Comparison | W2: El Mo3alem - eight source scenarios | AH2: Shared assumptions and reproduction notes
A3: Three manually selected configurations. Financial results are indicative; no automatic size optimization. | W3: STATIC SNAPSHOTS - captured 22 Oct 2026. These results do not update automatically. Re-run and verify each scenario after changing any recorded input or assumption.
W4: Scenario | Y4: Scenario 1 | Z4: Scenario 2 | AA4: Scenario 3 | AB4: Scenario 4 | AC4: Scenario 5 | AD4: Scenario 6 | AE4: Scenario 7 | AF4: Scenario 8 | AH4: Capture date | AK4: 2026-10-22
A5: Metric | B5: Unit | C5: Solar only | D5: Battery only | E5: Solar and battery | W5: Source design | Y5: 25 kW solar only | Z5: 10 kWh battery | AA5: 10 m2 + 10 kWh | AB5: 25 m2 + 10 kWh | AC5: 50 m2 + 20 kWh | AD5: 10 m2 + 30 kWh | AE5: 50 m2 + 50 kWh | AF5: 10 m2 + 50 kWh | AH5: Recalculation engine | AK5: LibreOffice; every case recalculated before capture
A6: Configuration status | C6: =IF(COUNTIFS(C926:C980,"ERROR:*")>0,"ERROR - see C926:C980",IF(COUNTIFS(C926:C980,"WARNING:*")>0,"Valid with warnings - see checks","Valid for indicative calculation")) -> Valid with warnings - see checks | D6: =IF(COUNTIFS(G926:G980,"ERROR:*")>0,"ERROR - see G926:G980",IF(COUNTIFS(G926:G980,"WARNING:*")>0,"Valid with warnings - see checks","Valid for indicative calculation")) -> Valid with warnings - see checks | E6: =IF(COUNTIFS(K926:K980,"ERROR:*")>0,"ERROR - see K926:K980",IF(COUNTIFS(K926:K980,"WARNING:*")>0,"Valid with warnings - see checks","Valid for indicative calculation")) -> Valid with warnings - see checks | W6: Model column | Y6: Solar only | Z6: Battery only | AA6: Solar and battery | AB6: Solar and battery | AC6: Solar and battery | AD6: Solar and battery | AE6: Solar and battery | AF6: Solar and battery | AH6: Consumption source | AK6: Verified receipt: 2,421 kWh and EGP 8,279. August 2026.
A7: PV capacity | B7: kWp | C7: =C51 -> 8.8 | D7: =D51 -> 0 | E7: =E51 -> 11 | H7: Equipment and quantities — edit yellow cells | W7: Implemented scope | Y7: PV self-use; no export | Z7: Backup only | AA7: PV self-use + backup | AB7: PV self-use + backup | AC7: PV self-use + backup | AD7: Partial: PV + backup | AE7: Partial: PV + backup | AF7: Partial: PV + backup | AH7: Billing interval | AK7: 30-day planning assumption; actual interval unconfirmed
A8: Nominal battery capacity | B8: kWh | C8: =C52 -> 0 | D8: =D52 -> 16 | E8: =E52 -> 16 | H8: Setting | I8: Unit | J8: Solar only | K8: Battery only | L8: Solar and battery | W8: Design status | Y8: Roof / hardware unverified | Z8: Backup overload (3 < 4 kW) | AA8: Roof conflict | AB8: Roof conflict | AC8: Roof conflict | AD8: Roof conflict; scope incomplete | AE8: Roof conflict; scope incomplete | AF8: Roof conflict; scope incomplete | AH8: Forecast calendar start | AK8: 2027
A9: Inverter capacity | B9: kW | C9: =C53 -> 10 | D9: =D53 -> 5 | E9: =E53 -> 12 | H9: Panel model | J9: PV550 | K9: PV550 | L9: PV550 | W9: Manager document location | Y9: PART 3 / SCENARIO 1 | Z9: PART 3 / SCENARIO 2 | AA9: PART 3 / SCENARIO 3 | AB9: PART 3 / SCENARIO 4 | AC9: PART 3 / SCENARIO 5 | AD9: PART 3 / SCENARIO 6 | AE9: PART 3 / SCENARIO 7 | AF9: PART 3 / SCENARIO 8 | AH9: Study period (years) | AK9: 10
A10: Required roof area | B10: m² | C10: =C59 -> 62.4 | D10: =D59 -> 0 | E10: =E59 -> 78 | H10: Panel quantity | J10: 16 | K10: 0 | L10: 20 | W10: Recorded inputs and equipment | AH10: Discount rate | AK10: 0.1
A11: Initial investment | B11: EGP | C11: =C64 -> 143440 | D11: =D64 -> 273064 | E11: =E64 -> 416064 | H11: Battery model | J11: BAT16 | K11: BAT16 | L11: BAT16 | W11: Input mode | Y11: Bill and consumption | Z11: Bill and consumption | AA11: Bill and consumption | AB11: Bill and consumption | AC11: Bill and consumption | AD11: Bill and consumption | AE11: Bill and consumption | AF11: Bill and consumption | AH11: Tariff escalation | AK11: 0
A12: Year 1 solar generation | B12: kWh | C12: =SUM(F161:F172) -> 16001.656 | D12: =SUM(F411:F422) -> 0 | E12: =SUM(F661:F672) -> 20002.07 | H12: Battery unit quantity | J12: 0 | K12: 1 | L12: 1 | W12: Measured monthly consumption | X12: kWh | Y12: 2421 | Z12: 2421 | AA12: 2421 | AB12: 2421 | AC12: 2421 | AD12: 2421 | AE12: 2421 | AF12: 2421 | AH12: Cost escalation | AK12: 0
A13: Year 1 baseline bill | B13: EGP | C13: =$B$79 -> 83544.51 | D13: =$B$79 -> 83544.51 | E13: =$B$79 -> 83544.51 | H13: Inverter model | J13: GRID10 | K13: HYB5 | L13: HYB12 | W13: Recorded monthly payment | X13: EGP | Y13: 8279 | Z13: 8279 | AA13: 8279 | AB13: 8279 | AC13: 8279 | AD13: 8279 | AE13: 8279 | AF13: 8279 | AH13: PV degradation per year | AK13: 0.005
A14: Year 1 bill after installation | B14: EGP | C14: =IF(C65=1,SUM(N161:N172),"Invalid") -> 42587.264 | D14: =IF(D65=1,SUM(N411:N422),"Invalid") -> 83544.51 | E14: =IF(E65=1,SUM(N661:N672),"Invalid") -> 31310.42 | H14: Reserved share of usable capacity | I14: % | J14: 0.2 | K14: 1 | L14: 0.2 | W14: Billing period (planning assumption) | X14: days | Y14: 30 | Z14: 30 | AA14: 30 | AB14: 30 | AC14: 30 | AD14: 30 | AE14: 30 | AF14: 30 | AH14: Charge efficiency | AK14: 0.975
A15: Year 1 bill savings | B15: EGP | C15: =IF(C65=1,SUM(O161:O172),"Invalid") -> 40957.246 | D15: =IF(D65=1,SUM(O411:O422),"Invalid") -> 0 | E15: =IF(E65=1,SUM(O661:O672),"Invalid") -> 52234.09 | H15: Battery-only operating mode | J15: Backup | K15: Backup | L15: Backup | W15: Tariff type | Y15: Commercial | Z15: Commercial | AA15: Commercial | AB15: Commercial | AC15: Commercial | AD15: Commercial | AE15: Commercial | AF15: Commercial | AH15: Discharge efficiency | AK15: 0.975
A16: Year 1 savings after maintenance | B16: EGP | C16: =IF(C65=1,C79,"Invalid") -> 39522.846 | D16: =IF(D65=1,G79,"Invalid") -> -2730.64 | E16: =IF(E65=1,K79,"Invalid") -> 48073.45 | H16: Grid-charged delivery limit | I16: kWh/day | J16: 8 | K16: 8 | L16: 8 | W16: Pricing basis | Y16: Official reference tariff | Z16: Official reference tariff | AA16: Official reference tariff | AB16: Official reference tariff | AC16: Official reference tariff | AD16: Official reference tariff | AE16: Official reference tariff | AF16: Official reference tariff | AH16: Combined round-trip efficiency | AK16: 0.950625
A17: NPV over study period | B17: EGP | C17: =IF(C65=1,SUM(D78:D98),"Invalid") -> 98257.868 | D17: =IF(D65=1,SUM(H78:H98),"Invalid") -> -289842.6 | E17: =IF(E65=1,SUM(L78:L98),"Invalid") -> -125124.27 | W17: Load distribution mode | Y17: Constant load | Z17: Constant load | AA17: Constant load | AB17: Constant load | AC17: Constant load | AD17: Constant load | AE17: Constant load | AF17: Constant load | AH17: Daylight hours | AK17: 12
A18: Simple payback | B18: years | C18: =IF(C65=0,"Invalid",IF(MIN(P79:P98)=999,"Not reached",MIN(P79:P98))) -> 3.6330159 | D18: =IF(D65=0,"Invalid",IF(MIN(R79:R98)=999,"Not reached",MIN(R79:R98))) -> Not reached | E18: =IF(E65=0,"Invalid",IF(MIN(T79:T98)=999,"Not reached",MIN(T79:T98))) -> 8.7959743 | H18: Unused fields: battery for solar-only and PV for battery-only. Grid-cycle mode applies only to the battery-only column. | W18: Daytime energy share | X18: % | Y18: 0.5 | Z18: 0.5 | AA18: 0.5 | AB18: 0.5 | AC18: 0.5 | AD18: 0.5 | AE18: 0.5 | AF18: 0.5 | AH18: Day / night energy split | AK18: 50% / 50%; constant-load assumption, not measured
A19: Discounted payback | B19: years | C19: =IF(C65=0,"Invalid",IF(MIN(Q79:Q98)=999,"Not reached",MIN(Q79:Q98))) -> 4.7500873 | D19: =IF(D65=0,"Invalid",IF(MIN(S79:S98)=999,"Not reached",MIN(S79:S98))) -> Not reached | E19: =IF(E65=0,"Invalid",IF(MIN(U79:U98)=999,"Not reached",MIN(U79:U98))) -> Not reached | W19: Roof input mode | Y19: Unspecified | Z19: Unspecified | AA19: Specified | AB19: Specified | AC19: Specified | AD19: Specified | AE19: Specified | AF19: Specified | AH19: PV charging window (hours) | AK19: 6
A20: Full-charge backup energy | B20: kWh AC | C20: =C68 -> 0 | D20: =D68 -> 12.48 | E20: =E68 -> 12.48 | H20: Live checks | J20: Solar only | K20: Battery only | L20: Solar and battery | W20: Available roof area | X20: m2 | Y20: Unspecified | Z20: Unspecified | AA20: 10 | AB20: 25 | AC20: 50 | AD20: 10 | AE20: 50 | AF20: 10 | AH20: Grid charging window (hours) | AK20: 8
A21: Maximum backup power | B21: kW | C21: =C69 -> 0 | D21: =D69 -> 5 | E21: =E69 -> 8 | H21: Errors | J21: =COUNTIFS(C926:C980,"ERROR:*") -> 0 | K21: =COUNTIFS(G926:G980,"ERROR:*") -> 0 | L21: =COUNTIFS(K926:K980,"ERROR:*") -> 0 | W21: Critical-load basis | Y21: Manager estimate; not measured | Z21: Manager estimate; not measured | AA21: Manager estimate; not measured | AB21: Manager estimate; not measured | AC21: Manager estimate; not measured | AD21: Manager estimate; not measured | AE21: Manager estimate; not measured | AF21: Manager estimate; not measured | AH21: Installation area multiplier | AK21: 1.5
A22: Backup hours from full charge | B22: hours | C22: =IF(C65=0,"Invalid",IF(C69=0,"Not available",IF(Inputs!$C$20="Unknown","Load unknown",IF(Inputs!$C$21>C69,"Load exceeds power limit",C68/Inputs!$C$21)))) -> Not available | D22: =IF(D65=0,"Invalid",IF(D69=0,"Not available",IF(Inputs!$C$20="Unknown","Load unknown",IF(Inputs!$C$21>D69,"Load exceeds power limit",D68/Inputs!$C$21)))) -> Load unknown | E22: =IF(E65=0,"Invalid",IF(E69=0,"Not available",IF(Inputs!$C$20="Unknown","Load unknown",IF(Inputs!$C$21>E69,"Load exceeds power limit",E68/Inputs!$C$21)))) -> Load unknown | H22: Warnings | J22: =COUNTIFS(C926:C980,"WARNING:*") -> 1 | K22: =COUNTIFS(G926:G980,"WARNING:*") -> 1 | L22: =COUNTIFS(K926:K980,"WARNING:*") -> 2 | W22: Critical load used for backup check | X22: kW | Y22: 4 | Z22: 4 | AA22: 4 | AB22: 4 | AC22: 4 | AD22: 4 | AE22: 4 | AF22: 4 | AH22: Annual maintenance / initial investment | AK22: 0.01
A23: Reserved backup energy | B23: kWh AC | C23: =IF(C58=1,C67*'Assumptions and Catalog'!$C$12,0) -> 0 | D23: =IF(D58=1,D67*'Assumptions and Catalog'!$C$12,0) -> 12.48 | E23: =IF(E58=1,E67*'Assumptions and Catalog'!$C$12,0) -> 2.496 | H23: Details | J23: =HYPERLINK("#'Scenarios'!C924","Open checks") -> Open checks | K23: =HYPERLINK("#'Scenarios'!G924","Open checks") -> Open checks | L23: =HYPERLINK("#'Scenarios'!K924","Open checks") -> Open checks | W23: Panel model slot | Y23: PV550 | Z23: PV670 | AA23: PV670 | AB23: PV670 | AC23: PV670 | AD23: PV670 | AE23: PV670 | AF23: PV670 | AH23: Battery replacement year | AK23: 11
A24: System role | C24: =IF(C65=0,"Invalid",IF(C15>0,IF(C69>0,"Bill savings + backup capability","Bill savings"),IF(C69>0,"Backup capability, no bill savings","No bill savings demonstrated"))) -> Bill savings | D24: =IF(D65=0,"Invalid",IF(D15>0,IF(D69>0,"Bill savings + backup capability","Bill savings"),IF(D69>0,"Backup capability, no bill savings","No bill savings demonstrated"))) -> Backup capability, no bill savings | E24: =IF(E65=0,"Invalid",IF(E15>0,IF(E69>0,"Bill savings + backup capability","Bill savings"),IF(E69>0,"Backup capability, no bill savings","No bill savings demonstrated"))) -> Bill savings + backup capability | W24: Panel rated power | X24: Wp | Y24: 550 | Z24: 670 | AA24: 670 | AB24: 670 | AC24: 670 | AD24: 670 | AE24: 670 | AF24: 670 | AH24: Battery replacement cost fraction | AK24: 1
A25: Financial outcome | C25: =IF(C65=0,"Invalid",IF(C17>0,"Positive NPV under assumptions",IF(C17=0,"Discounted breakeven","Negative NPV under assumptions"))) -> Positive NPV under assumptions | D25: =IF(D65=0,"Invalid",IF(D17>0,"Positive NPV under assumptions",IF(D17=0,"Discounted breakeven","Negative NPV under assumptions"))) -> Negative NPV under assumptions | E25: =IF(E65=0,"Invalid",IF(E17>0,"Positive NPV under assumptions",IF(E17=0,"Discounted breakeven","Negative NPV under assumptions"))) -> Negative NPV under assumptions | W25: Panel quantity | X25: units | Y25: 46 | Z25: 0 | AA25: 3 | AB25: 7 | AC25: 15 | AD25: 3 | AE25: 15 | AF25: 3 | AH25: Inverter replacement year | AK25: 12
A26: Roof area status | C26: =IF(Inputs!$C$14="Unspecified","Roof fit not verified",IF(C59<=Inputs!$C$15,"Within available area","Exceeds available area")) -> Roof fit not verified | D26: =IF(Inputs!$C$14="Unspecified","Roof fit not verified",IF(D59<=Inputs!$C$15,"Within available area","Exceeds available area")) -> Roof fit not verified | E26: =IF(Inputs!$C$14="Unspecified","Roof fit not verified",IF(E59<=Inputs!$C$15,"Within available area","Exceeds available area")) -> Roof fit not verified | W26: Battery unit model / capacity | Y26: BAT10 / 10 kWh | Z26: BAT10 / 10 kWh | AA26: BAT10 / 10 kWh | AB26: BAT10 / 10 kWh | AC26: BAT10 / 10 kWh | AD26: BAT10 / 10 kWh | AE26: BAT10 / 10 kWh | AF26: BAT10 / 10 kWh | AH26: Inverter replacement cost fraction | AK26: 1
W27: Battery unit quantity | X27: units | Y27: 0 | Z27: 1 | AA27: 1 | AB27: 1 | AC27: 2 | AD27: 3 | AE27: 5 | AF27: 5 | AH27: Battery capacity degradation per year | AK27: 0.02
A28: Full-charge backup is not guaranteed at outage time. Motor surge, load phase balance and site checks are not modeled. | W28: Temporary inverter catalog slot | Y28: GRID10 (25 kW test) | Z28: HYB5 (3 kW test) | AA28: HYB5 (3 kW test) | AB28: HYB5 (5 kW test) | AC28: HYB5 (10 kW test) | AD28: HYB5 (5 kW test) | AE28: HYB5 (10 kW test) | AF28: HYB5 (5 kW test) | AH28: Battery auxiliary use (kWh/day) | AK28: 0
A29: NPV excludes financing, taxes and outage value. The no-investment baseline has NPV = 0. | W29: Inverter AC rating | X29: kW | Y29: 25 | Z29: 3 | AA29: 3 | AB29: 5 | AC29: 10 | AD29: 5 | AE29: 10 | AF29: 5 | AH29: Cairo yield (kWh/kWp/day) | AK29: 4.98
W30: Inverter PV limit (assumed 1.3 x AC) | X30: kWp | Y30: 32.5 | Z30: 3.9 | AA30: 3.9 | AB30: 6.5 | AC30: 13 | AD30: 6.5 | AE30: 13 | AF30: 6.5 | AH30: PV550 area (m2/panel) | AK30: 2.6
A31: Battery savings vs matched PV | B31: EGP/year | E31: =IF(E65=1,SUM(Q661:Q672)-SUM(N661:N672),"Invalid") -> 10701.835 | W31: Effective battery charge power | X31: kW | Y31: 0 | Z31: 3 | AA31: 3 | AB31: 5 | AC31: 10 | AD31: 5 | AE31: 10 | AF31: 5 | AH31: PV670 area (m2/panel) | AK31: 2.7
A32: Incremental battery investment | B32: EGP | E32: =E61*(1+'Assumptions and Catalog'!$C$17) -> 240064 | W32: Effective battery discharge power | X32: kW | Y32: 0 | Z32: 3 | AA32: 3 | AB32: 5 | AC32: 10 | AD32: 5 | AE32: 10 | AF32: 5 | AH32: Battery usable fraction | AK32: 0.8
A33: Incremental comparison uses the same PV and hybrid inverter without a battery; no cheaper inverter alternative is assumed. | W33: Reserved share of usable capacity | X33: % | Y33: 0.2 | Z33: 1 | AA33: 0.2 | AB33: 0.2 | AC33: 0.2 | AD33: 0.2 | AE33: 0.2 | AF33: 0.2 | AH33: BAT10 charge/discharge limit (kW/unit) | AK33: 5
W34: Battery-only operating mode | Y34: Backup | Z34: Backup | AA34: Backup | AB34: Backup | AC34: Backup | AD34: Backup | AE34: Backup | AF34: Backup | AH34: Battery compatibility group | AK34: LV; assumed, not manufacturer verified
A35: =HYPERLINK("#'Solar Production'!A19","Open monthly solar production and bill savings") -> Open monthly solar production and bill savings | W35: Grid-cycle delivery setting (inactive) | X35: kWh/day | Y35: 8 | Z35: 8 | AA35: 8 | AB35: 8 | AC35: 8 | AD35: 8 | AE35: 8 | AF35: 8 | AH35: Inverter PV limit assumption | AK35: 1.3 x AC rating; same ratio as existing catalog
A36: Experimental copy: monthly seasonality enabled. Battery dispatch is still a monthly approximation. | W36: Panel unit cost from source | X36: EGP | Y36: 4260.8696 | Z36: Not used | AA36: 5766.6667 | AB36: 4690 | AC36: 4690 | AD36: 10766.667 | AE36: 4690 | AF36: 5833.3333 | AH36: Inverter charge power assumption | AK36: Equal to AC rating, capped by battery power
W37: Battery unit cost from source | X37: EGP | Y37: 115000 | Z37: 115000 | AA37: 115000 | AB37: 115000 | AC37: 115000 | AD37: 115000 | AE37: 115000 | AF37: 115000 | AH37: Critical load | AK37: 4 kW from manager estimate; not measured
W38: Inverter cost from source | X38: EGP | Y38: 140000 | Z38: 30000 | AA38: 30000 | AB38: 50000 | AC38: 100000 | AD38: 50000 | AE38: 100000 | AF38: 50000 | AH38: Backup interpretation | AK38: Full charge is conditional, not guaranteed at outage time
W39: Declared source capital total | X39: EGP | Y39: 413500 | Z39: 172500 | AA39: 197300 | AB39: 247000 | AC39: 467500 | AD39: 454800 | AE39: 812850 | AF39: 662500 | AH39: Backup outage energy | AK39: Outage events and recharge losses are not scheduled
W40: BOS fraction reconciling source total | X40: % | Y40: 0.23065476 | Z40: 0.18965517 | AA40: 0.21565003 | AB40: 0.24854673 | AC40: 0.16772824 | AD40: 0.064357594 | AE40: 0.090561481 | AF40: 0.031128405 | AH40: Source cost basis | AK40: Declared scenario total retained. Component range midpoints used.
W41: Source installation midpoint | X41: EGP | Y41: 77500 | Z41: 27500 | AA41: 35000 | AB41: 50000 | AC41: 67500 | AD41: 27500 | AE41: 67500 | AF41: 20000 | AH41: BOS override | AK41: (Declared capital total - equipment cost) / equipment cost
W42: Installation used (total less equipment) | X42: EGP | Y42: 77500 | Z42: 27500 | AA42: 35000 | AB42: 49170 | AC42: 67150 | AD42: 27500 | AE42: 67500 | AF42: 20000 | AH42: Capital reconciliation | AK42: S4: -830 EGP; S5: -350 EGP vs component midpoints
W43: Sum of source component midpoints | X43: EGP | Y43: 413500 | Z43: 172500 | AA43: 197300 | AB43: 247830 | AC43: 467850 | AD43: 454800 | AE43: 812850 | AF43: 662500 | AH43: Temporary catalog slots | AK43: Run-specific values restored after all snapshots
W44: Declared total less component sum | X44: EGP | Y44: 0 | Z44: 0 | AA44: 0 | AB44: -830 | AC44: -350 | AD44: 0 | AE44: 0 | AF44: 0 | AH44: Source solar assumption | AK44: Manager uses 5.4 x 0.80 = 4.32. Workbook keeps 4.98.
W45: Costs use manager component midpoints and the declared capital total. Installation is the residual needed to reconcile that total; this is not a supplier quotation. Temporary catalog changes are recorded above and restored in the live model. | AH45: Source financial assumption | AK45: Manager cash flows escalate; workbook retains zero escalation and 1% maintenance.
W46: Copied scenario outputs - original row order | AH46: Tariff status | AK46: Workbook reference tariff; current applicability not verified
W47: PV capacity | X47: kWp | Y47: 25.3 | Z47: 0 | AA47: 2.01 | AB47: 4.69 | AC47: 10.05 | AD47: 2.01 | AE47: 10.05 | AF47: 2.01 | AH47: Paid average rate | AK47: 8279 / 2421 = 3.4196613 EGP/kWh; not used as the tariff
W48: Nominal battery capacity | X48: kWh | Y48: 0 | Z48: 10 | AA48: 10 | AB48: 10 | AC48: 20 | AD48: 30 | AE48: 50 | AF48: 50 | AH48: Annual baseline interpretation | AK48: 80.7 kWh/day x calendar days; not monthly bill x 12
W49: Inverter capacity | X49: kW | Y49: 25 | Z49: 3 | AA49: 3 | AB49: 5 | AC49: 10 | AD49: 5 | AE49: 10 | AF49: 5 | AH49: Exports / peak / outage income | AK49: No export revenue, TOU benefit, demand-charge saving or outage value
A50: Sizing and cost details | W50: Required roof area | X50: m² | Y50: 179.4 | Z50: 0 | AA50: 12.15 | AB50: 28.35 | AC50: 60.75 | AD50: 12.15 | AE50: 60.75 | AF50: 12.15 | AH50: Scenario 1 limitation | AK50: 46 x 550 W = 25.3 kWp. AC 25 kW assumed; hourly clipping not modeled.
A51: Installed PV (kWp) | C51: =J10*INDEX('Assumptions and Catalog'!$C$73:$I$74,MATCH(J9,'Assumptions and Catalog'!$A$73:$A$74,0),1)/1000 -> 8.8 | D51: =0 -> 0 | E51: =L10*INDEX('Assumptions and Catalog'!$C$73:$I$74,MATCH(L9,'Assumptions and Catalog'!$A$73:$A$74,0),1)/1000 -> 11 | W51: Initial investment | X51: EGP | Y51: 413500 | Z51: 172500 | AA51: 197300 | AB51: 247000 | AC51: 467500 | AD51: 454800 | AE51: 812850 | AF51: 662500 | AH51: Source-result comparison | AK51: Source figures are context, not expected test results. Assumptions differ.
A52: Nominal battery capacity (kWh) | C52: =0 -> 0 | D52: =K12*INDEX('Assumptions and Catalog'!$C$79:$I$81,MATCH(K11,'Assumptions and Catalog'!$A$79:$A$81,0),1) -> 16 | E52: =L12*INDEX('Assumptions and Catalog'!$C$79:$I$81,MATCH(L11,'Assumptions and Catalog'!$A$79:$A$81,0),1) -> 16 | W52: Year 1 solar generation | X52: kWh | Y52: 45987.81 | Z52: 0 | AA52: 3653.577 | AB52: 8525.013 | AC52: 18267.885 | AD52: 3653.577 | AE52: 18267.885 | AF52: 3653.577 | AH52: Snapshot refresh | AK52: Re-enter recorded values, recalculate, verify, then replace that column with values.
A53: Inverter AC rating (kW) | C53: =INDEX('Assumptions and Catalog'!$C$86:$I$89,MATCH(J13,'Assumptions and Catalog'!$A$86:$A$89,0),1) -> 10 | D53: =INDEX('Assumptions and Catalog'!$C$86:$I$89,MATCH(K13,'Assumptions and Catalog'!$A$86:$A$89,0),1) -> 5 | E53: =INDEX('Assumptions and Catalog'!$C$86:$I$89,MATCH(L13,'Assumptions and Catalog'!$A$86:$A$89,0),1) -> 12 | W53: Year 1 baseline bill | X53: EGP | Y53: 83544.51 | Z53: 83544.51 | AA53: 83544.51 | AB53: 83544.51 | AC53: 83544.51 | AD53: 83544.51 | AE53: 83544.51 | AF53: 83544.51 | AH53: Restore status | AK53: Original live inputs, assumptions, catalogs and formulas restored.
A54: Inverter PV limit (kWp) | C54: =INDEX('Assumptions and Catalog'!$C$86:$I$89,MATCH(J13,'Assumptions and Catalog'!$A$86:$A$89,0),2) -> 13 | D54: =INDEX('Assumptions and Catalog'!$C$86:$I$89,MATCH(K13,'Assumptions and Catalog'!$A$86:$A$89,0),2) -> 6.5 | E54: =INDEX('Assumptions and Catalog'!$C$86:$I$89,MATCH(L13,'Assumptions and Catalog'!$A$86:$A$89,0),2) -> 15.6 | W54: Year 1 bill after installation | X54: EGP | Y54: 42012.255 | Z54: 83544.51 | AA54: Invalid | AB54: Invalid | AC54: Invalid | AD54: Invalid | AE54: Invalid | AF54: Invalid
A55: Usable internal capacity (kWh) | C55: =C52*INDEX('Assumptions and Catalog'!$C$79:$I$81,MATCH(J11,'Assumptions and Catalog'!$A$79:$A$81,0),2) -> 0 | D55: =D52*INDEX('Assumptions and Catalog'!$C$79:$I$81,MATCH(K11,'Assumptions and Catalog'!$A$79:$A$81,0),2) -> 12.8 | E55: =E52*INDEX('Assumptions and Catalog'!$C$79:$I$81,MATCH(L11,'Assumptions and Catalog'!$A$79:$A$81,0),2) -> 12.8 | W55: Year 1 bill savings | X55: EGP | Y55: 41532.255 | Z55: 0 | AA55: Invalid | AB55: Invalid | AC55: Invalid | AD55: Invalid | AE55: Invalid | AF55: Invalid | AH55: Source documents
A56: Battery charge limit (AC kW) | C56: =MIN(J12*INDEX('Assumptions and Catalog'!$C$79:$I$81,MATCH(J11,'Assumptions and Catalog'!$A$79:$A$81,0),3),INDEX('Assumptions and Catalog'!$C$86:$I$89,MATCH(J13,'Assumptions and Catalog'!$A$86:$A$89,0),3)) -> 0 | D56: =MIN(K12*INDEX('Assumptions and Catalog'!$C$79:$I$81,MATCH(K11,'Assumptions and Catalog'!$A$79:$A$81,0),3),INDEX('Assumptions and Catalog'!$C$86:$I$89,MATCH(K13,'Assumptions and Catalog'!$A$86:$A$89,0),3)) -> 5 | E56: =MIN(L12*INDEX('Assumptions and Catalog'!$C$79:$I$81,MATCH(L11,'Assumptions and Catalog'!$A$79:$A$81,0),3),INDEX('Assumptions and Catalog'!$C$86:$I$89,MATCH(L13,'Assumptions and Catalog'!$A$86:$A$89,0),3)) -> 8 | W56: Year 1 savings after maintenance | X56: EGP | Y56: 37397.255 | Z56: -1725 | AA56: Invalid | AB56: Invalid | AC56: Invalid | AD56: Invalid | AE56: Invalid | AF56: Invalid | AH56: Manager: PV + Battery Storage System for a Juice Shop in Egypt V1 -Mohamed Ismail.docx. Part 3, Scenarios 1-8; Part 4 comparison. User annotations are questions, not revised scenario specifications.
A57: Battery discharge limit (AC kW) | C57: =MIN(J12*INDEX('Assumptions and Catalog'!$C$79:$I$81,MATCH(J11,'Assumptions and Catalog'!$A$79:$A$81,0),4),C53) -> 0 | D57: =MIN(K12*INDEX('Assumptions and Catalog'!$C$79:$I$81,MATCH(K11,'Assumptions and Catalog'!$A$79:$A$81,0),4),D53) -> 5 | E57: =MIN(L12*INDEX('Assumptions and Catalog'!$C$79:$I$81,MATCH(L11,'Assumptions and Catalog'!$A$79:$A$81,0),4),E53) -> 8 | W57: NPV over study period | X57: EGP | Y57: -183507.92 | Z57: -183099.38 | AA57: Invalid | AB57: Invalid | AC57: Invalid | AD57: Invalid | AE57: Invalid | AF57: Invalid
A58: Backup supported 1/0 | C58: =0 -> 0 | D58: =INDEX('Assumptions and Catalog'!$C$86:$I$89,MATCH(K13,'Assumptions and Catalog'!$A$86:$A$89,0),4) -> 1 | E58: =INDEX('Assumptions and Catalog'!$C$86:$I$89,MATCH(L13,'Assumptions and Catalog'!$A$86:$A$89,0),4) -> 1 | W58: Simple payback | X58: years | Y58: Not reached | Z58: Not reached | AA58: Invalid | AB58: Invalid | AC58: Invalid | AD58: Invalid | AE58: Invalid | AF58: Invalid
A59: Required area (m2) | C59: =C51*1000/INDEX('Assumptions and Catalog'!$C$73:$I$74,MATCH(J9,'Assumptions and Catalog'!$A$73:$A$74,0),1)*INDEX('Assumptions and Catalog'!$C$73:$I$74,MATCH(J9,'Assumptions and Catalog'!$A$73:$A$74,0),2)*'Assumptions and Catalog'!$C$16 -> 62.4 | D59: =D51*1000/INDEX('Assumptions and Catalog'!$C$73:$I$74,MATCH(K9,'Assumptions and Catalog'!$A$73:$A$74,0),1)*INDEX('Assumptions and Catalog'!$C$73:$I$74,MATCH(K9,'Assumptions and Catalog'!$A$73:$A$74,0),2)*'Assumptions and Catalog'!$C$16 -> 0 | E59: =E51*1000/INDEX('Assumptions and Catalog'!$C$73:$I$74,MATCH(L9,'Assumptions and Catalog'!$A$73:$A$74,0),1)*INDEX('Assumptions and Catalog'!$C$73:$I$74,MATCH(L9,'Assumptions and Catalog'!$A$73:$A$74,0),2)*'Assumptions and Catalog'!$C$16 -> 78 | W59: Discounted payback | X59: years | Y59: Not reached | Z59: Not reached | AA59: Invalid | AB59: Invalid | AC59: Invalid | AD59: Invalid | AE59: Invalid | AF59: Invalid | AH59: Receipt baseline: AVESTA Egypt El Mo3alem Shop BESS Report.docx. Verified receipt figures; 2,421 kWh and EGP 8,279. Critical load is a separate manager estimate.
A60: PV panel cost (EGP) | C60: =C51*1000/INDEX('Assumptions and Catalog'!$C$73:$I$74,MATCH(J9,'Assumptions and Catalog'!$A$73:$A$74,0),1)*INDEX('Assumptions and Catalog'!$C$73:$I$74,MATCH(J9,'Assumptions and Catalog'!$A$73:$A$74,0),3) -> 70400 | D60: =D51*1000/INDEX('Assumptions and Catalog'!$C$73:$I$74,MATCH(K9,'Assumptions and Catalog'!$A$73:$A$74,0),1)*INDEX('Assumptions and Catalog'!$C$73:$I$74,MATCH(K9,'Assumptions and Catalog'!$A$73:$A$74,0),3) -> 0 | E60: =E51*1000/INDEX('Assumptions and Catalog'!$C$73:$I$74,MATCH(L9,'Assumptions and Catalog'!$A$73:$A$74,0),1)*INDEX('Assumptions and Catalog'!$C$73:$I$74,MATCH(L9,'Assumptions and Catalog'!$A$73:$A$74,0),3) -> 88000 | W60: Full-charge backup energy | X60: kWh AC | Y60: 0 | Z60: 7.8 | AA60: 7.8 | AB60: 7.8 | AC60: 15.6 | AD60: 23.4 | AE60: 39 | AF60: 39
A61: Battery cost (EGP) | C61: =C52/INDEX('Assumptions and Catalog'!$C$79:$I$81,MATCH(J11,'Assumptions and Catalog'!$A$79:$A$81,0),1)*INDEX('Assumptions and Catalog'!$C$79:$I$81,MATCH(J11,'Assumptions and Catalog'!$A$79:$A$81,0),5) -> 0 | D61: =D52/INDEX('Assumptions and Catalog'!$C$79:$I$81,MATCH(K11,'Assumptions and Catalog'!$A$79:$A$81,0),1)*INDEX('Assumptions and Catalog'!$C$79:$I$81,MATCH(K11,'Assumptions and Catalog'!$A$79:$A$81,0),5) -> 218240 | E61: =E52/INDEX('Assumptions and Catalog'!$C$79:$I$81,MATCH(L11,'Assumptions and Catalog'!$A$79:$A$81,0),1)*INDEX('Assumptions and Catalog'!$C$79:$I$81,MATCH(L11,'Assumptions and Catalog'!$A$79:$A$81,0),5) -> 218240 | W61: Maximum backup power | X61: kW | Y61: 0 | Z61: 3 | AA61: 3 | AB61: 5 | AC61: 10 | AD61: 5 | AE61: 10 | AF61: 5
A62: Inverter cost (EGP) | C62: =INDEX('Assumptions and Catalog'!$C$86:$I$89,MATCH(J13,'Assumptions and Catalog'!$A$86:$A$89,0),5) -> 60000 | D62: =INDEX('Assumptions and Catalog'!$C$86:$I$89,MATCH(K13,'Assumptions and Catalog'!$A$86:$A$89,0),5) -> 30000 | E62: =INDEX('Assumptions and Catalog'!$C$86:$I$89,MATCH(L13,'Assumptions and Catalog'!$A$86:$A$89,0),5) -> 72000 | W62: Backup hours from full charge | X62: hours | Y62: Not available | Z62: Load exceeds power limit | AA62: Invalid | AB62: Invalid | AC62: Invalid | AD62: Invalid | AE62: Invalid | AF62: Invalid | AH62: Repository: github.com/boodyelkady1998-sudo/avesta-bess-sizing-tool. Manager source: equations-presentation branch. Workbook baseline: excel-sheet-branch.
A63: Installation and BOS (EGP) | C63: =SUM(C60:C62)*'Assumptions and Catalog'!$C$17 -> 13040 | D63: =SUM(D60:D62)*'Assumptions and Catalog'!$C$17 -> 24824 | E63: =SUM(E60:E62)*'Assumptions and Catalog'!$C$17 -> 37824 | W63: Reserved backup energy | X63: kWh AC | Y63: 0 | Z63: 7.8 | AA63: 1.56 | AB63: 1.56 | AC63: 3.12 | AD63: 4.68 | AE63: 7.8 | AF63: 7.8
A64: Total investment (EGP) | C64: =SUM(C60:C63) -> 143440 | D64: =SUM(D60:D63) -> 273064 | E64: =SUM(E60:E63) -> 416064 | W64: System role | Y64: Bill savings | Z64: Backup capability, no bill savings | AA64: Invalid | AB64: Invalid | AC64: Invalid | AD64: Invalid | AE64: Invalid | AF64: Invalid
A65: Model validity 1/0 | C65: =IF(AND(Inputs!$L$3="Ready for indicative calculation",C51<=C54,OR(Inputs!$C$14="Unspecified",C59<=Inputs!$C$15),C66="Compatible under assumptions",J10>=0,J12>=0,MOD(J10,1)=0,MOD(J12,1)=0,J14>=0,J14<=1,'Assumptions and Catalog'!$C$11>0,'Assumptions and Catalog'!$C$11<=1,'Assumptions and Catalog'!$C$12>0,'Assumptions and Catalog'!$C$12<=1,'Assumptions and Catalog'!$C$6>=1,'Assumptions and Catalog'!$C$6<=20),1,0) -> 1 | D65: =IF(AND(Inputs!$L$3="Ready for indicative calculation",D51<=D54,OR(Inputs!$C$14="Unspecified",D59<=Inputs!$C$15),D66="Compatible under assumptions",K10>=0,K12>=0,MOD(K10,1)=0,MOD(K12,1)=0,K14>=0,K14<=1,'Assumptions and Catalog'!$C$11>0,'Assumptions and Catalog'!$C$11<=1,'Assumptions and Catalog'!$C$12>0,'Assumptions and Catalog'!$C$12<=1,'Assumptions and Catalog'!$C$6>=1,'Assumptions and Catalog'!$C$6<=20),1,0) -> 1 | E65: =IF(AND(Inputs!$L$3="Ready for indicative calculation",E51<=E54,OR(Inputs!$C$14="Unspecified",E59<=Inputs!$C$15),E66="Compatible under assumptions",L10>=0,L12>=0,MOD(L10,1)=0,MOD(L12,1)=0,L14>=0,L14<=1,'Assumptions and Catalog'!$C$11>0,'Assumptions and Catalog'!$C$11<=1,'Assumptions and Catalog'!$C$12>0,'Assumptions and Catalog'!$C$12<=1,'Assumptions and Catalog'!$C$6>=1,'Assumptions and Catalog'!$C$6<=20),1,0) -> 1 | W65: Financial outcome | Y65: Negative NPV under assumptions | Z65: Negative NPV under assumptions | AA65: Invalid | AB65: Invalid | AC65: Invalid | AD65: Invalid | AE65: Invalid | AF65: Invalid | AH65: Baseline native recalculation matched every original value with no formula errors. No business formula changes were required for these tests. Model limitations were retained, not hidden.
A66: Compatibility status | C66: =IF(OR(C52=0,INDEX('Assumptions and Catalog'!$C$79:$I$81,MATCH(J11,'Assumptions and Catalog'!$A$79:$A$81,0),6)=INDEX('Assumptions and Catalog'!$C$86:$I$89,MATCH(J13,'Assumptions and Catalog'!$A$86:$A$89,0),6)),"Compatible under assumptions","Incompatible") -> Compatible under assumptions | D66: =IF(OR(D52=0,INDEX('Assumptions and Catalog'!$C$79:$I$81,MATCH(K11,'Assumptions and Catalog'!$A$79:$A$81,0),6)=INDEX('Assumptions and Catalog'!$C$86:$I$89,MATCH(K13,'Assumptions and Catalog'!$A$86:$A$89,0),6)),"Compatible under assumptions","Incompatible") -> Compatible under assumptions | E66: =IF(OR(E52=0,INDEX('Assumptions and Catalog'!$C$79:$I$81,MATCH(L11,'Assumptions and Catalog'!$A$79:$A$81,0),6)=INDEX('Assumptions and Catalog'!$C$86:$I$89,MATCH(L13,'Assumptions and Catalog'!$A$86:$A$89,0),6)),"Compatible under assumptions","Incompatible") -> Compatible under assumptions | W66: Roof area status | Y66: Roof fit not verified | Z66: Roof fit not verified | AA66: Exceeds available area | AB66: Exceeds available area | AC66: Exceeds available area | AD66: Exceeds available area | AE66: Exceeds available area | AF66: Exceeds available area
A67: Reserved internal energy (kWh) | C67: =C55*J14 -> 0 | D67: =D55*K14 -> 12.8 | E67: =E55*L14 -> 2.56 | W67: Year-1 energy detail - diagnostic where roof is invalid
A68: Full-charge backup (kWh AC) | C68: =IF(C58=1,C55*'Assumptions and Catalog'!$C$12,0) -> 0 | D68: =IF(D58=1,D55*'Assumptions and Catalog'!$C$12,0) -> 12.48 | E68: =IF(E58=1,E55*'Assumptions and Catalog'!$C$12,0) -> 12.48 | W68: Direct solar use | X68: kWh/year | Y68: 14727.75 | Z68: 0 | AA68: 3653.577 | AB68: 8525.013 | AC68: 14727.75 | AD68: 3653.577 | AE68: 14727.75 | AF68: 3653.577 | AH68: Boundary tests - original live model
A69: Backup power (kW) | C69: =IF(C58=1,C57,0) -> 0 | D69: =IF(D58=1,D57,0) -> 5 | E69: =IF(E58=1,E57,0) -> 8 | W69: Solar energy sent to battery (AC input) | X69: kWh/year | Y69: 0 | Z69: 0 | AA69: 0 | AB69: 0 | AC69: 3540.135 | AD69: 0 | AE69: 3540.135 | AF69: 0
A70: Year 1 maintenance (EGP) | C70: =C64*'Assumptions and Catalog'!$C$18 -> 1434.4 | D70: =D64*'Assumptions and Catalog'!$C$18 -> 2730.64 | E70: =E64*'Assumptions and Catalog'!$C$18 -> 4160.64 | W70: Battery delivery to loads (AC output) | X70: kWh/year | Y70: 0 | Z70: 0 | AA70: 0 | AB70: 0 | AC70: 3365.3408 | AD70: 0 | AE70: 3365.3408 | AF70: 0 | AH70: Zero solar | AK70: PASS: no solar production or bill savings
W71: Battery conversion losses | X71: kWh/year | Y71: 0 | Z71: 0 | AA71: 0 | AB71: 0 | AC71: 174.79417 | AD71: 0 | AE71: 174.79417 | AF71: 0
W72: Unused solar energy; no export income | X72: kWh/year | Y72: 31260.06 | Z72: 0 | AA72: 0 | AB72: 0 | AC72: 0 | AD72: 0 | AE72: 0 | AF72: 0 | AH72: Zero battery | AK72: PASS: zero battery capacity, backup and incremental storage savings
W73: Grid energy purchased | X73: kWh/year | Y73: 14727.75 | Z73: 29455.5 | AA73: 25801.923 | AB73: 20930.487 | AC73: 11362.409 | AD73: 25801.923 | AE73: 11362.409 | AF73: 25801.923
W74: Daytime demand | X74: kWh/year | Y74: 14727.75 | Z74: 14727.75 | AA74: 14727.75 | AB74: 14727.75 | AC74: 14727.75 | AD74: 14727.75 | AE74: 14727.75 | AF74: 14727.75 | AH74: Night-only demand | AK74: PASS: solar-only bill savings equal zero
A75: Annual cash flows — year-end timing | W75: Nighttime demand | X75: kWh/year | Y75: 14727.75 | Z75: 14727.75 | AA75: 14727.75 | AB75: 14727.75 | AC75: 14727.75 | AD75: 14727.75 | AE75: 14727.75 | AF75: 14727.75
W76: Battery savings vs same PV without storage | X76: EGP/year | Y76: 0 | Z76: 0 | AA76: 5.4569682e-12 | AB76: 0 | AC76: 10958.382 | AD76: 5.4569682e-12 | AE76: 10958.382 | AF76: 5.4569682e-12 | AH76: Grid cycle at one tariff | AK76: PASS: charging losses increase the bill
A77: Year | B77: Baseline EGP | C77: Solar net cash flow | D77: Discounted solar cash flow | E77: Solar cumulative CF | F77: Cumulative discounted CF | G77: Battery net cash flow | H77: Discounted battery cash flow | I77: Battery cumulative CF | J77: Cumulative discounted CF | K77: Combined net cash flow | L77: Discounted combined cash flow | M77: Combined cumulative CF | N77: Cumulative discounted CF | P77: C Payback | Q77: C Discounted | R77: D Payback | S77: D Discounted | T77: E Payback | U77: E Discounted | W77: Conditional financial diagnostics - NOT a feasibility approval
A78: 0 | B78: 0 | C78: =-C64 -> -143440 | D78: =-C64 -> -143440 | E78: =-C64 -> -143440 | F78: =-C64 -> -143440 | G78: =-D64 -> -273064 | H78: =-D64 -> -273064 | I78: =-D64 -> -273064 | J78: =-D64 -> -273064 | K78: =-E64 -> -416064 | L78: =-E64 -> -416064 | M78: =-E64 -> -416064 | N78: =-E64 -> -416064 | W78: Conditional year-1 net savings | X78: EGP | Y78: 37397.255 | Z78: -1725 | AA78: 8330.0871 | AB78: 21570.537 | AC78: 47815.637 | AD78: 5755.0871 | AE78: 44362.137 | AF78: 3678.0871 | AH78: Insufficient roof | AK78: PASS: validity gate blocks financial results
A79: 1 | B79: =IF(A79<='Assumptions and Catalog'!$C$6,SUMIFS($M$161:$M$400,$A$161:$A$400,A79),0) -> 83544.51 | C79: =IF(A79<='Assumptions and Catalog'!$C$6,SUMIFS($O$161:$O$400,$A$161:$A$400,A79)-(C$70+IF(AND('Assumptions and Catalog'!$C$19>0,A79='Assumptions and Catalog'!$C$19),C$61*'Assumptions and Catalog'!$C$20,0)+IF(AND('Assumptions and Catalog'!$C$21>0,A79='Assumptions and Catalog'!$C$21),C$62*'Assumptions and Catalog'!$C$22,0))*(1+'Assumptions and Catalog'!$C$9)^(A79-1),0) -> 39522.846 | D79: =C79/(1+'Assumptions and Catalog'!$C$7)^A79 -> 35929.86 | E79: =E78+C79 -> -103917.15 | F79: =F78+D79 -> -107510.14 | G79: =IF(A79<='Assumptions and Catalog'!$C$6,SUMIFS($O$411:$O$650,$A$411:$A$650,A79)-(D$70+IF(AND('Assumptions and Catalog'!$C$19>0,A79='Assumptions and Catalog'!$C$19),D$61*'Assumptions and Catalog'!$C$20,0)+IF(AND('Assumptions and Catalog'!$C$21>0,A79='Assumptions and Catalog'!$C$21),D$62*'Assumptions and Catalog'!$C$22,0))*(1+'Assumptions and Catalog'!$C$9)^(A79-1),0) -> -2730.64 | H79: =G79/(1+'Assumptions and Catalog'!$C$7)^A79 -> -2482.4 | I79: =I78+G79 -> -275794.64 | J79: =J78+H79 -> -275546.4 | K79: =IF(A79<='Assumptions and Catalog'!$C$6,SUMIFS($O$661:$O$900,$A$661:$A$900,A79)-(E$70+IF(AND('Assumptions and Catalog'!$C$19>0,A79='Assumptions and Catalog'!$C$19),E$61*'Assumptions and Catalog'!$C$20,0)+IF(AND('Assumptions and Catalog'!$C$21>0,A79='Assumptions and Catalog'!$C$21),E$62*'Assumptions and Catalog'!$C$22,0))*(1+'Assumptions and Catalog'!$C$9)^(A79-1),0) -> 48073.45 | L79: =K79/(1+'Assumptions and Catalog'!$C$7)^A79 -> 43703.136 | M79: =M78+K79 -> -367990.55 | N79: =N78+L79 -> -372360.86 | P79: =IF(AND(A79<='Assumptions and Catalog'!$C$6,E79>=0,E78<0,C79>0),A79-1-E78/C79,999) -> 999 | Q79: =IF(AND(A79<='Assumptions and Catalog'!$C$6,F79>=0,F78<0,D79>0),A79-1-F78/D79,999) -> 999 | R79: =IF(AND(A79<='Assumptions and Catalog'!$C$6,I79>=0,I78<0,G79>0),A79-1-I78/G79,999) -> 999 | S79: =IF(AND(A79<='Assumptions and Catalog'!$C$6,J79>=0,J78<0,H79>0),A79-1-J78/H79,999) -> 999 | T79: =IF(AND(A79<='Assumptions and Catalog'!$C$6,M79>=0,M78<0,K79>0),A79-1-M78/K79,999) -> 999 | U79: =IF(AND(A79<='Assumptions and Catalog'!$C$6,N79>=0,N78<0,L79>0),A79-1-N78/L79,999) -> 999 | W79: Conditional 10-year NPV | X79: EGP | Y79: -183507.92 | Z79: -183099.38 | AA79: -147231.17 | AB79: -117062.26 | AC79: -180958.32 | AD79: -420553.43 | AE79: -547528.58 | AF79: -641015.69
A80: 2 | B80: =IF(A80<='Assumptions and Catalog'!$C$6,SUMIFS($M$161:$M$400,$A$161:$A$400,A80),0) -> 83772.084 | C80: =IF(A80<='Assumptions and Catalog'!$C$6,SUMIFS($O$161:$O$400,$A$161:$A$400,A80)-(C$70+IF(AND('Assumptions and Catalog'!$C$19>0,A80='Assumptions and Catalog'!$C$19),C$61*'Assumptions and Catalog'!$C$20,0)+IF(AND('Assumptions and Catalog'!$C$21>0,A80='Assumptions and Catalog'!$C$21),C$62*'Assumptions and Catalog'!$C$22,0))*(1+'Assumptions and Catalog'!$C$9)^(A80-1),0) -> 39587.166 | D80: =C80/(1+'Assumptions and Catalog'!$C$7)^A80 -> 32716.666 | E80: =E79+C80 -> -64329.989 | F80: =F79+D80 -> -74793.474 | G80: =IF(A80<='Assumptions and Catalog'!$C$6,SUMIFS($O$411:$O$650,$A$411:$A$650,A80)-(D$70+IF(AND('Assumptions and Catalog'!$C$19>0,A80='Assumptions and Catalog'!$C$19),D$61*'Assumptions and Catalog'!$C$20,0)+IF(AND('Assumptions and Catalog'!$C$21>0,A80='Assumptions and Catalog'!$C$21),D$62*'Assumptions and Catalog'!$C$22,0))*(1+'Assumptions and Catalog'!$C$9)^(A80-1),0) -> -2730.64 | H80: =G80/(1+'Assumptions and Catalog'!$C$7)^A80 -> -2256.7273 | I80: =I79+G80 -> -278525.28 | J80: =J79+H80 -> -277803.13 | K80: =IF(A80<='Assumptions and Catalog'!$C$6,SUMIFS($O$661:$O$900,$A$661:$A$900,A80)-(E$70+IF(AND('Assumptions and Catalog'!$C$19>0,A80='Assumptions and Catalog'!$C$19),E$61*'Assumptions and Catalog'!$C$20,0)+IF(AND('Assumptions and Catalog'!$C$21>0,A80='Assumptions and Catalog'!$C$21),E$62*'Assumptions and Catalog'!$C$22,0))*(1+'Assumptions and Catalog'!$C$9)^(A80-1),0) -> 48003.77 | L80: =K80/(1+'Assumptions and Catalog'!$C$7)^A80 -> 39672.537 | M80: =M79+K80 -> -319986.78 | N80: =N79+L80 -> -332688.33 | P80: =IF(AND(A80<='Assumptions and Catalog'!$C$6,E80>=0,E79<0,C80>0),A80-1-E79/C80,999) -> 999 | Q80: =IF(AND(A80<='Assumptions and Catalog'!$C$6,F80>=0,F79<0,D80>0),A80-1-F79/D80,999) -> 999 | R80: =IF(AND(A80<='Assumptions and Catalog'!$C$6,I80>=0,I79<0,G80>0),A80-1-I79/G80,999) -> 999 | S80: =IF(AND(A80<='Assumptions and Catalog'!$C$6,J80>=0,J79<0,H80>0),A80-1-J79/H80,999) -> 999 | T80: =IF(AND(A80<='Assumptions and Catalog'!$C$6,M80>=0,M79<0,K80>0),A80-1-M79/K80,999) -> 999 | U80: =IF(AND(A80<='Assumptions and Catalog'!$C$6,N80>=0,N79<0,L80>0),A80-1-N79/L80,999) -> 999 | W80: Conditional simple payback | X80: years | Y80: Not reached | Z80: Not reached | AA80: Not reached | AB80: Not reached | AC80: Not reached | AD80: Not reached | AE80: Not reached | AF80: Not reached | AH80: Critical-load overload | AK80: PASS: backup hours blocked by inverter power
A81: 3 | B81: =IF(A81<='Assumptions and Catalog'!$C$6,SUMIFS($M$161:$M$400,$A$161:$A$400,A81),0) -> 83544.51 | C81: =IF(A81<='Assumptions and Catalog'!$C$6,SUMIFS($O$161:$O$400,$A$161:$A$400,A81)-(C$70+IF(AND('Assumptions and Catalog'!$C$19>0,A81='Assumptions and Catalog'!$C$19),C$61*'Assumptions and Catalog'!$C$20,0)+IF(AND('Assumptions and Catalog'!$C$21>0,A81='Assumptions and Catalog'!$C$21),C$62*'Assumptions and Catalog'!$C$22,0))*(1+'Assumptions and Catalog'!$C$9)^(A81-1),0) -> 39418.51 | D81: =C81/(1+'Assumptions and Catalog'!$C$7)^A81 -> 29615.71 | E81: =E80+C81 -> -24911.478 | F81: =F80+D81 -> -45177.764 | G81: =IF(A81<='Assumptions and Catalog'!$C$6,SUMIFS($O$411:$O$650,$A$411:$A$650,A81)-(D$70+IF(AND('Assumptions and Catalog'!$C$19>0,A81='Assumptions and Catalog'!$C$19),D$61*'Assumptions and Catalog'!$C$20,0)+IF(AND('Assumptions and Catalog'!$C$21>0,A81='Assumptions and Catalog'!$C$21),D$62*'Assumptions and Catalog'!$C$22,0))*(1+'Assumptions and Catalog'!$C$9)^(A81-1),0) -> -2730.64 | H81: =G81/(1+'Assumptions and Catalog'!$C$7)^A81 -> -2051.5702 | I81: =I80+G81 -> -281255.92 | J81: =J80+H81 -> -279854.7 | K81: =IF(A81<='Assumptions and Catalog'!$C$6,SUMIFS($O$661:$O$900,$A$661:$A$900,A81)-(E$70+IF(AND('Assumptions and Catalog'!$C$19>0,A81='Assumptions and Catalog'!$C$19),E$61*'Assumptions and Catalog'!$C$20,0)+IF(AND('Assumptions and Catalog'!$C$21>0,A81='Assumptions and Catalog'!$C$21),E$62*'Assumptions and Catalog'!$C$22,0))*(1+'Assumptions and Catalog'!$C$9)^(A81-1),0) -> 47651.385 | L81: =K81/(1+'Assumptions and Catalog'!$C$7)^A81 -> 35801.191 | M81: =M80+K81 -> -272335.4 | N81: =N80+L81 -> -296887.14 | P81: =IF(AND(A81<='Assumptions and Catalog'!$C$6,E81>=0,E80<0,C81>0),A81-1-E80/C81,999) -> 999 | Q81: =IF(AND(A81<='Assumptions and Catalog'!$C$6,F81>=0,F80<0,D81>0),A81-1-F80/D81,999) -> 999 | R81: =IF(AND(A81<='Assumptions and Catalog'!$C$6,I81>=0,I80<0,G81>0),A81-1-I80/G81,999) -> 999 | S81: =IF(AND(A81<='Assumptions and Catalog'!$C$6,J81>=0,J80<0,H81>0),A81-1-J80/H81,999) -> 999 | T81: =IF(AND(A81<='Assumptions and Catalog'!$C$6,M81>=0,M80<0,K81>0),A81-1-M80/K81,999) -> 999 | U81: =IF(AND(A81<='Assumptions and Catalog'!$C$6,N81>=0,N80<0,L81>0),A81-1-N80/L81,999) -> 999 | W81: Conditional discounted payback | X81: years | Y81: Not reached | Z81: Not reached | AA81: Not reached | AB81: Not reached | AC81: Not reached | AD81: Not reached | AE81: Not reached | AF81: Not reached
A82: 4 | B82: =IF(A82<='Assumptions and Catalog'!$C$6,SUMIFS($M$161:$M$400,$A$161:$A$400,A82),0) -> 83544.51 | C82: =IF(A82<='Assumptions and Catalog'!$C$6,SUMIFS($O$161:$O$400,$A$161:$A$400,A82)-(C$70+IF(AND('Assumptions and Catalog'!$C$19>0,A82='Assumptions and Catalog'!$C$19),C$61*'Assumptions and Catalog'!$C$20,0)+IF(AND('Assumptions and Catalog'!$C$21>0,A82='Assumptions and Catalog'!$C$21),C$62*'Assumptions and Catalog'!$C$22,0))*(1+'Assumptions and Catalog'!$C$9)^(A82-1),0) -> 39353.635 | D82: =C82/(1+'Assumptions and Catalog'!$C$7)^A82 -> 26879.062 | E82: =E81+C82 -> 14442.157 | F82: =F81+D82 -> -18298.702 | G82: =IF(A82<='Assumptions and Catalog'!$C$6,SUMIFS($O$411:$O$650,$A$411:$A$650,A82)-(D$70+IF(AND('Assumptions and Catalog'!$C$19>0,A82='Assumptions and Catalog'!$C$19),D$61*'Assumptions and Catalog'!$C$20,0)+IF(AND('Assumptions and Catalog'!$C$21>0,A82='Assumptions and Catalog'!$C$21),D$62*'Assumptions and Catalog'!$C$22,0))*(1+'Assumptions and Catalog'!$C$9)^(A82-1),0) -> -2730.64 | H82: =G82/(1+'Assumptions and Catalog'!$C$7)^A82 -> -1865.0639 | I82: =I81+G82 -> -283986.56 | J82: =J81+H82 -> -281719.76 | K82: =IF(A82<='Assumptions and Catalog'!$C$6,SUMIFS($O$661:$O$900,$A$661:$A$900,A82)-(E$70+IF(AND('Assumptions and Catalog'!$C$19>0,A82='Assumptions and Catalog'!$C$19),E$61*'Assumptions and Catalog'!$C$20,0)+IF(AND('Assumptions and Catalog'!$C$21>0,A82='Assumptions and Catalog'!$C$21),E$62*'Assumptions and Catalog'!$C$22,0))*(1+'Assumptions and Catalog'!$C$9)^(A82-1),0) -> 47444.838 | L82: =K82/(1+'Assumptions and Catalog'!$C$7)^A82 -> 32405.463 | M82: =M81+K82 -> -224890.56 | N82: =N81+L82 -> -264481.67 | P82: =IF(AND(A82<='Assumptions and Catalog'!$C$6,E82>=0,E81<0,C82>0),A82-1-E81/C82,999) -> 3.6330159 | Q82: =IF(AND(A82<='Assumptions and Catalog'!$C$6,F82>=0,F81<0,D82>0),A82-1-F81/D82,999) -> 999 | R82: =IF(AND(A82<='Assumptions and Catalog'!$C$6,I82>=0,I81<0,G82>0),A82-1-I81/G82,999) -> 999 | S82: =IF(AND(A82<='Assumptions and Catalog'!$C$6,J82>=0,J81<0,H82>0),A82-1-J81/H82,999) -> 999 | T82: =IF(AND(A82<='Assumptions and Catalog'!$C$6,M82>=0,M81<0,K82>0),A82-1-M81/K82,999) -> 999 | U82: =IF(AND(A82<='Assumptions and Catalog'!$C$6,N82>=0,N81<0,L82>0),A82-1-N81/L82,999) -> 999 | W82: Conditional diagnostics are arithmetic only: they do not override roof failures, verify equipment, or include the missing TOU/peak benefits in Scenarios 6-8.
A83: 5 | B83: =IF(A83<='Assumptions and Catalog'!$C$6,SUMIFS($M$161:$M$400,$A$161:$A$400,A83),0) -> 83544.51 | C83: =IF(A83<='Assumptions and Catalog'!$C$6,SUMIFS($O$161:$O$400,$A$161:$A$400,A83)-(C$70+IF(AND('Assumptions and Catalog'!$C$19>0,A83='Assumptions and Catalog'!$C$19),C$61*'Assumptions and Catalog'!$C$20,0)+IF(AND('Assumptions and Catalog'!$C$21>0,A83='Assumptions and Catalog'!$C$21),C$62*'Assumptions and Catalog'!$C$22,0))*(1+'Assumptions and Catalog'!$C$9)^(A83-1),0) -> 39289.084 | D83: =C83/(1+'Assumptions and Catalog'!$C$7)^A83 -> 24395.43 | E83: =E82+C83 -> 53731.24 | F83: =F82+D83 -> 6096.7278 | G83: =IF(A83<='Assumptions and Catalog'!$C$6,SUMIFS($O$411:$O$650,$A$411:$A$650,A83)-(D$70+IF(AND('Assumptions and Catalog'!$C$19>0,A83='Assumptions and Catalog'!$C$19),D$61*'Assumptions and Catalog'!$C$20,0)+IF(AND('Assumptions and Catalog'!$C$21>0,A83='Assumptions and Catalog'!$C$21),D$62*'Assumptions and Catalog'!$C$22,0))*(1+'Assumptions and Catalog'!$C$9)^(A83-1),0) -> -2730.64 | H83: =G83/(1+'Assumptions and Catalog'!$C$7)^A83 -> -1695.5126 | I83: =I82+G83 -> -286717.2 | J83: =J82+H83 -> -283415.27 | K83: =IF(A83<='Assumptions and Catalog'!$C$6,SUMIFS($O$661:$O$900,$A$661:$A$900,A83)-(E$70+IF(AND('Assumptions and Catalog'!$C$19>0,A83='Assumptions and Catalog'!$C$19),E$61*'Assumptions and Catalog'!$C$20,0)+IF(AND('Assumptions and Catalog'!$C$21>0,A83='Assumptions and Catalog'!$C$21),E$62*'Assumptions and Catalog'!$C$22,0))*(1+'Assumptions and Catalog'!$C$9)^(A83-1),0) -> 47241.275 | L83: =K83/(1+'Assumptions and Catalog'!$C$7)^A83 -> 29333.115 | M83: =M82+K83 -> -177649.28 | N83: =N82+L83 -> -235148.56 | P83: =IF(AND(A83<='Assumptions and Catalog'!$C$6,E83>=0,E82<0,C83>0),A83-1-E82/C83,999) -> 999 | Q83: =IF(AND(A83<='Assumptions and Catalog'!$C$6,F83>=0,F82<0,D83>0),A83-1-F82/D83,999) -> 4.7500873 | R83: =IF(AND(A83<='Assumptions and Catalog'!$C$6,I83>=0,I82<0,G83>0),A83-1-I82/G83,999) -> 999 | S83: =IF(AND(A83<='Assumptions and Catalog'!$C$6,J83>=0,J82<0,H83>0),A83-1-J82/H83,999) -> 999 | T83: =IF(AND(A83<='Assumptions and Catalog'!$C$6,M83>=0,M82<0,K83>0),A83-1-M82/K83,999) -> 999 | U83: =IF(AND(A83<='Assumptions and Catalog'!$C$6,N83>=0,N82<0,L83>0),A83-1-N82/L83,999) -> 999 | W83: Verification and limitations | AH83: Run reproduction: apply the recorded Inputs settings, equipment quantities and temporary catalog prices/ratings. Use the recorded BOS fraction. Recalculate and compare to the independent-check rows before replacing snapshot values. Restore original settings afterwards.
A84: 6 | B84: =IF(A84<='Assumptions and Catalog'!$C$6,SUMIFS($M$161:$M$400,$A$161:$A$400,A84),0) -> 83772.084 | C84: =IF(A84<='Assumptions and Catalog'!$C$6,SUMIFS($O$161:$O$400,$A$161:$A$400,A84)-(C$70+IF(AND('Assumptions and Catalog'!$C$19>0,A84='Assumptions and Catalog'!$C$19),C$61*'Assumptions and Catalog'!$C$20,0)+IF(AND('Assumptions and Catalog'!$C$21>0,A84='Assumptions and Catalog'!$C$21),C$62*'Assumptions and Catalog'!$C$22,0))*(1+'Assumptions and Catalog'!$C$9)^(A84-1),0) -> 39336.745 | D84: =C84/(1+'Assumptions and Catalog'!$C$7)^A84 -> 22204.567 | E84: =E83+C84 -> 93067.986 | F84: =F83+D84 -> 28301.295 | G84: =IF(A84<='Assumptions and Catalog'!$C$6,SUMIFS($O$411:$O$650,$A$411:$A$650,A84)-(D$70+IF(AND('Assumptions and Catalog'!$C$19>0,A84='Assumptions and Catalog'!$C$19),D$61*'Assumptions and Catalog'!$C$20,0)+IF(AND('Assumptions and Catalog'!$C$21>0,A84='Assumptions and Catalog'!$C$21),D$62*'Assumptions and Catalog'!$C$22,0))*(1+'Assumptions and Catalog'!$C$9)^(A84-1),0) -> -2730.64 | H84: =G84/(1+'Assumptions and Catalog'!$C$7)^A84 -> -1541.3751 | I84: =I83+G84 -> -289447.84 | J84: =J83+H84 -> -284956.65 | K84: =IF(A84<='Assumptions and Catalog'!$C$6,SUMIFS($O$661:$O$900,$A$661:$A$900,A84)-(E$70+IF(AND('Assumptions and Catalog'!$C$19>0,A84='Assumptions and Catalog'!$C$19),E$61*'Assumptions and Catalog'!$C$20,0)+IF(AND('Assumptions and Catalog'!$C$21>0,A84='Assumptions and Catalog'!$C$21),E$62*'Assumptions and Catalog'!$C$22,0))*(1+'Assumptions and Catalog'!$C$9)^(A84-1),0) -> 47180.797 | L84: =K84/(1+'Assumptions and Catalog'!$C$7)^A84 -> 26632.33 | M84: =M83+K84 -> -130468.49 | N84: =N83+L84 -> -208516.23 | P84: =IF(AND(A84<='Assumptions and Catalog'!$C$6,E84>=0,E83<0,C84>0),A84-1-E83/C84,999) -> 999 | Q84: =IF(AND(A84<='Assumptions and Catalog'!$C$6,F84>=0,F83<0,D84>0),A84-1-F83/D84,999) -> 999 | R84: =IF(AND(A84<='Assumptions and Catalog'!$C$6,I84>=0,I83<0,G84>0),A84-1-I83/G84,999) -> 999 | S84: =IF(AND(A84<='Assumptions and Catalog'!$C$6,J84>=0,J83<0,H84>0),A84-1-J83/H84,999) -> 999 | T84: =IF(AND(A84<='Assumptions and Catalog'!$C$6,M84>=0,M83<0,K84>0),A84-1-M83/K84,999) -> 999 | U84: =IF(AND(A84<='Assumptions and Catalog'!$C$6,N84>=0,N83<0,L84>0),A84-1-N83/L84,999) -> 999 | W84: Independent comparison checks | X84: count | Y84: 2920 | Z84: 2920 | AA84: 2920 | AB84: 2920 | AC84: 2920 | AD84: 2920 | AE84: 2920 | AF84: 2920
A85: 7 | B85: =IF(A85<='Assumptions and Catalog'!$C$6,SUMIFS($M$161:$M$400,$A$161:$A$400,A85),0) -> 83544.51 | C85: =IF(A85<='Assumptions and Catalog'!$C$6,SUMIFS($O$161:$O$400,$A$161:$A$400,A85)-(C$70+IF(AND('Assumptions and Catalog'!$C$19>0,A85='Assumptions and Catalog'!$C$19),C$61*'Assumptions and Catalog'!$C$20,0)+IF(AND('Assumptions and Catalog'!$C$21>0,A85='Assumptions and Catalog'!$C$21),C$62*'Assumptions and Catalog'!$C$22,0))*(1+'Assumptions and Catalog'!$C$9)^(A85-1),0) -> 39160.948 | D85: =C85/(1+'Assumptions and Catalog'!$C$7)^A85 -> 20095.758 | E85: =E84+C85 -> 132228.93 | F85: =F84+D85 -> 48397.054 | G85: =IF(A85<='Assumptions and Catalog'!$C$6,SUMIFS($O$411:$O$650,$A$411:$A$650,A85)-(D$70+IF(AND('Assumptions and Catalog'!$C$19>0,A85='Assumptions and Catalog'!$C$19),D$61*'Assumptions and Catalog'!$C$20,0)+IF(AND('Assumptions and Catalog'!$C$21>0,A85='Assumptions and Catalog'!$C$21),D$62*'Assumptions and Catalog'!$C$22,0))*(1+'Assumptions and Catalog'!$C$9)^(A85-1),0) -> -2730.64 | H85: =G85/(1+'Assumptions and Catalog'!$C$7)^A85 -> -1401.2501 | I85: =I84+G85 -> -292178.48 | J85: =J84+H85 -> -286357.9 | K85: =IF(A85<='Assumptions and Catalog'!$C$6,SUMIFS($O$661:$O$900,$A$661:$A$900,A85)-(E$70+IF(AND('Assumptions and Catalog'!$C$19>0,A85='Assumptions and Catalog'!$C$19),E$61*'Assumptions and Catalog'!$C$20,0)+IF(AND('Assumptions and Catalog'!$C$21>0,A85='Assumptions and Catalog'!$C$21),E$62*'Assumptions and Catalog'!$C$22,0))*(1+'Assumptions and Catalog'!$C$9)^(A85-1),0) -> 46842.891 | L85: =K85/(1+'Assumptions and Catalog'!$C$7)^A85 -> 24037.81 | M85: =M84+K85 -> -83625.595 | N85: =N84+L85 -> -184478.42 | P85: =IF(AND(A85<='Assumptions and Catalog'!$C$6,E85>=0,E84<0,C85>0),A85-1-E84/C85,999) -> 999 | Q85: =IF(AND(A85<='Assumptions and Catalog'!$C$6,F85>=0,F84<0,D85>0),A85-1-F84/D85,999) -> 999 | R85: =IF(AND(A85<='Assumptions and Catalog'!$C$6,I85>=0,I84<0,G85>0),A85-1-I84/G85,999) -> 999 | S85: =IF(AND(A85<='Assumptions and Catalog'!$C$6,J85>=0,J84<0,H85>0),A85-1-J84/H85,999) -> 999 | T85: =IF(AND(A85<='Assumptions and Catalog'!$C$6,M85>=0,M84<0,K85>0),A85-1-M84/K85,999) -> 999 | U85: =IF(AND(A85<='Assumptions and Catalog'!$C$6,N85>=0,N84<0,L85>0),A85-1-N84/L85,999) -> 999 | W85: Largest numeric difference | X85: mixed units | Y85: 4.3655746e-10 | Z85: 4.3655746e-10 | AA85: 2.910383e-11 | AB85: 8.7311491e-11 | AC85: 1.1641532e-10 | AD85: 6.3664629e-12 | AE85: 1.1641532e-10 | AF85: 6.3664629e-12
A86: 8 | B86: =IF(A86<='Assumptions and Catalog'!$C$6,SUMIFS($M$161:$M$400,$A$161:$A$400,A86),0) -> 83544.51 | C86: =IF(A86<='Assumptions and Catalog'!$C$6,SUMIFS($O$161:$O$400,$A$161:$A$400,A86)-(C$70+IF(AND('Assumptions and Catalog'!$C$19>0,A86='Assumptions and Catalog'!$C$19),C$61*'Assumptions and Catalog'!$C$20,0)+IF(AND('Assumptions and Catalog'!$C$21>0,A86='Assumptions and Catalog'!$C$21),C$62*'Assumptions and Catalog'!$C$22,0))*(1+'Assumptions and Catalog'!$C$9)^(A86-1),0) -> 39097.361 | D86: =C86/(1+'Assumptions and Catalog'!$C$7)^A86 -> 18239.207 | E86: =E85+C86 -> 171326.29 | F86: =F85+D86 -> 66636.261 | G86: =IF(A86<='Assumptions and Catalog'!$C$6,SUMIFS($O$411:$O$650,$A$411:$A$650,A86)-(D$70+IF(AND('Assumptions and Catalog'!$C$19>0,A86='Assumptions and Catalog'!$C$19),D$61*'Assumptions and Catalog'!$C$20,0)+IF(AND('Assumptions and Catalog'!$C$21>0,A86='Assumptions and Catalog'!$C$21),D$62*'Assumptions and Catalog'!$C$22,0))*(1+'Assumptions and Catalog'!$C$9)^(A86-1),0) -> -2730.64 | H86: =G86/(1+'Assumptions and Catalog'!$C$7)^A86 -> -1273.8637 | I86: =I85+G86 -> -294909.12 | J86: =J85+H86 -> -287631.76 | K86: =IF(A86<='Assumptions and Catalog'!$C$6,SUMIFS($O$661:$O$900,$A$661:$A$900,A86)-(E$70+IF(AND('Assumptions and Catalog'!$C$19>0,A86='Assumptions and Catalog'!$C$19),E$61*'Assumptions and Catalog'!$C$20,0)+IF(AND('Assumptions and Catalog'!$C$21>0,A86='Assumptions and Catalog'!$C$21),E$62*'Assumptions and Catalog'!$C$22,0))*(1+'Assumptions and Catalog'!$C$9)^(A86-1),0) -> 46647.963 | L86: =K86/(1+'Assumptions and Catalog'!$C$7)^A86 -> 21761.619 | M86: =M85+K86 -> -36977.631 | N86: =N85+L86 -> -162716.8 | P86: =IF(AND(A86<='Assumptions and Catalog'!$C$6,E86>=0,E85<0,C86>0),A86-1-E85/C86,999) -> 999 | Q86: =IF(AND(A86<='Assumptions and Catalog'!$C$6,F86>=0,F85<0,D86>0),A86-1-F85/D86,999) -> 999 | R86: =IF(AND(A86<='Assumptions and Catalog'!$C$6,I86>=0,I85<0,G86>0),A86-1-I85/G86,999) -> 999 | S86: =IF(AND(A86<='Assumptions and Catalog'!$C$6,J86>=0,J85<0,H86>0),A86-1-J85/H86,999) -> 999 | T86: =IF(AND(A86<='Assumptions and Catalog'!$C$6,M86>=0,M85<0,K86>0),A86-1-M85/K86,999) -> 999 | U86: =IF(AND(A86<='Assumptions and Catalog'!$C$6,N86>=0,N85<0,L86>0),A86-1-N85/L86,999) -> 999 | W86: Native formula errors | X86: count | Y86: 0 | Z86: 0 | AA86: 0 | AB86: 0 | AC86: 0 | AD86: 0 | AE86: 0 | AF86: 0
A87: 9 | B87: =IF(A87<='Assumptions and Catalog'!$C$6,SUMIFS($M$161:$M$400,$A$161:$A$400,A87),0) -> 83544.51 | C87: =IF(A87<='Assumptions and Catalog'!$C$6,SUMIFS($O$161:$O$400,$A$161:$A$400,A87)-(C$70+IF(AND('Assumptions and Catalog'!$C$19>0,A87='Assumptions and Catalog'!$C$19),C$61*'Assumptions and Catalog'!$C$20,0)+IF(AND('Assumptions and Catalog'!$C$21>0,A87='Assumptions and Catalog'!$C$21),C$62*'Assumptions and Catalog'!$C$22,0))*(1+'Assumptions and Catalog'!$C$9)^(A87-1),0) -> 39034.091 | D87: =C87/(1+'Assumptions and Catalog'!$C$7)^A87 -> 16554.265 | E87: =E86+C87 -> 210360.39 | F87: =F86+D87 -> 83190.526 | G87: =IF(A87<='Assumptions and Catalog'!$C$6,SUMIFS($O$411:$O$650,$A$411:$A$650,A87)-(D$70+IF(AND('Assumptions and Catalog'!$C$19>0,A87='Assumptions and Catalog'!$C$19),D$61*'Assumptions and Catalog'!$C$20,0)+IF(AND('Assumptions and Catalog'!$C$21>0,A87='Assumptions and Catalog'!$C$21),D$62*'Assumptions and Catalog'!$C$22,0))*(1+'Assumptions and Catalog'!$C$9)^(A87-1),0) -> -2730.64 | H87: =G87/(1+'Assumptions and Catalog'!$C$7)^A87 -> -1158.0579 | I87: =I86+G87 -> -297639.76 | J87: =J86+H87 -> -288789.82 | K87: =IF(A87<='Assumptions and Catalog'!$C$6,SUMIFS($O$661:$O$900,$A$661:$A$900,A87)-(E$70+IF(AND('Assumptions and Catalog'!$C$19>0,A87='Assumptions and Catalog'!$C$19),E$61*'Assumptions and Catalog'!$C$20,0)+IF(AND('Assumptions and Catalog'!$C$21>0,A87='Assumptions and Catalog'!$C$21),E$62*'Assumptions and Catalog'!$C$22,0))*(1+'Assumptions and Catalog'!$C$9)^(A87-1),0) -> 46455.811 | L87: =K87/(1+'Assumptions and Catalog'!$C$7)^A87 -> 19701.799 | M87: =M86+K87 -> 9478.18 | N87: =N86+L87 -> -143015 | P87: =IF(AND(A87<='Assumptions and Catalog'!$C$6,E87>=0,E86<0,C87>0),A87-1-E86/C87,999) -> 999 | Q87: =IF(AND(A87<='Assumptions and Catalog'!$C$6,F87>=0,F86<0,D87>0),A87-1-F86/D87,999) -> 999 | R87: =IF(AND(A87<='Assumptions and Catalog'!$C$6,I87>=0,I86<0,G87>0),A87-1-I86/G87,999) -> 999 | S87: =IF(AND(A87<='Assumptions and Catalog'!$C$6,J87>=0,J86<0,H87>0),A87-1-J86/H87,999) -> 999 | T87: =IF(AND(A87<='Assumptions and Catalog'!$C$6,M87>=0,M86<0,K87>0),A87-1-M86/K87,999) -> 8.7959743 | U87: =IF(AND(A87<='Assumptions and Catalog'!$C$6,N87>=0,N86<0,L87>0),A87-1-N86/L87,999) -> 999 | W87: Roof validation | Y87: Roof fit not verified | Z87: Roof fit not verified | AA87: Exceeds available area | AB87: Exceeds available area | AC87: Exceeds available area | AD87: Exceeds available area | AE87: Exceeds available area | AF87: Exceeds available area
A88: 10 | B88: =IF(A88<='Assumptions and Catalog'!$C$6,SUMIFS($M$161:$M$400,$A$161:$A$400,A88),0) -> 83772.084 | C88: =IF(A88<='Assumptions and Catalog'!$C$6,SUMIFS($O$161:$O$400,$A$161:$A$400,A88)-(C$70+IF(AND('Assumptions and Catalog'!$C$19>0,A88='Assumptions and Catalog'!$C$19),C$61*'Assumptions and Catalog'!$C$20,0)+IF(AND('Assumptions and Catalog'!$C$21>0,A88='Assumptions and Catalog'!$C$21),C$62*'Assumptions and Catalog'!$C$22,0))*(1+'Assumptions and Catalog'!$C$9)^(A88-1),0) -> 39080.806 | D88: =C88/(1+'Assumptions and Catalog'!$C$7)^A88 -> 15067.343 | E88: =E87+C88 -> 249441.19 | F88: =F87+D88 -> 98257.868 | G88: =IF(A88<='Assumptions and Catalog'!$C$6,SUMIFS($O$411:$O$650,$A$411:$A$650,A88)-(D$70+IF(AND('Assumptions and Catalog'!$C$19>0,A88='Assumptions and Catalog'!$C$19),D$61*'Assumptions and Catalog'!$C$20,0)+IF(AND('Assumptions and Catalog'!$C$21>0,A88='Assumptions and Catalog'!$C$21),D$62*'Assumptions and Catalog'!$C$22,0))*(1+'Assumptions and Catalog'!$C$9)^(A88-1),0) -> -2730.64 | H88: =G88/(1+'Assumptions and Catalog'!$C$7)^A88 -> -1052.7799 | I88: =I87+G88 -> -300370.4 | J88: =J87+H88 -> -289842.6 | K88: =IF(A88<='Assumptions and Catalog'!$C$6,SUMIFS($O$661:$O$900,$A$661:$A$900,A88)-(E$70+IF(AND('Assumptions and Catalog'!$C$19>0,A88='Assumptions and Catalog'!$C$19),E$61*'Assumptions and Catalog'!$C$20,0)+IF(AND('Assumptions and Catalog'!$C$21>0,A88='Assumptions and Catalog'!$C$21),E$62*'Assumptions and Catalog'!$C$22,0))*(1+'Assumptions and Catalog'!$C$9)^(A88-1),0) -> 46403.945 | L88: =K88/(1+'Assumptions and Catalog'!$C$7)^A88 -> 17890.73 | M88: =M87+K88 -> 55882.125 | N88: =N87+L88 -> -125124.27 | P88: =IF(AND(A88<='Assumptions and Catalog'!$C$6,E88>=0,E87<0,C88>0),A88-1-E87/C88,999) -> 999 | Q88: =IF(AND(A88<='Assumptions and Catalog'!$C$6,F88>=0,F87<0,D88>0),A88-1-F87/D88,999) -> 999 | R88: =IF(AND(A88<='Assumptions and Catalog'!$C$6,I88>=0,I87<0,G88>0),A88-1-I87/G88,999) -> 999 | S88: =IF(AND(A88<='Assumptions and Catalog'!$C$6,J88>=0,J87<0,H88>0),A88-1-J87/H88,999) -> 999 | T88: =IF(AND(A88<='Assumptions and Catalog'!$C$6,M88>=0,M87<0,K88>0),A88-1-M87/K88,999) -> 999 | U88: =IF(AND(A88<='Assumptions and Catalog'!$C$6,N88>=0,N87<0,L88>0),A88-1-N87/L88,999) -> 999 | W88: Maximum monthly energy residual | X88: kWh | Y88: 0 | Z88: 0 | AA88: 0 | AB88: 0 | AC88: 3.6948222e-13 | AD88: 0 | AE88: 3.6948222e-13 | AF88: 0 | AH88: No outage schedule is available. Backup mode therefore includes no outage-cycle energy or recharging cost; zero auxiliary consumption is the existing assumption. Zero modeled battery-only bill savings is not a prediction of zero real-life standby losses.
A89: 11 | B89: =IF(A89<='Assumptions and Catalog'!$C$6,SUMIFS($M$161:$M$400,$A$161:$A$400,A89),0) -> 0 | C89: =IF(A89<='Assumptions and Catalog'!$C$6,SUMIFS($O$161:$O$400,$A$161:$A$400,A89)-(C$70+IF(AND('Assumptions and Catalog'!$C$19>0,A89='Assumptions and Catalog'!$C$19),C$61*'Assumptions and Catalog'!$C$20,0)+IF(AND('Assumptions and Catalog'!$C$21>0,A89='Assumptions and Catalog'!$C$21),C$62*'Assumptions and Catalog'!$C$22,0))*(1+'Assumptions and Catalog'!$C$9)^(A89-1),0) -> 0 | D89: =C89/(1+'Assumptions and Catalog'!$C$7)^A89 -> 0 | E89: =E88+C89 -> 249441.19 | F89: =F88+D89 -> 98257.868 | G89: =IF(A89<='Assumptions and Catalog'!$C$6,SUMIFS($O$411:$O$650,$A$411:$A$650,A89)-(D$70+IF(AND('Assumptions and Catalog'!$C$19>0,A89='Assumptions and Catalog'!$C$19),D$61*'Assumptions and Catalog'!$C$20,0)+IF(AND('Assumptions and Catalog'!$C$21>0,A89='Assumptions and Catalog'!$C$21),D$62*'Assumptions and Catalog'!$C$22,0))*(1+'Assumptions and Catalog'!$C$9)^(A89-1),0) -> 0 | H89: =G89/(1+'Assumptions and Catalog'!$C$7)^A89 -> 0 | I89: =I88+G89 -> -300370.4 | J89: =J88+H89 -> -289842.6 | K89: =IF(A89<='Assumptions and Catalog'!$C$6,SUMIFS($O$661:$O$900,$A$661:$A$900,A89)-(E$70+IF(AND('Assumptions and Catalog'!$C$19>0,A89='Assumptions and Catalog'!$C$19),E$61*'Assumptions and Catalog'!$C$20,0)+IF(AND('Assumptions and Catalog'!$C$21>0,A89='Assumptions and Catalog'!$C$21),E$62*'Assumptions and Catalog'!$C$22,0))*(1+'Assumptions and Catalog'!$C$9)^(A89-1),0) -> 0 | L89: =K89/(1+'Assumptions and Catalog'!$C$7)^A89 -> 0 | M89: =M88+K89 -> 55882.125 | N89: =N88+L89 -> -125124.27 | P89: =IF(AND(A89<='Assumptions and Catalog'!$C$6,E89>=0,E88<0,C89>0),A89-1-E88/C89,999) -> 999 | Q89: =IF(AND(A89<='Assumptions and Catalog'!$C$6,F89>=0,F88<0,D89>0),A89-1-F88/D89,999) -> 999 | R89: =IF(AND(A89<='Assumptions and Catalog'!$C$6,I89>=0,I88<0,G89>0),A89-1-I88/G89,999) -> 999 | S89: =IF(AND(A89<='Assumptions and Catalog'!$C$6,J89>=0,J88<0,H89>0),A89-1-J88/H89,999) -> 999 | T89: =IF(AND(A89<='Assumptions and Catalog'!$C$6,M89>=0,M88<0,K89>0),A89-1-M88/K89,999) -> 999 | U89: =IF(AND(A89<='Assumptions and Catalog'!$C$6,N89>=0,N88<0,L89>0),A89-1-N88/L89,999) -> 999 | W89: 4 kW critical-load power check | Y89: No backup | Z89: FAIL: 3 kW < 4 kW | AA89: FAIL: 3 kW < 4 kW | AB89: Rating sufficient; hardware unverified | AC89: Rating sufficient; hardware unverified | AD89: Rating sufficient; hardware unverified | AE89: Rating sufficient; hardware unverified | AF89: Rating sufficient; hardware unverified
A90: 12 | B90: =IF(A90<='Assumptions and Catalog'!$C$6,SUMIFS($M$161:$M$400,$A$161:$A$400,A90),0) -> 0 | C90: =IF(A90<='Assumptions and Catalog'!$C$6,SUMIFS($O$161:$O$400,$A$161:$A$400,A90)-(C$70+IF(AND('Assumptions and Catalog'!$C$19>0,A90='Assumptions and Catalog'!$C$19),C$61*'Assumptions and Catalog'!$C$20,0)+IF(AND('Assumptions and Catalog'!$C$21>0,A90='Assumptions and Catalog'!$C$21),C$62*'Assumptions and Catalog'!$C$22,0))*(1+'Assumptions and Catalog'!$C$9)^(A90-1),0) -> 0 | D90: =C90/(1+'Assumptions and Catalog'!$C$7)^A90 -> 0 | E90: =E89+C90 -> 249441.19 | F90: =F89+D90 -> 98257.868 | G90: =IF(A90<='Assumptions and Catalog'!$C$6,SUMIFS($O$411:$O$650,$A$411:$A$650,A90)-(D$70+IF(AND('Assumptions and Catalog'!$C$19>0,A90='Assumptions and Catalog'!$C$19),D$61*'Assumptions and Catalog'!$C$20,0)+IF(AND('Assumptions and Catalog'!$C$21>0,A90='Assumptions and Catalog'!$C$21),D$62*'Assumptions and Catalog'!$C$22,0))*(1+'Assumptions and Catalog'!$C$9)^(A90-1),0) -> 0 | H90: =G90/(1+'Assumptions and Catalog'!$C$7)^A90 -> 0 | I90: =I89+G90 -> -300370.4 | J90: =J89+H90 -> -289842.6 | K90: =IF(A90<='Assumptions and Catalog'!$C$6,SUMIFS($O$661:$O$900,$A$661:$A$900,A90)-(E$70+IF(AND('Assumptions and Catalog'!$C$19>0,A90='Assumptions and Catalog'!$C$19),E$61*'Assumptions and Catalog'!$C$20,0)+IF(AND('Assumptions and Catalog'!$C$21>0,A90='Assumptions and Catalog'!$C$21),E$62*'Assumptions and Catalog'!$C$22,0))*(1+'Assumptions and Catalog'!$C$9)^(A90-1),0) -> 0 | L90: =K90/(1+'Assumptions and Catalog'!$C$7)^A90 -> 0 | M90: =M89+K90 -> 55882.125 | N90: =N89+L90 -> -125124.27 | P90: =IF(AND(A90<='Assumptions and Catalog'!$C$6,E90>=0,E89<0,C90>0),A90-1-E89/C90,999) -> 999 | Q90: =IF(AND(A90<='Assumptions and Catalog'!$C$6,F90>=0,F89<0,D90>0),A90-1-F89/D90,999) -> 999 | R90: =IF(AND(A90<='Assumptions and Catalog'!$C$6,I90>=0,I89<0,G90>0),A90-1-I89/G90,999) -> 999 | S90: =IF(AND(A90<='Assumptions and Catalog'!$C$6,J90>=0,J89<0,H90>0),A90-1-J89/H90,999) -> 999 | T90: =IF(AND(A90<='Assumptions and Catalog'!$C$6,M90>=0,M89<0,K90>0),A90-1-M89/K90,999) -> 999 | U90: =IF(AND(A90<='Assumptions and Catalog'!$C$6,N90>=0,N89<0,L90>0),A90-1-N89/L90,999) -> 999 | W90: Arithmetic verification | Y90: PASS within model scope | Z90: PASS within model scope | AA90: PASS within model scope | AB90: PASS within model scope | AC90: PASS within model scope | AD90: PASS within model scope | AE90: PASS within model scope | AF90: PASS within model scope
A91: 13 | B91: =IF(A91<='Assumptions and Catalog'!$C$6,SUMIFS($M$161:$M$400,$A$161:$A$400,A91),0) -> 0 | C91: =IF(A91<='Assumptions and Catalog'!$C$6,SUMIFS($O$161:$O$400,$A$161:$A$400,A91)-(C$70+IF(AND('Assumptions and Catalog'!$C$19>0,A91='Assumptions and Catalog'!$C$19),C$61*'Assumptions and Catalog'!$C$20,0)+IF(AND('Assumptions and Catalog'!$C$21>0,A91='Assumptions and Catalog'!$C$21),C$62*'Assumptions and Catalog'!$C$22,0))*(1+'Assumptions and Catalog'!$C$9)^(A91-1),0) -> 0 | D91: =C91/(1+'Assumptions and Catalog'!$C$7)^A91 -> 0 | E91: =E90+C91 -> 249441.19 | F91: =F90+D91 -> 98257.868 | G91: =IF(A91<='Assumptions and Catalog'!$C$6,SUMIFS($O$411:$O$650,$A$411:$A$650,A91)-(D$70+IF(AND('Assumptions and Catalog'!$C$19>0,A91='Assumptions and Catalog'!$C$19),D$61*'Assumptions and Catalog'!$C$20,0)+IF(AND('Assumptions and Catalog'!$C$21>0,A91='Assumptions and Catalog'!$C$21),D$62*'Assumptions and Catalog'!$C$22,0))*(1+'Assumptions and Catalog'!$C$9)^(A91-1),0) -> 0 | H91: =G91/(1+'Assumptions and Catalog'!$C$7)^A91 -> 0 | I91: =I90+G91 -> -300370.4 | J91: =J90+H91 -> -289842.6 | K91: =IF(A91<='Assumptions and Catalog'!$C$6,SUMIFS($O$661:$O$900,$A$661:$A$900,A91)-(E$70+IF(AND('Assumptions and Catalog'!$C$19>0,A91='Assumptions and Catalog'!$C$19),E$61*'Assumptions and Catalog'!$C$20,0)+IF(AND('Assumptions and Catalog'!$C$21>0,A91='Assumptions and Catalog'!$C$21),E$62*'Assumptions and Catalog'!$C$22,0))*(1+'Assumptions and Catalog'!$C$9)^(A91-1),0) -> 0 | L91: =K91/(1+'Assumptions and Catalog'!$C$7)^A91 -> 0 | M91: =M90+K91 -> 55882.125 | N91: =N90+L91 -> -125124.27 | P91: =IF(AND(A91<='Assumptions and Catalog'!$C$6,E91>=0,E90<0,C91>0),A91-1-E90/C91,999) -> 999 | Q91: =IF(AND(A91<='Assumptions and Catalog'!$C$6,F91>=0,F90<0,D91>0),A91-1-F90/D91,999) -> 999 | R91: =IF(AND(A91<='Assumptions and Catalog'!$C$6,I91>=0,I90<0,G91>0),A91-1-I90/G91,999) -> 999 | S91: =IF(AND(A91<='Assumptions and Catalog'!$C$6,J91>=0,J90<0,H91>0),A91-1-J90/H91,999) -> 999 | T91: =IF(AND(A91<='Assumptions and Catalog'!$C$6,M91>=0,M90<0,K91>0),A91-1-M90/K91,999) -> 999 | U91: =IF(AND(A91<='Assumptions and Catalog'!$C$6,N91>=0,N90<0,L91>0),A91-1-N90/L91,999) -> 999 | W91: Full scenario validation | Y91: Not a site feasibility approval | Z91: Critical backup requirement not met | AA91: FAIL: roof constraint | AB91: FAIL: roof constraint | AC91: FAIL: roof constraint | AD91: FAIL: roof; INCOMPLETE: TOU/peak | AE91: FAIL: roof; INCOMPLETE: TOU/peak | AF91: FAIL: roof; INCOMPLETE: TOU/peak
A92: 14 | B92: =IF(A92<='Assumptions and Catalog'!$C$6,SUMIFS($M$161:$M$400,$A$161:$A$400,A92),0) -> 0 | C92: =IF(A92<='Assumptions and Catalog'!$C$6,SUMIFS($O$161:$O$400,$A$161:$A$400,A92)-(C$70+IF(AND('Assumptions and Catalog'!$C$19>0,A92='Assumptions and Catalog'!$C$19),C$61*'Assumptions and Catalog'!$C$20,0)+IF(AND('Assumptions and Catalog'!$C$21>0,A92='Assumptions and Catalog'!$C$21),C$62*'Assumptions and Catalog'!$C$22,0))*(1+'Assumptions and Catalog'!$C$9)^(A92-1),0) -> 0 | D92: =C92/(1+'Assumptions and Catalog'!$C$7)^A92 -> 0 | E92: =E91+C92 -> 249441.19 | F92: =F91+D92 -> 98257.868 | G92: =IF(A92<='Assumptions and Catalog'!$C$6,SUMIFS($O$411:$O$650,$A$411:$A$650,A92)-(D$70+IF(AND('Assumptions and Catalog'!$C$19>0,A92='Assumptions and Catalog'!$C$19),D$61*'Assumptions and Catalog'!$C$20,0)+IF(AND('Assumptions and Catalog'!$C$21>0,A92='Assumptions and Catalog'!$C$21),D$62*'Assumptions and Catalog'!$C$22,0))*(1+'Assumptions and Catalog'!$C$9)^(A92-1),0) -> 0 | H92: =G92/(1+'Assumptions and Catalog'!$C$7)^A92 -> 0 | I92: =I91+G92 -> -300370.4 | J92: =J91+H92 -> -289842.6 | K92: =IF(A92<='Assumptions and Catalog'!$C$6,SUMIFS($O$661:$O$900,$A$661:$A$900,A92)-(E$70+IF(AND('Assumptions and Catalog'!$C$19>0,A92='Assumptions and Catalog'!$C$19),E$61*'Assumptions and Catalog'!$C$20,0)+IF(AND('Assumptions and Catalog'!$C$21>0,A92='Assumptions and Catalog'!$C$21),E$62*'Assumptions and Catalog'!$C$22,0))*(1+'Assumptions and Catalog'!$C$9)^(A92-1),0) -> 0 | L92: =K92/(1+'Assumptions and Catalog'!$C$7)^A92 -> 0 | M92: =M91+K92 -> 55882.125 | N92: =N91+L92 -> -125124.27 | P92: =IF(AND(A92<='Assumptions and Catalog'!$C$6,E92>=0,E91<0,C92>0),A92-1-E91/C92,999) -> 999 | Q92: =IF(AND(A92<='Assumptions and Catalog'!$C$6,F92>=0,F91<0,D92>0),A92-1-F91/D92,999) -> 999 | R92: =IF(AND(A92<='Assumptions and Catalog'!$C$6,I92>=0,I91<0,G92>0),A92-1-I91/G92,999) -> 999 | S92: =IF(AND(A92<='Assumptions and Catalog'!$C$6,J92>=0,J91<0,H92>0),A92-1-J91/H92,999) -> 999 | T92: =IF(AND(A92<='Assumptions and Catalog'!$C$6,M92>=0,M91<0,K92>0),A92-1-M91/K92,999) -> 999 | U92: =IF(AND(A92<='Assumptions and Catalog'!$C$6,N92>=0,N91<0,L92>0),A92-1-N91/L92,999) -> 999 | W92: Scenario-specific findings
A93: 15 | B93: =IF(A93<='Assumptions and Catalog'!$C$6,SUMIFS($M$161:$M$400,$A$161:$A$400,A93),0) -> 0 | C93: =IF(A93<='Assumptions and Catalog'!$C$6,SUMIFS($O$161:$O$400,$A$161:$A$400,A93)-(C$70+IF(AND('Assumptions and Catalog'!$C$19>0,A93='Assumptions and Catalog'!$C$19),C$61*'Assumptions and Catalog'!$C$20,0)+IF(AND('Assumptions and Catalog'!$C$21>0,A93='Assumptions and Catalog'!$C$21),C$62*'Assumptions and Catalog'!$C$22,0))*(1+'Assumptions and Catalog'!$C$9)^(A93-1),0) -> 0 | D93: =C93/(1+'Assumptions and Catalog'!$C$7)^A93 -> 0 | E93: =E92+C93 -> 249441.19 | F93: =F92+D93 -> 98257.868 | G93: =IF(A93<='Assumptions and Catalog'!$C$6,SUMIFS($O$411:$O$650,$A$411:$A$650,A93)-(D$70+IF(AND('Assumptions and Catalog'!$C$19>0,A93='Assumptions and Catalog'!$C$19),D$61*'Assumptions and Catalog'!$C$20,0)+IF(AND('Assumptions and Catalog'!$C$21>0,A93='Assumptions and Catalog'!$C$21),D$62*'Assumptions and Catalog'!$C$22,0))*(1+'Assumptions and Catalog'!$C$9)^(A93-1),0) -> 0 | H93: =G93/(1+'Assumptions and Catalog'!$C$7)^A93 -> 0 | I93: =I92+G93 -> -300370.4 | J93: =J92+H93 -> -289842.6 | K93: =IF(A93<='Assumptions and Catalog'!$C$6,SUMIFS($O$661:$O$900,$A$661:$A$900,A93)-(E$70+IF(AND('Assumptions and Catalog'!$C$19>0,A93='Assumptions and Catalog'!$C$19),E$61*'Assumptions and Catalog'!$C$20,0)+IF(AND('Assumptions and Catalog'!$C$21>0,A93='Assumptions and Catalog'!$C$21),E$62*'Assumptions and Catalog'!$C$22,0))*(1+'Assumptions and Catalog'!$C$9)^(A93-1),0) -> 0 | L93: =K93/(1+'Assumptions and Catalog'!$C$7)^A93 -> 0 | M93: =M92+K93 -> 55882.125 | N93: =N92+L93 -> -125124.27 | P93: =IF(AND(A93<='Assumptions and Catalog'!$C$6,E93>=0,E92<0,C93>0),A93-1-E92/C93,999) -> 999 | Q93: =IF(AND(A93<='Assumptions and Catalog'!$C$6,F93>=0,F92<0,D93>0),A93-1-F92/D93,999) -> 999 | R93: =IF(AND(A93<='Assumptions and Catalog'!$C$6,I93>=0,I92<0,G93>0),A93-1-I92/G93,999) -> 999 | S93: =IF(AND(A93<='Assumptions and Catalog'!$C$6,J93>=0,J92<0,H93>0),A93-1-J92/H93,999) -> 999 | T93: =IF(AND(A93<='Assumptions and Catalog'!$C$6,M93>=0,M92<0,K93>0),A93-1-M92/K93,999) -> 999 | U93: =IF(AND(A93<='Assumptions and Catalog'!$C$6,N93>=0,N92<0,L93>0),A93-1-N92/L93,999) -> 999 | W93: Source findings and scenario limitations | Y93: 46 x 550 W = 25.3 kWp, not 25 kWp. Grid inverter AC rating assumed 25 kW; verify hardware. Roof unspecified. No export income. | Z93: 3 kW inverter cannot supply the source 4 kW critical load. | AA93: Roof exceeds stated area under the unchanged 1.5 installation factor. Inverter 3 kW is below the assumed 4 kW critical load. | AB93: Roof exceeds stated area under the unchanged 1.5 installation factor. Declared capital total differs from component midpoints by -830 EGP; residual installation reconciles it. | AC93: Roof exceeds stated area under the unchanged 1.5 installation factor. Declared capital total differs from component midpoints by -350 EGP; residual installation reconciles it. | AD93: Roof exceeds stated area under the unchanged 1.5 installation factor. TOU/peak operation is not implemented; no such savings included. | AE93: Roof exceeds stated area under the unchanged 1.5 installation factor. TOU/peak operation is not implemented; no such savings included. | AF93: Roof exceeds stated area under the unchanged 1.5 installation factor. TOU/peak operation is not implemented; no such savings included. | AH93: The model aggregates daily energy into months. It does not prove hourly overlap of solar and load, motor starting capability, clipping, physical roof layout or manufacturer compatibility. Those limitations also apply when arithmetic checks pass.
A94: 16 | B94: =IF(A94<='Assumptions and Catalog'!$C$6,SUMIFS($M$161:$M$400,$A$161:$A$400,A94),0) -> 0 | C94: =IF(A94<='Assumptions and Catalog'!$C$6,SUMIFS($O$161:$O$400,$A$161:$A$400,A94)-(C$70+IF(AND('Assumptions and Catalog'!$C$19>0,A94='Assumptions and Catalog'!$C$19),C$61*'Assumptions and Catalog'!$C$20,0)+IF(AND('Assumptions and Catalog'!$C$21>0,A94='Assumptions and Catalog'!$C$21),C$62*'Assumptions and Catalog'!$C$22,0))*(1+'Assumptions and Catalog'!$C$9)^(A94-1),0) -> 0 | D94: =C94/(1+'Assumptions and Catalog'!$C$7)^A94 -> 0 | E94: =E93+C94 -> 249441.19 | F94: =F93+D94 -> 98257.868 | G94: =IF(A94<='Assumptions and Catalog'!$C$6,SUMIFS($O$411:$O$650,$A$411:$A$650,A94)-(D$70+IF(AND('Assumptions and Catalog'!$C$19>0,A94='Assumptions and Catalog'!$C$19),D$61*'Assumptions and Catalog'!$C$20,0)+IF(AND('Assumptions and Catalog'!$C$21>0,A94='Assumptions and Catalog'!$C$21),D$62*'Assumptions and Catalog'!$C$22,0))*(1+'Assumptions and Catalog'!$C$9)^(A94-1),0) -> 0 | H94: =G94/(1+'Assumptions and Catalog'!$C$7)^A94 -> 0 | I94: =I93+G94 -> -300370.4 | J94: =J93+H94 -> -289842.6 | K94: =IF(A94<='Assumptions and Catalog'!$C$6,SUMIFS($O$661:$O$900,$A$661:$A$900,A94)-(E$70+IF(AND('Assumptions and Catalog'!$C$19>0,A94='Assumptions and Catalog'!$C$19),E$61*'Assumptions and Catalog'!$C$20,0)+IF(AND('Assumptions and Catalog'!$C$21>0,A94='Assumptions and Catalog'!$C$21),E$62*'Assumptions and Catalog'!$C$22,0))*(1+'Assumptions and Catalog'!$C$9)^(A94-1),0) -> 0 | L94: =K94/(1+'Assumptions and Catalog'!$C$7)^A94 -> 0 | M94: =M93+K94 -> 55882.125 | N94: =N93+L94 -> -125124.27 | P94: =IF(AND(A94<='Assumptions and Catalog'!$C$6,E94>=0,E93<0,C94>0),A94-1-E93/C94,999) -> 999 | Q94: =IF(AND(A94<='Assumptions and Catalog'!$C$6,F94>=0,F93<0,D94>0),A94-1-F93/D94,999) -> 999 | R94: =IF(AND(A94<='Assumptions and Catalog'!$C$6,I94>=0,I93<0,G94>0),A94-1-I93/G94,999) -> 999 | S94: =IF(AND(A94<='Assumptions and Catalog'!$C$6,J94>=0,J93<0,H94>0),A94-1-J93/H94,999) -> 999 | T94: =IF(AND(A94<='Assumptions and Catalog'!$C$6,M94>=0,M93<0,K94>0),A94-1-M93/K94,999) -> 999 | U94: =IF(AND(A94<='Assumptions and Catalog'!$C$6,N94>=0,N93<0,L94>0),A94-1-N93/L94,999) -> 999
A95: 17 | B95: =IF(A95<='Assumptions and Catalog'!$C$6,SUMIFS($M$161:$M$400,$A$161:$A$400,A95),0) -> 0 | C95: =IF(A95<='Assumptions and Catalog'!$C$6,SUMIFS($O$161:$O$400,$A$161:$A$400,A95)-(C$70+IF(AND('Assumptions and Catalog'!$C$19>0,A95='Assumptions and Catalog'!$C$19),C$61*'Assumptions and Catalog'!$C$20,0)+IF(AND('Assumptions and Catalog'!$C$21>0,A95='Assumptions and Catalog'!$C$21),C$62*'Assumptions and Catalog'!$C$22,0))*(1+'Assumptions and Catalog'!$C$9)^(A95-1),0) -> 0 | D95: =C95/(1+'Assumptions and Catalog'!$C$7)^A95 -> 0 | E95: =E94+C95 -> 249441.19 | F95: =F94+D95 -> 98257.868 | G95: =IF(A95<='Assumptions and Catalog'!$C$6,SUMIFS($O$411:$O$650,$A$411:$A$650,A95)-(D$70+IF(AND('Assumptions and Catalog'!$C$19>0,A95='Assumptions and Catalog'!$C$19),D$61*'Assumptions and Catalog'!$C$20,0)+IF(AND('Assumptions and Catalog'!$C$21>0,A95='Assumptions and Catalog'!$C$21),D$62*'Assumptions and Catalog'!$C$22,0))*(1+'Assumptions and Catalog'!$C$9)^(A95-1),0) -> 0 | H95: =G95/(1+'Assumptions and Catalog'!$C$7)^A95 -> 0 | I95: =I94+G95 -> -300370.4 | J95: =J94+H95 -> -289842.6 | K95: =IF(A95<='Assumptions and Catalog'!$C$6,SUMIFS($O$661:$O$900,$A$661:$A$900,A95)-(E$70+IF(AND('Assumptions and Catalog'!$C$19>0,A95='Assumptions and Catalog'!$C$19),E$61*'Assumptions and Catalog'!$C$20,0)+IF(AND('Assumptions and Catalog'!$C$21>0,A95='Assumptions and Catalog'!$C$21),E$62*'Assumptions and Catalog'!$C$22,0))*(1+'Assumptions and Catalog'!$C$9)^(A95-1),0) -> 0 | L95: =K95/(1+'Assumptions and Catalog'!$C$7)^A95 -> 0 | M95: =M94+K95 -> 55882.125 | N95: =N94+L95 -> -125124.27 | P95: =IF(AND(A95<='Assumptions and Catalog'!$C$6,E95>=0,E94<0,C95>0),A95-1-E94/C95,999) -> 999 | Q95: =IF(AND(A95<='Assumptions and Catalog'!$C$6,F95>=0,F94<0,D95>0),A95-1-F94/D95,999) -> 999 | R95: =IF(AND(A95<='Assumptions and Catalog'!$C$6,I95>=0,I94<0,G95>0),A95-1-I94/G95,999) -> 999 | S95: =IF(AND(A95<='Assumptions and Catalog'!$C$6,J95>=0,J94<0,H95>0),A95-1-J94/H95,999) -> 999 | T95: =IF(AND(A95<='Assumptions and Catalog'!$C$6,M95>=0,M94<0,K95>0),A95-1-M94/K95,999) -> 999 | U95: =IF(AND(A95<='Assumptions and Catalog'!$C$6,N95>=0,N94<0,L95>0),A95-1-N94/L95,999) -> 999
A96: 18 | B96: =IF(A96<='Assumptions and Catalog'!$C$6,SUMIFS($M$161:$M$400,$A$161:$A$400,A96),0) -> 0 | C96: =IF(A96<='Assumptions and Catalog'!$C$6,SUMIFS($O$161:$O$400,$A$161:$A$400,A96)-(C$70+IF(AND('Assumptions and Catalog'!$C$19>0,A96='Assumptions and Catalog'!$C$19),C$61*'Assumptions and Catalog'!$C$20,0)+IF(AND('Assumptions and Catalog'!$C$21>0,A96='Assumptions and Catalog'!$C$21),C$62*'Assumptions and Catalog'!$C$22,0))*(1+'Assumptions and Catalog'!$C$9)^(A96-1),0) -> 0 | D96: =C96/(1+'Assumptions and Catalog'!$C$7)^A96 -> 0 | E96: =E95+C96 -> 249441.19 | F96: =F95+D96 -> 98257.868 | G96: =IF(A96<='Assumptions and Catalog'!$C$6,SUMIFS($O$411:$O$650,$A$411:$A$650,A96)-(D$70+IF(AND('Assumptions and Catalog'!$C$19>0,A96='Assumptions and Catalog'!$C$19),D$61*'Assumptions and Catalog'!$C$20,0)+IF(AND('Assumptions and Catalog'!$C$21>0,A96='Assumptions and Catalog'!$C$21),D$62*'Assumptions and Catalog'!$C$22,0))*(1+'Assumptions and Catalog'!$C$9)^(A96-1),0) -> 0 | H96: =G96/(1+'Assumptions and Catalog'!$C$7)^A96 -> 0 | I96: =I95+G96 -> -300370.4 | J96: =J95+H96 -> -289842.6 | K96: =IF(A96<='Assumptions and Catalog'!$C$6,SUMIFS($O$661:$O$900,$A$661:$A$900,A96)-(E$70+IF(AND('Assumptions and Catalog'!$C$19>0,A96='Assumptions and Catalog'!$C$19),E$61*'Assumptions and Catalog'!$C$20,0)+IF(AND('Assumptions and Catalog'!$C$21>0,A96='Assumptions and Catalog'!$C$21),E$62*'Assumptions and Catalog'!$C$22,0))*(1+'Assumptions and Catalog'!$C$9)^(A96-1),0) -> 0 | L96: =K96/(1+'Assumptions and Catalog'!$C$7)^A96 -> 0 | M96: =M95+K96 -> 55882.125 | N96: =N95+L96 -> -125124.27 | P96: =IF(AND(A96<='Assumptions and Catalog'!$C$6,E96>=0,E95<0,C96>0),A96-1-E95/C96,999) -> 999 | Q96: =IF(AND(A96<='Assumptions and Catalog'!$C$6,F96>=0,F95<0,D96>0),A96-1-F95/D96,999) -> 999 | R96: =IF(AND(A96<='Assumptions and Catalog'!$C$6,I96>=0,I95<0,G96>0),A96-1-I95/G96,999) -> 999 | S96: =IF(AND(A96<='Assumptions and Catalog'!$C$6,J96>=0,J95<0,H96>0),A96-1-J95/H96,999) -> 999 | T96: =IF(AND(A96<='Assumptions and Catalog'!$C$6,M96>=0,M95<0,K96>0),A96-1-M95/K96,999) -> 999 | U96: =IF(AND(A96<='Assumptions and Catalog'!$C$6,N96>=0,N95<0,L96>0),A96-1-N95/L96,999) -> 999
A97: 19 | B97: =IF(A97<='Assumptions and Catalog'!$C$6,SUMIFS($M$161:$M$400,$A$161:$A$400,A97),0) -> 0 | C97: =IF(A97<='Assumptions and Catalog'!$C$6,SUMIFS($O$161:$O$400,$A$161:$A$400,A97)-(C$70+IF(AND('Assumptions and Catalog'!$C$19>0,A97='Assumptions and Catalog'!$C$19),C$61*'Assumptions and Catalog'!$C$20,0)+IF(AND('Assumptions and Catalog'!$C$21>0,A97='Assumptions and Catalog'!$C$21),C$62*'Assumptions and Catalog'!$C$22,0))*(1+'Assumptions and Catalog'!$C$9)^(A97-1),0) -> 0 | D97: =C97/(1+'Assumptions and Catalog'!$C$7)^A97 -> 0 | E97: =E96+C97 -> 249441.19 | F97: =F96+D97 -> 98257.868 | G97: =IF(A97<='Assumptions and Catalog'!$C$6,SUMIFS($O$411:$O$650,$A$411:$A$650,A97)-(D$70+IF(AND('Assumptions and Catalog'!$C$19>0,A97='Assumptions and Catalog'!$C$19),D$61*'Assumptions and Catalog'!$C$20,0)+IF(AND('Assumptions and Catalog'!$C$21>0,A97='Assumptions and Catalog'!$C$21),D$62*'Assumptions and Catalog'!$C$22,0))*(1+'Assumptions and Catalog'!$C$9)^(A97-1),0) -> 0 | H97: =G97/(1+'Assumptions and Catalog'!$C$7)^A97 -> 0 | I97: =I96+G97 -> -300370.4 | J97: =J96+H97 -> -289842.6 | K97: =IF(A97<='Assumptions and Catalog'!$C$6,SUMIFS($O$661:$O$900,$A$661:$A$900,A97)-(E$70+IF(AND('Assumptions and Catalog'!$C$19>0,A97='Assumptions and Catalog'!$C$19),E$61*'Assumptions and Catalog'!$C$20,0)+IF(AND('Assumptions and Catalog'!$C$21>0,A97='Assumptions and Catalog'!$C$21),E$62*'Assumptions and Catalog'!$C$22,0))*(1+'Assumptions and Catalog'!$C$9)^(A97-1),0) -> 0 | L97: =K97/(1+'Assumptions and Catalog'!$C$7)^A97 -> 0 | M97: =M96+K97 -> 55882.125 | N97: =N96+L97 -> -125124.27 | P97: =IF(AND(A97<='Assumptions and Catalog'!$C$6,E97>=0,E96<0,C97>0),A97-1-E96/C97,999) -> 999 | Q97: =IF(AND(A97<='Assumptions and Catalog'!$C$6,F97>=0,F96<0,D97>0),A97-1-F96/D97,999) -> 999 | R97: =IF(AND(A97<='Assumptions and Catalog'!$C$6,I97>=0,I96<0,G97>0),A97-1-I96/G97,999) -> 999 | S97: =IF(AND(A97<='Assumptions and Catalog'!$C$6,J97>=0,J96<0,H97>0),A97-1-J96/H97,999) -> 999 | T97: =IF(AND(A97<='Assumptions and Catalog'!$C$6,M97>=0,M96<0,K97>0),A97-1-M96/K97,999) -> 999 | U97: =IF(AND(A97<='Assumptions and Catalog'!$C$6,N97>=0,N96<0,L97>0),A97-1-N96/L97,999) -> 999
A98: 20 | B98: =IF(A98<='Assumptions and Catalog'!$C$6,SUMIFS($M$161:$M$400,$A$161:$A$400,A98),0) -> 0 | C98: =IF(A98<='Assumptions and Catalog'!$C$6,SUMIFS($O$161:$O$400,$A$161:$A$400,A98)-(C$70+IF(AND('Assumptions and Catalog'!$C$19>0,A98='Assumptions and Catalog'!$C$19),C$61*'Assumptions and Catalog'!$C$20,0)+IF(AND('Assumptions and Catalog'!$C$21>0,A98='Assumptions and Catalog'!$C$21),C$62*'Assumptions and Catalog'!$C$22,0))*(1+'Assumptions and Catalog'!$C$9)^(A98-1),0) -> 0 | D98: =C98/(1+'Assumptions and Catalog'!$C$7)^A98 -> 0 | E98: =E97+C98 -> 249441.19 | F98: =F97+D98 -> 98257.868 | G98: =IF(A98<='Assumptions and Catalog'!$C$6,SUMIFS($O$411:$O$650,$A$411:$A$650,A98)-(D$70+IF(AND('Assumptions and Catalog'!$C$19>0,A98='Assumptions and Catalog'!$C$19),D$61*'Assumptions and Catalog'!$C$20,0)+IF(AND('Assumptions and Catalog'!$C$21>0,A98='Assumptions and Catalog'!$C$21),D$62*'Assumptions and Catalog'!$C$22,0))*(1+'Assumptions and Catalog'!$C$9)^(A98-1),0) -> 0 | H98: =G98/(1+'Assumptions and Catalog'!$C$7)^A98 -> 0 | I98: =I97+G98 -> -300370.4 | J98: =J97+H98 -> -289842.6 | K98: =IF(A98<='Assumptions and Catalog'!$C$6,SUMIFS($O$661:$O$900,$A$661:$A$900,A98)-(E$70+IF(AND('Assumptions and Catalog'!$C$19>0,A98='Assumptions and Catalog'!$C$19),E$61*'Assumptions and Catalog'!$C$20,0)+IF(AND('Assumptions and Catalog'!$C$21>0,A98='Assumptions and Catalog'!$C$21),E$62*'Assumptions and Catalog'!$C$22,0))*(1+'Assumptions and Catalog'!$C$9)^(A98-1),0) -> 0 | L98: =K98/(1+'Assumptions and Catalog'!$C$7)^A98 -> 0 | M98: =M97+K98 -> 55882.125 | N98: =N97+L98 -> -125124.27 | P98: =IF(AND(A98<='Assumptions and Catalog'!$C$6,E98>=0,E97<0,C98>0),A98-1-E97/C98,999) -> 999 | Q98: =IF(AND(A98<='Assumptions and Catalog'!$C$6,F98>=0,F97<0,D98>0),A98-1-F97/D98,999) -> 999 | R98: =IF(AND(A98<='Assumptions and Catalog'!$C$6,I98>=0,I97<0,G98>0),A98-1-I97/G98,999) -> 999 | S98: =IF(AND(A98<='Assumptions and Catalog'!$C$6,J98>=0,J97<0,H98>0),A98-1-J97/H98,999) -> 999 | T98: =IF(AND(A98<='Assumptions and Catalog'!$C$6,M98>=0,M97<0,K98>0),A98-1-M97/K98,999) -> 999 | U98: =IF(AND(A98<='Assumptions and Catalog'!$C$6,N98>=0,N97<0,L98>0),A98-1-N97/L98,999) -> 999
W100: Manager reported results - different assumptions
W101: Manager reported annual savings | X101: EGP | Y101: 132000 | Z101: 0 | AA101: 10716 | AB101: 24996 | AC101: 53436 | AD101: 14875 | AE101: 57700 | AF101: 14900
A102: Payback is the first cumulative cash-flow crossing of zero. Fractional years are interpolated. Later replacement can reduce the balance. | W102: Manager reported 10-year NPV | X102: EGP | Y102: 691632 | Z102: -210000 | AA102: -143300 | AB102: -94062 | AC102: -108832 | AD102: -407873 | AE102: -524119 | AF102: -649520
...

Sheet Future Changes

Sheet Saved Scenarios

Sheet Solar Production
A2: AVESTA - Solar Production | Experimental Copy
A3: Cairo fixed location. Yellow cells are editable. Monthly battery dispatch remains an approximation.
A5: Panel tilt (degrees) | C5: 30 | E5: Tilt: 0 = horizontal; 90 = vertical.
A6: Compass azimuth (deg) | C6: 180 | E6: Azimuth: 0/360 = north; 90 = east; 180 = south; 270 = west.
A7: Study year shown | C7: 1 | E7: The same roof orientation applies to both solar configurations.
A8: Calendar year shown | C8: ='Assumptions and Catalog'!C24+C7-1 -> 2027
A9: Latitude (fixed) | C9: 30.0444 | E9: PVGIS 5.3 / SARAH3 | Climate: 2005-2023 | Retrieved: 26 Oct 2026
A10: Longitude (fixed) | C10: 31.2357 | E10: Crystalline silicon; free-standing; terrain horizon included.
A11: PVGIS system loss | C11: 0.14 | E11: 14% system loss is already included; no second performance ratio.
A12: Solar input status | C12: =IF(AND(ISNUMBER(C5),C5>=0,C5<=90,ISNUMBER(C6),C6>=0,C6<=360,ISNUMBER(C7),C7>=1,C7<='Assumptions and Catalog'!C6,C7<=20,C7=INT(C7)),"OK","INVALID: tilt 0-90, azimuth 0-360, study year within horizon (max 20)") -> OK
A14: =HYPERLINK("https://re.jrc.ec.europa.eu/api/v5_3/PVcalc?lat=30.0444&lon=31.2357&peakpower=1&loss=14&raddatabase=PVGIS-SARAH3&pvtechchoice=crystSi&mountingplace=free&angle="&C5&"&aspect="&(C6-180)&"&outputformat=json","Open PVGIS source for selected tilt and azimuth (internet required)") -> Open PVGIS source for selected tilt and azimuth (internet required)
A15: =HYPERLINK("https://joint-research-centre.ec.europa.eu/photovoltaic-geographical-information-system-pvgis/using-pvgis-5/pvgis-5-user-manual_en","PVGIS methodology and data documentation") -> PVGIS methodology and data documentation
A16: Offline calculation: bilinear interpolation of PVGIS results on a 5-degree tilt / 15-degree azimuth grid.
A17: Source values are for 1 kWp. Monthly climate averages are not a forecast of the selected calendar year.
A19: Month | B19: Ref. days | C19: PV yield kWh/kWp/mo | D19: PV yield kWh/kWp/day | E19: Solar only PV kWh | F19: Solar only Bill saving EGP | G19: Combined PV kWh | H19: Combined Bill saving EGP | I19: Battery only Bill saving EGP | J19: Calendar days
A20: 1 | B20: 31 | C20: =IF($C$12="OK",(1-$C$44)*(1-$C$45)*INDEX($D$70:$D$5769,($C$40/5*25+$C$42/15)*12+A20)+$C$44*(1-$C$45)*INDEX($D$70:$D$5769,($C$41/5*25+$C$42/15)*12+A20)+(1-$C$44)*$C$45*INDEX($D$70:$D$5769,($C$40/5*25+$C$43/15)*12+A20)+$C$44*$C$45*INDEX($D$70:$D$5769,($C$41/5*25+$C$43/15)*12+A20),NA()) -> 131.3 | D20: =C20/B20 -> 4.2354839 | E20: =IF(AND($C$12="OK",Scenarios!C$65=1),SUMIFS(Scenarios!$F$161:$F$400,Scenarios!$A$161:$A$400,$C$7,Scenarios!$B$161:$B$400,A20),NA()) -> 1155.44 | F20: =IF(AND($C$12="OK",Scenarios!C$65=1),SUMIFS(Scenarios!$O$161:$O$400,Scenarios!$A$161:$A$400,$C$7,Scenarios!$B$161:$B$400,A20),NA()) -> 3258.3408 | G20: =IF(AND($C$12="OK",Scenarios!E$65=1),SUMIFS(Scenarios!$F$661:$F$900,Scenarios!$A$661:$A$900,$C$7,Scenarios!$B$661:$B$900,A20),NA()) -> 1444.3 | H20: =IF(AND($C$12="OK",Scenarios!E$65=1),SUMIFS(Scenarios!$O$661:$O$900,Scenarios!$A$661:$A$900,$C$7,Scenarios!$B$661:$B$900,A20),NA()) -> 4045.9905 | I20: =IF(AND($C$12="OK",Scenarios!D$65=1),SUMIFS(Scenarios!$O$411:$O$650,Scenarios!$A$411:$A$650,$C$7,Scenarios!$B$411:$B$650,A20),NA()) -> 0 | J20: =DAY(DATE($C$8,A20+1,0)) -> 31
A21: 2 | B21: 28 | C21: =IF($C$12="OK",(1-$C$44)*(1-$C$45)*INDEX($D$70:$D$5769,($C$40/5*25+$C$42/15)*12+A21)+$C$44*(1-$C$45)*INDEX($D$70:$D$5769,($C$41/5*25+$C$42/15)*12+A21)+(1-$C$44)*$C$45*INDEX($D$70:$D$5769,($C$40/5*25+$C$43/15)*12+A21)+$C$44*$C$45*INDEX($D$70:$D$5769,($C$41/5*25+$C$43/15)*12+A21),NA()) -> 129.45 | D21: =C21/B21 -> 4.6232143 | E21: =IF(AND($C$12="OK",Scenarios!C$65=1),SUMIFS(Scenarios!$F$161:$F$400,Scenarios!$A$161:$A$400,$C$7,Scenarios!$B$161:$B$400,A21),NA()) -> 1139.16 | F21: =IF(AND($C$12="OK",Scenarios!C$65=1),SUMIFS(Scenarios!$O$161:$O$400,Scenarios!$A$161:$A$400,$C$7,Scenarios!$B$161:$B$400,A21),NA()) -> 3186.036 | G21: =IF(AND($C$12="OK",Scenarios!E$65=1),SUMIFS(Scenarios!$F$661:$F$900,Scenarios!$A$661:$A$900,$C$7,Scenarios!$B$661:$B$900,A21),NA()) -> 1423.95 | H21: =IF(AND($C$12="OK",Scenarios!E$65=1),SUMIFS(Scenarios!$O$661:$O$900,Scenarios!$A$661:$A$900,$C$7,Scenarios!$B$661:$B$900,A21),NA()) -> 4091.885 | I21: =IF(AND($C$12="OK",Scenarios!D$65=1),SUMIFS(Scenarios!$O$411:$O$650,Scenarios!$A$411:$A$650,$C$7,Scenarios!$B$411:$B$650,A21),NA()) -> 0 | J21: =DAY(DATE($C$8,A21+1,0)) -> 28
A22: 3 | B22: 31 | C22: =IF($C$12="OK",(1-$C$44)*(1-$C$45)*INDEX($D$70:$D$5769,($C$40/5*25+$C$42/15)*12+A22)+$C$44*(1-$C$45)*INDEX($D$70:$D$5769,($C$41/5*25+$C$42/15)*12+A22)+(1-$C$44)*$C$45*INDEX($D$70:$D$5769,($C$40/5*25+$C$43/15)*12+A22)+$C$44*$C$45*INDEX($D$70:$D$5769,($C$41/5*25+$C$43/15)*12+A22),NA()) -> 161.06 | D22: =C22/B22 -> 5.1954839 | E22: =IF(AND($C$12="OK",Scenarios!C$65=1),SUMIFS(Scenarios!$F$161:$F$400,Scenarios!$A$161:$A$400,$C$7,Scenarios!$B$161:$B$400,A22),NA()) -> 1417.328 | F22: =IF(AND($C$12="OK",Scenarios!C$65=1),SUMIFS(Scenarios!$O$161:$O$400,Scenarios!$A$161:$A$400,$C$7,Scenarios!$B$161:$B$400,A22),NA()) -> 3527.397 | G22: =IF(AND($C$12="OK",Scenarios!E$65=1),SUMIFS(Scenarios!$F$661:$F$900,Scenarios!$A$661:$A$900,$C$7,Scenarios!$B$661:$B$900,A22),NA()) -> 1771.66 | H22: =IF(AND($C$12="OK",Scenarios!E$65=1),SUMIFS(Scenarios!$O$661:$O$900,Scenarios!$A$661:$A$900,$C$7,Scenarios!$B$661:$B$900,A22),NA()) -> 4522.2656 | I22: =IF(AND($C$12="OK",Scenarios!D$65=1),SUMIFS(Scenarios!$O$411:$O$650,Scenarios!$A$411:$A$650,$C$7,Scenarios!$B$411:$B$650,A22),NA()) -> 0 | J22: =DAY(DATE($C$8,A22+1,0)) -> 31
A23: 4 | B23: 30 | C23: =IF($C$12="OK",(1-$C$44)*(1-$C$45)*INDEX($D$70:$D$5769,($C$40/5*25+$C$42/15)*12+A23)+$C$44*(1-$C$45)*INDEX($D$70:$D$5769,($C$41/5*25+$C$42/15)*12+A23)+(1-$C$44)*$C$45*INDEX($D$70:$D$5769,($C$40/5*25+$C$43/15)*12+A23)+$C$44*$C$45*INDEX($D$70:$D$5769,($C$41/5*25+$C$43/15)*12+A23),NA()) -> 160.86 | D23: =C23/B23 -> 5.362 | E23: =IF(AND($C$12="OK",Scenarios!C$65=1),SUMIFS(Scenarios!$F$161:$F$400,Scenarios!$A$161:$A$400,$C$7,Scenarios!$B$161:$B$400,A23),NA()) -> 1415.568 | F23: =IF(AND($C$12="OK",Scenarios!C$65=1),SUMIFS(Scenarios!$O$161:$O$400,Scenarios!$A$161:$A$400,$C$7,Scenarios!$B$161:$B$400,A23),NA()) -> 3413.61 | G23: =IF(AND($C$12="OK",Scenarios!E$65=1),SUMIFS(Scenarios!$F$661:$F$900,Scenarios!$A$661:$A$900,$C$7,Scenarios!$B$661:$B$900,A23),NA()) -> 1769.46 | H23: =IF(AND($C$12="OK",Scenarios!E$65=1),SUMIFS(Scenarios!$O$661:$O$900,Scenarios!$A$661:$A$900,$C$7,Scenarios!$B$661:$B$900,A23),NA()) -> 4378.8054 | I23: =IF(AND($C$12="OK",Scenarios!D$65=1),SUMIFS(Scenarios!$O$411:$O$650,Scenarios!$A$411:$A$650,$C$7,Scenarios!$B$411:$B$650,A23),NA()) -> 0 | J23: =DAY(DATE($C$8,A23+1,0)) -> 30
A24: 5 | B24: 31 | C24: =IF($C$12="OK",(1-$C$44)*(1-$C$45)*INDEX($D$70:$D$5769,($C$40/5*25+$C$42/15)*12+A24)+$C$44*(1-$C$45)*INDEX($D$70:$D$5769,($C$41/5*25+$C$42/15)*12+A24)+(1-$C$44)*$C$45*INDEX($D$70:$D$5769,($C$40/5*25+$C$43/15)*12+A24)+$C$44*$C$45*INDEX($D$70:$D$5769,($C$41/5*25+$C$43/15)*12+A24),NA()) -> 162.72 | D24: =C24/B24 -> 5.2490323 | E24: =IF(AND($C$12="OK",Scenarios!C$65=1),SUMIFS(Scenarios!$F$161:$F$400,Scenarios!$A$161:$A$400,$C$7,Scenarios!$B$161:$B$400,A24),NA()) -> 1431.936 | F24: =IF(AND($C$12="OK",Scenarios!C$65=1),SUMIFS(Scenarios!$O$161:$O$400,Scenarios!$A$161:$A$400,$C$7,Scenarios!$B$161:$B$400,A24),NA()) -> 3527.397 | G24: =IF(AND($C$12="OK",Scenarios!E$65=1),SUMIFS(Scenarios!$F$661:$F$900,Scenarios!$A$661:$A$900,$C$7,Scenarios!$B$661:$B$900,A24),NA()) -> 1789.92 | H24: =IF(AND($C$12="OK",Scenarios!E$65=1),SUMIFS(Scenarios!$O$661:$O$900,Scenarios!$A$661:$A$900,$C$7,Scenarios!$B$661:$B$900,A24),NA()) -> 4522.2656 | I24: =IF(AND($C$12="OK",Scenarios!D$65=1),SUMIFS(Scenarios!$O$411:$O$650,Scenarios!$A$411:$A$650,$C$7,Scenarios!$B$411:$B$650,A24),NA()) -> 0 | J24: =DAY(DATE($C$8,A24+1,0)) -> 31
A25: 6 | B25: 30 | C25: =IF($C$12="OK",(1-$C$44)*(1-$C$45)*INDEX($D$70:$D$5769,($C$40/5*25+$C$42/15)*12+A25)+$C$44*(1-$C$45)*INDEX($D$70:$D$5769,($C$41/5*25+$C$42/15)*12+A25)+(1-$C$44)*$C$45*INDEX($D$70:$D$5769,($C$40/5*25+$C$43/15)*12+A25)+$C$44*$C$45*INDEX($D$70:$D$5769,($C$41/5*25+$C$43/15)*12+A25),NA()) -> 158.62 | D25: =C25/B25 -> 5.2873333 | E25: =IF(AND($C$12="OK",Scenarios!C$65=1),SUMIFS(Scenarios!$F$161:$F$400,Scenarios!$A$161:$A$400,$C$7,Scenarios!$B$161:$B$400,A25),NA()) -> 1395.856 | F25: =IF(AND($C$12="OK",Scenarios!C$65=1),SUMIFS(Scenarios!$O$161:$O$400,Scenarios!$A$161:$A$400,$C$7,Scenarios!$B$161:$B$400,A25),NA()) -> 3413.61 | G25: =IF(AND($C$12="OK",Scenarios!E$65=1),SUMIFS(Scenarios!$F$661:$F$900,Scenarios!$A$661:$A$900,$C$7,Scenarios!$B$661:$B$900,A25),NA()) -> 1744.82 | H25: =IF(AND($C$12="OK",Scenarios!E$65=1),SUMIFS(Scenarios!$O$661:$O$900,Scenarios!$A$661:$A$900,$C$7,Scenarios!$B$661:$B$900,A25),NA()) -> 4378.8054 | I25: =IF(AND($C$12="OK",Scenarios!D$65=1),SUMIFS(Scenarios!$O$411:$O$650,Scenarios!$A$411:$A$650,$C$7,Scenarios!$B$411:$B$650,A25),NA()) -> 0 | J25: =DAY(DATE($C$8,A25+1,0)) -> 30
A26: 7 | B26: 31 | C26: =IF($C$12="OK",(1-$C$44)*(1-$C$45)*INDEX($D$70:$D$5769,($C$40/5*25+$C$42/15)*12+A26)+$C$44*(1-$C$45)*INDEX($D$70:$D$5769,($C$41/5*25+$C$42/15)*12+A26)+(1-$C$44)*$C$45*INDEX($D$70:$D$5769,($C$40/5*25+$C$43/15)*12+A26)+$C$44*$C$45*INDEX($D$70:$D$5769,($C$41/5*25+$C$43/15)*12+A26),NA()) -> 164.66 | D26: =C26/B26 -> 5.3116129 | E26: =IF(AND($C$12="OK",Scenarios!C$65=1),SUMIFS(Scenarios!$F$161:$F$400,Scenarios!$A$161:$A$400,$C$7,Scenarios!$B$161:$B$400,A26),NA()) -> 1449.008 | F26: =IF(AND($C$12="OK",Scenarios!C$65=1),SUMIFS(Scenarios!$O$161:$O$400,Scenarios!$A$161:$A$400,$C$7,Scenarios!$B$161:$B$400,A26),NA()) -> 3527.397 | G26: =IF(AND($C$12="OK",Scenarios!E$65=1),SUMIFS(Scenarios!$F$661:$F$900,Scenarios!$A$661:$A$900,$C$7,Scenarios!$B$661:$B$900,A26),NA()) -> 1811.26 | H26: =IF(AND($C$12="OK",Scenarios!E$65=1),SUMIFS(Scenarios!$O$661:$O$900,Scenarios!$A$661:$A$900,$C$7,Scenarios!$B$661:$B$900,A26),NA()) -> 4522.2656 | I26: =IF(AND($C$12="OK",Scenarios!D$65=1),SUMIFS(Scenarios!$O$411:$O$650,Scenarios!$A$411:$A$650,$C$7,Scenarios!$B$411:$B$650,A26),NA()) -> 0 | J26: =DAY(DATE($C$8,A26+1,0)) -> 31
A27: 8 | B27: 31 | C27: =IF($C$12="OK",(1-$C$44)*(1-$C$45)*INDEX($D$70:$D$5769,($C$40/5*25+$C$42/15)*12+A27)+$C$44*(1-$C$45)*INDEX($D$70:$D$5769,($C$41/5*25+$C$42/15)*12+A27)+(1-$C$44)*$C$45*INDEX($D$70:$D$5769,($C$40/5*25+$C$43/15)*12+A27)+$C$44*$C$45*INDEX($D$70:$D$5769,($C$41/5*25+$C$43/15)*12+A27),NA()) -> 166.8 | D27: =C27/B27 -> 5.3806452 | E27: =IF(AND($C$12="OK",Scenarios!C$65=1),SUMIFS(Scenarios!$F$161:$F$400,Scenarios!$A$161:$A$400,$C$7,Scenarios!$B$161:$B$400,A27),NA()) -> 1467.84 | F27: =IF(AND($C$12="OK",Scenarios!C$65=1),SUMIFS(Scenarios!$O$161:$O$400,Scenarios!$A$161:$A$400,$C$7,Scenarios!$B$161:$B$400,A27),NA()) -> 3527.397 | G27: =IF(AND($C$12="OK",Scenarios!E$65=1),SUMIFS(Scenarios!$F$661:$F$900,Scenarios!$A$661:$A$900,$C$7,Scenarios!$B$661:$B$900,A27),NA()) -> 1834.8 | H27: =IF(AND($C$12="OK",Scenarios!E$65=1),SUMIFS(Scenarios!$O$661:$O$900,Scenarios!$A$661:$A$900,$C$7,Scenarios!$B$661:$B$900,A27),NA()) -> 4522.2656 | I27: =IF(AND($C$12="OK",Scenarios!D$65=1),SUMIFS(Scenarios!$O$411:$O$650,Scenarios!$A$411:$A$650,$C$7,Scenarios!$B$411:$B$650,A27),NA()) -> 0 | J27: =DAY(DATE($C$8,A27+1,0)) -> 31
A28: 9 | B28: 30 | C28: =IF($C$12="OK",(1-$C$44)*(1-$C$45)*INDEX($D$70:$D$5769,($C$40/5*25+$C$42/15)*12+A28)+$C$44*(1-$C$45)*INDEX($D$70:$D$5769,($C$41/5*25+$C$42/15)*12+A28)+(1-$C$44)*$C$45*INDEX($D$70:$D$5769,($C$40/5*25+$C$43/15)*12+A28)+$C$44*$C$45*INDEX($D$70:$D$5769,($C$41/5*25+$C$43/15)*12+A28),NA()) -> 161 | D28: =C28/B28 -> 5.3666667 | E28: =IF(AND($C$12="OK",Scenarios!C$65=1),SUMIFS(Scenarios!$F$161:$F$400,Scenarios!$A$161:$A$400,$C$7,Scenarios!$B$161:$B$400,A28),NA()) -> 1416.8 | F28: =IF(AND($C$12="OK",Scenarios!C$65=1),SUMIFS(Scenarios!$O$161:$O$400,Scenarios!$A$161:$A$400,$C$7,Scenarios!$B$161:$B$400,A28),NA()) -> 3413.61 | G28: =IF(AND($C$12="OK",Scenarios!E$65=1),SUMIFS(Scenarios!$F$661:$F$900,Scenarios!$A$661:$A$900,$C$7,Scenarios!$B$661:$B$900,A28),NA()) -> 1771 | H28: =IF(AND($C$12="OK",Scenarios!E$65=1),SUMIFS(Scenarios!$O$661:$O$900,Scenarios!$A$661:$A$900,$C$7,Scenarios!$B$661:$B$900,A28),NA()) -> 4378.8054 | I28: =IF(AND($C$12="OK",Scenarios!D$65=1),SUMIFS(Scenarios!$O$411:$O$650,Scenarios!$A$411:$A$650,$C$7,Scenarios!$B$411:$B$650,A28),NA()) -> 0 | J28: =DAY(DATE($C$8,A28+1,0)) -> 30
A29: 10 | B29: 31 | C29: =IF($C$12="OK",(1-$C$44)*(1-$C$45)*INDEX($D$70:$D$5769,($C$40/5*25+$C$42/15)*12+A29)+$C$44*(1-$C$45)*INDEX($D$70:$D$5769,($C$41/5*25+$C$42/15)*12+A29)+(1-$C$44)*$C$45*INDEX($D$70:$D$5769,($C$40/5*25+$C$43/15)*12+A29)+$C$44*$C$45*INDEX($D$70:$D$5769,($C$41/5*25+$C$43/15)*12+A29),NA()) -> 154.53 | D29: =C29/B29 -> 4.9848387 | E29: =IF(AND($C$12="OK",Scenarios!C$65=1),SUMIFS(Scenarios!$F$161:$F$400,Scenarios!$A$161:$A$400,$C$7,Scenarios!$B$161:$B$400,A29),NA()) -> 1359.864 | F29: =IF(AND($C$12="OK",Scenarios!C$65=1),SUMIFS(Scenarios!$O$161:$O$400,Scenarios!$A$161:$A$400,$C$7,Scenarios!$B$161:$B$400,A29),NA()) -> 3527.397 | G29: =IF(AND($C$12="OK",Scenarios!E$65=1),SUMIFS(Scenarios!$F$661:$F$900,Scenarios!$A$661:$A$900,$C$7,Scenarios!$B$661:$B$900,A29),NA()) -> 1699.83 | H29: =IF(AND($C$12="OK",Scenarios!E$65=1),SUMIFS(Scenarios!$O$661:$O$900,Scenarios!$A$661:$A$900,$C$7,Scenarios!$B$661:$B$900,A29),NA()) -> 4522.2656 | I29: =IF(AND($C$12="OK",Scenarios!D$65=1),SUMIFS(Scenarios!$O$411:$O$650,Scenarios!$A$411:$A$650,$C$7,Scenarios!$B$411:$B$650,A29),NA()) -> 0 | J29: =DAY(DATE($C$8,A29+1,0)) -> 31
A30: 11 | B30: 30 | C30: =IF($C$12="OK",(1-$C$44)*(1-$C$45)*INDEX($D$70:$D$5769,($C$40/5*25+$C$42/15)*12+A30)+$C$44*(1-$C$45)*INDEX($D$70:$D$5769,($C$41/5*25+$C$42/15)*12+A30)+(1-$C$44)*$C$45*INDEX($D$70:$D$5769,($C$40/5*25+$C$43/15)*12+A30)+$C$44*$C$45*INDEX($D$70:$D$5769,($C$41/5*25+$C$43/15)*12+A30),NA()) -> 136.97 | D30: =C30/B30 -> 4.5656667 | E30: =IF(AND($C$12="OK",Scenarios!C$65=1),SUMIFS(Scenarios!$F$161:$F$400,Scenarios!$A$161:$A$400,$C$7,Scenarios!$B$161:$B$400,A30),NA()) -> 1205.336 | F30: =IF(AND($C$12="OK",Scenarios!C$65=1),SUMIFS(Scenarios!$O$161:$O$400,Scenarios!$A$161:$A$400,$C$7,Scenarios!$B$161:$B$400,A30),NA()) -> 3399.0475 | G30: =IF(AND($C$12="OK",Scenarios!E$65=1),SUMIFS(Scenarios!$F$661:$F$900,Scenarios!$A$661:$A$900,$C$7,Scenarios!$B$661:$B$900,A30),NA()) -> 1506.67 | H30: =IF(AND($C$12="OK",Scenarios!E$65=1),SUMIFS(Scenarios!$O$661:$O$900,Scenarios!$A$661:$A$900,$C$7,Scenarios!$B$661:$B$900,A30),NA()) -> 4329.0191 | I30: =IF(AND($C$12="OK",Scenarios!D$65=1),SUMIFS(Scenarios!$O$411:$O$650,Scenarios!$A$411:$A$650,$C$7,Scenarios!$B$411:$B$650,A30),NA()) -> 0 | J30: =DAY(DATE($C$8,A30+1,0)) -> 30
A31: 12 | B31: 31 | C31: =IF($C$12="OK",(1-$C$44)*(1-$C$45)*INDEX($D$70:$D$5769,($C$40/5*25+$C$42/15)*12+A31)+$C$44*(1-$C$45)*INDEX($D$70:$D$5769,($C$41/5*25+$C$42/15)*12+A31)+(1-$C$44)*$C$45*INDEX($D$70:$D$5769,($C$40/5*25+$C$43/15)*12+A31)+$C$44*$C$45*INDEX($D$70:$D$5769,($C$41/5*25+$C$43/15)*12+A31),NA()) -> 130.4 | D31: =C31/B31 -> 4.2064516 | E31: =IF(AND($C$12="OK",Scenarios!C$65=1),SUMIFS(Scenarios!$F$161:$F$400,Scenarios!$A$161:$A$400,$C$7,Scenarios!$B$161:$B$400,A31),NA()) -> 1147.52 | F31: =IF(AND($C$12="OK",Scenarios!C$65=1),SUMIFS(Scenarios!$O$161:$O$400,Scenarios!$A$161:$A$400,$C$7,Scenarios!$B$161:$B$400,A31),NA()) -> 3236.0064 | G31: =IF(AND($C$12="OK",Scenarios!E$65=1),SUMIFS(Scenarios!$F$661:$F$900,Scenarios!$A$661:$A$900,$C$7,Scenarios!$B$661:$B$900,A31),NA()) -> 1434.4 | H31: =IF(AND($C$12="OK",Scenarios!E$65=1),SUMIFS(Scenarios!$O$661:$O$900,Scenarios!$A$661:$A$900,$C$7,Scenarios!$B$661:$B$900,A31),NA()) -> 4019.451 | I31: =IF(AND($C$12="OK",Scenarios!D$65=1),SUMIFS(Scenarios!$O$411:$O$650,Scenarios!$A$411:$A$650,$C$7,Scenarios!$B$411:$B$650,A31),NA()) -> 0 | J31: =DAY(DATE($C$8,A31+1,0)) -> 31
A32: Annual total | B32: =SUM(B20:B31) -> 365 | C32: =SUM(C20:C31) -> 1818.37 | D32: =C32/B32 -> 4.9818356 | E32: =SUM(E20:E31) -> 16001.656 | F32: =SUM(F20:F31) -> 40957.246 | G32: =SUM(G20:G31) -> 20002.07 | H32: =SUM(H20:H31) -> 52234.09 | I32: =SUM(I20:I31) -> 0 | J32: =SUM(J20:J31) -> 365
A34: Bill savings = baseline bill minus new bill. Unused PV has no export revenue.
A35: Net savings below include annual maintenance and replacement costs from the existing financial model.
A36: Annual net saving EGP | E36: =IF(AND($C$12="OK",Scenarios!C65=1),INDEX(Scenarios!C79:C98,$C$7),NA()) -> 39522.846 | G36: =IF(AND($C$12="OK",Scenarios!E65=1),INDEX(Scenarios!K79:K98,$C$7),NA()) -> 48073.45 | I36: =IF(AND($C$12="OK",Scenarios!D65=1),INDEX(Scenarios!G79:G98,$C$7),NA()) -> -2730.64
A38: Interpolation calculations
A40: Lower tilt | C40: =MIN(85,INT(C5/5)*5) -> 30
A41: Upper tilt | C41: =C40+5 -> 35
A42: Lower azimuth | C42: =MIN(345,INT(C6/15)*15) -> 180
A43: Upper azimuth | C43: =C42+15 -> 195
A44: Tilt weight | C44: =(C5-C40)/5 -> 0
A45: Azimuth weight | C45: =(C6-C42)/15 -> 0
A47: Model limits and next step
A48: Next: evaluate battery benefit with hourly PV, load and state-of-charge calculations, not monthly budgets.
A49: Roof/building shadows, row shading and inverter-specific clipping are not resolved by this monthly table.
A50: Changing orientation does not recalculate roof spacing. Existing saved scenarios remain historical captures.
A51: Calendar scaling: PVGIS monthly E_m / reference-month days x actual month days; then annual degradation.
A52: This is an experimental copy. The original workbook is retained until the trial is accepted.
A54: Raw PVGIS source table below: 475 orientations x 12 months. Values already include modeled PV losses.
A69: Tilt deg | B69: Compass deg | C69: Month | D69: E_m kWh/kWp | E69: E_d source rounded | F69: PVGIS source URL
A70: 0 | B70: 0 | C70: 1 | D70: 88.85 | E70: 2.87 | F70: https://re.jrc.ec.europa.eu/api/v5_3/PVcalc?lat=30.0444&lon=31.2357&peakpower=1&loss=14&angle=0&aspect=-180&outputformat=json&raddatabase=PVGIS-SARAH3&pvtechchoice=crystSi&mountingplace=free&usehorizon=1
A71: 0 | B71: 0 | C71: 2 | D71: 98.94 | E71: 3.53 | F71: https://re.jrc.ec.europa.eu/api/v5_3/PVcalc?lat=30.0444&lon=31.2357&peakpower=1&loss=14&angle=0&aspect=-180&outputformat=json&raddatabase=PVGIS-SARAH3&pvtechchoice=crystSi&mountingplace=free&usehorizon=1
A72: 0 | B72: 0 | C72: 3 | D72: 139.85 | E72: 4.51 | F72: https://re.jrc.ec.europa.eu/api/v5_3/PVcalc?lat=30.0444&lon=31.2357&peakpower=1&loss=14&angle=0&aspect=-180&outputformat=json&raddatabase=PVGIS-SARAH3&pvtechchoice=crystSi&mountingplace=free&usehorizon=1
A73: 0 | B73: 0 | C73: 4 | D73: 158.15 | E73: 5.27 | F73: https://re.jrc.ec.europa.eu/api/v5_3/PVcalc?lat=30.0444&lon=31.2357&peakpower=1&loss=14&angle=0&aspect=-180&outputformat=json&raddatabase=PVGIS-SARAH3&pvtechchoice=crystSi&mountingplace=free&usehorizon=1
A74: 0 | B74: 0 | C74: 5 | D74: 176.18 | E74: 5.68 | F74: https://re.jrc.ec.europa.eu/api/v5_3/PVcalc?lat=30.0444&lon=31.2357&peakpower=1&loss=14&angle=0&aspect=-180&outputformat=json&raddatabase=PVGIS-SARAH3&pvtechchoice=crystSi&mountingplace=free&usehorizon=1
A75: 0 | B75: 0 | C75: 6 | D75: 181.03 | E75: 6.03 | F75: https://re.jrc.ec.europa.eu/api/v5_3/PVcalc?lat=30.0444&lon=31.2357&peakpower=1&loss=14&angle=0&aspect=-180&outputformat=json&raddatabase=PVGIS-SARAH3&pvtechchoice=crystSi&mountingplace=free&usehorizon=1
A76: 0 | B76: 0 | C76: 7 | D76: 183.54 | E76: 5.92 | F76: https://re.jrc.ec.europa.eu/api/v5_3/PVcalc?lat=30.0444&lon=31.2357&peakpower=1&loss=14&angle=0&aspect=-180&outputformat=json&raddatabase=PVGIS-SARAH3&pvtechchoice=crystSi&mountingplace=free&usehorizon=1
A77: 0 | B77: 0 | C77: 8 | D77: 170.73 | E77: 5.51 | F77: https://re.jrc.ec.europa.eu/api/v5_3/PVcalc?lat=30.0444&lon=31.2357&peakpower=1&loss=14&angle=0&aspect=-180&outputformat=json&raddatabase=PVGIS-SARAH3&pvtechchoice=crystSi&mountingplace=free&usehorizon=1
A78: 0 | B78: 0 | C78: 9 | D78: 146.05 | E78: 4.87 | F78: https://re.jrc.ec.europa.eu/api/v5_3/PVcalc?lat=30.0444&lon=31.2357&peakpower=1&loss=14&angle=0&aspect=-180&outputformat=json&raddatabase=PVGIS-SARAH3&pvtechchoice=crystSi&mountingplace=free&usehorizon=1
A79: 0 | B79: 0 | C79: 10 | D79: 122.34 | E79: 3.95 | F79: https://re.jrc.ec.europa.eu/api/v5_3/PVcalc?lat=30.0444&lon=31.2357&peakpower=1&loss=14&angle=0&aspect=-180&outputformat=json&raddatabase=PVGIS-SARAH3&pvtechchoice=crystSi&mountingplace=free&usehorizon=1
A80: 0 | B80: 0 | C80: 11 | D80: 94.5 | E80: 3.15 | F80: https://re.jrc.ec.europa.eu/api/v5_3/PVcalc?lat=30.0444&lon=31.2357&peakpower=1&loss=14&angle=0&aspect=-180&outputformat=json&raddatabase=PVGIS-SARAH3&pvtechchoice=crystSi&mountingplace=free&usehorizon=1
A81: 0 | B81: 0 | C81: 12 | D81: 83.98 | E81: 2.71 | F81: https://re.jrc.ec.europa.eu/api/v5_3/PVcalc?lat=30.0444&lon=31.2357&peakpower=1&loss=14&angle=0&aspect=-180&outputformat=json&raddatabase=PVGIS-SARAH3&pvtechchoice=crystSi&mountingplace=free&usehorizon=1
... A5769: 90 | B5769: 360 | C5769: 12 | D5769: 10.36 | E5769: 0.33 | F5769: https://re.jrc.ec.europa.eu/api/v5_3/PVcalc?lat=30.0444&lon=31.2357&peakpower=1&loss=14&angle=90&aspect=180&outputformat=json&raddatabase=PVGIS-SARAH3&pvtechchoice=crystSi&mountingplace=free&usehorizon=1
