Workbook

Sheet Inputs
A2: AVESTA — Case Inputs | J2: Selected consumption and bill
A3: Edit the yellow cells. Location is fixed at Cairo. Initial values are the previous El Mo3alem example, not new measurements. | J3: Input status | L3: =IF(OR(C10<=0,COUNT(C10)=0),"Enter billing days",IF(AND(C6<>"Bill only",OR(C7<0,COUNT(C7)=0)),"Enter consumption",IF(AND(C6<>"Consumption only",OR(C8<0,COUNT(C8)=0)),"Enter bill amount",IF(AND(C6="Bill only",C66<>1),"Bill does not give a unique consumption",IF(AND(C14="Specified",OR(C15<=0,COUNT(C15)=0)),"Enter a positive area",IF(AND(C17="Known",OR(C18<0,C18>1,COUNT(C18)=0)),"Check daytime share",IF(AND(C20="Known",OR(C21<=0,COUNT(C21)=0)),"Enter a positive critical load","Ready for indicative calculation"))))))) -> Ready for indicative calculation
J4: Selected monthly use (kWh) | L4: =IF(L3<>"Ready for indicative calculation","Not available",IF(C6="Bill only",SUM(G50:G63),C7)) -> 2421
A5: Case name | C5: El Mo3alem shop — example | J5: Average consumption (kWh/day) | L5: =IF(ISNUMBER(L4),L4/C10,"Not available") -> 80.7
A6: Input mode | C6: Bill and consumption | J6: Active daytime energy share | L6: =IF(C17="Known",C18,'Assumptions and Catalog'!$C$13/24) -> 0.5
A7: Monthly consumption (kWh) | C7: 2421 | E7: Monthly use, not the cumulative meter reading | J7: Reference official bill (EGP) | L7: =IF(ISNUMBER(L4),IF(Inputs!$C$9="Residential",IF(L4<='Assumptions and Catalog'!$C$50,L4*'Assumptions and Catalog'!$H$50+'Assumptions and Catalog'!$E$50+'Assumptions and Catalog'!$F$50,IF(L4<='Assumptions and Catalog'!$C$51,L4*'Assumptions and Catalog'!$H$51+'Assumptions and Catalog'!$E$51+'Assumptions and Catalog'!$F$51,IF(L4<='Assumptions and Catalog'!$C$52,L4*'Assumptions and Catalog'!$H$52+'Assumptions and Catalog'!$E$52+'Assumptions and Catalog'!$F$52,IF(L4<='Assumptions and Catalog'!$C$53,L4*'Assumptions and Catalog'!$H$53+'Assumptions and Catalog'!$E$53+'Assumptions and Catalog'!$F$53,IF(L4<='Assumptions and Catalog'!$C$54,L4*'Assumptions and Catalog'!$H$54+'Assumptions and Catalog'!$E$54+'Assumptions and Catalog'!$F$54,IF(L4<='Assumptions and Catalog'!$C$55,L4*'Assumptions and Catalog'!$H$55+'Assumptions and Catalog'!$E$55+'Assumptions and Catalog'!$F$55,IF(L4<='Assumptions and Catalog'!$C$56,L4*'Assumptions and Catalog'!$H$56+'Assumptions and Catalog'!$E$56+'Assumptions and Catalog'!$F$56,IF(L4<='Assumptions and Catalog'!$C$57,L4*'Assumptions and Catalog'!$H$57+'Assumptions and Catalog'!$E$57+'Assumptions and Catalog'!$F$57,"Out of range")))))))),IF(L4<='Assumptions and Catalog'!$C$60,L4*'Assumptions and Catalog'!$H$60+'Assumptions and Catalog'!$E$60+'Assumptions and Catalog'!$F$60,IF(L4<='Assumptions and Catalog'!$C$61,L4*'Assumptions and Catalog'!$H$61+'Assumptions and Catalog'!$E$61+'Assumptions and Catalog'!$F$61,IF(L4<='Assumptions and Catalog'!$C$62,L4*'Assumptions and Catalog'!$H$62+'Assumptions and Catalog'!$E$62+'Assumptions and Catalog'!$F$62,IF(L4<='Assumptions and Catalog'!$C$63,L4*'Assumptions and Catalog'!$H$63+'Assumptions and Catalog'!$E$63+'Assumptions and Catalog'!$F$63,IF(L4<='Assumptions and Catalog'!$C$64,L4*'Assumptions and Catalog'!$H$64+'Assumptions and Catalog'!$E$64+'Assumptions and Catalog'!$F$64,IF(L4<='Assumptions and Catalog'!$C$65,L4*'Assumptions and Catalog'!$H$65+'Assumptions and Catalog'!$E$65+'Assumptions and Catalog'!$F$65,"Out of range"))))))),"Not available") -> 6867.22
A8: Monthly bill amount (EGP) | C8: 8279 | E8: Consumption bill, not a prepaid top-up | J8: Paid less official bill (EGP) | L8: =IF(AND(C6="Bill and consumption",ISNUMBER(L7)),C8-L7,"Not available") -> 1411.78
A9: Tariff category | C9: Commercial | J9: Active pricing basis | L9: =IF(AND(C6="Bill and consumption",C7>0,C11="Actual flat rate"),"Actual flat rate","Official") -> Actual flat rate
A10: Billing period days | C10: 30 | J10: Actual average (EGP/kWh) | L10: =IF(AND(C6="Bill and consumption",C7>0),C8/C7,"Not available") -> 3.4196613
A11: Pricing basis | C11: Actual flat rate | E11: Actual flat rate is available only with both bill amount and consumption | J11: Official average (EGP/kWh) | L11: =IF(AND(ISNUMBER(L4),L4>0),L7/L4,"Not available") -> 2.8365221
J12: Average rate difference (EGP/kWh) | L12: =IF(AND(ISNUMBER(L10),ISNUMBER(L11)),L10-L11,"Not available") -> 0.5831392
J13: Selected baseline bill (EGP) | L13: =IF(ISNUMBER(L4),IF(L9="Actual flat rate",L4*L10,L7),"Not available") -> 8279
A14: Available installation area | C14: Unspecified | J14: Reference-data status | L14: ="Reference tariffs and prices: verify before commercial use" -> Reference tariffs and prices: verify before commercial use
A15: Available area (m2) | C15: 50 | E15: Usable installation area after obstacles; unspecified area sets no cap
A17: Energy distribution | C17: Constant load
A18: Daytime energy share | C18: 0.5 | E18: Share of energy, not appliance count; night share is calculated
A20: Critical load | C20: Unknown
A21: Critical load (kW) | C21: 4 | E21: When unknown, no customer-specific backup hours are calculated
A39: Enter the case inputs, review assumptions, then choose equipment and quantities on the Scenarios sheet.
A40: Actual flat rate spreads the paid bill over kWh; it may differ from the marginal cost of avoided electricity.
A41: One representative day/night cycle per month with constant daily load. This is not an hourly simulation.
A47: Inverse-bill calculations — audit detail
A49: Tariff | B49: Above | C49: Up to | D49: Candidate kWh | E49: Candidate bill | F49: Valid solution 1/0 | G49: Accepted kWh
A50: ='Assumptions and Catalog'!$A$50 -> Residential | B50: ='Assumptions and Catalog'!$B$50 -> -1 | C50: ='Assumptions and Catalog'!$C$50 -> 0 | D50: =IF('Assumptions and Catalog'!$H$50=0,0,($C$8-'Assumptions and Catalog'!$E$50-'Assumptions and Catalog'!$F$50)/'Assumptions and Catalog'!$H$50) -> 0 | E50: =D50*'Assumptions and Catalog'!$H$50+'Assumptions and Catalog'!$E$50+'Assumptions and Catalog'!$F$50 -> 9 | F50: =IF(AND(A50=$C$9,D50>B50,D50<=C50,D50>=0,ABS(E50-$C$8)<='Assumptions and Catalog'!$C$25),1,0) -> 0 | G50: =IF(F50=1,D50,0) -> 0
A51: ='Assumptions and Catalog'!$A$51 -> Residential | B51: ='Assumptions and Catalog'!$B$51 -> 0 | C51: ='Assumptions and Catalog'!$C$51 -> 50 | D51: =IF('Assumptions and Catalog'!$H$51=0,0,($C$8-'Assumptions and Catalog'!$E$51-'Assumptions and Catalog'!$F$51)/'Assumptions and Catalog'!$H$51) -> 12173.529 | E51: =D51*'Assumptions and Catalog'!$H$51+'Assumptions and Catalog'!$E$51+'Assumptions and Catalog'!$F$51 -> 8279 | F51: =IF(AND(A51=$C$9,D51>B51,D51<=C51,D51>=0,ABS(E51-$C$8)<='Assumptions and Catalog'!$C$25),1,0) -> 0 | G51: =IF(F51=1,D51,0) -> 0
A52: ='Assumptions and Catalog'!$A$52 -> Residential | B52: ='Assumptions and Catalog'!$B$52 -> 50 | C52: ='Assumptions and Catalog'!$C$52 -> 100 | D52: =IF('Assumptions and Catalog'!$H$52=0,0,($C$8-'Assumptions and Catalog'!$E$52-'Assumptions and Catalog'!$F$52)/'Assumptions and Catalog'!$H$52) -> 9524.7126 | E52: =D52*'Assumptions and Catalog'!$H$52+'Assumptions and Catalog'!$E$52+'Assumptions and Catalog'!$F$52 -> 8279 | F52: =IF(AND(A52=$C$9,D52>B52,D52<=C52,D52>=0,ABS(E52-$C$8)<='Assumptions and Catalog'!$C$25),1,0) -> 0 | G52: =IF(F52=1,D52,0) -> 0
A53: ='Assumptions and Catalog'!$A$53 -> Residential | B53: ='Assumptions and Catalog'!$B$53 -> 100 | C53: ='Assumptions and Catalog'!$C$53 -> 200 | D53: =IF('Assumptions and Catalog'!$H$53=0,0,($C$8-'Assumptions and Catalog'!$E$53-'Assumptions and Catalog'!$F$53)/'Assumptions and Catalog'!$H$53) -> 8273 | E53: =D53*'Assumptions and Catalog'!$H$53+'Assumptions and Catalog'!$E$53+'Assumptions and Catalog'!$F$53 -> 8279 | F53: =IF(AND(A53=$C$9,D53>B53,D53<=C53,D53>=0,ABS(E53-$C$8)<='Assumptions and Catalog'!$C$25),1,0) -> 0 | G53: =IF(F53=1,D53,0) -> 0
A54: ='Assumptions and Catalog'!$A$54 -> Residential | B54: ='Assumptions and Catalog'!$B$54 -> 200 | C54: ='Assumptions and Catalog'!$C$54 -> 350 | D54: =IF('Assumptions and Catalog'!$H$54=0,0,($C$8-'Assumptions and Catalog'!$E$54-'Assumptions and Catalog'!$F$54)/'Assumptions and Catalog'!$H$54) -> 4863.5838 | E54: =D54*'Assumptions and Catalog'!$H$54+'Assumptions and Catalog'!$E$54+'Assumptions and Catalog'!$F$54 -> 8279 | F54: =IF(AND(A54=$C$9,D54>B54,D54<=C54,D54>=0,ABS(E54-$C$8)<='Assumptions and Catalog'!$C$25),1,0) -> 0 | G54: =IF(F54=1,D54,0) -> 0
A55: ='Assumptions and Catalog'!$A$55 -> Residential | B55: ='Assumptions and Catalog'!$B$55 -> 350 | C55: ='Assumptions and Catalog'!$C$55 -> 650 | D55: =IF('Assumptions and Catalog'!$H$55=0,0,($C$8-'Assumptions and Catalog'!$E$55-'Assumptions and Catalog'!$F$55)/'Assumptions and Catalog'!$H$55) -> 3930.0459 | E55: =D55*'Assumptions and Catalog'!$H$55+'Assumptions and Catalog'!$E$55+'Assumptions and Catalog'!$F$55 -> 8279 | F55: =IF(AND(A55=$C$9,D55>B55,D55<=C55,D55>=0,ABS(E55-$C$8)<='Assumptions and Catalog'!$C$25),1,0) -> 0 | G55: =IF(F55=1,D55,0) -> 0
A56: ='Assumptions and Catalog'!$A$56 -> Residential | B56: ='Assumptions and Catalog'!$B$56 -> 650 | C56: ='Assumptions and Catalog'!$C$56 -> 1000 | D56: =IF('Assumptions and Catalog'!$H$56=0,0,($C$8-'Assumptions and Catalog'!$E$56-'Assumptions and Catalog'!$F$56)/'Assumptions and Catalog'!$H$56) -> 3512.3404 | E56: =D56*'Assumptions and Catalog'!$H$56+'Assumptions and Catalog'!$E$56+'Assumptions and Catalog'!$F$56 -> 8279 | F56: =IF(AND(A56=$C$9,D56>B56,D56<=C56,D56>=0,ABS(E56-$C$8)<='Assumptions and Catalog'!$C$25),1,0) -> 0 | G56: =IF(F56=1,D56,0) -> 0
A57: ='Assumptions and Catalog'!$A$57 -> Residential | B57: ='Assumptions and Catalog'!$B$57 -> 1000 | C57: ='Assumptions and Catalog'!$C$57 -> 10000000 | D57: =IF('Assumptions and Catalog'!$H$57=0,0,($C$8-'Assumptions and Catalog'!$E$57-'Assumptions and Catalog'!$F$57)/'Assumptions and Catalog'!$H$57) -> 2850.8651 | E57: =D57*'Assumptions and Catalog'!$H$57+'Assumptions and Catalog'!$E$57+'Assumptions and Catalog'!$F$57 -> 8279 | F57: =IF(AND(A57=$C$9,D57>B57,D57<=C57,D57>=0,ABS(E57-$C$8)<='Assumptions and Catalog'!$C$25),1,0) -> 0 | G57: =IF(F57=1,D57,0) -> 0
A58: ='Assumptions and Catalog'!$A$60 -> Commercial | B58: ='Assumptions and Catalog'!$B$60 -> -1 | C58: ='Assumptions and Catalog'!$C$60 -> 0 | D58: =IF('Assumptions and Catalog'!$H$60=0,0,($C$8-'Assumptions and Catalog'!$E$60-'Assumptions and Catalog'!$F$60)/'Assumptions and Catalog'!$H$60) -> 0 | E58: =D58*'Assumptions and Catalog'!$H$60+'Assumptions and Catalog'!$E$60+'Assumptions and Catalog'!$F$60 -> 9 | F58: =IF(AND(A58=$C$9,D58>B58,D58<=C58,D58>=0,ABS(E58-$C$8)<='Assumptions and Catalog'!$C$25),1,0) -> 0 | G58: =IF(F58=1,D58,0) -> 0
A59: ='Assumptions and Catalog'!$A$61 -> Commercial | B59: ='Assumptions and Catalog'!$B$61 -> 0 | C59: ='Assumptions and Catalog'!$C$61 -> 100 | D59: =IF('Assumptions and Catalog'!$H$61=0,0,($C$8-'Assumptions and Catalog'!$E$61-'Assumptions and Catalog'!$F$61)/'Assumptions and Catalog'!$H$61) -> 5014.5455 | E59: =D59*'Assumptions and Catalog'!$H$61+'Assumptions and Catalog'!$E$61+'Assumptions and Catalog'!$F$61 -> 8279 | F59: =IF(AND(A59=$C$9,D59>B59,D59<=C59,D59>=0,ABS(E59-$C$8)<='Assumptions and Catalog'!$C$25),1,0) -> 0 | G59: =IF(F59=1,D59,0) -> 0
A60: ='Assumptions and Catalog'!$A$62 -> Commercial | B60: ='Assumptions and Catalog'!$B$62 -> 100 | C60: ='Assumptions and Catalog'!$C$62 -> 250 | D60: =IF('Assumptions and Catalog'!$H$62=0,0,($C$8-'Assumptions and Catalog'!$E$62-'Assumptions and Catalog'!$F$62)/'Assumptions and Catalog'!$H$62) -> 3773.516 | E60: =D60*'Assumptions and Catalog'!$H$62+'Assumptions and Catalog'!$E$62+'Assumptions and Catalog'!$F$62 -> 8279 | F60: =IF(AND(A60=$C$9,D60>B60,D60<=C60,D60>=0,ABS(E60-$C$8)<='Assumptions and Catalog'!$C$25),1,0) -> 0 | G60: =IF(F60=1,D60,0) -> 0
A61: ='Assumptions and Catalog'!$A$63 -> Commercial | B61: ='Assumptions and Catalog'!$B$63 -> 250 | C61: ='Assumptions and Catalog'!$C$63 -> 600 | D61: =IF('Assumptions and Catalog'!$H$63=0,0,($C$8-'Assumptions and Catalog'!$E$63-'Assumptions and Catalog'!$F$63)/'Assumptions and Catalog'!$H$63) -> 3093.2584 | E61: =D61*'Assumptions and Catalog'!$H$63+'Assumptions and Catalog'!$E$63+'Assumptions and Catalog'!$F$63 -> 8279 | F61: =IF(AND(A61=$C$9,D61>B61,D61<=C61,D61>=0,ABS(E61-$C$8)<='Assumptions and Catalog'!$C$25),1,0) -> 0 | G61: =IF(F61=1,D61,0) -> 0
A62: ='Assumptions and Catalog'!$A$64 -> Commercial | B62: ='Assumptions and Catalog'!$B$64 -> 600 | C62: ='Assumptions and Catalog'!$C$64 -> 1000 | D62: =IF('Assumptions and Catalog'!$H$64=0,0,($C$8-'Assumptions and Catalog'!$E$64-'Assumptions and Catalog'!$F$64)/'Assumptions and Catalog'!$H$64) -> 3001.444 | E62: =D62*'Assumptions and Catalog'!$H$64+'Assumptions and Catalog'!$E$64+'Assumptions and Catalog'!$F$64 -> 8279 | F62: =IF(AND(A62=$C$9,D62>B62,D62<=C62,D62>=0,ABS(E62-$C$8)<='Assumptions and Catalog'!$C$25),1,0) -> 0 | G62: =IF(F62=1,D62,0) -> 0
A63: ='Assumptions and Catalog'!$A$65 -> Commercial | B63: ='Assumptions and Catalog'!$B$65 -> 1000 | C63: ='Assumptions and Catalog'!$C$65 -> 10000000 | D63: =IF('Assumptions and Catalog'!$H$65=0,0,($C$8-'Assumptions and Catalog'!$E$65-'Assumptions and Catalog'!$F$65)/'Assumptions and Catalog'!$H$65) -> 2921.6312 | E63: =D63*'Assumptions and Catalog'!$H$65+'Assumptions and Catalog'!$E$65+'Assumptions and Catalog'!$F$65 -> 8279 | F63: =IF(AND(A63=$C$9,D63>B63,D63<=C63,D63>=0,ABS(E63-$C$8)<='Assumptions and Catalog'!$C$25),1,0) -> 1 | G63: =IF(F63=1,D63,0) -> 2921.6312
A66: Accepted solution count | C66: =SUM(F50:F63) -> 1

Sheet Assumptions and Catalog
A2: AVESTA — Assumptions and Catalog
A3: Yellow cells are editable. Equipment prices and limits are illustrative, not supplier quotes or manufacturer specifications.
A6: Study period | B6: years | C6: 10 | D6: 1 to 20
A7: Nominal discount rate | B7: % | C7: 0.1 | D7: Illustrative assumption; approval needed
A8: Tariff and fee escalation | B8: % per year | C8: 0 | D8: Flat by default; applies to all bill components
A9: Maintenance cost escalation | B9: % per year | C9: 0 | D9: Assumed cost escalation
A10: Annual PV degradation | B10: % per year | C10: 0.005 | D10: Assumption
A11: Charge efficiency | B11: % | C11: 0.975 | D11: AC input to stored energy
A12: Discharge efficiency | B12: % | C12: 0.975 | D12: Stored energy to AC load
A13: Daytime duration | B13: hours/day | C13: 12 | D13: Not PSH; used only to split daily load
A14: PV charging window | B14: hours/day | C14: 6 | D14: Approximate power window, not hourly simulation
A15: Grid charging window | B15: hours/day | C15: 8 | D15: Battery-only scenario
A16: Installation area multiplier | B16: times panel area | C16: 1.5 | D16: Includes assumed installation clearances
A17: Installation and BOS | B17: % of equipment | C17: 0.1 | D17: Applied once to PV, battery and inverter
... A26: Battery auxiliary consumption | B26: kWh/day | C26: 0 | D26: Not estimated; enter standby consumption
A29: Cairo average solar yield
A31: Average daily PV yield | B31: kWh/kWp/day | C31: 4.98 | D31: Monthly generation = PV kWp × daily yield × calendar days.
A33: 4.98 kWh/kWp/day is the rounded Cairo annual daily average from the previous PVGIS reference.
A34: Cairo; south-facing, 30° tilt. PV losses are included. No monthly solar seasonality is modeled.
A35: Source: European Commission JRC PVGIS 5.3 / SARAH3, prior project extract dated 30 September 2026.
A36: https://re.jrc.ec.europa.eu/pvg_tools/en/
A46: Editable reference tariff bands
A47: Tariffs from prior project files; current applicability could not be confirmed from the regulator link. Verify before commercial use.
A49: Type | B49: Above kWh | C49: Up to kWh | D49: Energy rate | E49: Energy intercept | F49: Service fee (EGP) | G49: Stamp/kWh | H49: Marginal rate incl. stamp
A50: Residential | B50: -1 | C50: 0 | D50: 0 | E50: 0 | F50: 9 | G50: 0 | H50: =D50+G50 -> 0
A51: Residential | B51: 0 | C51: 50 | D51: 0.68 | E51: 0 | F51: 1 | G51: 0 | H51: =D51+G51 -> 0.68
A52: Residential | B52: 50 | C52: 100 | D52: 0.87 | E52: =C51*D51-C51*D52 -> -9.5 | F52: 2 | G52: 0 | H52: =D52+G52 -> 0.87
A53: Residential | B53: 100 | C53: 200 | D53: 1 | E53: 0 | F53: 6 | G53: 0 | H53: =D53+G53 -> 1
A54: Residential | B54: 200 | C54: 350 | D54: 1.73 | E54: =C53*D53-C53*D54 -> -146 | F54: 11 | G54: 0 | H54: =D54+G54 -> 1.73
A55: Residential | B55: 350 | C55: 650 | D55: 2.18 | E55: =C54*D54+E54-C54*D55 -> -303.5 | F55: 15 | G55: 0 | H55: =D55+G55 -> 2.18
A56: Residential | B56: 650 | C56: 1000 | D56: 2.35 | E56: 0 | F56: 25 | G56: 0 | H56: =D56+G56 -> 2.35
A57: Residential | B57: 1000 | C57: 10000000 | D57: 2.89 | E57: 0 | F57: 40 | G57: 0 | H57: =D57+G57 -> 2.89
A60: Commercial | B60: -1 | C60: 0 | D60: 0 | E60: 0 | F60: 9 | G60: 0 | H60: =D60+G60 -> 0
A61: Commercial | B61: 0 | C61: 100 | D61: 1.62 | E61: 0 | F61: 5 | G61: 0.03 | H61: =D61+G61 -> 1.65
A62: Commercial | B62: 100 | C62: 250 | D62: 2.16 | E62: 0 | F62: 15 | G62: 0.03 | H62: =D62+G62 -> 2.19
A63: Commercial | B63: 250 | C63: 600 | D63: 2.64 | E63: 0 | F63: 20 | G63: 0.03 | H63: =D63+G63 -> 2.67
A64: Commercial | B64: 600 | C64: 1000 | D64: 2.74 | E64: =C63*D63-C63*D64 -> -60 | F64: 25 | G64: 0.03 | H64: =D64+G64 -> 2.77
A65: Commercial | B65: 1000 | C65: 10000000 | D65: 2.79 | E65: 0 | F65: 40 | G65: 0.03 | H65: =D65+G65 -> 2.82
A67: Residential rates: prior project model; service fees require confirmation. Commercial: prior El Mo3alem presentation (April 2026).
A68: https://www.egyptera.org/ar/TarrifApril2026.aspx — verification on 19 October 2026 returned 404. Annual stamp excluded.
A71: Example panels — replace with supplier specifications
A72: ID | B72: Name | C72: Wp | D72: Panel area (m2) | E72: Panel price (EGP)
A73: PV550 | B73: Example panel 550 | C73: 550 | D73: 2.6 | E73: 4400
A74: PV670 | B74: Example panel 670 | C74: 670 | D74: 2.7 | E74: 5360
A77: Example batteries — confirm real compatibility
A78: ID | B78: Description | C78: Nominal kWh | D78: Usable fraction | E78: Charge kW | F78: Discharge kW | G78: Price (EGP) | H78: Compatibility group
A79: BAT10 | B79: Example battery 10 | C79: 10 | D79: 0.8 | E79: 5 | F79: 5 | G79: 136400 | H79: LV
A80: BAT16 | B80: Example battery 16 | C80: 16 | D80: 0.8 | E80: 8 | F80: 8 | G80: 218240 | H80: LV
A81: BAT32 | B81: Example battery 32 | C81: 32 | D81: 0.8 | E81: 10 | F81: 10 | G81: 436480 | H81: LV
A84: Example inverters — not product recommendations
A85: ID | B85: Description | C85: AC kW | D85: PV limit kWp | E85: Charge kW | F85: Backup 1/0 | G85: Price (EGP) | H85: Compatibility group | I85: Phases
A86: GRID10 | B86: Grid-tied solar 10 | C86: 10 | D86: 13 | E86: 0 | F86: 0 | G86: 60000 | H86: NONE | I86: 3
A87: HYB5 | B87: Hybrid 5 | C87: 5 | D87: 6.5 | E87: 5 | F87: 1 | G87: 30000 | H87: LV | I87: 1
A88: HYB12 | B88: Hybrid 12 | C88: 12 | D88: 15.6 | E88: 10 | F88: 1 | G88: 72000 | H88: LV | I88: 3
A89: HYB20 | B89: Hybrid 20 | C89: 20 | D89: 26 | E89: 15 | F89: 1 | G89: 120000 | H89: LV | I89: 3
A92: Example prices from the prior presentation: PV 8,000 EGP/kWp, battery 13,640 EGP/kWh, inverter 6,000 EGP/kW.
A93: Power, area and compatibility limits are illustrative. They are not certified AVESTA specifications and exclude load starting currents.
A100: Formula reference
A101: Each distinct calculation is explained once. Repeated monthly and scenario formulas use the same rule. Cell references point to the working formulas.
A103: Calculation | B103: Equation / rule | D103: Parameters and units | G103: Purpose and workbook location
A104: 1. Consumption and tariff
A105: Input validity | B105: Ready only when the selected inputs are numeric and within their permitted ranges. | D105: Days > 0. Consumption and bill >= 0 when required. Specified roof and known critical load > 0. Day share is 0 to 1. Bill-only requires exactly one valid solution. | G105: Stops unavailable or ambiguous inputs from being treated as a valid case. Inputs!C25.
A106: Tariff marginal rate | B106: m = energy rate + stamp rate | D106: m: EGP/kWh. Energy rate: column D. Stamp rate: column G in the tariff table. | G106: Combines variable charges for the selected band. Assumptions and Catalog!H50:H65.
A107: Tariff band intercept | B107: b = previous upper limit × previous rate + previous intercept - previous upper limit × new rate | D107: b: fixed energy adjustment in EGP. Used only for the continuous bands. Other bands use their entered intercept, including full-consumption resets. | G107: Preserves the specific tariff's band rules. Assumptions and Catalog!E52, E54:E55 and E64.
A108: Official monthly bill | B108: T(E) = E × m + b + fee, using the first band whose upper limit contains E | D108: E: monthly kWh. m: marginal EGP/kWh. b: energy intercept, EGP. fee: service charge, EGP. Tariff type selects the residential or commercial table. | G108: Computes the actual piecewise bill instead of multiplying all consumption by an average price. Inputs!C29 and Scenarios!M:N monthly blocks.
A109: Inverse bill candidate | B109: E_candidate = (Paid - b - fee) / m; use 0 when m = 0 | D109: Paid, b and fee: EGP. m: EGP/kWh. Each tariff band is tested separately. The zero-rate band's candidate still has to pass the bill check. | G109: Estimates monthly consumption when only the bill is known. Inputs!D50:D63.
A110: Inverse bill validation | B110: Valid = 1 if type matches, lower < E_candidate <= upper, E_candidate >= 0 and ABS(candidate bill - Paid) <= tolerance; otherwise 0 | D110: Candidate bill = E_candidate × m + b + fee. Tolerance: Assumptions and Catalog!C25, EGP. Bounds and tariff type come from the selected band. | G110: Rejects candidates that do not belong to the band or do not reproduce the bill. Inputs!E50:F63.
A111: Accepted consumption | B111: Solution count = SUM(valid flags). E_month = SUM(valid candidates) only if count = 1; otherwise use entered kWh when that input mode applies | D111: Valid candidates: candidate kWh where flag = 1, else 0. Invalid inputs return an unavailable message. | G111: Avoids silently selecting a solution when bill inversion is ambiguous. Inputs!G50:G63, C66 and C26.
A112: Daily consumption | B112: E_day = E_month / period days | D112: E_month: accepted monthly kWh. Period days: Inputs!C10. E_day: kWh/day. | G112: Normalizes the entered billing period to a constant daily load used throughout the forecast. Inputs!C27.
A113: Day and night split | B113: Day share = entered share if known, else daylight hours / 24. Day load = E_day × day share. Night load = E_day - day load | D113: Day and night loads: kWh/day. Daylight hours: Assumptions and Catalog!C13. Share is a fraction of energy, not appliance count. | G113: Separates direct solar demand from demand that may use stored energy. Inputs!C28; Scenarios!D:E monthly blocks.
A114: Actual and official average prices | B114: p_actual = Paid / E_month; p_official = T(E_month) / E_month; price gap = p_actual - p_official | D114: Prices: EGP/kWh. Actual price requires both bill and positive consumption. Official average also requires positive consumption. | G114: Shows the difference between the paid average and the tariff-based average. Inputs!C32:C34.
A115: Bill difference | B115: Bill gap = Paid - T(E_month) | D115: Paid and official bill: EGP for the entered month. Available only when both bill and consumption were supplied. | G115: Shows how much more or less was paid than the reference tariff calculation. Inputs!C30.
A116: Selected pricing basis | B116: B(E) = E × p_actual in Actual flat mode; otherwise B(E) = T(E) | D116: Actual flat mode is accepted only with both bill and positive consumption. B(E): EGP for any monthly import E. | G116: Uses the chosen price basis consistently for baseline and post-installation bills. Inputs!C31, C35; Scenarios!M, N and Q monthly blocks. A paid average is not necessarily an avoidable marginal price.
A117: 2. Equipment, area and initial investment
A118: Catalog lookup | B118: Specification = INDEX(catalog data, MATCH(selected model ID, catalog IDs, 0), specification column) | D118: Model IDs: Scenarios!C39:E43. Catalogs: Assumptions and Catalog rows 73:74, 79:81 and 86:89. | G118: Retrieves the chosen equipment's capacity, power, area, price and compatibility. Used throughout Scenarios!C51:E70.
A119: Installed PV capacity | B119: P_PV = panel count × panel Wp / 1000 | D119: P_PV: kWp. Panel rating: Wp. Battery-only sets PV capacity to zero. | G119: Determines solar generation and checks the inverter PV limit. Scenarios!C51:E51; summary row 7.
A120: Battery nominal and usable capacity | B120: C_nom = battery count × unit kWh. C_usable = C_nom × usable fraction | D120: Capacities: kWh stored internally. Usable fraction: catalog value from 0 to 1. Solar-only sets nominal battery capacity to zero. | G120: Distinguishes purchased capacity from usable storage before reserve and losses. Scenarios!C52:E52 and C55:E55; summary row 8.
A121: Inverter ratings and support | B121: P_inv, PV_limit and backup flag = selected inverter catalog values | D121: P_inv: AC kW. PV_limit: allowed PV kWp. Backup flag: 1 supported, 0 unsupported; solar-only forces 0. | G121: Supplies the inverter limits and backup eligibility. Scenarios!C53:E54 and C58:E58; summary row 9.
A122: Charge and discharge power limits | B122: P_ch = MIN(count × battery charge kW, inverter charge kW). P_dis = MIN(count × battery discharge kW, inverter AC kW) | D122: P_ch and P_dis: kW at the model's AC boundary. Battery count and ratings come from the selected configuration. | G122: Limits charging, discharge and backup by both battery and inverter ratings. Scenarios!C56:E57.
A123: Installation area | B123: Area = (P_PV × 1000 / panel Wp) × panel area × spacing factor | D123: Area and panel area: m2. Spacing factor: Assumptions and Catalog!C16. Parenthesis recovers the active panel count. | G123: Checks whether the chosen array fits a specified roof. An unspecified roof does not constrain sizing. Scenarios!C59:E59; summary row 10.
A124: Equipment costs | B124: PV cost = active panel count × panel price. Battery cost = active battery count × battery price. Inverter cost = catalog inverter price | D124: Costs: EGP. Active counts are recovered from installed capacities, so inactive scenario equipment is excluded. | G124: Builds the equipment subtotal from the selected models and quantities. Scenarios!C60:E62.
A125: BOS and initial investment | B125: BOS = (PV cost + battery cost + inverter cost) × BOS rate. CAPEX = equipment subtotal + BOS | D125: BOS: installation and balance of system cost, EGP. BOS rate: Assumptions and Catalog!C17. CAPEX: upfront EGP. | G125: Calculates the year-zero investment without adding installation twice. Scenarios!C63:E64; summary row 11.
A126: Battery compatibility | B126: Compatible if nominal battery capacity = 0 OR battery group = inverter group | D126: Compatibility group: catalog text, such as LV. This is a catalog-group check, not a complete electrical design check. | G126: Flags incompatible selections before interpreting the results. Scenarios!C66:E66.
A127: Configuration validity | B127: Valid = 1 when inputs are ready, PV <= inverter PV limit, specified roof fits, compatibility passes, counts are nonnegative integers, reserve is 0 to 1, efficiencies are > 0 and <= 1, and study years are 1 to 20 | D127: Limits and flags come from the input, assumptions and sizing cells. All conditions must pass. | G127: Gates reported financial results and backup runtime. Scenarios!C65:E65 and C6:E6.
A128: Roof status | B128: Unspecified roof: fit not verified. Specified roof: compare required area <= available area | D128: Both areas: m2. Available area: Inputs!C15, used only when Inputs!C14 is Specified. | G128: Separates an unconstrained estimate from a layout that fits the supplied area. Scenarios!C26:E26.
A129: Year-one maintenance | B129: OM_1 = CAPEX × annual maintenance rate | D129: OM_1: EGP/year. Maintenance rate: Assumptions and Catalog!C18. | G129: Provides the recurring operating-cost base used in annual net savings. Scenarios!C70:E70.
A130: 3. Monthly solar and battery energy
A131: Monthly calculation scope | B131: Solar-only: rows 161:400. Battery-only: rows 411:650. Solar + battery: rows 661:900. Each block has 12 months × 20 years. | D131: Unless stated otherwise, references below are in Scenarios. y is study year starting at 1. n is calendar days in the month. Monthly energy is kWh. | G131: Explains repeated formulas once. The study horizon controls financial inclusion; monthly physical calculations remain available for all 20 years.
A132: Calendar month length | B132: n = DAY(DATE(first forecast year + y - 1, month + 1, 0)) | D132: First forecast year: Assumptions and Catalog!C24. Month: 1 to 12. n includes leap years. | G132: Converts constant daily energy into the correct monthly quantity. Scenarios monthly column C.
A133: Solar generation | B133: E_PV = P_PV × Y_daily × n × (1 - d_PV)^(y - 1) | D133: P_PV: installed kWp. Y_daily: Assumptions and Catalog!C31, kWh/kWp/day. d_PV: annual PV degradation at C10. | G133: Uses the single Cairo average and annual degradation. The yield includes PV losses; no monthly seasonality or hourly clipping is modeled. Scenarios monthly column F.
A134: Direct solar use | B134: E_direct = MIN(E_PV, day load × n) | D134: E_PV: monthly solar generation. Day load: kWh/day from the consumption split. | G134: Limits directly consumed solar to estimated daytime energy demand. Scenarios monthly column G. This is an aggregate energy estimate.
A135: Battery age | B135: Age = y - replacement year if replacement year > 0 and y >= replacement year; otherwise Age = y - 1 | D135: Age: years. Battery replacement year: Assumptions and Catalog!C19. A replacement resets age to zero once. | G135: Resets capacity degradation in the replacement year. Scenarios monthly column R. The annual model applies fresh capacity for that year and books replacement cost at year-end.
A136: Capacity available for cycling | B136: C_cycle = C_usable × (1 - reserve fraction) × (1 - d_batt)^Age | D136: C_cycle: stored kWh per modeled daily cycle. Reserve: Scenarios row 44. d_batt: Assumptions and Catalog!C23. | G136: Excludes reserved energy and accounts for battery capacity degradation. Scenarios monthly column P.
A137: Combined system battery delivery | B137: E_dis = MIN(night load × n, C_cycle × eta_dis × n, (E_PV - E_direct) × eta_ch × eta_dis, P_ch × h_PV × eta_ch × eta_dis × n, P_dis × (24 - h_day) × n) | D137: E_dis: AC kWh/month. eta_ch / eta_dis: C11 / C12. h_PV: PV charge window C14, hours/day. h_day: daylight hours C13. P_ch / P_dis: kW. C_cycle: stored kWh. | G137: Uses the smallest of night demand, usable storage, solar surplus, charging-power and discharging-power limits. Scenarios!I661:I900.
A138: Battery-only grid-cycle delivery | B138: E_dis = n × MIN(daily target, E_day, C_cycle × eta_dis, P_dis × (24 - h_grid), P_ch × h_grid × eta_ch × eta_dis) in Grid cycle mode; otherwise 0 | D138: Daily target: Scenarios!D46, AC kWh/day. h_grid: Assumptions and Catalog!C15, hours/day. Other symbols are defined above. | G138: Limits grid-charged battery cycling. Backup mode does not perform a daily cycle. Solar-only delivery is always 0. Scenarios!I411:I650 and I161:I400.
A139: Charging energy | B139: E_charge = E_dis / (eta_ch × eta_dis) | D139: E_charge: AC kWh/month required to deliver E_dis. eta_ch and eta_dis: charging and discharging efficiencies. | G139: Includes both losses and charges only enough to support modeled discharge. Scenarios monthly column H.
A140: Unused solar | B140: E_surplus = MAX(E_PV - E_direct - E_charge, 0) for solar scenarios; battery-only excludes grid charging from this subtraction | D140: All energies: kWh/month. E_charge is solar charging only for the combined system. | G140: Identifies solar energy not used onsite. It earns no export income in this model. Scenarios monthly column J.
A141: Battery conversion losses | B141: E_loss = E_charge - E_dis | D141: E_loss: kWh/month. Charge and discharge are measured at the AC boundaries. | G141: Quantifies energy lost in storage conversion. Scenarios monthly column K.
A142: Auxiliary energy | B142: E_aux = auxiliary kWh/day × n when a battery is installed; otherwise 0 | D142: Auxiliary consumption: Assumptions and Catalog!C26. Solar-only always uses 0. | G142: Adds battery standby/auxiliary energy to grid demand. Embedded in monthly columns L and S.
... A148: Year-one energy and bill summaries | B148: PV generation = SUM(first 12 monthly PV values). Baseline bill, system bill and bill savings = their respective first-year monthly sums | D148: Energy: kWh/year. Bills: EGP/year. Baseline is shared because all scenarios serve the same load. | G148: Presents comparable first-year totals. Scenarios!C12:E15. System bill and savings are gated by configuration validity.
...

Sheet Scenarios
A2: AVESTA — Scenario Comparison
A3: Three manually selected configurations. Financial results are indicative; no automatic size optimization.
A5: Metric | B5: Unit | C5: Solar only | D5: Battery only | E5: Solar and battery
A6: Configuration status | C6: =IF(C65=1,"Valid for indicative calculation","Check inputs / area / compatibility") -> Valid for indicative calculation | D6: =IF(D65=1,"Valid for indicative calculation","Check inputs / area / compatibility") -> Valid for indicative calculation | E6: =IF(E65=1,"Valid for indicative calculation","Check inputs / area / compatibility") -> Valid for indicative calculation
A7: PV capacity | B7: kWp | C7: =C51 -> 6.7 | D7: =D51 -> 0 | E7: =E51 -> 5.5 | H7: Equipment and quantities — edit yellow cells
A8: Nominal battery capacity | B8: kWh | C8: =C52 -> 0 | D8: =D52 -> 64 | E8: =E52 -> 160 | H8: Setting | I8: Unit | J8: Solar only | K8: Battery only | L8: Solar and battery
A9: Inverter capacity | B9: kW | C9: =C53 -> 10 | D9: =D53 -> 5 | E9: =E53 -> 12 | H9: Panel model | J9: PV670 | K9: PV550 | L9: PV550
A10: Required roof area | B10: m² | C10: =C59 -> 40.5 | D10: =D59 -> 0 | E10: =E59 -> 39 | H10: Panel quantity | J10: 10 | K10: 0 | L10: 10
A11: Initial investment | B11: EGP | C11: =C64 -> 124960 | D11: =D64 -> 993256 | E11: =E64 -> 2528240 | H11: Battery model | J11: BAT32 | K11: BAT32 | L11: BAT32
A12: Year 1 solar generation | B12: kWh | C12: =SUM(F161:F172) -> 12178.59 | D12: =SUM(F411:F422) -> 0 | E12: =SUM(F661:F672) -> 9997.35 | H12: Battery unit quantity | J12: 0 | K12: 2 | L12: 5
A13: Year 1 baseline bill | B13: EGP | C13: =$B$79 -> 100727.83 | D13: =$B$79 -> 100727.83 | E13: =$B$79 -> 100727.83 | H13: Inverter model | J13: GRID10 | K13: HYB5 | L13: HYB12
A14: Year 1 bill after installation | B14: EGP | C14: =IF(C65=1,SUM(N161:N172),"Invalid") -> 59081.18 | D14: =IF(D65=1,SUM(N411:N422),"Invalid") -> 100727.83 | E14: =IF(E65=1,SUM(N661:N672),"Invalid") -> 66540.282 | H14: Reserved share of usable capacity | I14: % | J14: 0.2 | K14: 1 | L14: 0.2
A15: Year 1 bill savings | B15: EGP | C15: =IF(C65=1,SUM(O161:O172),"Invalid") -> 41646.653 | D15: =IF(D65=1,SUM(O411:O422),"Invalid") -> 0 | E15: =IF(E65=1,SUM(O661:O672),"Invalid") -> 34187.551 | H15: Battery-only operating mode | J15: Backup | K15: Backup | L15: Backup
A16: Year 1 savings after maintenance | B16: EGP | C16: =IF(C65=1,C79,"Invalid") -> 40397.053 | D16: =IF(D65=1,G79,"Invalid") -> -9932.56 | E16: =IF(E65=1,K79,"Invalid") -> 8905.1509 | H16: Grid-charged delivery limit | I16: kWh/day | J16: 8 | K16: 8 | L16: 8
A17: NPV over study period | B17: EGP | C17: =IF(C65=1,SUM(D78:D98),"Invalid") -> 118751.58 | D17: =IF(D65=1,SUM(H78:H98),"Invalid") -> -1054287.3 | E17: =IF(E65=1,SUM(L78:L98),"Invalid") -> -2477224.6
A18: Simple payback | B18: years | C18: =IF(C65=0,"Invalid",IF(MIN(P79:P98)=999,"Not reached",MIN(P79:P98))) -> 3.1075781 | D18: =IF(D65=0,"Invalid",IF(MIN(R79:R98)=999,"Not reached",MIN(R79:R98))) -> Not reached | E18: =IF(E65=0,"Invalid",IF(MIN(T79:T98)=999,"Not reached",MIN(T79:T98))) -> Not reached | H18: Unused fields: battery for solar-only and PV for battery-only. Grid-cycle mode applies only to the battery-only column.
A19: Discounted payback | B19: years | C19: =IF(C65=0,"Invalid",IF(MIN(Q79:Q98)=999,"Not reached",MIN(Q79:Q98))) -> 3.9161381 | D19: =IF(D65=0,"Invalid",IF(MIN(S79:S98)=999,"Not reached",MIN(S79:S98))) -> Not reached | E19: =IF(E65=0,"Invalid",IF(MIN(U79:U98)=999,"Not reached",MIN(U79:U98))) -> Not reached
A20: Full-charge backup energy | B20: kWh AC | C20: =C68 -> 0 | D20: =D68 -> 49.92 | E20: =E68 -> 124.8
A21: Maximum backup power | B21: kW | C21: =C69 -> 0 | D21: =D69 -> 5 | E21: =E69 -> 12
A22: Backup hours from full charge | B22: hours | C22: =IF(C65=0,"Invalid",IF(C69=0,"Not available",IF(Inputs!$C$20="Unknown","Load unknown",IF(Inputs!$C$21>C69,"Load exceeds power limit",C68/Inputs!$C$21)))) -> Not available | D22: =IF(D65=0,"Invalid",IF(D69=0,"Not available",IF(Inputs!$C$20="Unknown","Load unknown",IF(Inputs!$C$21>D69,"Load exceeds power limit",D68/Inputs!$C$21)))) -> Load unknown | E22: =IF(E65=0,"Invalid",IF(E69=0,"Not available",IF(Inputs!$C$20="Unknown","Load unknown",IF(Inputs!$C$21>E69,"Load exceeds power limit",E68/Inputs!$C$21)))) -> Load unknown
A23: Reserved backup energy | B23: kWh AC | C23: =IF(C58=1,C67*'Assumptions and Catalog'!$C$12,0) -> 0 | D23: =IF(D58=1,D67*'Assumptions and Catalog'!$C$12,0) -> 49.92 | E23: =IF(E58=1,E67*'Assumptions and Catalog'!$C$12,0) -> 24.96
A24: System role | C24: =IF(C65=0,"Invalid",IF(C15>0,IF(C69>0,"Bill savings + backup capability","Bill savings"),IF(C69>0,"Backup capability, no bill savings","No bill savings demonstrated"))) -> Bill savings | D24: =IF(D65=0,"Invalid",IF(D15>0,IF(D69>0,"Bill savings + backup capability","Bill savings"),IF(D69>0,"Backup capability, no bill savings","No bill savings demonstrated"))) -> Backup capability, no bill savings | E24: =IF(E65=0,"Invalid",IF(E15>0,IF(E69>0,"Bill savings + backup capability","Bill savings"),IF(E69>0,"Backup capability, no bill savings","No bill savings demonstrated"))) -> Bill savings + backup capability
A25: Financial outcome | C25: =IF(C65=0,"Invalid",IF(C17>0,"Positive NPV under assumptions",IF(C17=0,"Discounted breakeven","Negative NPV under assumptions"))) -> Positive NPV under assumptions | D25: =IF(D65=0,"Invalid",IF(D17>0,"Positive NPV under assumptions",IF(D17=0,"Discounted breakeven","Negative NPV under assumptions"))) -> Negative NPV under assumptions | E25: =IF(E65=0,"Invalid",IF(E17>0,"Positive NPV under assumptions",IF(E17=0,"Discounted breakeven","Negative NPV under assumptions"))) -> Negative NPV under assumptions
A26: Roof area status | C26: =IF(Inputs!$C$14="Unspecified","Roof fit not verified",IF(C59<=Inputs!$C$15,"Within available area","Exceeds available area")) -> Roof fit not verified | D26: =IF(Inputs!$C$14="Unspecified","Roof fit not verified",IF(D59<=Inputs!$C$15,"Within available area","Exceeds available area")) -> Roof fit not verified | E26: =IF(Inputs!$C$14="Unspecified","Roof fit not verified",IF(E59<=Inputs!$C$15,"Within available area","Exceeds available area")) -> Roof fit not verified
A28: Full-charge backup is not guaranteed at outage time. Motor surge, load phase balance and site checks are not modeled.
A29: NPV excludes financing, taxes and outage value. The no-investment baseline has NPV = 0.
A31: Battery savings vs matched PV | B31: EGP/year | E31: =IF(E65=1,SUM(Q661:Q672)-SUM(N661:N672),"Invalid") -> 0
A32: Incremental battery investment | B32: EGP | E32: =E61*(1+'Assumptions and Catalog'!$C$17) -> 2400640
A33: Incremental comparison uses the same PV and hybrid inverter without a battery; no cheaper inverter alternative is assumed.
A50: Sizing and cost details
A51: Installed PV (kWp) | C51: =J10*INDEX('Assumptions and Catalog'!$C$73:$I$74,MATCH(J9,'Assumptions and Catalog'!$A$73:$A$74,0),1)/1000 -> 6.7 | D51: =0 -> 0 | E51: =L10*INDEX('Assumptions and Catalog'!$C$73:$I$74,MATCH(L9,'Assumptions and Catalog'!$A$73:$A$74,0),1)/1000 -> 5.5
A52: Nominal battery capacity (kWh) | C52: =0 -> 0 | D52: =K12*INDEX('Assumptions and Catalog'!$C$79:$I$81,MATCH(K11,'Assumptions and Catalog'!$A$79:$A$81,0),1) -> 64 | E52: =L12*INDEX('Assumptions and Catalog'!$C$79:$I$81,MATCH(L11,'Assumptions and Catalog'!$A$79:$A$81,0),1) -> 160
A53: Inverter AC rating (kW) | C53: =INDEX('Assumptions and Catalog'!$C$86:$I$89,MATCH(J13,'Assumptions and Catalog'!$A$86:$A$89,0),1) -> 10 | D53: =INDEX('Assumptions and Catalog'!$C$86:$I$89,MATCH(K13,'Assumptions and Catalog'!$A$86:$A$89,0),1) -> 5 | E53: =INDEX('Assumptions and Catalog'!$C$86:$I$89,MATCH(L13,'Assumptions and Catalog'!$A$86:$A$89,0),1) -> 12
A54: Inverter PV limit (kWp) | C54: =INDEX('Assumptions and Catalog'!$C$86:$I$89,MATCH(J13,'Assumptions and Catalog'!$A$86:$A$89,0),2) -> 13 | D54: =INDEX('Assumptions and Catalog'!$C$86:$I$89,MATCH(K13,'Assumptions and Catalog'!$A$86:$A$89,0),2) -> 6.5 | E54: =INDEX('Assumptions and Catalog'!$C$86:$I$89,MATCH(L13,'Assumptions and Catalog'!$A$86:$A$89,0),2) -> 15.6
A55: Usable internal capacity (kWh) | C55: =C52*INDEX('Assumptions and Catalog'!$C$79:$I$81,MATCH(J11,'Assumptions and Catalog'!$A$79:$A$81,0),2) -> 0 | D55: =D52*INDEX('Assumptions and Catalog'!$C$79:$I$81,MATCH(K11,'Assumptions and Catalog'!$A$79:$A$81,0),2) -> 51.2 | E55: =E52*INDEX('Assumptions and Catalog'!$C$79:$I$81,MATCH(L11,'Assumptions and Catalog'!$A$79:$A$81,0),2) -> 128
A56: Battery charge limit (AC kW) | C56: =MIN(J12*INDEX('Assumptions and Catalog'!$C$79:$I$81,MATCH(J11,'Assumptions and Catalog'!$A$79:$A$81,0),3),INDEX('Assumptions and Catalog'!$C$86:$I$89,MATCH(J13,'Assumptions and Catalog'!$A$86:$A$89,0),3)) -> 0 | D56: =MIN(K12*INDEX('Assumptions and Catalog'!$C$79:$I$81,MATCH(K11,'Assumptions and Catalog'!$A$79:$A$81,0),3),INDEX('Assumptions and Catalog'!$C$86:$I$89,MATCH(K13,'Assumptions and Catalog'!$A$86:$A$89,0),3)) -> 5 | E56: =MIN(L12*INDEX('Assumptions and Catalog'!$C$79:$I$81,MATCH(L11,'Assumptions and Catalog'!$A$79:$A$81,0),3),INDEX('Assumptions and Catalog'!$C$86:$I$89,MATCH(L13,'Assumptions and Catalog'!$A$86:$A$89,0),3)) -> 10
A57: Battery discharge limit (AC kW) | C57: =MIN(J12*INDEX('Assumptions and Catalog'!$C$79:$I$81,MATCH(J11,'Assumptions and Catalog'!$A$79:$A$81,0),4),C53) -> 0 | D57: =MIN(K12*INDEX('Assumptions and Catalog'!$C$79:$I$81,MATCH(K11,'Assumptions and Catalog'!$A$79:$A$81,0),4),D53) -> 5 | E57: =MIN(L12*INDEX('Assumptions and Catalog'!$C$79:$I$81,MATCH(L11,'Assumptions and Catalog'!$A$79:$A$81,0),4),E53) -> 12
A58: Backup supported 1/0 | C58: =0 -> 0 | D58: =INDEX('Assumptions and Catalog'!$C$86:$I$89,MATCH(K13,'Assumptions and Catalog'!$A$86:$A$89,0),4) -> 1 | E58: =INDEX('Assumptions and Catalog'!$C$86:$I$89,MATCH(L13,'Assumptions and Catalog'!$A$86:$A$89,0),4) -> 1
A59: Required area (m2) | C59: =C51*1000/INDEX('Assumptions and Catalog'!$C$73:$I$74,MATCH(J9,'Assumptions and Catalog'!$A$73:$A$74,0),1)*INDEX('Assumptions and Catalog'!$C$73:$I$74,MATCH(J9,'Assumptions and Catalog'!$A$73:$A$74,0),2)*'Assumptions and Catalog'!$C$16 -> 40.5 | D59: =D51*1000/INDEX('Assumptions and Catalog'!$C$73:$I$74,MATCH(K9,'Assumptions and Catalog'!$A$73:$A$74,0),1)*INDEX('Assumptions and Catalog'!$C$73:$I$74,MATCH(K9,'Assumptions and Catalog'!$A$73:$A$74,0),2)*'Assumptions and Catalog'!$C$16 -> 0 | E59: =E51*1000/INDEX('Assumptions and Catalog'!$C$73:$I$74,MATCH(L9,'Assumptions and Catalog'!$A$73:$A$74,0),1)*INDEX('Assumptions and Catalog'!$C$73:$I$74,MATCH(L9,'Assumptions and Catalog'!$A$73:$A$74,0),2)*'Assumptions and Catalog'!$C$16 -> 39
A60: PV panel cost (EGP) | C60: =C51*1000/INDEX('Assumptions and Catalog'!$C$73:$I$74,MATCH(J9,'Assumptions and Catalog'!$A$73:$A$74,0),1)*INDEX('Assumptions and Catalog'!$C$73:$I$74,MATCH(J9,'Assumptions and Catalog'!$A$73:$A$74,0),3) -> 53600 | D60: =D51*1000/INDEX('Assumptions and Catalog'!$C$73:$I$74,MATCH(K9,'Assumptions and Catalog'!$A$73:$A$74,0),1)*INDEX('Assumptions and Catalog'!$C$73:$I$74,MATCH(K9,'Assumptions and Catalog'!$A$73:$A$74,0),3) -> 0 | E60: =E51*1000/INDEX('Assumptions and Catalog'!$C$73:$I$74,MATCH(L9,'Assumptions and Catalog'!$A$73:$A$74,0),1)*INDEX('Assumptions and Catalog'!$C$73:$I$74,MATCH(L9,'Assumptions and Catalog'!$A$73:$A$74,0),3) -> 44000
A61: Battery cost (EGP) | C61: =C52/INDEX('Assumptions and Catalog'!$C$79:$I$81,MATCH(J11,'Assumptions and Catalog'!$A$79:$A$81,0),1)*INDEX('Assumptions and Catalog'!$C$79:$I$81,MATCH(J11,'Assumptions and Catalog'!$A$79:$A$81,0),5) -> 0 | D61: =D52/INDEX('Assumptions and Catalog'!$C$79:$I$81,MATCH(K11,'Assumptions and Catalog'!$A$79:$A$81,0),1)*INDEX('Assumptions and Catalog'!$C$79:$I$81,MATCH(K11,'Assumptions and Catalog'!$A$79:$A$81,0),5) -> 872960 | E61: =E52/INDEX('Assumptions and Catalog'!$C$79:$I$81,MATCH(L11,'Assumptions and Catalog'!$A$79:$A$81,0),1)*INDEX('Assumptions and Catalog'!$C$79:$I$81,MATCH(L11,'Assumptions and Catalog'!$A$79:$A$81,0),5) -> 2182400
A62: Inverter cost (EGP) | C62: =INDEX('Assumptions and Catalog'!$C$86:$I$89,MATCH(J13,'Assumptions and Catalog'!$A$86:$A$89,0),5) -> 60000 | D62: =INDEX('Assumptions and Catalog'!$C$86:$I$89,MATCH(K13,'Assumptions and Catalog'!$A$86:$A$89,0),5) -> 30000 | E62: =INDEX('Assumptions and Catalog'!$C$86:$I$89,MATCH(L13,'Assumptions and Catalog'!$A$86:$A$89,0),5) -> 72000
A63: Installation and BOS (EGP) | C63: =SUM(C60:C62)*'Assumptions and Catalog'!$C$17 -> 11360 | D63: =SUM(D60:D62)*'Assumptions and Catalog'!$C$17 -> 90296 | E63: =SUM(E60:E62)*'Assumptions and Catalog'!$C$17 -> 229840
A64: Total investment (EGP) | C64: =SUM(C60:C63) -> 124960 | D64: =SUM(D60:D63) -> 993256 | E64: =SUM(E60:E63) -> 2528240
A65: Model validity 1/0 | C65: =IF(AND(Inputs!$L$3="Ready for indicative calculation",C51<=C54,OR(Inputs!$C$14="Unspecified",C59<=Inputs!$C$15),C66="Compatible under assumptions",J10>=0,J12>=0,MOD(J10,1)=0,MOD(J12,1)=0,J14>=0,J14<=1,'Assumptions and Catalog'!$C$11>0,'Assumptions and Catalog'!$C$11<=1,'Assumptions and Catalog'!$C$12>0,'Assumptions and Catalog'!$C$12<=1,'Assumptions and Catalog'!$C$6>=1,'Assumptions and Catalog'!$C$6<=20),1,0) -> 1 | D65: =IF(AND(Inputs!$L$3="Ready for indicative calculation",D51<=D54,OR(Inputs!$C$14="Unspecified",D59<=Inputs!$C$15),D66="Compatible under assumptions",K10>=0,K12>=0,MOD(K10,1)=0,MOD(K12,1)=0,K14>=0,K14<=1,'Assumptions and Catalog'!$C$11>0,'Assumptions and Catalog'!$C$11<=1,'Assumptions and Catalog'!$C$12>0,'Assumptions and Catalog'!$C$12<=1,'Assumptions and Catalog'!$C$6>=1,'Assumptions and Catalog'!$C$6<=20),1,0) -> 1 | E65: =IF(AND(Inputs!$L$3="Ready for indicative calculation",E51<=E54,OR(Inputs!$C$14="Unspecified",E59<=Inputs!$C$15),E66="Compatible under assumptions",L10>=0,L12>=0,MOD(L10,1)=0,MOD(L12,1)=0,L14>=0,L14<=1,'Assumptions and Catalog'!$C$11>0,'Assumptions and Catalog'!$C$11<=1,'Assumptions and Catalog'!$C$12>0,'Assumptions and Catalog'!$C$12<=1,'Assumptions and Catalog'!$C$6>=1,'Assumptions and Catalog'!$C$6<=20),1,0) -> 1
A66: Compatibility status | C66: =IF(OR(C52=0,INDEX('Assumptions and Catalog'!$C$79:$I$81,MATCH(J11,'Assumptions and Catalog'!$A$79:$A$81,0),6)=INDEX('Assumptions and Catalog'!$C$86:$I$89,MATCH(J13,'Assumptions and Catalog'!$A$86:$A$89,0),6)),"Compatible under assumptions","Incompatible") -> Compatible under assumptions | D66: =IF(OR(D52=0,INDEX('Assumptions and Catalog'!$C$79:$I$81,MATCH(K11,'Assumptions and Catalog'!$A$79:$A$81,0),6)=INDEX('Assumptions and Catalog'!$C$86:$I$89,MATCH(K13,'Assumptions and Catalog'!$A$86:$A$89,0),6)),"Compatible under assumptions","Incompatible") -> Compatible under assumptions | E66: =IF(OR(E52=0,INDEX('Assumptions and Catalog'!$C$79:$I$81,MATCH(L11,'Assumptions and Catalog'!$A$79:$A$81,0),6)=INDEX('Assumptions and Catalog'!$C$86:$I$89,MATCH(L13,'Assumptions and Catalog'!$A$86:$A$89,0),6)),"Compatible under assumptions","Incompatible") -> Compatible under assumptions
A67: Reserved internal energy (kWh) | C67: =C55*J14 -> 0 | D67: =D55*K14 -> 51.2 | E67: =E55*L14 -> 25.6
A68: Full-charge backup (kWh AC) | C68: =IF(C58=1,C55*'Assumptions and Catalog'!$C$12,0) -> 0 | D68: =IF(D58=1,D55*'Assumptions and Catalog'!$C$12,0) -> 49.92 | E68: =IF(E58=1,E55*'Assumptions and Catalog'!$C$12,0) -> 124.8
A69: Backup power (kW) | C69: =IF(C58=1,C57,0) -> 0 | D69: =IF(D58=1,D57,0) -> 5 | E69: =IF(E58=1,E57,0) -> 12
A70: Year 1 maintenance (EGP) | C70: =C64*'Assumptions and Catalog'!$C$18 -> 1249.6 | D70: =D64*'Assumptions and Catalog'!$C$18 -> 9932.56 | E70: =E64*'Assumptions and Catalog'!$C$18 -> 25282.4
A75: Annual cash flows — year-end timing
A77: Year | B77: Baseline EGP | C77: Solar net cash flow | D77: Discounted solar cash flow | E77: Solar cumulative CF | F77: Cumulative discounted CF | G77: Battery net cash flow | H77: Discounted battery cash flow | I77: Battery cumulative CF | J77: Cumulative discounted CF | K77: Combined net cash flow | L77: Discounted combined cash flow | M77: Combined cumulative CF | N77: Cumulative discounted CF | P77: C Payback | Q77: C Discounted | R77: D Payback | S77: D Discounted | T77: E Payback | U77: E Discounted
A78: 0 | B78: 0 | C78: =-C64 -> -124960 | D78: =-C64 -> -124960 | E78: =-C64 -> -124960 | F78: =-C64 -> -124960 | G78: =-D64 -> -993256 | H78: =-D64 -> -993256 | I78: =-D64 -> -993256 | J78: =-D64 -> -993256 | K78: =-E64 -> -2528240 | L78: =-E64 -> -2528240 | M78: =-E64 -> -2528240 | N78: =-E64 -> -2528240
A79: 1 | B79: =IF(A79<='Assumptions and Catalog'!$C$6,SUMIFS($M$161:$M$400,$A$161:$A$400,A79),0) -> 100727.83 | C79: =IF(A79<='Assumptions and Catalog'!$C$6,SUMIFS($O$161:$O$400,$A$161:$A$400,A79)-(C$70+IF(AND('Assumptions and Catalog'!$C$19>0,A79='Assumptions and Catalog'!$C$19),C$61*'Assumptions and Catalog'!$C$20,0)+IF(AND('Assumptions and Catalog'!$C$21>0,A79='Assumptions and Catalog'!$C$21),C$62*'Assumptions and Catalog'!$C$22,0))*(1+'Assumptions and Catalog'!$C$9)^(A79-1),0) -> 40397.053 | D79: =C79/(1+'Assumptions and Catalog'!$C$7)^A79 -> 36724.594 | E79: =E78+C79 -> -84562.947 | F79: =F78+D79 -> -88235.406 | G79: =IF(A79<='Assumptions and Catalog'!$C$6,SUMIFS($O$411:$O$650,$A$411:$A$650,A79)-(D$70+IF(AND('Assumptions and Catalog'!$C$19>0,A79='Assumptions and Catalog'!$C$19),D$61*'Assumptions and Catalog'!$C$20,0)+IF(AND('Assumptions and Catalog'!$C$21>0,A79='Assumptions and Catalog'!$C$21),D$62*'Assumptions and Catalog'!$C$22,0))*(1+'Assumptions and Catalog'!$C$9)^(A79-1),0) -> -9932.56 | H79: =G79/(1+'Assumptions and Catalog'!$C$7)^A79 -> -9029.6 | I79: =I78+G79 -> -1003188.6 | J79: =J78+H79 -> -1002285.6 | K79: =IF(A79<='Assumptions and Catalog'!$C$6,SUMIFS($O$661:$O$900,$A$661:$A$900,A79)-(E$70+IF(AND('Assumptions and Catalog'!$C$19>0,A79='Assumptions and Catalog'!$C$19),E$61*'Assumptions and Catalog'!$C$20,0)+IF(AND('Assumptions and Catalog'!$C$21>0,A79='Assumptions and Catalog'!$C$21),E$62*'Assumptions and Catalog'!$C$22,0))*(1+'Assumptions and Catalog'!$C$9)^(A79-1),0) -> 8905.1509 | L79: =K79/(1+'Assumptions and Catalog'!$C$7)^A79 -> 8095.5917 | M79: =M78+K79 -> -2519334.8 | N79: =N78+L79 -> -2520144.4 | P79: =IF(AND(A79<='Assumptions and Catalog'!$C$6,E79>=0,E78<0,C79>0),A79-1-E78/C79,999) -> 999 | Q79: =IF(AND(A79<='Assumptions and Catalog'!$C$6,F79>=0,F78<0,D79>0),A79-1-F78/D79,999) -> 999 | R79: =IF(AND(A79<='Assumptions and Catalog'!$C$6,I79>=0,I78<0,G79>0),A79-1-I78/G79,999) -> 999 | S79: =IF(AND(A79<='Assumptions and Catalog'!$C$6,J79>=0,J78<0,H79>0),A79-1-J78/H79,999) -> 999 | T79: =IF(AND(A79<='Assumptions and Catalog'!$C$6,M79>=0,M78<0,K79>0),A79-1-M78/K79,999) -> 999 | U79: =IF(AND(A79<='Assumptions and Catalog'!$C$6,N79>=0,N78<0,L79>0),A79-1-N78/L79,999) -> 999
A80: 2 | B80: =IF(A80<='Assumptions and Catalog'!$C$6,SUMIFS($M$161:$M$400,$A$161:$A$400,A80),0) -> 101003.8 | C80: =IF(A80<='Assumptions and Catalog'!$C$6,SUMIFS($O$161:$O$400,$A$161:$A$400,A80)-(C$70+IF(AND('Assumptions and Catalog'!$C$19>0,A80='Assumptions and Catalog'!$C$19),C$61*'Assumptions and Catalog'!$C$20,0)+IF(AND('Assumptions and Catalog'!$C$21>0,A80='Assumptions and Catalog'!$C$21),C$62*'Assumptions and Catalog'!$C$22,0))*(1+'Assumptions and Catalog'!$C$9)^(A80-1),0) -> 40302.35 | D80: =C80/(1+'Assumptions and Catalog'!$C$7)^A80 -> 33307.727 | E80: =E79+C80 -> -44260.598 | F80: =F79+D80 -> -54927.68 | G80: =IF(A80<='Assumptions and Catalog'!$C$6,SUMIFS($O$411:$O$650,$A$411:$A$650,A80)-(D$70+IF(AND('Assumptions and Catalog'!$C$19>0,A80='Assumptions and Catalog'!$C$19),D$61*'Assumptions and Catalog'!$C$20,0)+IF(AND('Assumptions and Catalog'!$C$21>0,A80='Assumptions and Catalog'!$C$21),D$62*'Assumptions and Catalog'!$C$22,0))*(1+'Assumptions and Catalog'!$C$9)^(A80-1),0) -> -9932.56 | H80: =G80/(1+'Assumptions and Catalog'!$C$7)^A80 -> -8208.7273 | I80: =I79+G80 -> -1013121.1 | J80: =J79+H80 -> -1010494.3 | K80: =IF(A80<='Assumptions and Catalog'!$C$6,SUMIFS($O$661:$O$900,$A$661:$A$900,A80)-(E$70+IF(AND('Assumptions and Catalog'!$C$19>0,A80='Assumptions and Catalog'!$C$19),E$61*'Assumptions and Catalog'!$C$20,0)+IF(AND('Assumptions and Catalog'!$C$21>0,A80='Assumptions and Catalog'!$C$21),E$62*'Assumptions and Catalog'!$C$22,0))*(1+'Assumptions and Catalog'!$C$9)^(A80-1),0) -> 8827.4093 | L80: =K80/(1+'Assumptions and Catalog'!$C$7)^A80 -> 7295.3796 | M80: =M79+K80 -> -2510507.4 | N80: =N79+L80 -> -2512849 | P80: =IF(AND(A80<='Assumptions and Catalog'!$C$6,E80>=0,E79<0,C80>0),A80-1-E79/C80,999) -> 999 | Q80: =IF(AND(A80<='Assumptions and Catalog'!$C$6,F80>=0,F79<0,D80>0),A80-1-F79/D80,999) -> 999 | R80: =IF(AND(A80<='Assumptions and Catalog'!$C$6,I80>=0,I79<0,G80>0),A80-1-I79/G80,999) -> 999 | S80: =IF(AND(A80<='Assumptions and Catalog'!$C$6,J80>=0,J79<0,H80>0),A80-1-J79/H80,999) -> 999 | T80: =IF(AND(A80<='Assumptions and Catalog'!$C$6,M80>=0,M79<0,K80>0),A80-1-M79/K80,999) -> 999 | U80: =IF(AND(A80<='Assumptions and Catalog'!$C$6,N80>=0,N79<0,L80>0),A80-1-N79/L80,999) -> 999
A81: 3 | B81: =IF(A81<='Assumptions and Catalog'!$C$6,SUMIFS($M$161:$M$400,$A$161:$A$400,A81),0) -> 100727.83 | C81: =IF(A81<='Assumptions and Catalog'!$C$6,SUMIFS($O$161:$O$400,$A$161:$A$400,A81)-(C$70+IF(AND('Assumptions and Catalog'!$C$19>0,A81='Assumptions and Catalog'!$C$19),C$61*'Assumptions and Catalog'!$C$20,0)+IF(AND('Assumptions and Catalog'!$C$21>0,A81='Assumptions and Catalog'!$C$21),C$62*'Assumptions and Catalog'!$C$22,0))*(1+'Assumptions and Catalog'!$C$9)^(A81-1),0) -> 39981.628 | D81: =C81/(1+'Assumptions and Catalog'!$C$7)^A81 -> 30038.789 | E81: =E80+C81 -> -4278.9701 | F81: =F80+D81 -> -24888.891 | G81: =IF(A81<='Assumptions and Catalog'!$C$6,SUMIFS($O$411:$O$650,$A$411:$A$650,A81)-(D$70+IF(AND('Assumptions and Catalog'!$C$19>0,A81='Assumptions and Catalog'!$C$19),D$61*'Assumptions and Catalog'!$C$20,0)+IF(AND('Assumptions and Catalog'!$C$21>0,A81='Assumptions and Catalog'!$C$21),D$62*'Assumptions and Catalog'!$C$22,0))*(1+'Assumptions and Catalog'!$C$9)^(A81-1),0) -> -9932.56 | H81: =G81/(1+'Assumptions and Catalog'!$C$7)^A81 -> -7462.4793 | I81: =I80+G81 -> -1023053.7 | J81: =J80+H81 -> -1017956.8 | K81: =IF(A81<='Assumptions and Catalog'!$C$6,SUMIFS($O$661:$O$900,$A$661:$A$900,A81)-(E$70+IF(AND('Assumptions and Catalog'!$C$19>0,A81='Assumptions and Catalog'!$C$19),E$61*'Assumptions and Catalog'!$C$20,0)+IF(AND('Assumptions and Catalog'!$C$21>0,A81='Assumptions and Catalog'!$C$21),E$62*'Assumptions and Catalog'!$C$22,0))*(1+'Assumptions and Catalog'!$C$9)^(A81-1),0) -> 8564.13 | L81: =K81/(1+'Assumptions and Catalog'!$C$7)^A81 -> 6434.3577 | M81: =M80+K81 -> -2501943.3 | N81: =N80+L81 -> -2506414.7 | P81: =IF(AND(A81<='Assumptions and Catalog'!$C$6,E81>=0,E80<0,C81>0),A81-1-E80/C81,999) -> 999 | Q81: =IF(AND(A81<='Assumptions and Catalog'!$C$6,F81>=0,F80<0,D81>0),A81-1-F80/D81,999) -> 999 | R81: =IF(AND(A81<='Assumptions and Catalog'!$C$6,I81>=0,I80<0,G81>0),A81-1-I80/G81,999) -> 999 | S81: =IF(AND(A81<='Assumptions and Catalog'!$C$6,J81>=0,J80<0,H81>0),A81-1-J80/H81,999) -> 999 | T81: =IF(AND(A81<='Assumptions and Catalog'!$C$6,M81>=0,M80<0,K81>0),A81-1-M80/K81,999) -> 999 | U81: =IF(AND(A81<='Assumptions and Catalog'!$C$6,N81>=0,N80<0,L81>0),A81-1-N80/L81,999) -> 999
A82: 4 | B82: =IF(A82<='Assumptions and Catalog'!$C$6,SUMIFS($M$161:$M$400,$A$161:$A$400,A82),0) -> 100727.83 | C82: =IF(A82<='Assumptions and Catalog'!$C$6,SUMIFS($O$161:$O$400,$A$161:$A$400,A82)-(C$70+IF(AND('Assumptions and Catalog'!$C$19>0,A82='Assumptions and Catalog'!$C$19),C$61*'Assumptions and Catalog'!$C$20,0)+IF(AND('Assumptions and Catalog'!$C$21>0,A82='Assumptions and Catalog'!$C$21),C$62*'Assumptions and Catalog'!$C$22,0))*(1+'Assumptions and Catalog'!$C$9)^(A82-1),0) -> 39775.471 | D82: =C82/(1+'Assumptions and Catalog'!$C$7)^A82 -> 27167.182 | E82: =E81+C82 -> 35496.501 | F82: =F81+D82 -> 2278.2911 | G82: =IF(A82<='Assumptions and Catalog'!$C$6,SUMIFS($O$411:$O$650,$A$411:$A$650,A82)-(D$70+IF(AND('Assumptions and Catalog'!$C$19>0,A82='Assumptions and Catalog'!$C$19),D$61*'Assumptions and Catalog'!$C$20,0)+IF(AND('Assumptions and Catalog'!$C$21>0,A82='Assumptions and Catalog'!$C$21),D$62*'Assumptions and Catalog'!$C$22,0))*(1+'Assumptions and Catalog'!$C$9)^(A82-1),0) -> -9932.56 | H82: =G82/(1+'Assumptions and Catalog'!$C$7)^A82 -> -6784.0721 | I82: =I81+G82 -> -1032986.2 | J82: =J81+H82 -> -1024740.9 | K82: =IF(A82<='Assumptions and Catalog'!$C$6,SUMIFS($O$661:$O$900,$A$661:$A$900,A82)-(E$70+IF(AND('Assumptions and Catalog'!$C$19>0,A82='Assumptions and Catalog'!$C$19),E$61*'Assumptions and Catalog'!$C$20,0)+IF(AND('Assumptions and Catalog'!$C$21>0,A82='Assumptions and Catalog'!$C$21),E$62*'Assumptions and Catalog'!$C$22,0))*(1+'Assumptions and Catalog'!$C$9)^(A82-1),0) -> 8394.8974 | L82: =K82/(1+'Assumptions and Catalog'!$C$7)^A82 -> 5733.8279 | M82: =M81+K82 -> -2493548.4 | N82: =N81+L82 -> -2500680.8 | P82: =IF(AND(A82<='Assumptions and Catalog'!$C$6,E82>=0,E81<0,C82>0),A82-1-E81/C82,999) -> 3.1075781 | Q82: =IF(AND(A82<='Assumptions and Catalog'!$C$6,F82>=0,F81<0,D82>0),A82-1-F81/D82,999) -> 3.9161381 | R82: =IF(AND(A82<='Assumptions and Catalog'!$C$6,I82>=0,I81<0,G82>0),A82-1-I81/G82,999) -> 999 | S82: =IF(AND(A82<='Assumptions and Catalog'!$C$6,J82>=0,J81<0,H82>0),A82-1-J81/H82,999) -> 999 | T82: =IF(AND(A82<='Assumptions and Catalog'!$C$6,M82>=0,M81<0,K82>0),A82-1-M81/K82,999) -> 999 | U82: =IF(AND(A82<='Assumptions and Catalog'!$C$6,N82>=0,N81<0,L82>0),A82-1-N81/L82,999) -> 999
A83: 5 | B83: =IF(A83<='Assumptions and Catalog'!$C$6,SUMIFS($M$161:$M$400,$A$161:$A$400,A83),0) -> 100727.83 | C83: =IF(A83<='Assumptions and Catalog'!$C$6,SUMIFS($O$161:$O$400,$A$161:$A$400,A83)-(C$70+IF(AND('Assumptions and Catalog'!$C$19>0,A83='Assumptions and Catalog'!$C$19),C$61*'Assumptions and Catalog'!$C$20,0)+IF(AND('Assumptions and Catalog'!$C$21>0,A83='Assumptions and Catalog'!$C$21),C$62*'Assumptions and Catalog'!$C$22,0))*(1+'Assumptions and Catalog'!$C$9)^(A83-1),0) -> 39570.346 | D83: =C83/(1+'Assumptions and Catalog'!$C$7)^A83 -> 24570.072 | E83: =E82+C83 -> 75066.847 | F83: =F82+D83 -> 26848.363 | G83: =IF(A83<='Assumptions and Catalog'!$C$6,SUMIFS($O$411:$O$650,$A$411:$A$650,A83)-(D$70+IF(AND('Assumptions and Catalog'!$C$19>0,A83='Assumptions and Catalog'!$C$19),D$61*'Assumptions and Catalog'!$C$20,0)+IF(AND('Assumptions and Catalog'!$C$21>0,A83='Assumptions and Catalog'!$C$21),D$62*'Assumptions and Catalog'!$C$22,0))*(1+'Assumptions and Catalog'!$C$9)^(A83-1),0) -> -9932.56 | H83: =G83/(1+'Assumptions and Catalog'!$C$7)^A83 -> -6167.3383 | I83: =I82+G83 -> -1042918.8 | J83: =J82+H83 -> -1030908.2 | K83: =IF(A83<='Assumptions and Catalog'!$C$6,SUMIFS($O$661:$O$900,$A$661:$A$900,A83)-(E$70+IF(AND('Assumptions and Catalog'!$C$19>0,A83='Assumptions and Catalog'!$C$19),E$61*'Assumptions and Catalog'!$C$20,0)+IF(AND('Assumptions and Catalog'!$C$21>0,A83='Assumptions and Catalog'!$C$21),E$62*'Assumptions and Catalog'!$C$22,0))*(1+'Assumptions and Catalog'!$C$9)^(A83-1),0) -> 8226.5109 | L83: =K83/(1+'Assumptions and Catalog'!$C$7)^A83 -> 5108.016 | M83: =M82+K83 -> -2485321.9 | N83: =N82+L83 -> -2495572.8 | P83: =IF(AND(A83<='Assumptions and Catalog'!$C$6,E83>=0,E82<0,C83>0),A83-1-E82/C83,999) -> 999 | Q83: =IF(AND(A83<='Assumptions and Catalog'!$C$6,F83>=0,F82<0,D83>0),A83-1-F82/D83,999) -> 999 | R83: =IF(AND(A83<='Assumptions and Catalog'!$C$6,I83>=0,I82<0,G83>0),A83-1-I82/G83,999) -> 999 | S83: =IF(AND(A83<='Assumptions and Catalog'!$C$6,J83>=0,J82<0,H83>0),A83-1-J82/H83,999) -> 999 | T83: =IF(AND(A83<='Assumptions and Catalog'!$C$6,M83>=0,M82<0,K83>0),A83-1-M82/K83,999) -> 999 | U83: =IF(AND(A83<='Assumptions and Catalog'!$C$6,N83>=0,N82<0,L83>0),A83-1-N82/L83,999) -> 999
A84: 6 | B84: =IF(A84<='Assumptions and Catalog'!$C$6,SUMIFS($M$161:$M$400,$A$161:$A$400,A84),0) -> 101003.8 | C84: =IF(A84<='Assumptions and Catalog'!$C$6,SUMIFS($O$161:$O$400,$A$161:$A$400,A84)-(C$70+IF(AND('Assumptions and Catalog'!$C$19>0,A84='Assumptions and Catalog'!$C$19),C$61*'Assumptions and Catalog'!$C$20,0)+IF(AND('Assumptions and Catalog'!$C$21>0,A84='Assumptions and Catalog'!$C$21),C$62*'Assumptions and Catalog'!$C$22,0))*(1+'Assumptions and Catalog'!$C$9)^(A84-1),0) -> 39477.523 | D84: =C84/(1+'Assumptions and Catalog'!$C$7)^A84 -> 22284.032 | E84: =E83+C84 -> 114544.37 | F84: =F83+D84 -> 49132.395 | G84: =IF(A84<='Assumptions and Catalog'!$C$6,SUMIFS($O$411:$O$650,$A$411:$A$650,A84)-(D$70+IF(AND('Assumptions and Catalog'!$C$19>0,A84='Assumptions and Catalog'!$C$19),D$61*'Assumptions and Catalog'!$C$20,0)+IF(AND('Assumptions and Catalog'!$C$21>0,A84='Assumptions and Catalog'!$C$21),D$62*'Assumptions and Catalog'!$C$22,0))*(1+'Assumptions and Catalog'!$C$9)^(A84-1),0) -> -9932.56 | H84: =G84/(1+'Assumptions and Catalog'!$C$7)^A84 -> -5606.6712 | I84: =I83+G84 -> -1052851.4 | J84: =J83+H84 -> -1036514.9 | K84: =IF(A84<='Assumptions and Catalog'!$C$6,SUMIFS($O$661:$O$900,$A$661:$A$900,A84)-(E$70+IF(AND('Assumptions and Catalog'!$C$19>0,A84='Assumptions and Catalog'!$C$19),E$61*'Assumptions and Catalog'!$C$20,0)+IF(AND('Assumptions and Catalog'!$C$21>0,A84='Assumptions and Catalog'!$C$21),E$62*'Assumptions and Catalog'!$C$22,0))*(1+'Assumptions and Catalog'!$C$9)^(A84-1),0) -> 8150.3126 | L84: =K84/(1+'Assumptions and Catalog'!$C$7)^A84 -> 4600.639 | M84: =M83+K84 -> -2477171.6 | N84: =N83+L84 -> -2490972.2 | P84: =IF(AND(A84<='Assumptions and Catalog'!$C$6,E84>=0,E83<0,C84>0),A84-1-E83/C84,999) -> 999 | Q84: =IF(AND(A84<='Assumptions and Catalog'!$C$6,F84>=0,F83<0,D84>0),A84-1-F83/D84,999) -> 999 | R84: =IF(AND(A84<='Assumptions and Catalog'!$C$6,I84>=0,I83<0,G84>0),A84-1-I83/G84,999) -> 999 | S84: =IF(AND(A84<='Assumptions and Catalog'!$C$6,J84>=0,J83<0,H84>0),A84-1-J83/H84,999) -> 999 | T84: =IF(AND(A84<='Assumptions and Catalog'!$C$6,M84>=0,M83<0,K84>0),A84-1-M83/K84,999) -> 999 | U84: =IF(AND(A84<='Assumptions and Catalog'!$C$6,N84>=0,N83<0,L84>0),A84-1-N83/L84,999) -> 999
A85: 7 | B85: =IF(A85<='Assumptions and Catalog'!$C$6,SUMIFS($M$161:$M$400,$A$161:$A$400,A85),0) -> 100727.83 | C85: =IF(A85<='Assumptions and Catalog'!$C$6,SUMIFS($O$161:$O$400,$A$161:$A$400,A85)-(C$70+IF(AND('Assumptions and Catalog'!$C$19>0,A85='Assumptions and Catalog'!$C$19),C$61*'Assumptions and Catalog'!$C$20,0)+IF(AND('Assumptions and Catalog'!$C$21>0,A85='Assumptions and Catalog'!$C$21),C$62*'Assumptions and Catalog'!$C$22,0))*(1+'Assumptions and Catalog'!$C$9)^(A85-1),0) -> 39163.167 | D85: =C85/(1+'Assumptions and Catalog'!$C$7)^A85 -> 20096.897 | E85: =E84+C85 -> 153707.54 | F85: =F84+D85 -> 69229.292 | G85: =IF(A85<='Assumptions and Catalog'!$C$6,SUMIFS($O$411:$O$650,$A$411:$A$650,A85)-(D$70+IF(AND('Assumptions and Catalog'!$C$19>0,A85='Assumptions and Catalog'!$C$19),D$61*'Assumptions and Catalog'!$C$20,0)+IF(AND('Assumptions and Catalog'!$C$21>0,A85='Assumptions and Catalog'!$C$21),D$62*'Assumptions and Catalog'!$C$22,0))*(1+'Assumptions and Catalog'!$C$9)^(A85-1),0) -> -9932.56 | H85: =G85/(1+'Assumptions and Catalog'!$C$7)^A85 -> -5096.9738 | I85: =I84+G85 -> -1062783.9 | J85: =J84+H85 -> -1041611.9 | K85: =IF(A85<='Assumptions and Catalog'!$C$6,SUMIFS($O$661:$O$900,$A$661:$A$900,A85)-(E$70+IF(AND('Assumptions and Catalog'!$C$19>0,A85='Assumptions and Catalog'!$C$19),E$61*'Assumptions and Catalog'!$C$20,0)+IF(AND('Assumptions and Catalog'!$C$21>0,A85='Assumptions and Catalog'!$C$21),E$62*'Assumptions and Catalog'!$C$22,0))*(1+'Assumptions and Catalog'!$C$9)^(A85-1),0) -> 7892.2595 | L85: =K85/(1+'Assumptions and Catalog'!$C$7)^A85 -> 4049.977 | M85: =M84+K85 -> -2469279.3 | N85: =N84+L85 -> -2486922.2 | P85: =IF(AND(A85<='Assumptions and Catalog'!$C$6,E85>=0,E84<0,C85>0),A85-1-E84/C85,999) -> 999 | Q85: =IF(AND(A85<='Assumptions and Catalog'!$C$6,F85>=0,F84<0,D85>0),A85-1-F84/D85,999) -> 999 | R85: =IF(AND(A85<='Assumptions and Catalog'!$C$6,I85>=0,I84<0,G85>0),A85-1-I84/G85,999) -> 999 | S85: =IF(AND(A85<='Assumptions and Catalog'!$C$6,J85>=0,J84<0,H85>0),A85-1-J84/H85,999) -> 999 | T85: =IF(AND(A85<='Assumptions and Catalog'!$C$6,M85>=0,M84<0,K85>0),A85-1-M84/K85,999) -> 999 | U85: =IF(AND(A85<='Assumptions and Catalog'!$C$6,N85>=0,N84<0,L85>0),A85-1-N84/L85,999) -> 999
A86: 8 | B86: =IF(A86<='Assumptions and Catalog'!$C$6,SUMIFS($M$161:$M$400,$A$161:$A$400,A86),0) -> 100727.83 | C86: =IF(A86<='Assumptions and Catalog'!$C$6,SUMIFS($O$161:$O$400,$A$161:$A$400,A86)-(C$70+IF(AND('Assumptions and Catalog'!$C$19>0,A86='Assumptions and Catalog'!$C$19),C$61*'Assumptions and Catalog'!$C$20,0)+IF(AND('Assumptions and Catalog'!$C$21>0,A86='Assumptions and Catalog'!$C$21),C$62*'Assumptions and Catalog'!$C$22,0))*(1+'Assumptions and Catalog'!$C$9)^(A86-1),0) -> 38961.103 | D86: =C86/(1+'Assumptions and Catalog'!$C$7)^A86 -> 18175.642 | E86: =E85+C86 -> 192668.64 | F86: =F85+D86 -> 87404.934 | G86: =IF(A86<='Assumptions and Catalog'!$C$6,SUMIFS($O$411:$O$650,$A$411:$A$650,A86)-(D$70+IF(AND('Assumptions and Catalog'!$C$19>0,A86='Assumptions and Catalog'!$C$19),D$61*'Assumptions and Catalog'!$C$20,0)+IF(AND('Assumptions and Catalog'!$C$21>0,A86='Assumptions and Catalog'!$C$21),D$62*'Assumptions and Catalog'!$C$22,0))*(1+'Assumptions and Catalog'!$C$9)^(A86-1),0) -> -9932.56 | H86: =G86/(1+'Assumptions and Catalog'!$C$7)^A86 -> -4633.6125 | I86: =I85+G86 -> -1072716.5 | J86: =J85+H86 -> -1046245.5 | K86: =IF(A86<='Assumptions and Catalog'!$C$6,SUMIFS($O$661:$O$900,$A$661:$A$900,A86)-(E$70+IF(AND('Assumptions and Catalog'!$C$19>0,A86='Assumptions and Catalog'!$C$19),E$61*'Assumptions and Catalog'!$C$20,0)+IF(AND('Assumptions and Catalog'!$C$21>0,A86='Assumptions and Catalog'!$C$21),E$62*'Assumptions and Catalog'!$C$22,0))*(1+'Assumptions and Catalog'!$C$9)^(A86-1),0) -> 7726.3862 | L86: =K86/(1+'Assumptions and Catalog'!$C$7)^A86 -> 3604.4162 | M86: =M85+K86 -> -2461552.9 | N86: =N85+L86 -> -2483317.8 | P86: =IF(AND(A86<='Assumptions and Catalog'!$C$6,E86>=0,E85<0,C86>0),A86-1-E85/C86,999) -> 999 | Q86: =IF(AND(A86<='Assumptions and Catalog'!$C$6,F86>=0,F85<0,D86>0),A86-1-F85/D86,999) -> 999 | R86: =IF(AND(A86<='Assumptions and Catalog'!$C$6,I86>=0,I85<0,G86>0),A86-1-I85/G86,999) -> 999 | S86: =IF(AND(A86<='Assumptions and Catalog'!$C$6,J86>=0,J85<0,H86>0),A86-1-J85/H86,999) -> 999 | T86: =IF(AND(A86<='Assumptions and Catalog'!$C$6,M86>=0,M85<0,K86>0),A86-1-M85/K86,999) -> 999 | U86: =IF(AND(A86<='Assumptions and Catalog'!$C$6,N86>=0,N85<0,L86>0),A86-1-N85/L86,999) -> 999
A87: 9 | B87: =IF(A87<='Assumptions and Catalog'!$C$6,SUMIFS($M$161:$M$400,$A$161:$A$400,A87),0) -> 100727.83 | C87: =IF(A87<='Assumptions and Catalog'!$C$6,SUMIFS($O$161:$O$400,$A$161:$A$400,A87)-(C$70+IF(AND('Assumptions and Catalog'!$C$19>0,A87='Assumptions and Catalog'!$C$19),C$61*'Assumptions and Catalog'!$C$20,0)+IF(AND('Assumptions and Catalog'!$C$21>0,A87='Assumptions and Catalog'!$C$21),C$62*'Assumptions and Catalog'!$C$22,0))*(1+'Assumptions and Catalog'!$C$9)^(A87-1),0) -> 38760.05 | D87: =C87/(1+'Assumptions and Catalog'!$C$7)^A87 -> 16438.045 | E87: =E86+C87 -> 231428.69 | F87: =F86+D87 -> 103842.98 | G87: =IF(A87<='Assumptions and Catalog'!$C$6,SUMIFS($O$411:$O$650,$A$411:$A$650,A87)-(D$70+IF(AND('Assumptions and Catalog'!$C$19>0,A87='Assumptions and Catalog'!$C$19),D$61*'Assumptions and Catalog'!$C$20,0)+IF(AND('Assumptions and Catalog'!$C$21>0,A87='Assumptions and Catalog'!$C$21),D$62*'Assumptions and Catalog'!$C$22,0))*(1+'Assumptions and Catalog'!$C$9)^(A87-1),0) -> -9932.56 | H87: =G87/(1+'Assumptions and Catalog'!$C$7)^A87 -> -4212.375 | I87: =I86+G87 -> -1082649 | J87: =J86+H87 -> -1050457.8 | K87: =IF(A87<='Assumptions and Catalog'!$C$6,SUMIFS($O$661:$O$900,$A$661:$A$900,A87)-(E$70+IF(AND('Assumptions and Catalog'!$C$19>0,A87='Assumptions and Catalog'!$C$19),E$61*'Assumptions and Catalog'!$C$20,0)+IF(AND('Assumptions and Catalog'!$C$21>0,A87='Assumptions and Catalog'!$C$21),E$62*'Assumptions and Catalog'!$C$22,0))*(1+'Assumptions and Catalog'!$C$9)^(A87-1),0) -> 7561.3423 | L87: =K87/(1+'Assumptions and Catalog'!$C$7)^A87 -> 3206.7473 | M87: =M86+K87 -> -2453991.6 | N87: =N86+L87 -> -2480111 | P87: =IF(AND(A87<='Assumptions and Catalog'!$C$6,E87>=0,E86<0,C87>0),A87-1-E86/C87,999) -> 999 | Q87: =IF(AND(A87<='Assumptions and Catalog'!$C$6,F87>=0,F86<0,D87>0),A87-1-F86/D87,999) -> 999 | R87: =IF(AND(A87<='Assumptions and Catalog'!$C$6,I87>=0,I86<0,G87>0),A87-1-I86/G87,999) -> 999 | S87: =IF(AND(A87<='Assumptions and Catalog'!$C$6,J87>=0,J86<0,H87>0),A87-1-J86/H87,999) -> 999 | T87: =IF(AND(A87<='Assumptions and Catalog'!$C$6,M87>=0,M86<0,K87>0),A87-1-M86/K87,999) -> 999 | U87: =IF(AND(A87<='Assumptions and Catalog'!$C$6,N87>=0,N86<0,L87>0),A87-1-N86/L87,999) -> 999
A88: 10 | B88: =IF(A88<='Assumptions and Catalog'!$C$6,SUMIFS($M$161:$M$400,$A$161:$A$400,A88),0) -> 101003.8 | C88: =IF(A88<='Assumptions and Catalog'!$C$6,SUMIFS($O$161:$O$400,$A$161:$A$400,A88)-(C$70+IF(AND('Assumptions and Catalog'!$C$19>0,A88='Assumptions and Catalog'!$C$19),C$61*'Assumptions and Catalog'!$C$20,0)+IF(AND('Assumptions and Catalog'!$C$21>0,A88='Assumptions and Catalog'!$C$21),C$62*'Assumptions and Catalog'!$C$22,0))*(1+'Assumptions and Catalog'!$C$9)^(A88-1),0) -> 38669.069 | D88: =C88/(1+'Assumptions and Catalog'!$C$7)^A88 -> 14908.6 | E88: =E87+C88 -> 270097.76 | F88: =F87+D88 -> 118751.58 | G88: =IF(A88<='Assumptions and Catalog'!$C$6,SUMIFS($O$411:$O$650,$A$411:$A$650,A88)-(D$70+IF(AND('Assumptions and Catalog'!$C$19>0,A88='Assumptions and Catalog'!$C$19),D$61*'Assumptions and Catalog'!$C$20,0)+IF(AND('Assumptions and Catalog'!$C$21>0,A88='Assumptions and Catalog'!$C$21),D$62*'Assumptions and Catalog'!$C$22,0))*(1+'Assumptions and Catalog'!$C$9)^(A88-1),0) -> -9932.56 | H88: =G88/(1+'Assumptions and Catalog'!$C$7)^A88 -> -3829.4319 | I88: =I87+G88 -> -1092581.6 | J88: =J87+H88 -> -1054287.3 | K88: =IF(A88<='Assumptions and Catalog'!$C$6,SUMIFS($O$661:$O$900,$A$661:$A$900,A88)-(E$70+IF(AND('Assumptions and Catalog'!$C$19>0,A88='Assumptions and Catalog'!$C$19),E$61*'Assumptions and Catalog'!$C$20,0)+IF(AND('Assumptions and Catalog'!$C$21>0,A88='Assumptions and Catalog'!$C$21),E$62*'Assumptions and Catalog'!$C$22,0))*(1+'Assumptions and Catalog'!$C$9)^(A88-1),0) -> 7486.6565 | L88: =K88/(1+'Assumptions and Catalog'!$C$7)^A88 -> 2886.4302 | M88: =M87+K88 -> -2446504.9 | N88: =N87+L88 -> -2477224.6 | P88: =IF(AND(A88<='Assumptions and Catalog'!$C$6,E88>=0,E87<0,C88>0),A88-1-E87/C88,999) -> 999 | Q88: =IF(AND(A88<='Assumptions and Catalog'!$C$6,F88>=0,F87<0,D88>0),A88-1-F87/D88,999) -> 999 | R88: =IF(AND(A88<='Assumptions and Catalog'!$C$6,I88>=0,I87<0,G88>0),A88-1-I87/G88,999) -> 999 | S88: =IF(AND(A88<='Assumptions and Catalog'!$C$6,J88>=0,J87<0,H88>0),A88-1-J87/H88,999) -> 999 | T88: =IF(AND(A88<='Assumptions and Catalog'!$C$6,M88>=0,M87<0,K88>0),A88-1-M87/K88,999) -> 999 | U88: =IF(AND(A88<='Assumptions and Catalog'!$C$6,N88>=0,N87<0,L88>0),A88-1-N87/L88,999) -> 999
A89: 11 | B89: =IF(A89<='Assumptions and Catalog'!$C$6,SUMIFS($M$161:$M$400,$A$161:$A$400,A89),0) -> 0 | C89: =IF(A89<='Assumptions and Catalog'!$C$6,SUMIFS($O$161:$O$400,$A$161:$A$400,A89)-(C$70+IF(AND('Assumptions and Catalog'!$C$19>0,A89='Assumptions and Catalog'!$C$19),C$61*'Assumptions and Catalog'!$C$20,0)+IF(AND('Assumptions and Catalog'!$C$21>0,A89='Assumptions and Catalog'!$C$21),C$62*'Assumptions and Catalog'!$C$22,0))*(1+'Assumptions and Catalog'!$C$9)^(A89-1),0) -> 0 | D89: =C89/(1+'Assumptions and Catalog'!$C$7)^A89 -> 0 | E89: =E88+C89 -> 270097.76 | F89: =F88+D89 -> 118751.58 | G89: =IF(A89<='Assumptions and Catalog'!$C$6,SUMIFS($O$411:$O$650,$A$411:$A$650,A89)-(D$70+IF(AND('Assumptions and Catalog'!$C$19>0,A89='Assumptions and Catalog'!$C$19),D$61*'Assumptions and Catalog'!$C$20,0)+IF(AND('Assumptions and Catalog'!$C$21>0,A89='Assumptions and Catalog'!$C$21),D$62*'Assumptions and Catalog'!$C$22,0))*(1+'Assumptions and Catalog'!$C$9)^(A89-1),0) -> 0 | H89: =G89/(1+'Assumptions and Catalog'!$C$7)^A89 -> 0 | I89: =I88+G89 -> -1092581.6 | J89: =J88+H89 -> -1054287.3 | K89: =IF(A89<='Assumptions and Catalog'!$C$6,SUMIFS($O$661:$O$900,$A$661:$A$900,A89)-(E$70+IF(AND('Assumptions and Catalog'!$C$19>0,A89='Assumptions and Catalog'!$C$19),E$61*'Assumptions and Catalog'!$C$20,0)+IF(AND('Assumptions and Catalog'!$C$21>0,A89='Assumptions and Catalog'!$C$21),E$62*'Assumptions and Catalog'!$C$22,0))*(1+'Assumptions and Catalog'!$C$9)^(A89-1),0) -> 0 | L89: =K89/(1+'Assumptions and Catalog'!$C$7)^A89 -> 0 | M89: =M88+K89 -> -2446504.9 | N89: =N88+L89 -> -2477224.6 | P89: =IF(AND(A89<='Assumptions and Catalog'!$C$6,E89>=0,E88<0,C89>0),A89-1-E88/C89,999) -> 999 | Q89: =IF(AND(A89<='Assumptions and Catalog'!$C$6,F89>=0,F88<0,D89>0),A89-1-F88/D89,999) -> 999 | R89: =IF(AND(A89<='Assumptions and Catalog'!$C$6,I89>=0,I88<0,G89>0),A89-1-I88/G89,999) -> 999 | S89: =IF(AND(A89<='Assumptions and Catalog'!$C$6,J89>=0,J88<0,H89>0),A89-1-J88/H89,999) -> 999 | T89: =IF(AND(A89<='Assumptions and Catalog'!$C$6,M89>=0,M88<0,K89>0),A89-1-M88/K89,999) -> 999 | U89: =IF(AND(A89<='Assumptions and Catalog'!$C$6,N89>=0,N88<0,L89>0),A89-1-N88/L89,999) -> 999
A90: 12 | B90: =IF(A90<='Assumptions and Catalog'!$C$6,SUMIFS($M$161:$M$400,$A$161:$A$400,A90),0) -> 0 | C90: =IF(A90<='Assumptions and Catalog'!$C$6,SUMIFS($O$161:$O$400,$A$161:$A$400,A90)-(C$70+IF(AND('Assumptions and Catalog'!$C$19>0,A90='Assumptions and Catalog'!$C$19),C$61*'Assumptions and Catalog'!$C$20,0)+IF(AND('Assumptions and Catalog'!$C$21>0,A90='Assumptions and Catalog'!$C$21),C$62*'Assumptions and Catalog'!$C$22,0))*(1+'Assumptions and Catalog'!$C$9)^(A90-1),0) -> 0 | D90: =C90/(1+'Assumptions and Catalog'!$C$7)^A90 -> 0 | E90: =E89+C90 -> 270097.76 | F90: =F89+D90 -> 118751.58 | G90: =IF(A90<='Assumptions and Catalog'!$C$6,SUMIFS($O$411:$O$650,$A$411:$A$650,A90)-(D$70+IF(AND('Assumptions and Catalog'!$C$19>0,A90='Assumptions and Catalog'!$C$19),D$61*'Assumptions and Catalog'!$C$20,0)+IF(AND('Assumptions and Catalog'!$C$21>0,A90='Assumptions and Catalog'!$C$21),D$62*'Assumptions and Catalog'!$C$22,0))*(1+'Assumptions and Catalog'!$C$9)^(A90-1),0) -> 0 | H90: =G90/(1+'Assumptions and Catalog'!$C$7)^A90 -> 0 | I90: =I89+G90 -> -1092581.6 | J90: =J89+H90 -> -1054287.3 | K90: =IF(A90<='Assumptions and Catalog'!$C$6,SUMIFS($O$661:$O$900,$A$661:$A$900,A90)-(E$70+IF(AND('Assumptions and Catalog'!$C$19>0,A90='Assumptions and Catalog'!$C$19),E$61*'Assumptions and Catalog'!$C$20,0)+IF(AND('Assumptions and Catalog'!$C$21>0,A90='Assumptions and Catalog'!$C$21),E$62*'Assumptions and Catalog'!$C$22,0))*(1+'Assumptions and Catalog'!$C$9)^(A90-1),0) -> 0 | L90: =K90/(1+'Assumptions and Catalog'!$C$7)^A90 -> 0 | M90: =M89+K90 -> -2446504.9 | N90: =N89+L90 -> -2477224.6 | P90: =IF(AND(A90<='Assumptions and Catalog'!$C$6,E90>=0,E89<0,C90>0),A90-1-E89/C90,999) -> 999 | Q90: =IF(AND(A90<='Assumptions and Catalog'!$C$6,F90>=0,F89<0,D90>0),A90-1-F89/D90,999) -> 999 | R90: =IF(AND(A90<='Assumptions and Catalog'!$C$6,I90>=0,I89<0,G90>0),A90-1-I89/G90,999) -> 999 | S90: =IF(AND(A90<='Assumptions and Catalog'!$C$6,J90>=0,J89<0,H90>0),A90-1-J89/H90,999) -> 999 | T90: =IF(AND(A90<='Assumptions and Catalog'!$C$6,M90>=0,M89<0,K90>0),A90-1-M89/K90,999) -> 999 | U90: =IF(AND(A90<='Assumptions and Catalog'!$C$6,N90>=0,N89<0,L90>0),A90-1-N89/L90,999) -> 999
... A98: 20 | B98: =IF(A98<='Assumptions and Catalog'!$C$6,SUMIFS($M$161:$M$400,$A$161:$A$400,A98),0) -> 0 | C98: =IF(A98<='Assumptions and Catalog'!$C$6,SUMIFS($O$161:$O$400,$A$161:$A$400,A98)-(C$70+IF(AND('Assumptions and Catalog'!$C$19>0,A98='Assumptions and Catalog'!$C$19),C$61*'Assumptions and Catalog'!$C$20,0)+IF(AND('Assumptions and Catalog'!$C$21>0,A98='Assumptions and Catalog'!$C$21),C$62*'Assumptions and Catalog'!$C$22,0))*(1+'Assumptions and Catalog'!$C$9)^(A98-1),0) -> 0 | D98: =C98/(1+'Assumptions and Catalog'!$C$7)^A98 -> 0 | E98: =E97+C98 -> 270097.76 | F98: =F97+D98 -> 118751.58 | G98: =IF(A98<='Assumptions and Catalog'!$C$6,SUMIFS($O$411:$O$650,$A$411:$A$650,A98)-(D$70+IF(AND('Assumptions and Catalog'!$C$19>0,A98='Assumptions and Catalog'!$C$19),D$61*'Assumptions and Catalog'!$C$20,0)+IF(AND('Assumptions and Catalog'!$C$21>0,A98='Assumptions and Catalog'!$C$21),D$62*'Assumptions and Catalog'!$C$22,0))*(1+'Assumptions and Catalog'!$C$9)^(A98-1),0) -> 0 | H98: =G98/(1+'Assumptions and Catalog'!$C$7)^A98 -> 0 | I98: =I97+G98 -> -1092581.6 | J98: =J97+H98 -> -1054287.3 | K98: =IF(A98<='Assumptions and Catalog'!$C$6,SUMIFS($O$661:$O$900,$A$661:$A$900,A98)-(E$70+IF(AND('Assumptions and Catalog'!$C$19>0,A98='Assumptions and Catalog'!$C$19),E$61*'Assumptions and Catalog'!$C$20,0)+IF(AND('Assumptions and Catalog'!$C$21>0,A98='Assumptions and Catalog'!$C$21),E$62*'Assumptions and Catalog'!$C$22,0))*(1+'Assumptions and Catalog'!$C$9)^(A98-1),0) -> 0 | L98: =K98/(1+'Assumptions and Catalog'!$C$7)^A98 -> 0 | M98: =M97+K98 -> -2446504.9 | N98: =N97+L98 -> -2477224.6 | P98: =IF(AND(A98<='Assumptions and Catalog'!$C$6,E98>=0,E97<0,C98>0),A98-1-E97/C98,999) -> 999 | Q98: =IF(AND(A98<='Assumptions and Catalog'!$C$6,F98>=0,F97<0,D98>0),A98-1-F97/D98,999) -> 999 | R98: =IF(AND(A98<='Assumptions and Catalog'!$C$6,I98>=0,I97<0,G98>0),A98-1-I97/G98,999) -> 999 | S98: =IF(AND(A98<='Assumptions and Catalog'!$C$6,J98>=0,J97<0,H98>0),A98-1-J97/H98,999) -> 999 | T98: =IF(AND(A98<='Assumptions and Catalog'!$C$6,M98>=0,M97<0,K98>0),A98-1-M97/K98,999) -> 999 | U98: =IF(AND(A98<='Assumptions and Catalog'!$C$6,N98>=0,N97<0,L98>0),A98-1-N97/L98,999) -> 999
A102: Payback is the first cumulative cash-flow crossing of zero. Fractional years are interpolated. Later replacement can reduce the balance.
A103: Grants, financing, taxes, residual value and outage value are excluded. A battery does not generate energy.
A104: Annual degradation; one replacement in the selected year. Full-charge backup figures relate to year 1.
A158: Solar only — monthly calculations
A160: years | B160: month | C160: Days | D160: Day load kWh/d | E160: Night load kWh/d | F160: PV kWh/mo | G160: Direct use kWh/mo | H160: Charge kWh/mo | I160: Discharge kWh/mo | J160: Unused PV kWh/mo | K160: Losses kWh/mo | L160: Grid imports kWh/mo | M160: Baseline EGP | N160: New bill EGP | O160: Bill savings EGP | P160: Operating capacity kWh | Q160: Matched PV-only bill (EGP) | R160: Battery age | S160: Balance check kWh
A161: 1 | B161: 1 | C161: =DAY(DATE('Assumptions and Catalog'!$C$24+A161-1,B161+1,0)) -> 31 | D161: =IF(ISNUMBER(Inputs!$L$5),Inputs!$L$5*Inputs!$L$6,0) -> 40.35 | E161: =IF(ISNUMBER(Inputs!$L$5),Inputs!$L$5-D161,0) -> 40.35 | F161: =C$51*'Assumptions and Catalog'!$C$31*C161*(1-'Assumptions and Catalog'!$C$10)^(A161-1) -> 1034.346 | G161: =MIN(F161,D161*C161) -> 1034.346 | H161: =I161/('Assumptions and Catalog'!$C$11*'Assumptions and Catalog'!$C$12) -> 0 | I161: =0 -> 0 | J161: =MAX(F161-G161-H161,0) -> 0 | K161: =H161-I161 -> 0 | L161: =(D161+E161)*C161-G161-I161+0+0 -> 1467.354 | M161: =IF(ISNUMBER(Inputs!$L$5),(IF(Inputs!$L$9="Actual flat rate",((D161+E161)*C161)*Inputs!$L$10,IF(Inputs!$C$9="Residential",IF(((D161+E161)*C161)<='Assumptions and Catalog'!$C$50,((D161+E161)*C161)*'Assumptions and Catalog'!$H$50+'Assumptions and Catalog'!$E$50+'Assumptions and Catalog'!$F$50,IF(((D161+E161)*C161)<='Assumptions and Catalog'!$C$51,((D161+E161)*C161)*'Assumptions and Catalog'!$H$51+'Assumptions and Catalog'!$E$51+'Assumptions and Catalog'!$F$51,IF(((D161+E161)*C161)<='Assumptions and Catalog'!$C$52,((D161+E161)*C161)*'Assumptions and Catalog'!$H$52+'Assumptions and Catalog'!$E$52+'Assumptions and Catalog'!$F$52,IF(((D161+E161)*C161)<='Assumptions and Catalog'!$C$53,((D161+E161)*C161)*'Assumptions and Catalog'!$H$53+'Assumptions and Catalog'!$E$53+'Assumptions and Catalog'!$F$53,IF(((D161+E161)*C161)<='Assumptions and Catalog'!$C$54,((D161+E161)*C161)*'Assumptions and Catalog'!$H$54+'Assumptions and Catalog'!$E$54+'Assumptions and Catalog'!$F$54,IF(((D161+E161)*C161)<='Assumptions and Catalog'!$C$55,((D161+E161)*C161)*'Assumptions and Catalog'!$H$55+'Assumptions and Catalog'!$E$55+'Assumptions and Catalog'!$F$55,IF(((D161+E161)*C161)<='Assumptions and Catalog'!$C$56,((D161+E161)*C161)*'Assumptions and Catalog'!$H$56+'Assumptions and Catalog'!$E$56+'Assumptions and Catalog'!$F$56,IF(((D161+E161)*C161)<='Assumptions and Catalog'!$C$57,((D161+E161)*C161)*'Assumptions and Catalog'!$H$57+'Assumptions and Catalog'!$E$57+'Assumptions and Catalog'!$F$57,"Out of range")))))))),IF(((D161+E161)*C161)<='Assumptions and Catalog'!$C$60,((D161+E161)*C161)*'Assumptions and Catalog'!$H$60+'Assumptions and Catalog'!$E$60+'Assumptions and Catalog'!$F$60,IF(((D161+E161)*C161)<='Assumptions and Catalog'!$C$61,((D161+E161)*C161)*'Assumptions and Catalog'!$H$61+'Assumptions and Catalog'!$E$61+'Assumptions and Catalog'!$F$61,IF(((D161+E161)*C161)<='Assumptions and Catalog'!$C$62,((D161+E161)*C161)*'Assumptions and Catalog'!$H$62+'Assumptions and Catalog'!$E$62+'Assumptions and Catalog'!$F$62,IF(((D161+E161)*C161)<='Assumptions and Catalog'!$C$63,((D161+E161)*C161)*'Assumptions and Catalog'!$H$63+'Assumptions and Catalog'!$E$63+'Assumptions and Catalog'!$F$63,IF(((D161+E161)*C161)<='Assumptions and Catalog'!$C$64,((D161+E161)*C161)*'Assumptions and Catalog'!$H$64+'Assumptions and Catalog'!$E$64+'Assumptions and Catalog'!$F$64,IF(((D161+E161)*C161)<='Assumptions and Catalog'!$C$65,((D161+E161)*C161)*'Assumptions and Catalog'!$H$65+'Assumptions and Catalog'!$E$65+'Assumptions and Catalog'!$F$65,"Out of range")))))))))*(1+'Assumptions and Catalog'!$C$8)^(A161-1),0) -> 8554.9667 | N161: =IF(ISNUMBER(Inputs!$L$5),(IF(Inputs!$L$9="Actual flat rate",L161*Inputs!$L$10,IF(Inputs!$C$9="Residential",IF(L161<='Assumptions and Catalog'!$C$50,L161*'Assumptions and Catalog'!$H$50+'Assumptions and Catalog'!$E$50+'Assumptions and Catalog'!$F$50,IF(L161<='Assumptions and Catalog'!$C$51,L161*'Assumptions and Catalog'!$H$51+'Assumptions and Catalog'!$E$51+'Assumptions and Catalog'!$F$51,IF(L161<='Assumptions and Catalog'!$C$52,L161*'Assumptions and Catalog'!$H$52+'Assumptions and Catalog'!$E$52+'Assumptions and Catalog'!$F$52,IF(L161<='Assumptions and Catalog'!$C$53,L161*'Assumptions and Catalog'!$H$53+'Assumptions and Catalog'!$E$53+'Assumptions and Catalog'!$F$53,IF(L161<='Assumptions and Catalog'!$C$54,L161*'Assumptions and Catalog'!$H$54+'Assumptions and Catalog'!$E$54+'Assumptions and Catalog'!$F$54,IF(L161<='Assumptions and Catalog'!$C$55,L161*'Assumptions and Catalog'!$H$55+'Assumptions and Catalog'!$E$55+'Assumptions and Catalog'!$F$55,IF(L161<='Assumptions and Catalog'!$C$56,L161*'Assumptions and Catalog'!$H$56+'Assumptions and Catalog'!$E$56+'Assumptions and Catalog'!$F$56,IF(L161<='Assumptions and Catalog'!$C$57,L161*'Assumptions and Catalog'!$H$57+'Assumptions and Catalog'!$E$57+'Assumptions and Catalog'!$F$57,"Out of range")))))))),IF(L161<='Assumptions and Catalog'!$C$60,L161*'Assumptions and Catalog'!$H$60+'Assumptions and Catalog'!$E$60+'Assumptions and Catalog'!$F$60,IF(L161<='Assumptions and Catalog'!$C$61,L161*'Assumptions and Catalog'!$H$61+'Assumptions and Catalog'!$E$61+'Assumptions and Catalog'!$F$61,IF(L161<='Assumptions and Catalog'!$C$62,L161*'Assumptions and Catalog'!$H$62+'Assumptions and Catalog'!$E$62+'Assumptions and Catalog'!$F$62,IF(L161<='Assumptions and Catalog'!$C$63,L161*'Assumptions and Catalog'!$H$63+'Assumptions and Catalog'!$E$63+'Assumptions and Catalog'!$F$63,IF(L161<='Assumptions and Catalog'!$C$64,L161*'Assumptions and Catalog'!$H$64+'Assumptions and Catalog'!$E$64+'Assumptions and Catalog'!$F$64,IF(L161<='Assumptions and Catalog'!$C$65,L161*'Assumptions and Catalog'!$H$65+'Assumptions and Catalog'!$E$65+'Assumptions and Catalog'!$F$65,"Out of range")))))))))*(1+'Assumptions and Catalog'!$C$8)^(A161-1),0) -> 5017.8537 | O161: =M161-N161 -> 3537.113 | P161: =C$55*(1-J$14)*(1-'Assumptions and Catalog'!$C$23)^R161 -> 0 | Q161: =IF(ISNUMBER(Inputs!$L$5),(IF(Inputs!$L$9="Actual flat rate",((D161+E161)*C161-G161)*Inputs!$L$10,IF(Inputs!$C$9="Residential",IF(((D161+E161)*C161-G161)<='Assumptions and Catalog'!$C$50,((D161+E161)*C161-G161)*'Assumptions and Catalog'!$H$50+'Assumptions and Catalog'!$E$50+'Assumptions and Catalog'!$F$50,IF(((D161+E161)*C161-G161)<='Assumptions and Catalog'!$C$51,((D161+E161)*C161-G161)*'Assumptions and Catalog'!$H$51+'Assumptions and Catalog'!$E$51+'Assumptions and Catalog'!$F$51,IF(((D161+E161)*C161-G161)<='Assumptions and Catalog'!$C$52,((D161+E161)*C161-G161)*'Assumptions and Catalog'!$H$52+'Assumptions and Catalog'!$E$52+'Assumptions and Catalog'!$F$52,IF(((D161+E161)*C161-G161)<='Assumptions and Catalog'!$C$53,((D161+E161)*C161-G161)*'Assumptions and Catalog'!$H$53+'Assumptions and Catalog'!$E$53+'Assumptions and Catalog'!$F$53,IF(((D161+E161)*C161-G161)<='Assumptions and Catalog'!$C$54,((D161+E161)*C161-G161)*'Assumptions and Catalog'!$H$54+'Assumptions and Catalog'!$E$54+'Assumptions and Catalog'!$F$54,IF(((D161+E161)*C161-G161)<='Assumptions and Catalog'!$C$55,((D161+E161)*C161-G161)*'Assumptions and Catalog'!$H$55+'Assumptions and Catalog'!$E$55+'Assumptions and Catalog'!$F$55,IF(((D161+E161)*C161-G161)<='Assumptions and Catalog'!$C$56,((D161+E161)*C161-G161)*'Assumptions and Catalog'!$H$56+'Assumptions and Catalog'!$E$56+'Assumptions and Catalog'!$F$56,IF(((D161+E161)*C161-G161)<='Assumptions and Catalog'!$C$57,((D161+E161)*C161-G161)*'Assumptions and Catalog'!$H$57+'Assumptions and Catalog'!$E$57+'Assumptions and Catalog'!$F$57,"Out of range")))))))),IF(((D161+E161)*C161-G161)<='Assumptions and Catalog'!$C$60,((D161+E161)*C161-G161)*'Assumptions and Catalog'!$H$60+'Assumptions and Catalog'!$E$60+'Assumptions and Catalog'!$F$60,IF(((D161+E161)*C161-G161)<='Assumptions and Catalog'!$C$61,((D161+E161)*C161-G161)*'Assumptions and Catalog'!$H$61+'Assumptions and Catalog'!$E$61+'Assumptions and Catalog'!$F$61,IF(((D161+E161)*C161-G161)<='Assumptions and Catalog'!$C$62,((D161+E161)*C161-G161)*'Assumptions and Catalog'!$H$62+'Assumptions and Catalog'!$E$62+'Assumptions and Catalog'!$F$62,IF(((D161+E161)*C161-G161)<='Assumptions and Catalog'!$C$63,((D161+E161)*C161-G161)*'Assumptions and Catalog'!$H$63+'Assumptions and Catalog'!$E$63+'Assumptions and Catalog'!$F$63,IF(((D161+E161)*C161-G161)<='Assumptions and Catalog'!$C$64,((D161+E161)*C161-G161)*'Assumptions and Catalog'!$H$64+'Assumptions and Catalog'!$E$64+'Assumptions and Catalog'!$F$64,IF(((D161+E161)*C161-G161)<='Assumptions and Catalog'!$C$65,((D161+E161)*C161-G161)*'Assumptions and Catalog'!$H$65+'Assumptions and Catalog'!$E$65+'Assumptions and Catalog'!$F$65,"Out of range")))))))))*(1+'Assumptions and Catalog'!$C$8)^(A161-1),0) -> 5017.8537 | R161: =IF(AND('Assumptions and Catalog'!$C$19>0,A161>='Assumptions and Catalog'!$C$19),A161-'Assumptions and Catalog'!$C$19,A161-1) -> 0 | S161: =F161+L161-(D161+E161)*C161-J161-K161-0 -> 0
A162: 1 | B162: 2 | C162: =DAY(DATE('Assumptions and Catalog'!$C$24+A162-1,B162+1,0)) -> 28 | D162: =IF(ISNUMBER(Inputs!$L$5),Inputs!$L$5*Inputs!$L$6,0) -> 40.35 | E162: =IF(ISNUMBER(Inputs!$L$5),Inputs!$L$5-D162,0) -> 40.35 | F162: =C$51*'Assumptions and Catalog'!$C$31*C162*(1-'Assumptions and Catalog'!$C$10)^(A162-1) -> 934.248 | G162: =MIN(F162,D162*C162) -> 934.248 | H162: =I162/('Assumptions and Catalog'!$C$11*'Assumptions and Catalog'!$C$12) -> 0 | I162: =0 -> 0 | J162: =MAX(F162-G162-H162,0) -> 0 | K162: =H162-I162 -> 0 | L162: =(D162+E162)*C162-G162-I162+0+0 -> 1325.352 | M162: =IF(ISNUMBER(Inputs!$L$5),(IF(Inputs!$L$9="Actual flat rate",((D162+E162)*C162)*Inputs!$L$10,IF(Inputs!$C$9="Residential",IF(((D162+E162)*C162)<='Assumptions and Catalog'!$C$50,((D162+E162)*C162)*'Assumptions and Catalog'!$H$50+'Assumptions and Catalog'!$E$50+'Assumptions and Catalog'!$F$50,IF(((D162+E162)*C162)<='Assumptions and Catalog'!$C$51,((D162+E162)*C162)*'Assumptions and Catalog'!$H$51+'Assumptions and Catalog'!$E$51+'Assumptions and Catalog'!$F$51,IF(((D162+E162)*C162)<='Assumptions and Catalog'!$C$52,((D162+E162)*C162)*'Assumptions and Catalog'!$H$52+'Assumptions and Catalog'!$E$52+'Assumptions and Catalog'!$F$52,IF(((D162+E162)*C162)<='Assumptions and Catalog'!$C$53,((D162+E162)*C162)*'Assumptions and Catalog'!$H$53+'Assumptions and Catalog'!$E$53+'Assumptions and Catalog'!$F$53,IF(((D162+E162)*C162)<='Assumptions and Catalog'!$C$54,((D162+E162)*C162)*'Assumptions and Catalog'!$H$54+'Assumptions and Catalog'!$E$54+'Assumptions and Catalog'!$F$54,IF(((D162+E162)*C162)<='Assumptions and Catalog'!$C$55,((D162+E162)*C162)*'Assumptions and Catalog'!$H$55+'Assumptions and Catalog'!$E$55+'Assumptions and Catalog'!$F$55,IF(((D162+E162)*C162)<='Assumptions and Catalog'!$C$56,((D162+E162)*C162)*'Assumptions and Catalog'!$H$56+'Assumptions and Catalog'!$E$56+'Assumptions and Catalog'!$F$56,IF(((D162+E162)*C162)<='Assumptions and Catalog'!$C$57,((D162+E162)*C162)*'Assumptions and Catalog'!$H$57+'Assumptions and Catalog'!$E$57+'Assumptions and Catalog'!$F$57,"Out of range")))))))),IF(((D162+E162)*C162)<='Assumptions and Catalog'!$C$60,((D162+E162)*C162)*'Assumptions and Catalog'!$H$60+'Assumptions and Catalog'!$E$60+'Assumptions and Catalog'!$F$60,IF(((D162+E162)*C162)<='Assumptions and Catalog'!$C$61,((D162+E162)*C162)*'Assumptions and Catalog'!$H$61+'Assumptions and Catalog'!$E$61+'Assumptions and Catalog'!$F$61,IF(((D162+E162)*C162)<='Assumptions and Catalog'!$C$62,((D162+E162)*C162)*'Assumptions and Catalog'!$H$62+'Assumptions and Catalog'!$E$62+'Assumptions and Catalog'!$F$62,IF(((D162+E162)*C162)<='Assumptions and Catalog'!$C$63,((D162+E162)*C162)*'Assumptions and Catalog'!$H$63+'Assumptions and Catalog'!$E$63+'Assumptions and Catalog'!$F$63,IF(((D162+E162)*C162)<='Assumptions and Catalog'!$C$64,((D162+E162)*C162)*'Assumptions and Catalog'!$H$64+'Assumptions and Catalog'!$E$64+'Assumptions and Catalog'!$F$64,IF(((D162+E162)*C162)<='Assumptions and Catalog'!$C$65,((D162+E162)*C162)*'Assumptions and Catalog'!$H$65+'Assumptions and Catalog'!$E$65+'Assumptions and Catalog'!$F$65,"Out of range")))))))))*(1+'Assumptions and Catalog'!$C$8)^(A162-1),0) -> 7727.0667 | N162: =IF(ISNUMBER(Inputs!$L$5),(IF(Inputs!$L$9="Actual flat rate",L162*Inputs!$L$10,IF(Inputs!$C$9="Residential",IF(L162<='Assumptions and Catalog'!$C$50,L162*'Assumptions and Catalog'!$H$50+'Assumptions and Catalog'!$E$50+'Assumptions and Catalog'!$F$50,IF(L162<='Assumptions and Catalog'!$C$51,L162*'Assumptions and Catalog'!$H$51+'Assumptions and Catalog'!$E$51+'Assumptions and Catalog'!$F$51,IF(L162<='Assumptions and Catalog'!$C$52,L162*'Assumptions and Catalog'!$H$52+'Assumptions and Catalog'!$E$52+'Assumptions and Catalog'!$F$52,IF(L162<='Assumptions and Catalog'!$C$53,L162*'Assumptions and Catalog'!$H$53+'Assumptions and Catalog'!$E$53+'Assumptions and Catalog'!$F$53,IF(L162<='Assumptions and Catalog'!$C$54,L162*'Assumptions and Catalog'!$H$54+'Assumptions and Catalog'!$E$54+'Assumptions and Catalog'!$F$54,IF(L162<='Assumptions and Catalog'!$C$55,L162*'Assumptions and Catalog'!$H$55+'Assumptions and Catalog'!$E$55+'Assumptions and Catalog'!$F$55,IF(L162<='Assumptions and Catalog'!$C$56,L162*'Assumptions and Catalog'!$H$56+'Assumptions and Catalog'!$E$56+'Assumptions and Catalog'!$F$56,IF(L162<='Assumptions and Catalog'!$C$57,L162*'Assumptions and Catalog'!$H$57+'Assumptions and Catalog'!$E$57+'Assumptions and Catalog'!$F$57,"Out of range")))))))),IF(L162<='Assumptions and Catalog'!$C$60,L162*'Assumptions and Catalog'!$H$60+'Assumptions and Catalog'!$E$60+'Assumptions and Catalog'!$F$60,IF(L162<='Assumptions and Catalog'!$C$61,L162*'Assumptions and Catalog'!$H$61+'Assumptions and Catalog'!$E$61+'Assumptions and Catalog'!$F$61,IF(L162<='Assumptions and Catalog'!$C$62,L162*'Assumptions and Catalog'!$H$62+'Assumptions and Catalog'!$E$62+'Assumptions and Catalog'!$F$62,IF(L162<='Assumptions and Catalog'!$C$63,L162*'Assumptions and Catalog'!$H$63+'Assumptions and Catalog'!$E$63+'Assumptions and Catalog'!$F$63,IF(L162<='Assumptions and Catalog'!$C$64,L162*'Assumptions and Catalog'!$H$64+'Assumptions and Catalog'!$E$64+'Assumptions and Catalog'!$F$64,IF(L162<='Assumptions and Catalog'!$C$65,L162*'Assumptions and Catalog'!$H$65+'Assumptions and Catalog'!$E$65+'Assumptions and Catalog'!$F$65,"Out of range")))))))))*(1+'Assumptions and Catalog'!$C$8)^(A162-1),0) -> 4532.2549 | O162: =M162-N162 -> 3194.8117 | P162: =C$55*(1-J$14)*(1-'Assumptions and Catalog'!$C$23)^R162 -> 0 | Q162: =IF(ISNUMBER(Inputs!$L$5),(IF(Inputs!$L$9="Actual flat rate",((D162+E162)*C162-G162)*Inputs!$L$10,IF(Inputs!$C$9="Residential",IF(((D162+E162)*C162-G162)<='Assumptions and Catalog'!$C$50,((D162+E162)*C162-G162)*'Assumptions and Catalog'!$H$50+'Assumptions and Catalog'!$E$50+'Assumptions and Catalog'!$F$50,IF(((D162+E162)*C162-G162)<='Assumptions and Catalog'!$C$51,((D162+E162)*C162-G162)*'Assumptions and Catalog'!$H$51+'Assumptions and Catalog'!$E$51+'Assumptions and Catalog'!$F$51,IF(((D162+E162)*C162-G162)<='Assumptions and Catalog'!$C$52,((D162+E162)*C162-G162)*'Assumptions and Catalog'!$H$52+'Assumptions and Catalog'!$E$52+'Assumptions and Catalog'!$F$52,IF(((D162+E162)*C162-G162)<='Assumptions and Catalog'!$C$53,((D162+E162)*C162-G162)*'Assumptions and Catalog'!$H$53+'Assumptions and Catalog'!$E$53+'Assumptions and Catalog'!$F$53,IF(((D162+E162)*C162-G162)<='Assumptions and Catalog'!$C$54,((D162+E162)*C162-G162)*'Assumptions and Catalog'!$H$54+'Assumptions and Catalog'!$E$54+'Assumptions and Catalog'!$F$54,IF(((D162+E162)*C162-G162)<='Assumptions and Catalog'!$C$55,((D162+E162)*C162-G162)*'Assumptions and Catalog'!$H$55+'Assumptions and Catalog'!$E$55+'Assumptions and Catalog'!$F$55,IF(((D162+E162)*C162-G162)<='Assumptions and Catalog'!$C$56,((D162+E162)*C162-G162)*'Assumptions and Catalog'!$H$56+'Assumptions and Catalog'!$E$56+'Assumptions and Catalog'!$F$56,IF(((D162+E162)*C162-G162)<='Assumptions and Catalog'!$C$57,((D162+E162)*C162-G162)*'Assumptions and Catalog'!$H$57+'Assumptions and Catalog'!$E$57+'Assumptions and Catalog'!$F$57,"Out of range")))))))),IF(((D162+E162)*C162-G162)<='Assumptions and Catalog'!$C$60,((D162+E162)*C162-G162)*'Assumptions and Catalog'!$H$60+'Assumptions and Catalog'!$E$60+'Assumptions and Catalog'!$F$60,IF(((D162+E162)*C162-G162)<='Assumptions and Catalog'!$C$61,((D162+E162)*C162-G162)*'Assumptions and Catalog'!$H$61+'Assumptions and Catalog'!$E$61+'Assumptions and Catalog'!$F$61,IF(((D162+E162)*C162-G162)<='Assumptions and Catalog'!$C$62,((D162+E162)*C162-G162)*'Assumptions and Catalog'!$H$62+'Assumptions and Catalog'!$E$62+'Assumptions and Catalog'!$F$62,IF(((D162+E162)*C162-G162)<='Assumptions and Catalog'!$C$63,((D162+E162)*C162-G162)*'Assumptions and Catalog'!$H$63+'Assumptions and Catalog'!$E$63+'Assumptions and Catalog'!$F$63,IF(((D162+E162)*C162-G162)<='Assumptions and Catalog'!$C$64,((D162+E162)*C162-G162)*'Assumptions and Catalog'!$H$64+'Assumptions and Catalog'!$E$64+'Assumptions and Catalog'!$F$64,IF(((D162+E162)*C162-G162)<='Assumptions and Catalog'!$C$65,((D162+E162)*C162-G162)*'Assumptions and Catalog'!$H$65+'Assumptions and Catalog'!$E$65+'Assumptions and Catalog'!$F$65,"Out of range")))))))))*(1+'Assumptions and Catalog'!$C$8)^(A162-1),0) -> 4532.2549 | R162: =IF(AND('Assumptions and Catalog'!$C$19>0,A162>='Assumptions and Catalog'!$C$19),A162-'Assumptions and Catalog'!$C$19,A162-1) -> 0 | S162: =F162+L162-(D162+E162)*C162-J162-K162-0 -> 0
A163: 1 | B163: 3 | C163: =DAY(DATE('Assumptions and Catalog'!$C$24+A163-1,B163+1,0)) -> 31 | D163: =IF(ISNUMBER(Inputs!$L$5),Inputs!$L$5*Inputs!$L$6,0) -> 40.35 | E163: =IF(ISNUMBER(Inputs!$L$5),Inputs!$L$5-D163,0) -> 40.35 | F163: =C$51*'Assumptions and Catalog'!$C$31*C163*(1-'Assumptions and Catalog'!$C$10)^(A163-1) -> 1034.346 | G163: =MIN(F163,D163*C163) -> 1034.346 | H163: =I163/('Assumptions and Catalog'!$C$11*'Assumptions and Catalog'!$C$12) -> 0 | I163: =0 -> 0 | J163: =MAX(F163-G163-H163,0) -> 0 | K163: =H163-I163 -> 0 | L163: =(D163+E163)*C163-G163-I163+0+0 -> 1467.354 | M163: =IF(ISNUMBER(Inputs!$L$5),(IF(Inputs!$L$9="Actual flat rate",((D163+E163)*C163)*Inputs!$L$10,IF(Inputs!$C$9="Residential",IF(((D163+E163)*C163)<='Assumptions and Catalog'!$C$50,((D163+E163)*C163)*'Assumptions and Catalog'!$H$50+'Assumptions and Catalog'!$E$50+'Assumptions and Catalog'!$F$50,IF(((D163+E163)*C163)<='Assumptions and Catalog'!$C$51,((D163+E163)*C163)*'Assumptions and Catalog'!$H$51+'Assumptions and Catalog'!$E$51+'Assumptions and Catalog'!$F$51,IF(((D163+E163)*C163)<='Assumptions and Catalog'!$C$52,((D163+E163)*C163)*'Assumptions and Catalog'!$H$52+'Assumptions and Catalog'!$E$52+'Assumptions and Catalog'!$F$52,IF(((D163+E163)*C163)<='Assumptions and Catalog'!$C$53,((D163+E163)*C163)*'Assumptions and Catalog'!$H$53+'Assumptions and Catalog'!$E$53+'Assumptions and Catalog'!$F$53,IF(((D163+E163)*C163)<='Assumptions and Catalog'!$C$54,((D163+E163)*C163)*'Assumptions and Catalog'!$H$54+'Assumptions and Catalog'!$E$54+'Assumptions and Catalog'!$F$54,IF(((D163+E163)*C163)<='Assumptions and Catalog'!$C$55,((D163+E163)*C163)*'Assumptions and Catalog'!$H$55+'Assumptions and Catalog'!$E$55+'Assumptions and Catalog'!$F$55,IF(((D163+E163)*C163)<='Assumptions and Catalog'!$C$56,((D163+E163)*C163)*'Assumptions and Catalog'!$H$56+'Assumptions and Catalog'!$E$56+'Assumptions and Catalog'!$F$56,IF(((D163+E163)*C163)<='Assumptions and Catalog'!$C$57,((D163+E163)*C163)*'Assumptions and Catalog'!$H$57+'Assumptions and Catalog'!$E$57+'Assumptions and Catalog'!$F$57,"Out of range")))))))),IF(((D163+E163)*C163)<='Assumptions and Catalog'!$C$60,((D163+E163)*C163)*'Assumptions and Catalog'!$H$60+'Assumptions and Catalog'!$E$60+'Assumptions and Catalog'!$F$60,IF(((D163+E163)*C163)<='Assumptions and Catalog'!$C$61,((D163+E163)*C163)*'Assumptions and Catalog'!$H$61+'Assumptions and Catalog'!$E$61+'Assumptions and Catalog'!$F$61,IF(((D163+E163)*C163)<='Assumptions and Catalog'!$C$62,((D163+E163)*C163)*'Assumptions and Catalog'!$H$62+'Assumptions and Catalog'!$E$62+'Assumptions and Catalog'!$F$62,IF(((D163+E163)*C163)<='Assumptions and Catalog'!$C$63,((D163+E163)*C163)*'Assumptions and Catalog'!$H$63+'Assumptions and Catalog'!$E$63+'Assumptions and Catalog'!$F$63,IF(((D163+E163)*C163)<='Assumptions and Catalog'!$C$64,((D163+E163)*C163)*'Assumptions and Catalog'!$H$64+'Assumptions and Catalog'!$E$64+'Assumptions and Catalog'!$F$64,IF(((D163+E163)*C163)<='Assumptions and Catalog'!$C$65,((D163+E163)*C163)*'Assumptions and Catalog'!$H$65+'Assumptions and Catalog'!$E$65+'Assumptions and Catalog'!$F$65,"Out of range")))))))))*(1+'Assumptions and Catalog'!$C$8)^(A163-1),0) -> 8554.9667 | N163: =IF(ISNUMBER(Inputs!$L$5),(IF(Inputs!$L$9="Actual flat rate",L163*Inputs!$L$10,IF(Inputs!$C$9="Residential",IF(L163<='Assumptions and Catalog'!$C$50,L163*'Assumptions and Catalog'!$H$50+'Assumptions and Catalog'!$E$50+'Assumptions and Catalog'!$F$50,IF(L163<='Assumptions and Catalog'!$C$51,L163*'Assumptions and Catalog'!$H$51+'Assumptions and Catalog'!$E$51+'Assumptions and Catalog'!$F$51,IF(L163<='Assumptions and Catalog'!$C$52,L163*'Assumptions and Catalog'!$H$52+'Assumptions and Catalog'!$E$52+'Assumptions and Catalog'!$F$52,IF(L163<='Assumptions and Catalog'!$C$53,L163*'Assumptions and Catalog'!$H$53+'Assumptions and Catalog'!$E$53+'Assumptions and Catalog'!$F$53,IF(L163<='Assumptions and Catalog'!$C$54,L163*'Assumptions and Catalog'!$H$54+'Assumptions and Catalog'!$E$54+'Assumptions and Catalog'!$F$54,IF(L163<='Assumptions and Catalog'!$C$55,L163*'Assumptions and Catalog'!$H$55+'Assumptions and Catalog'!$E$55+'Assumptions and Catalog'!$F$55,IF(L163<='Assumptions and Catalog'!$C$56,L163*'Assumptions and Catalog'!$H$56+'Assumptions and Catalog'!$E$56+'Assumptions and Catalog'!$F$56,IF(L163<='Assumptions and Catalog'!$C$57,L163*'Assumptions and Catalog'!$H$57+'Assumptions and Catalog'!$E$57+'Assumptions and Catalog'!$F$57,"Out of range")))))))),IF(L163<='Assumptions and Catalog'!$C$60,L163*'Assumptions and Catalog'!$H$60+'Assumptions and Catalog'!$E$60+'Assumptions and Catalog'!$F$60,IF(L163<='Assumptions and Catalog'!$C$61,L163*'Assumptions and Catalog'!$H$61+'Assumptions and Catalog'!$E$61+'Assumptions and Catalog'!$F$61,IF(L163<='Assumptions and Catalog'!$C$62,L163*'Assumptions and Catalog'!$H$62+'Assumptions and Catalog'!$E$62+'Assumptions and Catalog'!$F$62,IF(L163<='Assumptions and Catalog'!$C$63,L163*'Assumptions and Catalog'!$H$63+'Assumptions and Catalog'!$E$63+'Assumptions and Catalog'!$F$63,IF(L163<='Assumptions and Catalog'!$C$64,L163*'Assumptions and Catalog'!$H$64+'Assumptions and Catalog'!$E$64+'Assumptions and Catalog'!$F$64,IF(L163<='Assumptions and Catalog'!$C$65,L163*'Assumptions and Catalog'!$H$65+'Assumptions and Catalog'!$E$65+'Assumptions and Catalog'!$F$65,"Out of range")))))))))*(1+'Assumptions and Catalog'!$C$8)^(A163-1),0) -> 5017.8537 | O163: =M163-N163 -> 3537.113 | P163: =C$55*(1-J$14)*(1-'Assumptions and Catalog'!$C$23)^R163 -> 0 | Q163: =IF(ISNUMBER(Inputs!$L$5),(IF(Inputs!$L$9="Actual flat rate",((D163+E163)*C163-G163)*Inputs!$L$10,IF(Inputs!$C$9="Residential",IF(((D163+E163)*C163-G163)<='Assumptions and Catalog'!$C$50,((D163+E163)*C163-G163)*'Assumptions and Catalog'!$H$50+'Assumptions and Catalog'!$E$50+'Assumptions and Catalog'!$F$50,IF(((D163+E163)*C163-G163)<='Assumptions and Catalog'!$C$51,((D163+E163)*C163-G163)*'Assumptions and Catalog'!$H$51+'Assumptions and Catalog'!$E$51+'Assumptions and Catalog'!$F$51,IF(((D163+E163)*C163-G163)<='Assumptions and Catalog'!$C$52,((D163+E163)*C163-G163)*'Assumptions and Catalog'!$H$52+'Assumptions and Catalog'!$E$52+'Assumptions and Catalog'!$F$52,IF(((D163+E163)*C163-G163)<='Assumptions and Catalog'!$C$53,((D163+E163)*C163-G163)*'Assumptions and Catalog'!$H$53+'Assumptions and Catalog'!$E$53+'Assumptions and Catalog'!$F$53,IF(((D163+E163)*C163-G163)<='Assumptions and Catalog'!$C$54,((D163+E163)*C163-G163)*'Assumptions and Catalog'!$H$54+'Assumptions and Catalog'!$E$54+'Assumptions and Catalog'!$F$54,IF(((D163+E163)*C163-G163)<='Assumptions and Catalog'!$C$55,((D163+E163)*C163-G163)*'Assumptions and Catalog'!$H$55+'Assumptions and Catalog'!$E$55+'Assumptions and Catalog'!$F$55,IF(((D163+E163)*C163-G163)<='Assumptions and Catalog'!$C$56,((D163+E163)*C163-G163)*'Assumptions and Catalog'!$H$56+'Assumptions and Catalog'!$E$56+'Assumptions and Catalog'!$F$56,IF(((D163+E163)*C163-G163)<='Assumptions and Catalog'!$C$57,((D163+E163)*C163-G163)*'Assumptions and Catalog'!$H$57+'Assumptions and Catalog'!$E$57+'Assumptions and Catalog'!$F$57,"Out of range")))))))),IF(((D163+E163)*C163-G163)<='Assumptions and Catalog'!$C$60,((D163+E163)*C163-G163)*'Assumptions and Catalog'!$H$60+'Assumptions and Catalog'!$E$60+'Assumptions and Catalog'!$F$60,IF(((D163+E163)*C163-G163)<='Assumptions and Catalog'!$C$61,((D163+E163)*C163-G163)*'Assumptions and Catalog'!$H$61+'Assumptions and Catalog'!$E$61+'Assumptions and Catalog'!$F$61,IF(((D163+E163)*C163-G163)<='Assumptions and Catalog'!$C$62,((D163+E163)*C163-G163)*'Assumptions and Catalog'!$H$62+'Assumptions and Catalog'!$E$62+'Assumptions and Catalog'!$F$62,IF(((D163+E163)*C163-G163)<='Assumptions and Catalog'!$C$63,((D163+E163)*C163-G163)*'Assumptions and Catalog'!$H$63+'Assumptions and Catalog'!$E$63+'Assumptions and Catalog'!$F$63,IF(((D163+E163)*C163-G163)<='Assumptions and Catalog'!$C$64,((D163+E163)*C163-G163)*'Assumptions and Catalog'!$H$64+'Assumptions and Catalog'!$E$64+'Assumptions and Catalog'!$F$64,IF(((D163+E163)*C163-G163)<='Assumptions and Catalog'!$C$65,((D163+E163)*C163-G163)*'Assumptions and Catalog'!$H$65+'Assumptions and Catalog'!$E$65+'Assumptions and Catalog'!$F$65,"Out of range")))))))))*(1+'Assumptions and Catalog'!$C$8)^(A163-1),0) -> 5017.8537 | R163: =IF(AND('Assumptions and Catalog'!$C$19>0,A163>='Assumptions and Catalog'!$C$19),A163-'Assumptions and Catalog'!$C$19,A163-1) -> 0 | S163: =F163+L163-(D163+E163)*C163-J163-K163-0 -> 0
A164: 1 | B164: 4 | C164: =DAY(DATE('Assumptions and Catalog'!$C$24+A164-1,B164+1,0)) -> 30 | D164: =IF(ISNUMBER(Inputs!$L$5),Inputs!$L$5*Inputs!$L$6,0) -> 40.35 | E164: =IF(ISNUMBER(Inputs!$L$5),Inputs!$L$5-D164,0) -> 40.35 | F164: =C$51*'Assumptions and Catalog'!$C$31*C164*(1-'Assumptions and Catalog'!$C$10)^(A164-1) -> 1000.98 | G164: =MIN(F164,D164*C164) -> 1000.98 | H164: =I164/('Assumptions and Catalog'!$C$11*'Assumptions and Catalog'!$C$12) -> 0 | I164: =0 -> 0 | J164: =MAX(F164-G164-H164,0) -> 0 | K164: =H164-I164 -> 0 | L164: =(D164+E164)*C164-G164-I164+0+0 -> 1420.02 | M164: =IF(ISNUMBER(Inputs!$L$5),(IF(Inputs!$L$9="Actual flat rate",((D164+E164)*C164)*Inputs!$L$10,IF(Inputs!$C$9="Residential",IF(((D164+E164)*C164)<='Assumptions and Catalog'!$C$50,((D164+E164)*C164)*'Assumptions and Catalog'!$H$50+'Assumptions and Catalog'!$E$50+'Assumptions and Catalog'!$F$50,IF(((D164+E164)*C164)<='Assumptions and Catalog'!$C$51,((D164+E164)*C164)*'Assumptions and Catalog'!$H$51+'Assumptions and Catalog'!$E$51+'Assumptions and Catalog'!$F$51,IF(((D164+E164)*C164)<='Assumptions and Catalog'!$C$52,((D164+E164)*C164)*'Assumptions and Catalog'!$H$52+'Assumptions and Catalog'!$E$52+'Assumptions and Catalog'!$F$52,IF(((D164+E164)*C164)<='Assumptions and Catalog'!$C$53,((D164+E164)*C164)*'Assumptions and Catalog'!$H$53+'Assumptions and Catalog'!$E$53+'Assumptions and Catalog'!$F$53,IF(((D164+E164)*C164)<='Assumptions and Catalog'!$C$54,((D164+E164)*C164)*'Assumptions and Catalog'!$H$54+'Assumptions and Catalog'!$E$54+'Assumptions and Catalog'!$F$54,IF(((D164+E164)*C164)<='Assumptions and Catalog'!$C$55,((D164+E164)*C164)*'Assumptions and Catalog'!$H$55+'Assumptions and Catalog'!$E$55+'Assumptions and Catalog'!$F$55,IF(((D164+E164)*C164)<='Assumptions and Catalog'!$C$56,((D164+E164)*C164)*'Assumptions and Catalog'!$H$56+'Assumptions and Catalog'!$E$56+'Assumptions and Catalog'!$F$56,IF(((D164+E164)*C164)<='Assumptions and Catalog'!$C$57,((D164+E164)*C164)*'Assumptions and Catalog'!$H$57+'Assumptions and Catalog'!$E$57+'Assumptions and Catalog'!$F$57,"Out of range")))))))),IF(((D164+E164)*C164)<='Assumptions and Catalog'!$C$60,((D164+E164)*C164)*'Assumptions and Catalog'!$H$60+'Assumptions and Catalog'!$E$60+'Assumptions and Catalog'!$F$60,IF(((D164+E164)*C164)<='Assumptions and Catalog'!$C$61,((D164+E164)*C164)*'Assumptions and Catalog'!$H$61+'Assumptions and Catalog'!$E$61+'Assumptions and Catalog'!$F$61,IF(((D164+E164)*C164)<='Assumptions and Catalog'!$C$62,((D164+E164)*C164)*'Assumptions and Catalog'!$H$62+'Assumptions and Catalog'!$E$62+'Assumptions and Catalog'!$F$62,IF(((D164+E164)*C164)<='Assumptions and Catalog'!$C$63,((D164+E164)*C164)*'Assumptions and Catalog'!$H$63+'Assumptions and Catalog'!$E$63+'Assumptions and Catalog'!$F$63,IF(((D164+E164)*C164)<='Assumptions and Catalog'!$C$64,((D164+E164)*C164)*'Assumptions and Catalog'!$H$64+'Assumptions and Catalog'!$E$64+'Assumptions and Catalog'!$F$64,IF(((D164+E164)*C164)<='Assumptions and Catalog'!$C$65,((D164+E164)*C164)*'Assumptions and Catalog'!$H$65+'Assumptions and Catalog'!$E$65+'Assumptions and Catalog'!$F$65,"Out of range")))))))))*(1+'Assumptions and Catalog'!$C$8)^(A164-1),0) -> 8279 | N164: =IF(ISNUMBER(Inputs!$L$5),(IF(Inputs!$L$9="Actual flat rate",L164*Inputs!$L$10,IF(Inputs!$C$9="Residential",IF(L164<='Assumptions and Catalog'!$C$50,L164*'Assumptions and Catalog'!$H$50+'Assumptions and Catalog'!$E$50+'Assumptions and Catalog'!$F$50,IF(L164<='Assumptions and Catalog'!$C$51,L164*'Assumptions and Catalog'!$H$51+'Assumptions and Catalog'!$E$51+'Assumptions and Catalog'!$F$51,IF(L164<='Assumptions and Catalog'!$C$52,L164*'Assumptions and Catalog'!$H$52+'Assumptions and Catalog'!$E$52+'Assumptions and Catalog'!$F$52,IF(L164<='Assumptions and Catalog'!$C$53,L164*'Assumptions and Catalog'!$H$53+'Assumptions and Catalog'!$E$53+'Assumptions and Catalog'!$F$53,IF(L164<='Assumptions and Catalog'!$C$54,L164*'Assumptions and Catalog'!$H$54+'Assumptions and Catalog'!$E$54+'Assumptions and Catalog'!$F$54,IF(L164<='Assumptions and Catalog'!$C$55,L164*'Assumptions and Catalog'!$H$55+'Assumptions and Catalog'!$E$55+'Assumptions and Catalog'!$F$55,IF(L164<='Assumptions and Catalog'!$C$56,L164*'Assumptions and Catalog'!$H$56+'Assumptions and Catalog'!$E$56+'Assumptions and Catalog'!$F$56,IF(L164<='Assumptions and Catalog'!$C$57,L164*'Assumptions and Catalog'!$H$57+'Assumptions and Catalog'!$E$57+'Assumptions and Catalog'!$F$57,"Out of range")))))))),IF(L164<='Assumptions and Catalog'!$C$60,L164*'Assumptions and Catalog'!$H$60+'Assumptions and Catalog'!$E$60+'Assumptions and Catalog'!$F$60,IF(L164<='Assumptions and Catalog'!$C$61,L164*'Assumptions and Catalog'!$H$61+'Assumptions and Catalog'!$E$61+'Assumptions and Catalog'!$F$61,IF(L164<='Assumptions and Catalog'!$C$62,L164*'Assumptions and Catalog'!$H$62+'Assumptions and Catalog'!$E$62+'Assumptions and Catalog'!$F$62,IF(L164<='Assumptions and Catalog'!$C$63,L164*'Assumptions and Catalog'!$H$63+'Assumptions and Catalog'!$E$63+'Assumptions and Catalog'!$F$63,IF(L164<='Assumptions and Catalog'!$C$64,L164*'Assumptions and Catalog'!$H$64+'Assumptions and Catalog'!$E$64+'Assumptions and Catalog'!$F$64,IF(L164<='Assumptions and Catalog'!$C$65,L164*'Assumptions and Catalog'!$H$65+'Assumptions and Catalog'!$E$65+'Assumptions and Catalog'!$F$65,"Out of range")))))))))*(1+'Assumptions and Catalog'!$C$8)^(A164-1),0) -> 4855.9874 | O164: =M164-N164 -> 3423.0126 | P164: =C$55*(1-J$14)*(1-'Assumptions and Catalog'!$C$23)^R164 -> 0 | Q164: =IF(ISNUMBER(Inputs!$L$5),(IF(Inputs!$L$9="Actual flat rate",((D164+E164)*C164-G164)*Inputs!$L$10,IF(Inputs!$C$9="Residential",IF(((D164+E164)*C164-G164)<='Assumptions and Catalog'!$C$50,((D164+E164)*C164-G164)*'Assumptions and Catalog'!$H$50+'Assumptions and Catalog'!$E$50+'Assumptions and Catalog'!$F$50,IF(((D164+E164)*C164-G164)<='Assumptions and Catalog'!$C$51,((D164+E164)*C164-G164)*'Assumptions and Catalog'!$H$51+'Assumptions and Catalog'!$E$51+'Assumptions and Catalog'!$F$51,IF(((D164+E164)*C164-G164)<='Assumptions and Catalog'!$C$52,((D164+E164)*C164-G164)*'Assumptions and Catalog'!$H$52+'Assumptions and Catalog'!$E$52+'Assumptions and Catalog'!$F$52,IF(((D164+E164)*C164-G164)<='Assumptions and Catalog'!$C$53,((D164+E164)*C164-G164)*'Assumptions and Catalog'!$H$53+'Assumptions and Catalog'!$E$53+'Assumptions and Catalog'!$F$53,IF(((D164+E164)*C164-G164)<='Assumptions and Catalog'!$C$54,((D164+E164)*C164-G164)*'Assumptions and Catalog'!$H$54+'Assumptions and Catalog'!$E$54+'Assumptions and Catalog'!$F$54,IF(((D164+E164)*C164-G164)<='Assumptions and Catalog'!$C$55,((D164+E164)*C164-G164)*'Assumptions and Catalog'!$H$55+'Assumptions and Catalog'!$E$55+'Assumptions and Catalog'!$F$55,IF(((D164+E164)*C164-G164)<='Assumptions and Catalog'!$C$56,((D164+E164)*C164-G164)*'Assumptions and Catalog'!$H$56+'Assumptions and Catalog'!$E$56+'Assumptions and Catalog'!$F$56,IF(((D164+E164)*C164-G164)<='Assumptions and Catalog'!$C$57,((D164+E164)*C164-G164)*'Assumptions and Catalog'!$H$57+'Assumptions and Catalog'!$E$57+'Assumptions and Catalog'!$F$57,"Out of range")))))))),IF(((D164+E164)*C164-G164)<='Assumptions and Catalog'!$C$60,((D164+E164)*C164-G164)*'Assumptions and Catalog'!$H$60+'Assumptions and Catalog'!$E$60+'Assumptions and Catalog'!$F$60,IF(((D164+E164)*C164-G164)<='Assumptions and Catalog'!$C$61,((D164+E164)*C164-G164)*'Assumptions and Catalog'!$H$61+'Assumptions and Catalog'!$E$61+'Assumptions and Catalog'!$F$61,IF(((D164+E164)*C164-G164)<='Assumptions and Catalog'!$C$62,((D164+E164)*C164-G164)*'Assumptions and Catalog'!$H$62+'Assumptions and Catalog'!$E$62+'Assumptions and Catalog'!$F$62,IF(((D164+E164)*C164-G164)<='Assumptions and Catalog'!$C$63,((D164+E164)*C164-G164)*'Assumptions and Catalog'!$H$63+'Assumptions and Catalog'!$E$63+'Assumptions and Catalog'!$F$63,IF(((D164+E164)*C164-G164)<='Assumptions and Catalog'!$C$64,((D164+E164)*C164-G164)*'Assumptions and Catalog'!$H$64+'Assumptions and Catalog'!$E$64+'Assumptions and Catalog'!$F$64,IF(((D164+E164)*C164-G164)<='Assumptions and Catalog'!$C$65,((D164+E164)*C164-G164)*'Assumptions and Catalog'!$H$65+'Assumptions and Catalog'!$E$65+'Assumptions and Catalog'!$F$65,"Out of range")))))))))*(1+'Assumptions and Catalog'!$C$8)^(A164-1),0) -> 4855.9874 | R164: =IF(AND('Assumptions and Catalog'!$C$19>0,A164>='Assumptions and Catalog'!$C$19),A164-'Assumptions and Catalog'!$C$19,A164-1) -> 0 | S164: =F164+L164-(D164+E164)*C164-J164-K164-0 -> 0
A165: 1 | B165: 5 | C165: =DAY(DATE('Assumptions and Catalog'!$C$24+A165-1,B165+1,0)) -> 31 | D165: =IF(ISNUMBER(Inputs!$L$5),Inputs!$L$5*Inputs!$L$6,0) -> 40.35 | E165: =IF(ISNUMBER(Inputs!$L$5),Inputs!$L$5-D165,0) -> 40.35 | F165: =C$51*'Assumptions and Catalog'!$C$31*C165*(1-'Assumptions and Catalog'!$C$10)^(A165-1) -> 1034.346 | G165: =MIN(F165,D165*C165) -> 1034.346 | H165: =I165/('Assumptions and Catalog'!$C$11*'Assumptions and Catalog'!$C$12) -> 0 | I165: =0 -> 0 | J165: =MAX(F165-G165-H165,0) -> 0 | K165: =H165-I165 -> 0 | L165: =(D165+E165)*C165-G165-I165+0+0 -> 1467.354 | M165: =IF(ISNUMBER(Inputs!$L$5),(IF(Inputs!$L$9="Actual flat rate",((D165+E165)*C165)*Inputs!$L$10,IF(Inputs!$C$9="Residential",IF(((D165+E165)*C165)<='Assumptions and Catalog'!$C$50,((D165+E165)*C165)*'Assumptions and Catalog'!$H$50+'Assumptions and Catalog'!$E$50+'Assumptions and Catalog'!$F$50,IF(((D165+E165)*C165)<='Assumptions and Catalog'!$C$51,((D165+E165)*C165)*'Assumptions and Catalog'!$H$51+'Assumptions and Catalog'!$E$51+'Assumptions and Catalog'!$F$51,IF(((D165+E165)*C165)<='Assumptions and Catalog'!$C$52,((D165+E165)*C165)*'Assumptions and Catalog'!$H$52+'Assumptions and Catalog'!$E$52+'Assumptions and Catalog'!$F$52,IF(((D165+E165)*C165)<='Assumptions and Catalog'!$C$53,((D165+E165)*C165)*'Assumptions and Catalog'!$H$53+'Assumptions and Catalog'!$E$53+'Assumptions and Catalog'!$F$53,IF(((D165+E165)*C165)<='Assumptions and Catalog'!$C$54,((D165+E165)*C165)*'Assumptions and Catalog'!$H$54+'Assumptions and Catalog'!$E$54+'Assumptions and Catalog'!$F$54,IF(((D165+E165)*C165)<='Assumptions and Catalog'!$C$55,((D165+E165)*C165)*'Assumptions and Catalog'!$H$55+'Assumptions and Catalog'!$E$55+'Assumptions and Catalog'!$F$55,IF(((D165+E165)*C165)<='Assumptions and Catalog'!$C$56,((D165+E165)*C165)*'Assumptions and Catalog'!$H$56+'Assumptions and Catalog'!$E$56+'Assumptions and Catalog'!$F$56,IF(((D165+E165)*C165)<='Assumptions and Catalog'!$C$57,((D165+E165)*C165)*'Assumptions and Catalog'!$H$57+'Assumptions and Catalog'!$E$57+'Assumptions and Catalog'!$F$57,"Out of range")))))))),IF(((D165+E165)*C165)<='Assumptions and Catalog'!$C$60,((D165+E165)*C165)*'Assumptions and Catalog'!$H$60+'Assumptions and Catalog'!$E$60+'Assumptions and Catalog'!$F$60,IF(((D165+E165)*C165)<='Assumptions and Catalog'!$C$61,((D165+E165)*C165)*'Assumptions and Catalog'!$H$61+'Assumptions and Catalog'!$E$61+'Assumptions and Catalog'!$F$61,IF(((D165+E165)*C165)<='Assumptions and Catalog'!$C$62,((D165+E165)*C165)*'Assumptions and Catalog'!$H$62+'Assumptions and Catalog'!$E$62+'Assumptions and Catalog'!$F$62,IF(((D165+E165)*C165)<='Assumptions and Catalog'!$C$63,((D165+E165)*C165)*'Assumptions and Catalog'!$H$63+'Assumptions and Catalog'!$E$63+'Assumptions and Catalog'!$F$63,IF(((D165+E165)*C165)<='Assumptions and Catalog'!$C$64,((D165+E165)*C165)*'Assumptions and Catalog'!$H$64+'Assumptions and Catalog'!$E$64+'Assumptions and Catalog'!$F$64,IF(((D165+E165)*C165)<='Assumptions and Catalog'!$C$65,((D165+E165)*C165)*'Assumptions and Catalog'!$H$65+'Assumptions and Catalog'!$E$65+'Assumptions and Catalog'!$F$65,"Out of range")))))))))*(1+'Assumptions and Catalog'!$C$8)^(A165-1),0) -> 8554.9667 | N165: =IF(ISNUMBER(Inputs!$L$5),(IF(Inputs!$L$9="Actual flat rate",L165*Inputs!$L$10,IF(Inputs!$C$9="Residential",IF(L165<='Assumptions and Catalog'!$C$50,L165*'Assumptions and Catalog'!$H$50+'Assumptions and Catalog'!$E$50+'Assumptions and Catalog'!$F$50,IF(L165<='Assumptions and Catalog'!$C$51,L165*'Assumptions and Catalog'!$H$51+'Assumptions and Catalog'!$E$51+'Assumptions and Catalog'!$F$51,IF(L165<='Assumptions and Catalog'!$C$52,L165*'Assumptions and Catalog'!$H$52+'Assumptions and Catalog'!$E$52+'Assumptions and Catalog'!$F$52,IF(L165<='Assumptions and Catalog'!$C$53,L165*'Assumptions and Catalog'!$H$53+'Assumptions and Catalog'!$E$53+'Assumptions and Catalog'!$F$53,IF(L165<='Assumptions and Catalog'!$C$54,L165*'Assumptions and Catalog'!$H$54+'Assumptions and Catalog'!$E$54+'Assumptions and Catalog'!$F$54,IF(L165<='Assumptions and Catalog'!$C$55,L165*'Assumptions and Catalog'!$H$55+'Assumptions and Catalog'!$E$55+'Assumptions and Catalog'!$F$55,IF(L165<='Assumptions and Catalog'!$C$56,L165*'Assumptions and Catalog'!$H$56+'Assumptions and Catalog'!$E$56+'Assumptions and Catalog'!$F$56,IF(L165<='Assumptions and Catalog'!$C$57,L165*'Assumptions and Catalog'!$H$57+'Assumptions and Catalog'!$E$57+'Assumptions and Catalog'!$F$57,"Out of range")))))))),IF(L165<='Assumptions and Catalog'!$C$60,L165*'Assumptions and Catalog'!$H$60+'Assumptions and Catalog'!$E$60+'Assumptions and Catalog'!$F$60,IF(L165<='Assumptions and Catalog'!$C$61,L165*'Assumptions and Catalog'!$H$61+'Assumptions and Catalog'!$E$61+'Assumptions and Catalog'!$F$61,IF(L165<='Assumptions and Catalog'!$C$62,L165*'Assumptions and Catalog'!$H$62+'Assumptions and Catalog'!$E$62+'Assumptions and Catalog'!$F$62,IF(L165<='Assumptions and Catalog'!$C$63,L165*'Assumptions and Catalog'!$H$63+'Assumptions and Catalog'!$E$63+'Assumptions and Catalog'!$F$63,IF(L165<='Assumptions and Catalog'!$C$64,L165*'Assumptions and Catalog'!$H$64+'Assumptions and Catalog'!$E$64+'Assumptions and Catalog'!$F$64,IF(L165<='Assumptions and Catalog'!$C$65,L165*'Assumptions and Catalog'!$H$65+'Assumptions and Catalog'!$E$65+'Assumptions and Catalog'!$F$65,"Out of range")))))))))*(1+'Assumptions and Catalog'!$C$8)^(A165-1),0) -> 5017.8537 | O165: =M165-N165 -> 3537.113 | P165: =C$55*(1-J$14)*(1-'Assumptions and Catalog'!$C$23)^R165 -> 0 | Q165: =IF(ISNUMBER(Inputs!$L$5),(IF(Inputs!$L$9="Actual flat rate",((D165+E165)*C165-G165)*Inputs!$L$10,IF(Inputs!$C$9="Residential",IF(((D165+E165)*C165-G165)<='Assumptions and Catalog'!$C$50,((D165+E165)*C165-G165)*'Assumptions and Catalog'!$H$50+'Assumptions and Catalog'!$E$50+'Assumptions and Catalog'!$F$50,IF(((D165+E165)*C165-G165)<='Assumptions and Catalog'!$C$51,((D165+E165)*C165-G165)*'Assumptions and Catalog'!$H$51+'Assumptions and Catalog'!$E$51+'Assumptions and Catalog'!$F$51,IF(((D165+E165)*C165-G165)<='Assumptions and Catalog'!$C$52,((D165+E165)*C165-G165)*'Assumptions and Catalog'!$H$52+'Assumptions and Catalog'!$E$52+'Assumptions and Catalog'!$F$52,IF(((D165+E165)*C165-G165)<='Assumptions and Catalog'!$C$53,((D165+E165)*C165-G165)*'Assumptions and Catalog'!$H$53+'Assumptions and Catalog'!$E$53+'Assumptions and Catalog'!$F$53,IF(((D165+E165)*C165-G165)<='Assumptions and Catalog'!$C$54,((D165+E165)*C165-G165)*'Assumptions and Catalog'!$H$54+'Assumptions and Catalog'!$E$54+'Assumptions and Catalog'!$F$54,IF(((D165+E165)*C165-G165)<='Assumptions and Catalog'!$C$55,((D165+E165)*C165-G165)*'Assumptions and Catalog'!$H$55+'Assumptions and Catalog'!$E$55+'Assumptions and Catalog'!$F$55,IF(((D165+E165)*C165-G165)<='Assumptions and Catalog'!$C$56,((D165+E165)*C165-G165)*'Assumptions and Catalog'!$H$56+'Assumptions and Catalog'!$E$56+'Assumptions and Catalog'!$F$56,IF(((D165+E165)*C165-G165)<='Assumptions and Catalog'!$C$57,((D165+E165)*C165-G165)*'Assumptions and Catalog'!$H$57+'Assumptions and Catalog'!$E$57+'Assumptions and Catalog'!$F$57,"Out of range")))))))),IF(((D165+E165)*C165-G165)<='Assumptions and Catalog'!$C$60,((D165+E165)*C165-G165)*'Assumptions and Catalog'!$H$60+'Assumptions and Catalog'!$E$60+'Assumptions and Catalog'!$F$60,IF(((D165+E165)*C165-G165)<='Assumptions and Catalog'!$C$61,((D165+E165)*C165-G165)*'Assumptions and Catalog'!$H$61+'Assumptions and Catalog'!$E$61+'Assumptions and Catalog'!$F$61,IF(((D165+E165)*C165-G165)<='Assumptions and Catalog'!$C$62,((D165+E165)*C165-G165)*'Assumptions and Catalog'!$H$62+'Assumptions and Catalog'!$E$62+'Assumptions and Catalog'!$F$62,IF(((D165+E165)*C165-G165)<='Assumptions and Catalog'!$C$63,((D165+E165)*C165-G165)*'Assumptions and Catalog'!$H$63+'Assumptions and Catalog'!$E$63+'Assumptions and Catalog'!$F$63,IF(((D165+E165)*C165-G165)<='Assumptions and Catalog'!$C$64,((D165+E165)*C165-G165)*'Assumptions and Catalog'!$H$64+'Assumptions and Catalog'!$E$64+'Assumptions and Catalog'!$F$64,IF(((D165+E165)*C165-G165)<='Assumptions and Catalog'!$C$65,((D165+E165)*C165-G165)*'Assumptions and Catalog'!$H$65+'Assumptions and Catalog'!$E$65+'Assumptions and Catalog'!$F$65,"Out of range")))))))))*(1+'Assumptions and Catalog'!$C$8)^(A165-1),0) -> 5017.8537 | R165: =IF(AND('Assumptions and Catalog'!$C$19>0,A165>='Assumptions and Catalog'!$C$19),A165-'Assumptions and Catalog'!$C$19,A165-1) -> 0 | S165: =F165+L165-(D165+E165)*C165-J165-K165-0 -> 0
A166: 1 | B166: 6 | C166: =DAY(DATE('Assumptions and Catalog'!$C$24+A166-1,B166+1,0)) -> 30 | D166: =IF(ISNUMBER(Inputs!$L$5),Inputs!$L$5*Inputs!$L$6,0) -> 40.35 | E166: =IF(ISNUMBER(Inputs!$L$5),Inputs!$L$5-D166,0) -> 40.35 | F166: =C$51*'Assumptions and Catalog'!$C$31*C166*(1-'Assumptions and Catalog'!$C$10)^(A166-1) -> 1000.98 | G166: =MIN(F166,D166*C166) -> 1000.98 | H166: =I166/('Assumptions and Catalog'!$C$11*'Assumptions and Catalog'!$C$12) -> 0 | I166: =0 -> 0 | J166: =MAX(F166-G166-H166,0) -> 0 | K166: =H166-I166 -> 0 | L166: =(D166+E166)*C166-G166-I166+0+0 -> 1420.02 | M166: =IF(ISNUMBER(Inputs!$L$5),(IF(Inputs!$L$9="Actual flat rate",((D166+E166)*C166)*Inputs!$L$10,IF(Inputs!$C$9="Residential",IF(((D166+E166)*C166)<='Assumptions and Catalog'!$C$50,((D166+E166)*C166)*'Assumptions and Catalog'!$H$50+'Assumptions and Catalog'!$E$50+'Assumptions and Catalog'!$F$50,IF(((D166+E166)*C166)<='Assumptions and Catalog'!$C$51,((D166+E166)*C166)*'Assumptions and Catalog'!$H$51+'Assumptions and Catalog'!$E$51+'Assumptions and Catalog'!$F$51,IF(((D166+E166)*C166)<='Assumptions and Catalog'!$C$52,((D166+E166)*C166)*'Assumptions and Catalog'!$H$52+'Assumptions and Catalog'!$E$52+'Assumptions and Catalog'!$F$52,IF(((D166+E166)*C166)<='Assumptions and Catalog'!$C$53,((D166+E166)*C166)*'Assumptions and Catalog'!$H$53+'Assumptions and Catalog'!$E$53+'Assumptions and Catalog'!$F$53,IF(((D166+E166)*C166)<='Assumptions and Catalog'!$C$54,((D166+E166)*C166)*'Assumptions and Catalog'!$H$54+'Assumptions and Catalog'!$E$54+'Assumptions and Catalog'!$F$54,IF(((D166+E166)*C166)<='Assumptions and Catalog'!$C$55,((D166+E166)*C166)*'Assumptions and Catalog'!$H$55+'Assumptions and Catalog'!$E$55+'Assumptions and Catalog'!$F$55,IF(((D166+E166)*C166)<='Assumptions and Catalog'!$C$56,((D166+E166)*C166)*'Assumptions and Catalog'!$H$56+'Assumptions and Catalog'!$E$56+'Assumptions and Catalog'!$F$56,IF(((D166+E166)*C166)<='Assumptions and Catalog'!$C$57,((D166+E166)*C166)*'Assumptions and Catalog'!$H$57+'Assumptions and Catalog'!$E$57+'Assumptions and Catalog'!$F$57,"Out of range")))))))),IF(((D166+E166)*C166)<='Assumptions and Catalog'!$C$60,((D166+E166)*C166)*'Assumptions and Catalog'!$H$60+'Assumptions and Catalog'!$E$60+'Assumptions and Catalog'!$F$60,IF(((D166+E166)*C166)<='Assumptions and Catalog'!$C$61,((D166+E166)*C166)*'Assumptions and Catalog'!$H$61+'Assumptions and Catalog'!$E$61+'Assumptions and Catalog'!$F$61,IF(((D166+E166)*C166)<='Assumptions and Catalog'!$C$62,((D166+E166)*C166)*'Assumptions and Catalog'!$H$62+'Assumptions and Catalog'!$E$62+'Assumptions and Catalog'!$F$62,IF(((D166+E166)*C166)<='Assumptions and Catalog'!$C$63,((D166+E166)*C166)*'Assumptions and Catalog'!$H$63+'Assumptions and Catalog'!$E$63+'Assumptions and Catalog'!$F$63,IF(((D166+E166)*C166)<='Assumptions and Catalog'!$C$64,((D166+E166)*C166)*'Assumptions and Catalog'!$H$64+'Assumptions and Catalog'!$E$64+'Assumptions and Catalog'!$F$64,IF(((D166+E166)*C166)<='Assumptions and Catalog'!$C$65,((D166+E166)*C166)*'Assumptions and Catalog'!$H$65+'Assumptions and Catalog'!$E$65+'Assumptions and Catalog'!$F$65,"Out of range")))))))))*(1+'Assumptions and Catalog'!$C$8)^(A166-1),0) -> 8279 | N166: =IF(ISNUMBER(Inputs!$L$5),(IF(Inputs!$L$9="Actual flat rate",L166*Inputs!$L$10,IF(Inputs!$C$9="Residential",IF(L166<='Assumptions and Catalog'!$C$50,L166*'Assumptions and Catalog'!$H$50+'Assumptions and Catalog'!$E$50+'Assumptions and Catalog'!$F$50,IF(L166<='Assumptions and Catalog'!$C$51,L166*'Assumptions and Catalog'!$H$51+'Assumptions and Catalog'!$E$51+'Assumptions and Catalog'!$F$51,IF(L166<='Assumptions and Catalog'!$C$52,L166*'Assumptions and Catalog'!$H$52+'Assumptions and Catalog'!$E$52+'Assumptions and Catalog'!$F$52,IF(L166<='Assumptions and Catalog'!$C$53,L166*'Assumptions and Catalog'!$H$53+'Assumptions and Catalog'!$E$53+'Assumptions and Catalog'!$F$53,IF(L166<='Assumptions and Catalog'!$C$54,L166*'Assumptions and Catalog'!$H$54+'Assumptions and Catalog'!$E$54+'Assumptions and Catalog'!$F$54,IF(L166<='Assumptions and Catalog'!$C$55,L166*'Assumptions and Catalog'!$H$55+'Assumptions and Catalog'!$E$55+'Assumptions and Catalog'!$F$55,IF(L166<='Assumptions and Catalog'!$C$56,L166*'Assumptions and Catalog'!$H$56+'Assumptions and Catalog'!$E$56+'Assumptions and Catalog'!$F$56,IF(L166<='Assumptions and Catalog'!$C$57,L166*'Assumptions and Catalog'!$H$57+'Assumptions and Catalog'!$E$57+'Assumptions and Catalog'!$F$57,"Out of range")))))))),IF(L166<='Assumptions and Catalog'!$C$60,L166*'Assumptions and Catalog'!$H$60+'Assumptions and Catalog'!$E$60+'Assumptions and Catalog'!$F$60,IF(L166<='Assumptions and Catalog'!$C$61,L166*'Assumptions and Catalog'!$H$61+'Assumptions and Catalog'!$E$61+'Assumptions and Catalog'!$F$61,IF(L166<='Assumptions and Catalog'!$C$62,L166*'Assumptions and Catalog'!$H$62+'Assumptions and Catalog'!$E$62+'Assumptions and Catalog'!$F$62,IF(L166<='Assumptions and Catalog'!$C$63,L166*'Assumptions and Catalog'!$H$63+'Assumptions and Catalog'!$E$63+'Assumptions and Catalog'!$F$63,IF(L166<='Assumptions and Catalog'!$C$64,L166*'Assumptions and Catalog'!$H$64+'Assumptions and Catalog'!$E$64+'Assumptions and Catalog'!$F$64,IF(L166<='Assumptions and Catalog'!$C$65,L166*'Assumptions and Catalog'!$H$65+'Assumptions and Catalog'!$E$65+'Assumptions and Catalog'!$F$65,"Out of range")))))))))*(1+'Assumptions and Catalog'!$C$8)^(A166-1),0) -> 4855.9874 | O166: =M166-N166 -> 3423.0126 | P166: =C$55*(1-J$14)*(1-'Assumptions and Catalog'!$C$23)^R166 -> 0 | Q166: =IF(ISNUMBER(Inputs!$L$5),(IF(Inputs!$L$9="Actual flat rate",((D166+E166)*C166-G166)*Inputs!$L$10,IF(Inputs!$C$9="Residential",IF(((D166+E166)*C166-G166)<='Assumptions and Catalog'!$C$50,((D166+E166)*C166-G166)*'Assumptions and Catalog'!$H$50+'Assumptions and Catalog'!$E$50+'Assumptions and Catalog'!$F$50,IF(((D166+E166)*C166-G166)<='Assumptions and Catalog'!$C$51,((D166+E166)*C166-G166)*'Assumptions and Catalog'!$H$51+'Assumptions and Catalog'!$E$51+'Assumptions and Catalog'!$F$51,IF(((D166+E166)*C166-G166)<='Assumptions and Catalog'!$C$52,((D166+E166)*C166-G166)*'Assumptions and Catalog'!$H$52+'Assumptions and Catalog'!$E$52+'Assumptions and Catalog'!$F$52,IF(((D166+E166)*C166-G166)<='Assumptions and Catalog'!$C$53,((D166+E166)*C166-G166)*'Assumptions and Catalog'!$H$53+'Assumptions and Catalog'!$E$53+'Assumptions and Catalog'!$F$53,IF(((D166+E166)*C166-G166)<='Assumptions and Catalog'!$C$54,((D166+E166)*C166-G166)*'Assumptions and Catalog'!$H$54+'Assumptions and Catalog'!$E$54+'Assumptions and Catalog'!$F$54,IF(((D166+E166)*C166-G166)<='Assumptions and Catalog'!$C$55,((D166+E166)*C166-G166)*'Assumptions and Catalog'!$H$55+'Assumptions and Catalog'!$E$55+'Assumptions and Catalog'!$F$55,IF(((D166+E166)*C166-G166)<='Assumptions and Catalog'!$C$56,((D166+E166)*C166-G166)*'Assumptions and Catalog'!$H$56+'Assumptions and Catalog'!$E$56+'Assumptions and Catalog'!$F$56,IF(((D166+E166)*C166-G166)<='Assumptions and Catalog'!$C$57,((D166+E166)*C166-G166)*'Assumptions and Catalog'!$H$57+'Assumptions and Catalog'!$E$57+'Assumptions and Catalog'!$F$57,"Out of range")))))))),IF(((D166+E166)*C166-G166)<='Assumptions and Catalog'!$C$60,((D166+E166)*C166-G166)*'Assumptions and Catalog'!$H$60+'Assumptions and Catalog'!$E$60+'Assumptions and Catalog'!$F$60,IF(((D166+E166)*C166-G166)<='Assumptions and Catalog'!$C$61,((D166+E166)*C166-G166)*'Assumptions and Catalog'!$H$61+'Assumptions and Catalog'!$E$61+'Assumptions and Catalog'!$F$61,IF(((D166+E166)*C166-G166)<='Assumptions and Catalog'!$C$62,((D166+E166)*C166-G166)*'Assumptions and Catalog'!$H$62+'Assumptions and Catalog'!$E$62+'Assumptions and Catalog'!$F$62,IF(((D166+E166)*C166-G166)<='Assumptions and Catalog'!$C$63,((D166+E166)*C166-G166)*'Assumptions and Catalog'!$H$63+'Assumptions and Catalog'!$E$63+'Assumptions and Catalog'!$F$63,IF(((D166+E166)*C166-G166)<='Assumptions and Catalog'!$C$64,((D166+E166)*C166-G166)*'Assumptions and Catalog'!$H$64+'Assumptions and Catalog'!$E$64+'Assumptions and Catalog'!$F$64,IF(((D166+E166)*C166-G166)<='Assumptions and Catalog'!$C$65,((D166+E166)*C166-G166)*'Assumptions and Catalog'!$H$65+'Assumptions and Catalog'!$E$65+'Assumptions and Catalog'!$F$65,"Out of range")))))))))*(1+'Assumptions and Catalog'!$C$8)^(A166-1),0) -> 4855.9874 | R166: =IF(AND('Assumptions and Catalog'!$C$19>0,A166>='Assumptions and Catalog'!$C$19),A166-'Assumptions and Catalog'!$C$19,A166-1) -> 0 | S166: =F166+L166-(D166+E166)*C166-J166-K166-0 -> 0
A167: 1 | B167: 7 | C167: =DAY(DATE('Assumptions and Catalog'!$C$24+A167-1,B167+1,0)) -> 31 | D167: =IF(ISNUMBER(Inputs!$L$5),Inputs!$L$5*Inputs!$L$6,0) -> 40.35 | E167: =IF(ISNUMBER(Inputs!$L$5),Inputs!$L$5-D167,0) -> 40.35 | F167: =C$51*'Assumptions and Catalog'!$C$31*C167*(1-'Assumptions and Catalog'!$C$10)^(A167-1) -> 1034.346 | G167: =MIN(F167,D167*C167) -> 1034.346 | H167: =I167/('Assumptions and Catalog'!$C$11*'Assumptions and Catalog'!$C$12) -> 0 | I167: =0 -> 0 | J167: =MAX(F167-G167-H167,0) -> 0 | K167: =H167-I167 -> 0 | L167: =(D167+E167)*C167-G167-I167+0+0 -> 1467.354 | M167: =IF(ISNUMBER(Inputs!$L$5),(IF(Inputs!$L$9="Actual flat rate",((D167+E167)*C167)*Inputs!$L$10,IF(Inputs!$C$9="Residential",IF(((D167+E167)*C167)<='Assumptions and Catalog'!$C$50,((D167+E167)*C167)*'Assumptions and Catalog'!$H$50+'Assumptions and Catalog'!$E$50+'Assumptions and Catalog'!$F$50,IF(((D167+E167)*C167)<='Assumptions and Catalog'!$C$51,((D167+E167)*C167)*'Assumptions and Catalog'!$H$51+'Assumptions and Catalog'!$E$51+'Assumptions and Catalog'!$F$51,IF(((D167+E167)*C167)<='Assumptions and Catalog'!$C$52,((D167+E167)*C167)*'Assumptions and Catalog'!$H$52+'Assumptions and Catalog'!$E$52+'Assumptions and Catalog'!$F$52,IF(((D167+E167)*C167)<='Assumptions and Catalog'!$C$53,((D167+E167)*C167)*'Assumptions and Catalog'!$H$53+'Assumptions and Catalog'!$E$53+'Assumptions and Catalog'!$F$53,IF(((D167+E167)*C167)<='Assumptions and Catalog'!$C$54,((D167+E167)*C167)*'Assumptions and Catalog'!$H$54+'Assumptions and Catalog'!$E$54+'Assumptions and Catalog'!$F$54,IF(((D167+E167)*C167)<='Assumptions and Catalog'!$C$55,((D167+E167)*C167)*'Assumptions and Catalog'!$H$55+'Assumptions and Catalog'!$E$55+'Assumptions and Catalog'!$F$55,IF(((D167+E167)*C167)<='Assumptions and Catalog'!$C$56,((D167+E167)*C167)*'Assumptions and Catalog'!$H$56+'Assumptions and Catalog'!$E$56+'Assumptions and Catalog'!$F$56,IF(((D167+E167)*C167)<='Assumptions and Catalog'!$C$57,((D167+E167)*C167)*'Assumptions and Catalog'!$H$57+'Assumptions and Catalog'!$E$57+'Assumptions and Catalog'!$F$57,"Out of range")))))))),IF(((D167+E167)*C167)<='Assumptions and Catalog'!$C$60,((D167+E167)*C167)*'Assumptions and Catalog'!$H$60+'Assumptions and Catalog'!$E$60+'Assumptions and Catalog'!$F$60,IF(((D167+E167)*C167)<='Assumptions and Catalog'!$C$61,((D167+E167)*C167)*'Assumptions and Catalog'!$H$61+'Assumptions and Catalog'!$E$61+'Assumptions and Catalog'!$F$61,IF(((D167+E167)*C167)<='Assumptions and Catalog'!$C$62,((D167+E167)*C167)*'Assumptions and Catalog'!$H$62+'Assumptions and Catalog'!$E$62+'Assumptions and Catalog'!$F$62,IF(((D167+E167)*C167)<='Assumptions and Catalog'!$C$63,((D167+E167)*C167)*'Assumptions and Catalog'!$H$63+'Assumptions and Catalog'!$E$63+'Assumptions and Catalog'!$F$63,IF(((D167+E167)*C167)<='Assumptions and Catalog'!$C$64,((D167+E167)*C167)*'Assumptions and Catalog'!$H$64+'Assumptions and Catalog'!$E$64+'Assumptions and Catalog'!$F$64,IF(((D167+E167)*C167)<='Assumptions and Catalog'!$C$65,((D167+E167)*C167)*'Assumptions and Catalog'!$H$65+'Assumptions and Catalog'!$E$65+'Assumptions and Catalog'!$F$65,"Out of range")))))))))*(1+'Assumptions and Catalog'!$C$8)^(A167-1),0) -> 8554.9667 | N167: =IF(ISNUMBER(Inputs!$L$5),(IF(Inputs!$L$9="Actual flat rate",L167*Inputs!$L$10,IF(Inputs!$C$9="Residential",IF(L167<='Assumptions and Catalog'!$C$50,L167*'Assumptions and Catalog'!$H$50+'Assumptions and Catalog'!$E$50+'Assumptions and Catalog'!$F$50,IF(L167<='Assumptions and Catalog'!$C$51,L167*'Assumptions and Catalog'!$H$51+'Assumptions and Catalog'!$E$51+'Assumptions and Catalog'!$F$51,IF(L167<='Assumptions and Catalog'!$C$52,L167*'Assumptions and Catalog'!$H$52+'Assumptions and Catalog'!$E$52+'Assumptions and Catalog'!$F$52,IF(L167<='Assumptions and Catalog'!$C$53,L167*'Assumptions and Catalog'!$H$53+'Assumptions and Catalog'!$E$53+'Assumptions and Catalog'!$F$53,IF(L167<='Assumptions and Catalog'!$C$54,L167*'Assumptions and Catalog'!$H$54+'Assumptions and Catalog'!$E$54+'Assumptions and Catalog'!$F$54,IF(L167<='Assumptions and Catalog'!$C$55,L167*'Assumptions and Catalog'!$H$55+'Assumptions and Catalog'!$E$55+'Assumptions and Catalog'!$F$55,IF(L167<='Assumptions and Catalog'!$C$56,L167*'Assumptions and Catalog'!$H$56+'Assumptions and Catalog'!$E$56+'Assumptions and Catalog'!$F$56,IF(L167<='Assumptions and Catalog'!$C$57,L167*'Assumptions and Catalog'!$H$57+'Assumptions and Catalog'!$E$57+'Assumptions and Catalog'!$F$57,"Out of range")))))))),IF(L167<='Assumptions and Catalog'!$C$60,L167*'Assumptions and Catalog'!$H$60+'Assumptions and Catalog'!$E$60+'Assumptions and Catalog'!$F$60,IF(L167<='Assumptions and Catalog'!$C$61,L167*'Assumptions and Catalog'!$H$61+'Assumptions and Catalog'!$E$61+'Assumptions and Catalog'!$F$61,IF(L167<='Assumptions and Catalog'!$C$62,L167*'Assumptions and Catalog'!$H$62+'Assumptions and Catalog'!$E$62+'Assumptions and Catalog'!$F$62,IF(L167<='Assumptions and Catalog'!$C$63,L167*'Assumptions and Catalog'!$H$63+'Assumptions and Catalog'!$E$63+'Assumptions and Catalog'!$F$63,IF(L167<='Assumptions and Catalog'!$C$64,L167*'Assumptions and Catalog'!$H$64+'Assumptions and Catalog'!$E$64+'Assumptions and Catalog'!$F$64,IF(L167<='Assumptions and Catalog'!$C$65,L167*'Assumptions and Catalog'!$H$65+'Assumptions and Catalog'!$E$65+'Assumptions and Catalog'!$F$65,"Out of range")))))))))*(1+'Assumptions and Catalog'!$C$8)^(A167-1),0) -> 5017.8537 | O167: =M167-N167 -> 3537.113 | P167: =C$55*(1-J$14)*(1-'Assumptions and Catalog'!$C$23)^R167 -> 0 | Q167: =IF(ISNUMBER(Inputs!$L$5),(IF(Inputs!$L$9="Actual flat rate",((D167+E167)*C167-G167)*Inputs!$L$10,IF(Inputs!$C$9="Residential",IF(((D167+E167)*C167-G167)<='Assumptions and Catalog'!$C$50,((D167+E167)*C167-G167)*'Assumptions and Catalog'!$H$50+'Assumptions and Catalog'!$E$50+'Assumptions and Catalog'!$F$50,IF(((D167+E167)*C167-G167)<='Assumptions and Catalog'!$C$51,((D167+E167)*C167-G167)*'Assumptions and Catalog'!$H$51+'Assumptions and Catalog'!$E$51+'Assumptions and Catalog'!$F$51,IF(((D167+E167)*C167-G167)<='Assumptions and Catalog'!$C$52,((D167+E167)*C167-G167)*'Assumptions and Catalog'!$H$52+'Assumptions and Catalog'!$E$52+'Assumptions and Catalog'!$F$52,IF(((D167+E167)*C167-G167)<='Assumptions and Catalog'!$C$53,((D167+E167)*C167-G167)*'Assumptions and Catalog'!$H$53+'Assumptions and Catalog'!$E$53+'Assumptions and Catalog'!$F$53,IF(((D167+E167)*C167-G167)<='Assumptions and Catalog'!$C$54,((D167+E167)*C167-G167)*'Assumptions and Catalog'!$H$54+'Assumptions and Catalog'!$E$54+'Assumptions and Catalog'!$F$54,IF(((D167+E167)*C167-G167)<='Assumptions and Catalog'!$C$55,((D167+E167)*C167-G167)*'Assumptions and Catalog'!$H$55+'Assumptions and Catalog'!$E$55+'Assumptions and Catalog'!$F$55,IF(((D167+E167)*C167-G167)<='Assumptions and Catalog'!$C$56,((D167+E167)*C167-G167)*'Assumptions and Catalog'!$H$56+'Assumptions and Catalog'!$E$56+'Assumptions and Catalog'!$F$56,IF(((D167+E167)*C167-G167)<='Assumptions and Catalog'!$C$57,((D167+E167)*C167-G167)*'Assumptions and Catalog'!$H$57+'Assumptions and Catalog'!$E$57+'Assumptions and Catalog'!$F$57,"Out of range")))))))),IF(((D167+E167)*C167-G167)<='Assumptions and Catalog'!$C$60,((D167+E167)*C167-G167)*'Assumptions and Catalog'!$H$60+'Assumptions and Catalog'!$E$60+'Assumptions and Catalog'!$F$60,IF(((D167+E167)*C167-G167)<='Assumptions and Catalog'!$C$61,((D167+E167)*C167-G167)*'Assumptions and Catalog'!$H$61+'Assumptions and Catalog'!$E$61+'Assumptions and Catalog'!$F$61,IF(((D167+E167)*C167-G167)<='Assumptions and Catalog'!$C$62,((D167+E167)*C167-G167)*'Assumptions and Catalog'!$H$62+'Assumptions and Catalog'!$E$62+'Assumptions and Catalog'!$F$62,IF(((D167+E167)*C167-G167)<='Assumptions and Catalog'!$C$63,((D167+E167)*C167-G167)*'Assumptions and Catalog'!$H$63+'Assumptions and Catalog'!$E$63+'Assumptions and Catalog'!$F$63,IF(((D167+E167)*C167-G167)<='Assumptions and Catalog'!$C$64,((D167+E167)*C167-G167)*'Assumptions and Catalog'!$H$64+'Assumptions and Catalog'!$E$64+'Assumptions and Catalog'!$F$64,IF(((D167+E167)*C167-G167)<='Assumptions and Catalog'!$C$65,((D167+E167)*C167-G167)*'Assumptions and Catalog'!$H$65+'Assumptions and Catalog'!$E$65+'Assumptions and Catalog'!$F$65,"Out of range")))))))))*(1+'Assumptions and Catalog'!$C$8)^(A167-1),0) -> 5017.8537 | R167: =IF(AND('Assumptions and Catalog'!$C$19>0,A167>='Assumptions and Catalog'!$C$19),A167-'Assumptions and Catalog'!$C$19,A167-1) -> 0 | S167: =F167+L167-(D167+E167)*C167-J167-K167-0 -> 0
A168: 1 | B168: 8 | C168: =DAY(DATE('Assumptions and Catalog'!$C$24+A168-1,B168+1,0)) -> 31 | D168: =IF(ISNUMBER(Inputs!$L$5),Inputs!$L$5*Inputs!$L$6,0) -> 40.35 | E168: =IF(ISNUMBER(Inputs!$L$5),Inputs!$L$5-D168,0) -> 40.35 | F168: =C$51*'Assumptions and Catalog'!$C$31*C168*(1-'Assumptions and Catalog'!$C$10)^(A168-1) -> 1034.346 | G168: =MIN(F168,D168*C168) -> 1034.346 | H168: =I168/('Assumptions and Catalog'!$C$11*'Assumptions and Catalog'!$C$12) -> 0 | I168: =0 -> 0 | J168: =MAX(F168-G168-H168,0) -> 0 | K168: =H168-I168 -> 0 | L168: =(D168+E168)*C168-G168-I168+0+0 -> 1467.354 | M168: =IF(ISNUMBER(Inputs!$L$5),(IF(Inputs!$L$9="Actual flat rate",((D168+E168)*C168)*Inputs!$L$10,IF(Inputs!$C$9="Residential",IF(((D168+E168)*C168)<='Assumptions and Catalog'!$C$50,((D168+E168)*C168)*'Assumptions and Catalog'!$H$50+'Assumptions and Catalog'!$E$50+'Assumptions and Catalog'!$F$50,IF(((D168+E168)*C168)<='Assumptions and Catalog'!$C$51,((D168+E168)*C168)*'Assumptions and Catalog'!$H$51+'Assumptions and Catalog'!$E$51+'Assumptions and Catalog'!$F$51,IF(((D168+E168)*C168)<='Assumptions and Catalog'!$C$52,((D168+E168)*C168)*'Assumptions and Catalog'!$H$52+'Assumptions and Catalog'!$E$52+'Assumptions and Catalog'!$F$52,IF(((D168+E168)*C168)<='Assumptions and Catalog'!$C$53,((D168+E168)*C168)*'Assumptions and Catalog'!$H$53+'Assumptions and Catalog'!$E$53+'Assumptions and Catalog'!$F$53,IF(((D168+E168)*C168)<='Assumptions and Catalog'!$C$54,((D168+E168)*C168)*'Assumptions and Catalog'!$H$54+'Assumptions and Catalog'!$E$54+'Assumptions and Catalog'!$F$54,IF(((D168+E168)*C168)<='Assumptions and Catalog'!$C$55,((D168+E168)*C168)*'Assumptions and Catalog'!$H$55+'Assumptions and Catalog'!$E$55+'Assumptions and Catalog'!$F$55,IF(((D168+E168)*C168)<='Assumptions and Catalog'!$C$56,((D168+E168)*C168)*'Assumptions and Catalog'!$H$56+'Assumptions and Catalog'!$E$56+'Assumptions and Catalog'!$F$56,IF(((D168+E168)*C168)<='Assumptions and Catalog'!$C$57,((D168+E168)*C168)*'Assumptions and Catalog'!$H$57+'Assumptions and Catalog'!$E$57+'Assumptions and Catalog'!$F$57,"Out of range")))))))),IF(((D168+E168)*C168)<='Assumptions and Catalog'!$C$60,((D168+E168)*C168)*'Assumptions and Catalog'!$H$60+'Assumptions and Catalog'!$E$60+'Assumptions and Catalog'!$F$60,IF(((D168+E168)*C168)<='Assumptions and Catalog'!$C$61,((D168+E168)*C168)*'Assumptions and Catalog'!$H$61+'Assumptions and Catalog'!$E$61+'Assumptions and Catalog'!$F$61,IF(((D168+E168)*C168)<='Assumptions and Catalog'!$C$62,((D168+E168)*C168)*'Assumptions and Catalog'!$H$62+'Assumptions and Catalog'!$E$62+'Assumptions and Catalog'!$F$62,IF(((D168+E168)*C168)<='Assumptions and Catalog'!$C$63,((D168+E168)*C168)*'Assumptions and Catalog'!$H$63+'Assumptions and Catalog'!$E$63+'Assumptions and Catalog'!$F$63,IF(((D168+E168)*C168)<='Assumptions and Catalog'!$C$64,((D168+E168)*C168)*'Assumptions and Catalog'!$H$64+'Assumptions and Catalog'!$E$64+'Assumptions and Catalog'!$F$64,IF(((D168+E168)*C168)<='Assumptions and Catalog'!$C$65,((D168+E168)*C168)*'Assumptions and Catalog'!$H$65+'Assumptions and Catalog'!$E$65+'Assumptions and Catalog'!$F$65,"Out of range")))))))))*(1+'Assumptions and Catalog'!$C$8)^(A168-1),0) -> 8554.9667 | N168: =IF(ISNUMBER(Inputs!$L$5),(IF(Inputs!$L$9="Actual flat rate",L168*Inputs!$L$10,IF(Inputs!$C$9="Residential",IF(L168<='Assumptions and Catalog'!$C$50,L168*'Assumptions and Catalog'!$H$50+'Assumptions and Catalog'!$E$50+'Assumptions and Catalog'!$F$50,IF(L168<='Assumptions and Catalog'!$C$51,L168*'Assumptions and Catalog'!$H$51+'Assumptions and Catalog'!$E$51+'Assumptions and Catalog'!$F$51,IF(L168<='Assumptions and Catalog'!$C$52,L168*'Assumptions and Catalog'!$H$52+'Assumptions and Catalog'!$E$52+'Assumptions and Catalog'!$F$52,IF(L168<='Assumptions and Catalog'!$C$53,L168*'Assumptions and Catalog'!$H$53+'Assumptions and Catalog'!$E$53+'Assumptions and Catalog'!$F$53,IF(L168<='Assumptions and Catalog'!$C$54,L168*'Assumptions and Catalog'!$H$54+'Assumptions and Catalog'!$E$54+'Assumptions and Catalog'!$F$54,IF(L168<='Assumptions and Catalog'!$C$55,L168*'Assumptions and Catalog'!$H$55+'Assumptions and Catalog'!$E$55+'Assumptions and Catalog'!$F$55,IF(L168<='Assumptions and Catalog'!$C$56,L168*'Assumptions and Catalog'!$H$56+'Assumptions and Catalog'!$E$56+'Assumptions and Catalog'!$F$56,IF(L168<='Assumptions and Catalog'!$C$57,L168*'Assumptions and Catalog'!$H$57+'Assumptions and Catalog'!$E$57+'Assumptions and Catalog'!$F$57,"Out of range")))))))),IF(L168<='Assumptions and Catalog'!$C$60,L168*'Assumptions and Catalog'!$H$60+'Assumptions and Catalog'!$E$60+'Assumptions and Catalog'!$F$60,IF(L168<='Assumptions and Catalog'!$C$61,L168*'Assumptions and Catalog'!$H$61+'Assumptions and Catalog'!$E$61+'Assumptions and Catalog'!$F$61,IF(L168<='Assumptions and Catalog'!$C$62,L168*'Assumptions and Catalog'!$H$62+'Assumptions and Catalog'!$E$62+'Assumptions and Catalog'!$F$62,IF(L168<='Assumptions and Catalog'!$C$63,L168*'Assumptions and Catalog'!$H$63+'Assumptions and Catalog'!$E$63+'Assumptions and Catalog'!$F$63,IF(L168<='Assumptions and Catalog'!$C$64,L168*'Assumptions and Catalog'!$H$64+'Assumptions and Catalog'!$E$64+'Assumptions and Catalog'!$F$64,IF(L168<='Assumptions and Catalog'!$C$65,L168*'Assumptions and Catalog'!$H$65+'Assumptions and Catalog'!$E$65+'Assumptions and Catalog'!$F$65,"Out of range")))))))))*(1+'Assumptions and Catalog'!$C$8)^(A168-1),0) -> 5017.8537 | O168: =M168-N168 -> 3537.113 | P168: =C$55*(1-J$14)*(1-'Assumptions and Catalog'!$C$23)^R168 -> 0 | Q168: =IF(ISNUMBER(Inputs!$L$5),(IF(Inputs!$L$9="Actual flat rate",((D168+E168)*C168-G168)*Inputs!$L$10,IF(Inputs!$C$9="Residential",IF(((D168+E168)*C168-G168)<='Assumptions and Catalog'!$C$50,((D168+E168)*C168-G168)*'Assumptions and Catalog'!$H$50+'Assumptions and Catalog'!$E$50+'Assumptions and Catalog'!$F$50,IF(((D168+E168)*C168-G168)<='Assumptions and Catalog'!$C$51,((D168+E168)*C168-G168)*'Assumptions and Catalog'!$H$51+'Assumptions and Catalog'!$E$51+'Assumptions and Catalog'!$F$51,IF(((D168+E168)*C168-G168)<='Assumptions and Catalog'!$C$52,((D168+E168)*C168-G168)*'Assumptions and Catalog'!$H$52+'Assumptions and Catalog'!$E$52+'Assumptions and Catalog'!$F$52,IF(((D168+E168)*C168-G168)<='Assumptions and Catalog'!$C$53,((D168+E168)*C168-G168)*'Assumptions and Catalog'!$H$53+'Assumptions and Catalog'!$E$53+'Assumptions and Catalog'!$F$53,IF(((D168+E168)*C168-G168)<='Assumptions and Catalog'!$C$54,((D168+E168)*C168-G168)*'Assumptions and Catalog'!$H$54+'Assumptions and Catalog'!$E$54+'Assumptions and Catalog'!$F$54,IF(((D168+E168)*C168-G168)<='Assumptions and Catalog'!$C$55,((D168+E168)*C168-G168)*'Assumptions and Catalog'!$H$55+'Assumptions and Catalog'!$E$55+'Assumptions and Catalog'!$F$55,IF(((D168+E168)*C168-G168)<='Assumptions and Catalog'!$C$56,((D168+E168)*C168-G168)*'Assumptions and Catalog'!$H$56+'Assumptions and Catalog'!$E$56+'Assumptions and Catalog'!$F$56,IF(((D168+E168)*C168-G168)<='Assumptions and Catalog'!$C$57,((D168+E168)*C168-G168)*'Assumptions and Catalog'!$H$57+'Assumptions and Catalog'!$E$57+'Assumptions and Catalog'!$F$57,"Out of range")))))))),IF(((D168+E168)*C168-G168)<='Assumptions and Catalog'!$C$60,((D168+E168)*C168-G168)*'Assumptions and Catalog'!$H$60+'Assumptions and Catalog'!$E$60+'Assumptions and Catalog'!$F$60,IF(((D168+E168)*C168-G168)<='Assumptions and Catalog'!$C$61,((D168+E168)*C168-G168)*'Assumptions and Catalog'!$H$61+'Assumptions and Catalog'!$E$61+'Assumptions and Catalog'!$F$61,IF(((D168+E168)*C168-G168)<='Assumptions and Catalog'!$C$62,((D168+E168)*C168-G168)*'Assumptions and Catalog'!$H$62+'Assumptions and Catalog'!$E$62+'Assumptions and Catalog'!$F$62,IF(((D168+E168)*C168-G168)<='Assumptions and Catalog'!$C$63,((D168+E168)*C168-G168)*'Assumptions and Catalog'!$H$63+'Assumptions and Catalog'!$E$63+'Assumptions and Catalog'!$F$63,IF(((D168+E168)*C168-G168)<='Assumptions and Catalog'!$C$64,((D168+E168)*C168-G168)*'Assumptions and Catalog'!$H$64+'Assumptions and Catalog'!$E$64+'Assumptions and Catalog'!$F$64,IF(((D168+E168)*C168-G168)<='Assumptions and Catalog'!$C$65,((D168+E168)*C168-G168)*'Assumptions and Catalog'!$H$65+'Assumptions and Catalog'!$E$65+'Assumptions and Catalog'!$F$65,"Out of range")))))))))*(1+'Assumptions and Catalog'!$C$8)^(A168-1),0) -> 5017.8537 | R168: =IF(AND('Assumptions and Catalog'!$C$19>0,A168>='Assumptions and Catalog'!$C$19),A168-'Assumptions and Catalog'!$C$19,A168-1) -> 0 | S168: =F168+L168-(D168+E168)*C168-J168-K168-0 -> 0
A169: 1 | B169: 9 | C169: =DAY(DATE('Assumptions and Catalog'!$C$24+A169-1,B169+1,0)) -> 30 | D169: =IF(ISNUMBER(Inputs!$L$5),Inputs!$L$5*Inputs!$L$6,0) -> 40.35 | E169: =IF(ISNUMBER(Inputs!$L$5),Inputs!$L$5-D169,0) -> 40.35 | F169: =C$51*'Assumptions and Catalog'!$C$31*C169*(1-'Assumptions and Catalog'!$C$10)^(A169-1) -> 1000.98 | G169: =MIN(F169,D169*C169) -> 1000.98 | H169: =I169/('Assumptions and Catalog'!$C$11*'Assumptions and Catalog'!$C$12) -> 0 | I169: =0 -> 0 | J169: =MAX(F169-G169-H169,0) -> 0 | K169: =H169-I169 -> 0 | L169: =(D169+E169)*C169-G169-I169+0+0 -> 1420.02 | M169: =IF(ISNUMBER(Inputs!$L$5),(IF(Inputs!$L$9="Actual flat rate",((D169+E169)*C169)*Inputs!$L$10,IF(Inputs!$C$9="Residential",IF(((D169+E169)*C169)<='Assumptions and Catalog'!$C$50,((D169+E169)*C169)*'Assumptions and Catalog'!$H$50+'Assumptions and Catalog'!$E$50+'Assumptions and Catalog'!$F$50,IF(((D169+E169)*C169)<='Assumptions and Catalog'!$C$51,((D169+E169)*C169)*'Assumptions and Catalog'!$H$51+'Assumptions and Catalog'!$E$51+'Assumptions and Catalog'!$F$51,IF(((D169+E169)*C169)<='Assumptions and Catalog'!$C$52,((D169+E169)*C169)*'Assumptions and Catalog'!$H$52+'Assumptions and Catalog'!$E$52+'Assumptions and Catalog'!$F$52,IF(((D169+E169)*C169)<='Assumptions and Catalog'!$C$53,((D169+E169)*C169)*'Assumptions and Catalog'!$H$53+'Assumptions and Catalog'!$E$53+'Assumptions and Catalog'!$F$53,IF(((D169+E169)*C169)<='Assumptions and Catalog'!$C$54,((D169+E169)*C169)*'Assumptions and Catalog'!$H$54+'Assumptions and Catalog'!$E$54+'Assumptions and Catalog'!$F$54,IF(((D169+E169)*C169)<='Assumptions and Catalog'!$C$55,((D169+E169)*C169)*'Assumptions and Catalog'!$H$55+'Assumptions and Catalog'!$E$55+'Assumptions and Catalog'!$F$55,IF(((D169+E169)*C169)<='Assumptions and Catalog'!$C$56,((D169+E169)*C169)*'Assumptions and Catalog'!$H$56+'Assumptions and Catalog'!$E$56+'Assumptions and Catalog'!$F$56,IF(((D169+E169)*C169)<='Assumptions and Catalog'!$C$57,((D169+E169)*C169)*'Assumptions and Catalog'!$H$57+'Assumptions and Catalog'!$E$57+'Assumptions and Catalog'!$F$57,"Out of range")))))))),IF(((D169+E169)*C169)<='Assumptions and Catalog'!$C$60,((D169+E169)*C169)*'Assumptions and Catalog'!$H$60+'Assumptions and Catalog'!$E$60+'Assumptions and Catalog'!$F$60,IF(((D169+E169)*C169)<='Assumptions and Catalog'!$C$61,((D169+E169)*C169)*'Assumptions and Catalog'!$H$61+'Assumptions and Catalog'!$E$61+'Assumptions and Catalog'!$F$61,IF(((D169+E169)*C169)<='Assumptions and Catalog'!$C$62,((D169+E169)*C169)*'Assumptions and Catalog'!$H$62+'Assumptions and Catalog'!$E$62+'Assumptions and Catalog'!$F$62,IF(((D169+E169)*C169)<='Assumptions and Catalog'!$C$63,((D169+E169)*C169)*'Assumptions and Catalog'!$H$63+'Assumptions and Catalog'!$E$63+'Assumptions and Catalog'!$F$63,IF(((D169+E169)*C169)<='Assumptions and Catalog'!$C$64,((D169+E169)*C169)*'Assumptions and Catalog'!$H$64+'Assumptions and Catalog'!$E$64+'Assumptions and Catalog'!$F$64,IF(((D169+E169)*C169)<='Assumptions and Catalog'!$C$65,((D169+E169)*C169)*'Assumptions and Catalog'!$H$65+'Assumptions and Catalog'!$E$65+'Assumptions and Catalog'!$F$65,"Out of range")))))))))*(1+'Assumptions and Catalog'!$C$8)^(A169-1),0) -> 8279 | N169: =IF(ISNUMBER(Inputs!$L$5),(IF(Inputs!$L$9="Actual flat rate",L169*Inputs!$L$10,IF(Inputs!$C$9="Residential",IF(L169<='Assumptions and Catalog'!$C$50,L169*'Assumptions and Catalog'!$H$50+'Assumptions and Catalog'!$E$50+'Assumptions and Catalog'!$F$50,IF(L169<='Assumptions and Catalog'!$C$51,L169*'Assumptions and Catalog'!$H$51+'Assumptions and Catalog'!$E$51+'Assumptions and Catalog'!$F$51,IF(L169<='Assumptions and Catalog'!$C$52,L169*'Assumptions and Catalog'!$H$52+'Assumptions and Catalog'!$E$52+'Assumptions and Catalog'!$F$52,IF(L169<='Assumptions and Catalog'!$C$53,L169*'Assumptions and Catalog'!$H$53+'Assumptions and Catalog'!$E$53+'Assumptions and Catalog'!$F$53,IF(L169<='Assumptions and Catalog'!$C$54,L169*'Assumptions and Catalog'!$H$54+'Assumptions and Catalog'!$E$54+'Assumptions and Catalog'!$F$54,IF(L169<='Assumptions and Catalog'!$C$55,L169*'Assumptions and Catalog'!$H$55+'Assumptions and Catalog'!$E$55+'Assumptions and Catalog'!$F$55,IF(L169<='Assumptions and Catalog'!$C$56,L169*'Assumptions and Catalog'!$H$56+'Assumptions and Catalog'!$E$56+'Assumptions and Catalog'!$F$56,IF(L169<='Assumptions and Catalog'!$C$57,L169*'Assumptions and Catalog'!$H$57+'Assumptions and Catalog'!$E$57+'Assumptions and Catalog'!$F$57,"Out of range")))))))),IF(L169<='Assumptions and Catalog'!$C$60,L169*'Assumptions and Catalog'!$H$60+'Assumptions and Catalog'!$E$60+'Assumptions and Catalog'!$F$60,IF(L169<='Assumptions and Catalog'!$C$61,L169*'Assumptions and Catalog'!$H$61+'Assumptions and Catalog'!$E$61+'Assumptions and Catalog'!$F$61,IF(L169<='Assumptions and Catalog'!$C$62,L169*'Assumptions and Catalog'!$H$62+'Assumptions and Catalog'!$E$62+'Assumptions and Catalog'!$F$62,IF(L169<='Assumptions and Catalog'!$C$63,L169*'Assumptions and Catalog'!$H$63+'Assumptions and Catalog'!$E$63+'Assumptions and Catalog'!$F$63,IF(L169<='Assumptions and Catalog'!$C$64,L169*'Assumptions and Catalog'!$H$64+'Assumptions and Catalog'!$E$64+'Assumptions and Catalog'!$F$64,IF(L169<='Assumptions and Catalog'!$C$65,L169*'Assumptions and Catalog'!$H$65+'Assumptions and Catalog'!$E$65+'Assumptions and Catalog'!$F$65,"Out of range")))))))))*(1+'Assumptions and Catalog'!$C$8)^(A169-1),0) -> 4855.9874 | O169: =M169-N169 -> 3423.0126 | P169: =C$55*(1-J$14)*(1-'Assumptions and Catalog'!$C$23)^R169 -> 0 | Q169: =IF(ISNUMBER(Inputs!$L$5),(IF(Inputs!$L$9="Actual flat rate",((D169+E169)*C169-G169)*Inputs!$L$10,IF(Inputs!$C$9="Residential",IF(((D169+E169)*C169-G169)<='Assumptions and Catalog'!$C$50,((D169+E169)*C169-G169)*'Assumptions and Catalog'!$H$50+'Assumptions and Catalog'!$E$50+'Assumptions and Catalog'!$F$50,IF(((D169+E169)*C169-G169)<='Assumptions and Catalog'!$C$51,((D169+E169)*C169-G169)*'Assumptions and Catalog'!$H$51+'Assumptions and Catalog'!$E$51+'Assumptions and Catalog'!$F$51,IF(((D169+E169)*C169-G169)<='Assumptions and Catalog'!$C$52,((D169+E169)*C169-G169)*'Assumptions and Catalog'!$H$52+'Assumptions and Catalog'!$E$52+'Assumptions and Catalog'!$F$52,IF(((D169+E169)*C169-G169)<='Assumptions and Catalog'!$C$53,((D169+E169)*C169-G169)*'Assumptions and Catalog'!$H$53+'Assumptions and Catalog'!$E$53+'Assumptions and Catalog'!$F$53,IF(((D169+E169)*C169-G169)<='Assumptions and Catalog'!$C$54,((D169+E169)*C169-G169)*'Assumptions and Catalog'!$H$54+'Assumptions and Catalog'!$E$54+'Assumptions and Catalog'!$F$54,IF(((D169+E169)*C169-G169)<='Assumptions and Catalog'!$C$55,((D169+E169)*C169-G169)*'Assumptions and Catalog'!$H$55+'Assumptions and Catalog'!$E$55+'Assumptions and Catalog'!$F$55,IF(((D169+E169)*C169-G169)<='Assumptions and Catalog'!$C$56,((D169+E169)*C169-G169)*'Assumptions and Catalog'!$H$56+'Assumptions and Catalog'!$E$56+'Assumptions and Catalog'!$F$56,IF(((D169+E169)*C169-G169)<='Assumptions and Catalog'!$C$57,((D169+E169)*C169-G169)*'Assumptions and Catalog'!$H$57+'Assumptions and Catalog'!$E$57+'Assumptions and Catalog'!$F$57,"Out of range")))))))),IF(((D169+E169)*C169-G169)<='Assumptions and Catalog'!$C$60,((D169+E169)*C169-G169)*'Assumptions and Catalog'!$H$60+'Assumptions and Catalog'!$E$60+'Assumptions and Catalog'!$F$60,IF(((D169+E169)*C169-G169)<='Assumptions and Catalog'!$C$61,((D169+E169)*C169-G169)*'Assumptions and Catalog'!$H$61+'Assumptions and Catalog'!$E$61+'Assumptions and Catalog'!$F$61,IF(((D169+E169)*C169-G169)<='Assumptions and Catalog'!$C$62,((D169+E169)*C169-G169)*'Assumptions and Catalog'!$H$62+'Assumptions and Catalog'!$E$62+'Assumptions and Catalog'!$F$62,IF(((D169+E169)*C169-G169)<='Assumptions and Catalog'!$C$63,((D169+E169)*C169-G169)*'Assumptions and Catalog'!$H$63+'Assumptions and Catalog'!$E$63+'Assumptions and Catalog'!$F$63,IF(((D169+E169)*C169-G169)<='Assumptions and Catalog'!$C$64,((D169+E169)*C169-G169)*'Assumptions and Catalog'!$H$64+'Assumptions and Catalog'!$E$64+'Assumptions and Catalog'!$F$64,IF(((D169+E169)*C169-G169)<='Assumptions and Catalog'!$C$65,((D169+E169)*C169-G169)*'Assumptions and Catalog'!$H$65+'Assumptions and Catalog'!$E$65+'Assumptions and Catalog'!$F$65,"Out of range")))))))))*(1+'Assumptions and Catalog'!$C$8)^(A169-1),0) -> 4855.9874 | R169: =IF(AND('Assumptions and Catalog'!$C$19>0,A169>='Assumptions and Catalog'!$C$19),A169-'Assumptions and Catalog'!$C$19,A169-1) -> 0 | S169: =F169+L169-(D169+E169)*C169-J169-K169-0 -> 0
A170: 1 | B170: 10 | C170: =DAY(DATE('Assumptions and Catalog'!$C$24+A170-1,B170+1,0)) -> 31 | D170: =IF(ISNUMBER(Inputs!$L$5),Inputs!$L$5*Inputs!$L$6,0) -> 40.35 | E170: =IF(ISNUMBER(Inputs!$L$5),Inputs!$L$5-D170,0) -> 40.35 | F170: =C$51*'Assumptions and Catalog'!$C$31*C170*(1-'Assumptions and Catalog'!$C$10)^(A170-1) -> 1034.346 | G170: =MIN(F170,D170*C170) -> 1034.346 | H170: =I170/('Assumptions and Catalog'!$C$11*'Assumptions and Catalog'!$C$12) -> 0 | I170: =0 -> 0 | J170: =MAX(F170-G170-H170,0) -> 0 | K170: =H170-I170 -> 0 | L170: =(D170+E170)*C170-G170-I170+0+0 -> 1467.354 | M170: =IF(ISNUMBER(Inputs!$L$5),(IF(Inputs!$L$9="Actual flat rate",((D170+E170)*C170)*Inputs!$L$10,IF(Inputs!$C$9="Residential",IF(((D170+E170)*C170)<='Assumptions and Catalog'!$C$50,((D170+E170)*C170)*'Assumptions and Catalog'!$H$50+'Assumptions and Catalog'!$E$50+'Assumptions and Catalog'!$F$50,IF(((D170+E170)*C170)<='Assumptions and Catalog'!$C$51,((D170+E170)*C170)*'Assumptions and Catalog'!$H$51+'Assumptions and Catalog'!$E$51+'Assumptions and Catalog'!$F$51,IF(((D170+E170)*C170)<='Assumptions and Catalog'!$C$52,((D170+E170)*C170)*'Assumptions and Catalog'!$H$52+'Assumptions and Catalog'!$E$52+'Assumptions and Catalog'!$F$52,IF(((D170+E170)*C170)<='Assumptions and Catalog'!$C$53,((D170+E170)*C170)*'Assumptions and Catalog'!$H$53+'Assumptions and Catalog'!$E$53+'Assumptions and Catalog'!$F$53,IF(((D170+E170)*C170)<='Assumptions and Catalog'!$C$54,((D170+E170)*C170)*'Assumptions and Catalog'!$H$54+'Assumptions and Catalog'!$E$54+'Assumptions and Catalog'!$F$54,IF(((D170+E170)*C170)<='Assumptions and Catalog'!$C$55,((D170+E170)*C170)*'Assumptions and Catalog'!$H$55+'Assumptions and Catalog'!$E$55+'Assumptions and Catalog'!$F$55,IF(((D170+E170)*C170)<='Assumptions and Catalog'!$C$56,((D170+E170)*C170)*'Assumptions and Catalog'!$H$56+'Assumptions and Catalog'!$E$56+'Assumptions and Catalog'!$F$56,IF(((D170+E170)*C170)<='Assumptions and Catalog'!$C$57,((D170+E170)*C170)*'Assumptions and Catalog'!$H$57+'Assumptions and Catalog'!$E$57+'Assumptions and Catalog'!$F$57,"Out of range")))))))),IF(((D170+E170)*C170)<='Assumptions and Catalog'!$C$60,((D170+E170)*C170)*'Assumptions and Catalog'!$H$60+'Assumptions and Catalog'!$E$60+'Assumptions and Catalog'!$F$60,IF(((D170+E170)*C170)<='Assumptions and Catalog'!$C$61,((D170+E170)*C170)*'Assumptions and Catalog'!$H$61+'Assumptions and Catalog'!$E$61+'Assumptions and Catalog'!$F$61,IF(((D170+E170)*C170)<='Assumptions and Catalog'!$C$62,((D170+E170)*C170)*'Assumptions and Catalog'!$H$62+'Assumptions and Catalog'!$E$62+'Assumptions and Catalog'!$F$62,IF(((D170+E170)*C170)<='Assumptions and Catalog'!$C$63,((D170+E170)*C170)*'Assumptions and Catalog'!$H$63+'Assumptions and Catalog'!$E$63+'Assumptions and Catalog'!$F$63,IF(((D170+E170)*C170)<='Assumptions and Catalog'!$C$64,((D170+E170)*C170)*'Assumptions and Catalog'!$H$64+'Assumptions and Catalog'!$E$64+'Assumptions and Catalog'!$F$64,IF(((D170+E170)*C170)<='Assumptions and Catalog'!$C$65,((D170+E170)*C170)*'Assumptions and Catalog'!$H$65+'Assumptions and Catalog'!$E$65+'Assumptions and Catalog'!$F$65,"Out of range")))))))))*(1+'Assumptions and Catalog'!$C$8)^(A170-1),0) -> 8554.9667 | N170: =IF(ISNUMBER(Inputs!$L$5),(IF(Inputs!$L$9="Actual flat rate",L170*Inputs!$L$10,IF(Inputs!$C$9="Residential",IF(L170<='Assumptions and Catalog'!$C$50,L170*'Assumptions and Catalog'!$H$50+'Assumptions and Catalog'!$E$50+'Assumptions and Catalog'!$F$50,IF(L170<='Assumptions and Catalog'!$C$51,L170*'Assumptions and Catalog'!$H$51+'Assumptions and Catalog'!$E$51+'Assumptions and Catalog'!$F$51,IF(L170<='Assumptions and Catalog'!$C$52,L170*'Assumptions and Catalog'!$H$52+'Assumptions and Catalog'!$E$52+'Assumptions and Catalog'!$F$52,IF(L170<='Assumptions and Catalog'!$C$53,L170*'Assumptions and Catalog'!$H$53+'Assumptions and Catalog'!$E$53+'Assumptions and Catalog'!$F$53,IF(L170<='Assumptions and Catalog'!$C$54,L170*'Assumptions and Catalog'!$H$54+'Assumptions and Catalog'!$E$54+'Assumptions and Catalog'!$F$54,IF(L170<='Assumptions and Catalog'!$C$55,L170*'Assumptions and Catalog'!$H$55+'Assumptions and Catalog'!$E$55+'Assumptions and Catalog'!$F$55,IF(L170<='Assumptions and Catalog'!$C$56,L170*'Assumptions and Catalog'!$H$56+'Assumptions and Catalog'!$E$56+'Assumptions and Catalog'!$F$56,IF(L170<='Assumptions and Catalog'!$C$57,L170*'Assumptions and Catalog'!$H$57+'Assumptions and Catalog'!$E$57+'Assumptions and Catalog'!$F$57,"Out of range")))))))),IF(L170<='Assumptions and Catalog'!$C$60,L170*'Assumptions and Catalog'!$H$60+'Assumptions and Catalog'!$E$60+'Assumptions and Catalog'!$F$60,IF(L170<='Assumptions and Catalog'!$C$61,L170*'Assumptions and Catalog'!$H$61+'Assumptions and Catalog'!$E$61+'Assumptions and Catalog'!$F$61,IF(L170<='Assumptions and Catalog'!$C$62,L170*'Assumptions and Catalog'!$H$62+'Assumptions and Catalog'!$E$62+'Assumptions and Catalog'!$F$62,IF(L170<='Assumptions and Catalog'!$C$63,L170*'Assumptions and Catalog'!$H$63+'Assumptions and Catalog'!$E$63+'Assumptions and Catalog'!$F$63,IF(L170<='Assumptions and Catalog'!$C$64,L170*'Assumptions and Catalog'!$H$64+'Assumptions and Catalog'!$E$64+'Assumptions and Catalog'!$F$64,IF(L170<='Assumptions and Catalog'!$C$65,L170*'Assumptions and Catalog'!$H$65+'Assumptions and Catalog'!$E$65+'Assumptions and Catalog'!$F$65,"Out of range")))))))))*(1+'Assumptions and Catalog'!$C$8)^(A170-1),0) -> 5017.8537 | O170: =M170-N170 -> 3537.113 | P170: =C$55*(1-J$14)*(1-'Assumptions and Catalog'!$C$23)^R170 -> 0 | Q170: =IF(ISNUMBER(Inputs!$L$5),(IF(Inputs!$L$9="Actual flat rate",((D170+E170)*C170-G170)*Inputs!$L$10,IF(Inputs!$C$9="Residential",IF(((D170+E170)*C170-G170)<='Assumptions and Catalog'!$C$50,((D170+E170)*C170-G170)*'Assumptions and Catalog'!$H$50+'Assumptions and Catalog'!$E$50+'Assumptions and Catalog'!$F$50,IF(((D170+E170)*C170-G170)<='Assumptions and Catalog'!$C$51,((D170+E170)*C170-G170)*'Assumptions and Catalog'!$H$51+'Assumptions and Catalog'!$E$51+'Assumptions and Catalog'!$F$51,IF(((D170+E170)*C170-G170)<='Assumptions and Catalog'!$C$52,((D170+E170)*C170-G170)*'Assumptions and Catalog'!$H$52+'Assumptions and Catalog'!$E$52+'Assumptions and Catalog'!$F$52,IF(((D170+E170)*C170-G170)<='Assumptions and Catalog'!$C$53,((D170+E170)*C170-G170)*'Assumptions and Catalog'!$H$53+'Assumptions and Catalog'!$E$53+'Assumptions and Catalog'!$F$53,IF(((D170+E170)*C170-G170)<='Assumptions and Catalog'!$C$54,((D170+E170)*C170-G170)*'Assumptions and Catalog'!$H$54+'Assumptions and Catalog'!$E$54+'Assumptions and Catalog'!$F$54,IF(((D170+E170)*C170-G170)<='Assumptions and Catalog'!$C$55,((D170+E170)*C170-G170)*'Assumptions and Catalog'!$H$55+'Assumptions and Catalog'!$E$55+'Assumptions and Catalog'!$F$55,IF(((D170+E170)*C170-G170)<='Assumptions and Catalog'!$C$56,((D170+E170)*C170-G170)*'Assumptions and Catalog'!$H$56+'Assumptions and Catalog'!$E$56+'Assumptions and Catalog'!$F$56,IF(((D170+E170)*C170-G170)<='Assumptions and Catalog'!$C$57,((D170+E170)*C170-G170)*'Assumptions and Catalog'!$H$57+'Assumptions and Catalog'!$E$57+'Assumptions and Catalog'!$F$57,"Out of range")))))))),IF(((D170+E170)*C170-G170)<='Assumptions and Catalog'!$C$60,((D170+E170)*C170-G170)*'Assumptions and Catalog'!$H$60+'Assumptions and Catalog'!$E$60+'Assumptions and Catalog'!$F$60,IF(((D170+E170)*C170-G170)<='Assumptions and Catalog'!$C$61,((D170+E170)*C170-G170)*'Assumptions and Catalog'!$H$61+'Assumptions and Catalog'!$E$61+'Assumptions and Catalog'!$F$61,IF(((D170+E170)*C170-G170)<='Assumptions and Catalog'!$C$62,((D170+E170)*C170-G170)*'Assumptions and Catalog'!$H$62+'Assumptions and Catalog'!$E$62+'Assumptions and Catalog'!$F$62,IF(((D170+E170)*C170-G170)<='Assumptions and Catalog'!$C$63,((D170+E170)*C170-G170)*'Assumptions and Catalog'!$H$63+'Assumptions and Catalog'!$E$63+'Assumptions and Catalog'!$F$63,IF(((D170+E170)*C170-G170)<='Assumptions and Catalog'!$C$64,((D170+E170)*C170-G170)*'Assumptions and Catalog'!$H$64+'Assumptions and Catalog'!$E$64+'Assumptions and Catalog'!$F$64,IF(((D170+E170)*C170-G170)<='Assumptions and Catalog'!$C$65,((D170+E170)*C170-G170)*'Assumptions and Catalog'!$H$65+'Assumptions and Catalog'!$E$65+'Assumptions and Catalog'!$F$65,"Out of range")))))))))*(1+'Assumptions and Catalog'!$C$8)^(A170-1),0) -> 5017.8537 | R170: =IF(AND('Assumptions and Catalog'!$C$19>0,A170>='Assumptions and Catalog'!$C$19),A170-'Assumptions and Catalog'!$C$19,A170-1) -> 0 | S170: =F170+L170-(D170+E170)*C170-J170-K170-0 -> 0
A171: 1 | B171: 11 | C171: =DAY(DATE('Assumptions and Catalog'!$C$24+A171-1,B171+1,0)) -> 30 | D171: =IF(ISNUMBER(Inputs!$L$5),Inputs!$L$5*Inputs!$L$6,0) -> 40.35 | E171: =IF(ISNUMBER(Inputs!$L$5),Inputs!$L$5-D171,0) -> 40.35 | F171: =C$51*'Assumptions and Catalog'!$C$31*C171*(1-'Assumptions and Catalog'!$C$10)^(A171-1) -> 1000.98 | G171: =MIN(F171,D171*C171) -> 1000.98 | H171: =I171/('Assumptions and Catalog'!$C$11*'Assumptions and Catalog'!$C$12) -> 0 | I171: =0 -> 0 | J171: =MAX(F171-G171-H171,0) -> 0 | K171: =H171-I171 -> 0 | L171: =(D171+E171)*C171-G171-I171+0+0 -> 1420.02 | M171: =IF(ISNUMBER(Inputs!$L$5),(IF(Inputs!$L$9="Actual flat rate",((D171+E171)*C171)*Inputs!$L$10,IF(Inputs!$C$9="Residential",IF(((D171+E171)*C171)<='Assumptions and Catalog'!$C$50,((D171+E171)*C171)*'Assumptions and Catalog'!$H$50+'Assumptions and Catalog'!$E$50+'Assumptions and Catalog'!$F$50,IF(((D171+E171)*C171)<='Assumptions and Catalog'!$C$51,((D171+E171)*C171)*'Assumptions and Catalog'!$H$51+'Assumptions and Catalog'!$E$51+'Assumptions and Catalog'!$F$51,IF(((D171+E171)*C171)<='Assumptions and Catalog'!$C$52,((D171+E171)*C171)*'Assumptions and Catalog'!$H$52+'Assumptions and Catalog'!$E$52+'Assumptions and Catalog'!$F$52,IF(((D171+E171)*C171)<='Assumptions and Catalog'!$C$53,((D171+E171)*C171)*'Assumptions and Catalog'!$H$53+'Assumptions and Catalog'!$E$53+'Assumptions and Catalog'!$F$53,IF(((D171+E171)*C171)<='Assumptions and Catalog'!$C$54,((D171+E171)*C171)*'Assumptions and Catalog'!$H$54+'Assumptions and Catalog'!$E$54+'Assumptions and Catalog'!$F$54,IF(((D171+E171)*C171)<='Assumptions and Catalog'!$C$55,((D171+E171)*C171)*'Assumptions and Catalog'!$H$55+'Assumptions and Catalog'!$E$55+'Assumptions and Catalog'!$F$55,IF(((D171+E171)*C171)<='Assumptions and Catalog'!$C$56,((D171+E171)*C171)*'Assumptions and Catalog'!$H$56+'Assumptions and Catalog'!$E$56+'Assumptions and Catalog'!$F$56,IF(((D171+E171)*C171)<='Assumptions and Catalog'!$C$57,((D171+E171)*C171)*'Assumptions and Catalog'!$H$57+'Assumptions and Catalog'!$E$57+'Assumptions and Catalog'!$F$57,"Out of range")))))))),IF(((D171+E171)*C171)<='Assumptions and Catalog'!$C$60,((D171+E171)*C171)*'Assumptions and Catalog'!$H$60+'Assumptions and Catalog'!$E$60+'Assumptions and Catalog'!$F$60,IF(((D171+E171)*C171)<='Assumptions and Catalog'!$C$61,((D171+E171)*C171)*'Assumptions and Catalog'!$H$61+'Assumptions and Catalog'!$E$61+'Assumptions and Catalog'!$F$61,IF(((D171+E171)*C171)<='Assumptions and Catalog'!$C$62,((D171+E171)*C171)*'Assumptions and Catalog'!$H$62+'Assumptions and Catalog'!$E$62+'Assumptions and Catalog'!$F$62,IF(((D171+E171)*C171)<='Assumptions and Catalog'!$C$63,((D171+E171)*C171)*'Assumptions and Catalog'!$H$63+'Assumptions and Catalog'!$E$63+'Assumptions and Catalog'!$F$63,IF(((D171+E171)*C171)<='Assumptions and Catalog'!$C$64,((D171+E171)*C171)*'Assumptions and Catalog'!$H$64+'Assumptions and Catalog'!$E$64+'Assumptions and Catalog'!$F$64,IF(((D171+E171)*C171)<='Assumptions and Catalog'!$C$65,((D171+E171)*C171)*'Assumptions and Catalog'!$H$65+'Assumptions and Catalog'!$E$65+'Assumptions and Catalog'!$F$65,"Out of range")))))))))*(1+'Assumptions and Catalog'!$C$8)^(A171-1),0) -> 8279 | N171: =IF(ISNUMBER(Inputs!$L$5),(IF(Inputs!$L$9="Actual flat rate",L171*Inputs!$L$10,IF(Inputs!$C$9="Residential",IF(L171<='Assumptions and Catalog'!$C$50,L171*'Assumptions and Catalog'!$H$50+'Assumptions and Catalog'!$E$50+'Assumptions and Catalog'!$F$50,IF(L171<='Assumptions and Catalog'!$C$51,L171*'Assumptions and Catalog'!$H$51+'Assumptions and Catalog'!$E$51+'Assumptions and Catalog'!$F$51,IF(L171<='Assumptions and Catalog'!$C$52,L171*'Assumptions and Catalog'!$H$52+'Assumptions and Catalog'!$E$52+'Assumptions and Catalog'!$F$52,IF(L171<='Assumptions and Catalog'!$C$53,L171*'Assumptions and Catalog'!$H$53+'Assumptions and Catalog'!$E$53+'Assumptions and Catalog'!$F$53,IF(L171<='Assumptions and Catalog'!$C$54,L171*'Assumptions and Catalog'!$H$54+'Assumptions and Catalog'!$E$54+'Assumptions and Catalog'!$F$54,IF(L171<='Assumptions and Catalog'!$C$55,L171*'Assumptions and Catalog'!$H$55+'Assumptions and Catalog'!$E$55+'Assumptions and Catalog'!$F$55,IF(L171<='Assumptions and Catalog'!$C$56,L171*'Assumptions and Catalog'!$H$56+'Assumptions and Catalog'!$E$56+'Assumptions and Catalog'!$F$56,IF(L171<='Assumptions and Catalog'!$C$57,L171*'Assumptions and Catalog'!$H$57+'Assumptions and Catalog'!$E$57+'Assumptions and Catalog'!$F$57,"Out of range")))))))),IF(L171<='Assumptions and Catalog'!$C$60,L171*'Assumptions and Catalog'!$H$60+'Assumptions and Catalog'!$E$60+'Assumptions and Catalog'!$F$60,IF(L171<='Assumptions and Catalog'!$C$61,L171*'Assumptions and Catalog'!$H$61+'Assumptions and Catalog'!$E$61+'Assumptions and Catalog'!$F$61,IF(L171<='Assumptions and Catalog'!$C$62,L171*'Assumptions and Catalog'!$H$62+'Assumptions and Catalog'!$E$62+'Assumptions and Catalog'!$F$62,IF(L171<='Assumptions and Catalog'!$C$63,L171*'Assumptions and Catalog'!$H$63+'Assumptions and Catalog'!$E$63+'Assumptions and Catalog'!$F$63,IF(L171<='Assumptions and Catalog'!$C$64,L171*'Assumptions and Catalog'!$H$64+'Assumptions and Catalog'!$E$64+'Assumptions and Catalog'!$F$64,IF(L171<='Assumptions and Catalog'!$C$65,L171*'Assumptions and Catalog'!$H$65+'Assumptions and Catalog'!$E$65+'Assumptions and Catalog'!$F$65,"Out of range")))))))))*(1+'Assumptions and Catalog'!$C$8)^(A171-1),0) -> 4855.9874 | O171: =M171-N171 -> 3423.0126 | P171: =C$55*(1-J$14)*(1-'Assumptions and Catalog'!$C$23)^R171 -> 0 | Q171: =IF(ISNUMBER(Inputs!$L$5),(IF(Inputs!$L$9="Actual flat rate",((D171+E171)*C171-G171)*Inputs!$L$10,IF(Inputs!$C$9="Residential",IF(((D171+E171)*C171-G171)<='Assumptions and Catalog'!$C$50,((D171+E171)*C171-G171)*'Assumptions and Catalog'!$H$50+'Assumptions and Catalog'!$E$50+'Assumptions and Catalog'!$F$50,IF(((D171+E171)*C171-G171)<='Assumptions and Catalog'!$C$51,((D171+E171)*C171-G171)*'Assumptions and Catalog'!$H$51+'Assumptions and Catalog'!$E$51+'Assumptions and Catalog'!$F$51,IF(((D171+E171)*C171-G171)<='Assumptions and Catalog'!$C$52,((D171+E171)*C171-G171)*'Assumptions and Catalog'!$H$52+'Assumptions and Catalog'!$E$52+'Assumptions and Catalog'!$F$52,IF(((D171+E171)*C171-G171)<='Assumptions and Catalog'!$C$53,((D171+E171)*C171-G171)*'Assumptions and Catalog'!$H$53+'Assumptions and Catalog'!$E$53+'Assumptions and Catalog'!$F$53,IF(((D171+E171)*C171-G171)<='Assumptions and Catalog'!$C$54,((D171+E171)*C171-G171)*'Assumptions and Catalog'!$H$54+'Assumptions and Catalog'!$E$54+'Assumptions and Catalog'!$F$54,IF(((D171+E171)*C171-G171)<='Assumptions and Catalog'!$C$55,((D171+E171)*C171-G171)*'Assumptions and Catalog'!$H$55+'Assumptions and Catalog'!$E$55+'Assumptions and Catalog'!$F$55,IF(((D171+E171)*C171-G171)<='Assumptions and Catalog'!$C$56,((D171+E171)*C171-G171)*'Assumptions and Catalog'!$H$56+'Assumptions and Catalog'!$E$56+'Assumptions and Catalog'!$F$56,IF(((D171+E171)*C171-G171)<='Assumptions and Catalog'!$C$57,((D171+E171)*C171-G171)*'Assumptions and Catalog'!$H$57+'Assumptions and Catalog'!$E$57+'Assumptions and Catalog'!$F$57,"Out of range")))))))),IF(((D171+E171)*C171-G171)<='Assumptions and Catalog'!$C$60,((D171+E171)*C171-G171)*'Assumptions and Catalog'!$H$60+'Assumptions and Catalog'!$E$60+'Assumptions and Catalog'!$F$60,IF(((D171+E171)*C171-G171)<='Assumptions and Catalog'!$C$61,((D171+E171)*C171-G171)*'Assumptions and Catalog'!$H$61+'Assumptions and Catalog'!$E$61+'Assumptions and Catalog'!$F$61,IF(((D171+E171)*C171-G171)<='Assumptions and Catalog'!$C$62,((D171+E171)*C171-G171)*'Assumptions and Catalog'!$H$62+'Assumptions and Catalog'!$E$62+'Assumptions and Catalog'!$F$62,IF(((D171+E171)*C171-G171)<='Assumptions and Catalog'!$C$63,((D171+E171)*C171-G171)*'Assumptions and Catalog'!$H$63+'Assumptions and Catalog'!$E$63+'Assumptions and Catalog'!$F$63,IF(((D171+E171)*C171-G171)<='Assumptions and Catalog'!$C$64,((D171+E171)*C171-G171)*'Assumptions and Catalog'!$H$64+'Assumptions and Catalog'!$E$64+'Assumptions and Catalog'!$F$64,IF(((D171+E171)*C171-G171)<='Assumptions and Catalog'!$C$65,((D171+E171)*C171-G171)*'Assumptions and Catalog'!$H$65+'Assumptions and Catalog'!$E$65+'Assumptions and Catalog'!$F$65,"Out of range")))))))))*(1+'Assumptions and Catalog'!$C$8)^(A171-1),0) -> 4855.9874 | R171: =IF(AND('Assumptions and Catalog'!$C$19>0,A171>='Assumptions and Catalog'!$C$19),A171-'Assumptions and Catalog'!$C$19,A171-1) -> 0 | S171: =F171+L171-(D171+E171)*C171-J171-K171-0 -> 0
A172: 1 | B172: 12 | C172: =DAY(DATE('Assumptions and Catalog'!$C$24+A172-1,B172+1,0)) -> 31 | D172: =IF(ISNUMBER(Inputs!$L$5),Inputs!$L$5*Inputs!$L$6,0) -> 40.35 | E172: =IF(ISNUMBER(Inputs!$L$5),Inputs!$L$5-D172,0) -> 40.35 | F172: =C$51*'Assumptions and Catalog'!$C$31*C172*(1-'Assumptions and Catalog'!$C$10)^(A172-1) -> 1034.346 | G172: =MIN(F172,D172*C172) -> 1034.346 | H172: =I172/('Assumptions and Catalog'!$C$11*'Assumptions and Catalog'!$C$12) -> 0 | I172: =0 -> 0 | J172: =MAX(F172-G172-H172,0) -> 0 | K172: =H172-I172 -> 0 | L172: =(D172+E172)*C172-G172-I172+0+0 -> 1467.354 | M172: =IF(ISNUMBER(Inputs!$L$5),(IF(Inputs!$L$9="Actual flat rate",((D172+E172)*C172)*Inputs!$L$10,IF(Inputs!$C$9="Residential",IF(((D172+E172)*C172)<='Assumptions and Catalog'!$C$50,((D172+E172)*C172)*'Assumptions and Catalog'!$H$50+'Assumptions and Catalog'!$E$50+'Assumptions and Catalog'!$F$50,IF(((D172+E172)*C172)<='Assumptions and Catalog'!$C$51,((D172+E172)*C172)*'Assumptions and Catalog'!$H$51+'Assumptions and Catalog'!$E$51+'Assumptions and Catalog'!$F$51,IF(((D172+E172)*C172)<='Assumptions and Catalog'!$C$52,((D172+E172)*C172)*'Assumptions and Catalog'!$H$52+'Assumptions and Catalog'!$E$52+'Assumptions and Catalog'!$F$52,IF(((D172+E172)*C172)<='Assumptions and Catalog'!$C$53,((D172+E172)*C172)*'Assumptions and Catalog'!$H$53+'Assumptions and Catalog'!$E$53+'Assumptions and Catalog'!$F$53,IF(((D172+E172)*C172)<='Assumptions and Catalog'!$C$54,((D172+E172)*C172)*'Assumptions and Catalog'!$H$54+'Assumptions and Catalog'!$E$54+'Assumptions and Catalog'!$F$54,IF(((D172+E172)*C172)<='Assumptions and Catalog'!$C$55,((D172+E172)*C172)*'Assumptions and Catalog'!$H$55+'Assumptions and Catalog'!$E$55+'Assumptions and Catalog'!$F$55,IF(((D172+E172)*C172)<='Assumptions and Catalog'!$C$56,((D172+E172)*C172)*'Assumptions and Catalog'!$H$56+'Assumptions and Catalog'!$E$56+'Assumptions and Catalog'!$F$56,IF(((D172+E172)*C172)<='Assumptions and Catalog'!$C$57,((D172+E172)*C172)*'Assumptions and Catalog'!$H$57+'Assumptions and Catalog'!$E$57+'Assumptions and Catalog'!$F$57,"Out of range")))))))),IF(((D172+E172)*C172)<='Assumptions and Catalog'!$C$60,((D172+E172)*C172)*'Assumptions and Catalog'!$H$60+'Assumptions and Catalog'!$E$60+'Assumptions and Catalog'!$F$60,IF(((D172+E172)*C172)<='Assumptions and Catalog'!$C$61,((D172+E172)*C172)*'Assumptions and Catalog'!$H$61+'Assumptions and Catalog'!$E$61+'Assumptions and Catalog'!$F$61,IF(((D172+E172)*C172)<='Assumptions and Catalog'!$C$62,((D172+E172)*C172)*'Assumptions and Catalog'!$H$62+'Assumptions and Catalog'!$E$62+'Assumptions and Catalog'!$F$62,IF(((D172+E172)*C172)<='Assumptions and Catalog'!$C$63,((D172+E172)*C172)*'Assumptions and Catalog'!$H$63+'Assumptions and Catalog'!$E$63+'Assumptions and Catalog'!$F$63,IF(((D172+E172)*C172)<='Assumptions and Catalog'!$C$64,((D172+E172)*C172)*'Assumptions and Catalog'!$H$64+'Assumptions and Catalog'!$E$64+'Assumptions and Catalog'!$F$64,IF(((D172+E172)*C172)<='Assumptions and Catalog'!$C$65,((D172+E172)*C172)*'Assumptions and Catalog'!$H$65+'Assumptions and Catalog'!$E$65+'Assumptions and Catalog'!$F$65,"Out of range")))))))))*(1+'Assumptions and Catalog'!$C$8)^(A172-1),0) -> 8554.9667 | N172: =IF(ISNUMBER(Inputs!$L$5),(IF(Inputs!$L$9="Actual flat rate",L172*Inputs!$L$10,IF(Inputs!$C$9="Residential",IF(L172<='Assumptions and Catalog'!$C$50,L172*'Assumptions and Catalog'!$H$50+'Assumptions and Catalog'!$E$50+'Assumptions and Catalog'!$F$50,IF(L172<='Assumptions and Catalog'!$C$51,L172*'Assumptions and Catalog'!$H$51+'Assumptions and Catalog'!$E$51+'Assumptions and Catalog'!$F$51,IF(L172<='Assumptions and Catalog'!$C$52,L172*'Assumptions and Catalog'!$H$52+'Assumptions and Catalog'!$E$52+'Assumptions and Catalog'!$F$52,IF(L172<='Assumptions and Catalog'!$C$53,L172*'Assumptions and Catalog'!$H$53+'Assumptions and Catalog'!$E$53+'Assumptions and Catalog'!$F$53,IF(L172<='Assumptions and Catalog'!$C$54,L172*'Assumptions and Catalog'!$H$54+'Assumptions and Catalog'!$E$54+'Assumptions and Catalog'!$F$54,IF(L172<='Assumptions and Catalog'!$C$55,L172*'Assumptions and Catalog'!$H$55+'Assumptions and Catalog'!$E$55+'Assumptions and Catalog'!$F$55,IF(L172<='Assumptions and Catalog'!$C$56,L172*'Assumptions and Catalog'!$H$56+'Assumptions and Catalog'!$E$56+'Assumptions and Catalog'!$F$56,IF(L172<='Assumptions and Catalog'!$C$57,L172*'Assumptions and Catalog'!$H$57+'Assumptions and Catalog'!$E$57+'Assumptions and Catalog'!$F$57,"Out of range")))))))),IF(L172<='Assumptions and Catalog'!$C$60,L172*'Assumptions and Catalog'!$H$60+'Assumptions and Catalog'!$E$60+'Assumptions and Catalog'!$F$60,IF(L172<='Assumptions and Catalog'!$C$61,L172*'Assumptions and Catalog'!$H$61+'Assumptions and Catalog'!$E$61+'Assumptions and Catalog'!$F$61,IF(L172<='Assumptions and Catalog'!$C$62,L172*'Assumptions and Catalog'!$H$62+'Assumptions and Catalog'!$E$62+'Assumptions and Catalog'!$F$62,IF(L172<='Assumptions and Catalog'!$C$63,L172*'Assumptions and Catalog'!$H$63+'Assumptions and Catalog'!$E$63+'Assumptions and Catalog'!$F$63,IF(L172<='Assumptions and Catalog'!$C$64,L172*'Assumptions and Catalog'!$H$64+'Assumptions and Catalog'!$E$64+'Assumptions and Catalog'!$F$64,IF(L172<='Assumptions and Catalog'!$C$65,L172*'Assumptions and Catalog'!$H$65+'Assumptions and Catalog'!$E$65+'Assumptions and Catalog'!$F$65,"Out of range")))))))))*(1+'Assumptions and Catalog'!$C$8)^(A172-1),0) -> 5017.8537 | O172: =M172-N172 -> 3537.113 | P172: =C$55*(1-J$14)*(1-'Assumptions and Catalog'!$C$23)^R172 -> 0 | Q172: =IF(ISNUMBER(Inputs!$L$5),(IF(Inputs!$L$9="Actual flat rate",((D172+E172)*C172-G172)*Inputs!$L$10,IF(Inputs!$C$9="Residential",IF(((D172+E172)*C172-G172)<='Assumptions and Catalog'!$C$50,((D172+E172)*C172-G172)*'Assumptions and Catalog'!$H$50+'Assumptions and Catalog'!$E$50+'Assumptions and Catalog'!$F$50,IF(((D172+E172)*C172-G172)<='Assumptions and Catalog'!$C$51,((D172+E172)*C172-G172)*'Assumptions and Catalog'!$H$51+'Assumptions and Catalog'!$E$51+'Assumptions and Catalog'!$F$51,IF(((D172+E172)*C172-G172)<='Assumptions and Catalog'!$C$52,((D172+E172)*C172-G172)*'Assumptions and Catalog'!$H$52+'Assumptions and Catalog'!$E$52+'Assumptions and Catalog'!$F$52,IF(((D172+E172)*C172-G172)<='Assumptions and Catalog'!$C$53,((D172+E172)*C172-G172)*'Assumptions and Catalog'!$H$53+'Assumptions and Catalog'!$E$53+'Assumptions and Catalog'!$F$53,IF(((D172+E172)*C172-G172)<='Assumptions and Catalog'!$C$54,((D172+E172)*C172-G172)*'Assumptions and Catalog'!$H$54+'Assumptions and Catalog'!$E$54+'Assumptions and Catalog'!$F$54,IF(((D172+E172)*C172-G172)<='Assumptions and Catalog'!$C$55,((D172+E172)*C172-G172)*'Assumptions and Catalog'!$H$55+'Assumptions and Catalog'!$E$55+'Assumptions and Catalog'!$F$55,IF(((D172+E172)*C172-G172)<='Assumptions and Catalog'!$C$56,((D172+E172)*C172-G172)*'Assumptions and Catalog'!$H$56+'Assumptions and Catalog'!$E$56+'Assumptions and Catalog'!$F$56,IF(((D172+E172)*C172-G172)<='Assumptions and Catalog'!$C$57,((D172+E172)*C172-G172)*'Assumptions and Catalog'!$H$57+'Assumptions and Catalog'!$E$57+'Assumptions and Catalog'!$F$57,"Out of range")))))))),IF(((D172+E172)*C172-G172)<='Assumptions and Catalog'!$C$60,((D172+E172)*C172-G172)*'Assumptions and Catalog'!$H$60+'Assumptions and Catalog'!$E$60+'Assumptions and Catalog'!$F$60,IF(((D172+E172)*C172-G172)<='Assumptions and Catalog'!$C$61,((D172+E172)*C172-G172)*'Assumptions and Catalog'!$H$61+'Assumptions and Catalog'!$E$61+'Assumptions and Catalog'!$F$61,IF(((D172+E172)*C172-G172)<='Assumptions and Catalog'!$C$62,((D172+E172)*C172-G172)*'Assumptions and Catalog'!$H$62+'Assumptions and Catalog'!$E$62+'Assumptions and Catalog'!$F$62,IF(((D172+E172)*C172-G172)<='Assumptions and Catalog'!$C$63,((D172+E172)*C172-G172)*'Assumptions and Catalog'!$H$63+'Assumptions and Catalog'!$E$63+'Assumptions and Catalog'!$F$63,IF(((D172+E172)*C172-G172)<='Assumptions and Catalog'!$C$64,((D172+E172)*C172-G172)*'Assumptions and Catalog'!$H$64+'Assumptions and Catalog'!$E$64+'Assumptions and Catalog'!$F$64,IF(((D172+E172)*C172-G172)<='Assumptions and Catalog'!$C$65,((D172+E172)*C172-G172)*'Assumptions and Catalog'!$H$65+'Assumptions and Catalog'!$E$65+'Assumptions and Catalog'!$F$65,"Out of range")))))))))*(1+'Assumptions and Catalog'!$C$8)^(A172-1),0) -> 5017.8537 | R172: =IF(AND('Assumptions and Catalog'!$C$19>0,A172>='Assumptions and Catalog'!$C$19),A172-'Assumptions and Catalog'!$C$19,A172-1) -> 0 | S172: =F172+L172-(D172+E172)*C172-J172-K172-0 -> 0
... A400: 20 | B400: 12 | C400: =DAY(DATE('Assumptions and Catalog'!$C$24+A400-1,B400+1,0)) -> 31 | D400: =IF(ISNUMBER(Inputs!$L$5),Inputs!$L$5*Inputs!$L$6,0) -> 40.35 | E400: =IF(ISNUMBER(Inputs!$L$5),Inputs!$L$5-D400,0) -> 40.35 | F400: =C$51*'Assumptions and Catalog'!$C$31*C400*(1-'Assumptions and Catalog'!$C$10)^(A400-1) -> 940.38214 | G400: =MIN(F400,D400*C400) -> 940.38214 | H400: =I400/('Assumptions and Catalog'!$C$11*'Assumptions and Catalog'!$C$12) -> 0 | I400: =0 -> 0 | J400: =MAX(F400-G400-H400,0) -> 0 | K400: =H400-I400 -> 0 | L400: =(D400+E400)*C400-G400-I400+0+0 -> 1561.3179 | M400: =IF(ISNUMBER(Inputs!$L$5),(IF(Inputs!$L$9="Actual flat rate",((D400+E400)*C400)*Inputs!$L$10,IF(Inputs!$C$9="Residential",IF(((D400+E400)*C400)<='Assumptions and Catalog'!$C$50,((D400+E400)*C400)*'Assumptions and Catalog'!$H$50+'Assumptions and Catalog'!$E$50+'Assumptions and Catalog'!$F$50,IF(((D400+E400)*C400)<='Assumptions and Catalog'!$C$51,((D400+E400)*C400)*'Assumptions and Catalog'!$H$51+'Assumptions and Catalog'!$E$51+'Assumptions and Catalog'!$F$51,IF(((D400+E400)*C400)<='Assumptions and Catalog'!$C$52,((D400+E400)*C400)*'Assumptions and Catalog'!$H$52+'Assumptions and Catalog'!$E$52+'Assumptions and Catalog'!$F$52,IF(((D400+E400)*C400)<='Assumptions and Catalog'!$C$53,((D400+E400)*C400)*'Assumptions and Catalog'!$H$53+'Assumptions and Catalog'!$E$53+'Assumptions and Catalog'!$F$53,IF(((D400+E400)*C400)<='Assumptions and Catalog'!$C$54,((D400+E400)*C400)*'Assumptions and Catalog'!$H$54+'Assumptions and Catalog'!$E$54+'Assumptions and Catalog'!$F$54,IF(((D400+E400)*C400)<='Assumptions and Catalog'!$C$55,((D400+E400)*C400)*'Assumptions and Catalog'!$H$55+'Assumptions and Catalog'!$E$55+'Assumptions and Catalog'!$F$55,IF(((D400+E400)*C400)<='Assumptions and Catalog'!$C$56,((D400+E400)*C400)*'Assumptions and Catalog'!$H$56+'Assumptions and Catalog'!$E$56+'Assumptions and Catalog'!$F$56,IF(((D400+E400)*C400)<='Assumptions and Catalog'!$C$57,((D400+E400)*C400)*'Assumptions and Catalog'!$H$57+'Assumptions and Catalog'!$E$57+'Assumptions and Catalog'!$F$57,"Out of range")))))))),IF(((D400+E400)*C400)<='Assumptions and Catalog'!$C$60,((D400+E400)*C400)*'Assumptions and Catalog'!$H$60+'Assumptions and Catalog'!$E$60+'Assumptions and Catalog'!$F$60,IF(((D400+E400)*C400)<='Assumptions and Catalog'!$C$61,((D400+E400)*C400)*'Assumptions and Catalog'!$H$61+'Assumptions and Catalog'!$E$61+'Assumptions and Catalog'!$F$61,IF(((D400+E400)*C400)<='Assumptions and Catalog'!$C$62,((D400+E400)*C400)*'Assumptions and Catalog'!$H$62+'Assumptions and Catalog'!$E$62+'Assumptions and Catalog'!$F$62,IF(((D400+E400)*C400)<='Assumptions and Catalog'!$C$63,((D400+E400)*C400)*'Assumptions and Catalog'!$H$63+'Assumptions and Catalog'!$E$63+'Assumptions and Catalog'!$F$63,IF(((D400+E400)*C400)<='Assumptions and Catalog'!$C$64,((D400+E400)*C400)*'Assumptions and Catalog'!$H$64+'Assumptions and Catalog'!$E$64+'Assumptions and Catalog'!$F$64,IF(((D400+E400)*C400)<='Assumptions and Catalog'!$C$65,((D400+E400)*C400)*'Assumptions and Catalog'!$H$65+'Assumptions and Catalog'!$E$65+'Assumptions and Catalog'!$F$65,"Out of range")))))))))*(1+'Assumptions and Catalog'!$C$8)^(A400-1),0) -> 8554.9667 | N400: =IF(ISNUMBER(Inputs!$L$5),(IF(Inputs!$L$9="Actual flat rate",L400*Inputs!$L$10,IF(Inputs!$C$9="Residential",IF(L400<='Assumptions and Catalog'!$C$50,L400*'Assumptions and Catalog'!$H$50+'Assumptions and Catalog'!$E$50+'Assumptions and Catalog'!$F$50,IF(L400<='Assumptions and Catalog'!$C$51,L400*'Assumptions and Catalog'!$H$51+'Assumptions and Catalog'!$E$51+'Assumptions and Catalog'!$F$51,IF(L400<='Assumptions and Catalog'!$C$52,L400*'Assumptions and Catalog'!$H$52+'Assumptions and Catalog'!$E$52+'Assumptions and Catalog'!$F$52,IF(L400<='Assumptions and Catalog'!$C$53,L400*'Assumptions and Catalog'!$H$53+'Assumptions and Catalog'!$E$53+'Assumptions and Catalog'!$F$53,IF(L400<='Assumptions and Catalog'!$C$54,L400*'Assumptions and Catalog'!$H$54+'Assumptions and Catalog'!$E$54+'Assumptions and Catalog'!$F$54,IF(L400<='Assumptions and Catalog'!$C$55,L400*'Assumptions and Catalog'!$H$55+'Assumptions and Catalog'!$E$55+'Assumptions and Catalog'!$F$55,IF(L400<='Assumptions and Catalog'!$C$56,L400*'Assumptions and Catalog'!$H$56+'Assumptions and Catalog'!$E$56+'Assumptions and Catalog'!$F$56,IF(L400<='Assumptions and Catalog'!$C$57,L400*'Assumptions and Catalog'!$H$57+'Assumptions and Catalog'!$E$57+'Assumptions and Catalog'!$F$57,"Out of range")))))))),IF(L400<='Assumptions and Catalog'!$C$60,L400*'Assumptions and Catalog'!$H$60+'Assumptions and Catalog'!$E$60+'Assumptions and Catalog'!$F$60,IF(L400<='Assumptions and Catalog'!$C$61,L400*'Assumptions and Catalog'!$H$61+'Assumptions and Catalog'!$E$61+'Assumptions and Catalog'!$F$61,IF(L400<='Assumptions and Catalog'!$C$62,L400*'Assumptions and Catalog'!$H$62+'Assumptions and Catalog'!$E$62+'Assumptions and Catalog'!$F$62,IF(L400<='Assumptions and Catalog'!$C$63,L400*'Assumptions and Catalog'!$H$63+'Assumptions and Catalog'!$E$63+'Assumptions and Catalog'!$F$63,IF(L400<='Assumptions and Catalog'!$C$64,L400*'Assumptions and Catalog'!$H$64+'Assumptions and Catalog'!$E$64+'Assumptions and Catalog'!$F$64,IF(L400<='Assumptions and Catalog'!$C$65,L400*'Assumptions and Catalog'!$H$65+'Assumptions and Catalog'!$E$65+'Assumptions and Catalog'!$F$65,"Out of range")))))))))*(1+'Assumptions and Catalog'!$C$8)^(A400-1),0) -> 5339.1782 | O400: =M400-N400 -> 3215.7884 | P400: =C$55*(1-J$14)*(1-'Assumptions and Catalog'!$C$23)^R400 -> 0 | Q400: =IF(ISNUMBER(Inputs!$L$5),(IF(Inputs!$L$9="Actual flat rate",((D400+E400)*C400-G400)*Inputs!$L$10,IF(Inputs!$C$9="Residential",IF(((D400+E400)*C400-G400)<='Assumptions and Catalog'!$C$50,((D400+E400)*C400-G400)*'Assumptions and Catalog'!$H$50+'Assumptions and Catalog'!$E$50+'Assumptions and Catalog'!$F$50,IF(((D400+E400)*C400-G400)<='Assumptions and Catalog'!$C$51,((D400+E400)*C400-G400)*'Assumptions and Catalog'!$H$51+'Assumptions and Catalog'!$E$51+'Assumptions and Catalog'!$F$51,IF(((D400+E400)*C400-G400)<='Assumptions and Catalog'!$C$52,((D400+E400)*C400-G400)*'Assumptions and Catalog'!$H$52+'Assumptions and Catalog'!$E$52+'Assumptions and Catalog'!$F$52,IF(((D400+E400)*C400-G400)<='Assumptions and Catalog'!$C$53,((D400+E400)*C400-G400)*'Assumptions and Catalog'!$H$53+'Assumptions and Catalog'!$E$53+'Assumptions and Catalog'!$F$53,IF(((D400+E400)*C400-G400)<='Assumptions and Catalog'!$C$54,((D400+E400)*C400-G400)*'Assumptions and Catalog'!$H$54+'Assumptions and Catalog'!$E$54+'Assumptions and Catalog'!$F$54,IF(((D400+E400)*C400-G400)<='Assumptions and Catalog'!$C$55,((D400+E400)*C400-G400)*'Assumptions and Catalog'!$H$55+'Assumptions and Catalog'!$E$55+'Assumptions and Catalog'!$F$55,IF(((D400+E400)*C400-G400)<='Assumptions and Catalog'!$C$56,((D400+E400)*C400-G400)*'Assumptions and Catalog'!$H$56+'Assumptions and Catalog'!$E$56+'Assumptions and Catalog'!$F$56,IF(((D400+E400)*C400-G400)<='Assumptions and Catalog'!$C$57,((D400+E400)*C400-G400)*'Assumptions and Catalog'!$H$57+'Assumptions and Catalog'!$E$57+'Assumptions and Catalog'!$F$57,"Out of range")))))))),IF(((D400+E400)*C400-G400)<='Assumptions and Catalog'!$C$60,((D400+E400)*C400-G400)*'Assumptions and Catalog'!$H$60+'Assumptions and Catalog'!$E$60+'Assumptions and Catalog'!$F$60,IF(((D400+E400)*C400-G400)<='Assumptions and Catalog'!$C$61,((D400+E400)*C400-G400)*'Assumptions and Catalog'!$H$61+'Assumptions and Catalog'!$E$61+'Assumptions and Catalog'!$F$61,IF(((D400+E400)*C400-G400)<='Assumptions and Catalog'!$C$62,((D400+E400)*C400-G400)*'Assumptions and Catalog'!$H$62+'Assumptions and Catalog'!$E$62+'Assumptions and Catalog'!$F$62,IF(((D400+E400)*C400-G400)<='Assumptions and Catalog'!$C$63,((D400+E400)*C400-G400)*'Assumptions and Catalog'!$H$63+'Assumptions and Catalog'!$E$63+'Assumptions and Catalog'!$F$63,IF(((D400+E400)*C400-G400)<='Assumptions and Catalog'!$C$64,((D400+E400)*C400-G400)*'Assumptions and Catalog'!$H$64+'Assumptions and Catalog'!$E$64+'Assumptions and Catalog'!$F$64,IF(((D400+E400)*C400-G400)<='Assumptions and Catalog'!$C$65,((D400+E400)*C400-G400)*'Assumptions and Catalog'!$H$65+'Assumptions and Catalog'!$E$65+'Assumptions and Catalog'!$F$65,"Out of range")))))))))*(1+'Assumptions and Catalog'!$C$8)^(A400-1),0) -> 5339.1782 | R400: =IF(AND('Assumptions and Catalog'!$C$19>0,A400>='Assumptions and Catalog'!$C$19),A400-'Assumptions and Catalog'!$C$19,A400-1) -> 9 | S400: =F400+L400-(D400+E400)*C400-J400-K400-0 -> 0
A408: Battery only — monthly calculations
A410: years | B410: month | C410: Days | D410: Day load kWh/d | E410: Night load kWh/d | F410: PV kWh/mo | G410: Direct use kWh/mo | H410: Charge kWh/mo | I410: Discharge kWh/mo | J410: Unused PV kWh/mo | K410: Losses kWh/mo | L410: Grid imports kWh/mo | M410: Baseline EGP | N410: New bill EGP | O410: Bill savings EGP | P410: Operating capacity kWh | Q410: Matched PV-only bill (EGP) | R410: Battery age | S410: Balance check kWh
A411: 1 | B411: 1 | C411: =DAY(DATE('Assumptions and Catalog'!$C$24+A411-1,B411+1,0)) -> 31 | D411: =IF(ISNUMBER(Inputs!$L$5),Inputs!$L$5*Inputs!$L$6,0) -> 40.35 | E411: =IF(ISNUMBER(Inputs!$L$5),Inputs!$L$5-D411,0) -> 40.35 | F411: =D$51*'Assumptions and Catalog'!$C$31*C411*(1-'Assumptions and Catalog'!$C$10)^(A411-1) -> 0 | G411: =MIN(F411,D411*C411) -> 0 | H411: =I411/('Assumptions and Catalog'!$C$11*'Assumptions and Catalog'!$C$12) -> 0 | I411: =IF(K$15="Grid cycle",MIN(K$16,D411+E411,P411*'Assumptions and Catalog'!$C$12,D$57*(24-'Assumptions and Catalog'!$C$15),D$56*'Assumptions and Catalog'!$C$15*'Assumptions and Catalog'!$C$11*'Assumptions and Catalog'!$C$12)*C411,0) -> 0 | J411: =MAX(F411-G411-0,0) -> 0 | K411: =H411-I411 -> 0 | L411: =(D411+E411)*C411-G411-I411+H411+IF(D$52>0,'Assumptions and Catalog'!$C$26*C411,0) -> 2501.7 | M411: =IF(ISNUMBER(Inputs!$L$5),(IF(Inputs!$L$9="Actual flat rate",((D411+E411)*C411)*Inputs!$L$10,IF(Inputs!$C$9="Residential",IF(((D411+E411)*C411)<='Assumptions and Catalog'!$C$50,((D411+E411)*C411)*'Assumptions and Catalog'!$H$50+'Assumptions and Catalog'!$E$50+'Assumptions and Catalog'!$F$50,IF(((D411+E411)*C411)<='Assumptions and Catalog'!$C$51,((D411+E411)*C411)*'Assumptions and Catalog'!$H$51+'Assumptions and Catalog'!$E$51+'Assumptions and Catalog'!$F$51,IF(((D411+E411)*C411)<='Assumptions and Catalog'!$C$52,((D411+E411)*C411)*'Assumptions and Catalog'!$H$52+'Assumptions and Catalog'!$E$52+'Assumptions and Catalog'!$F$52,IF(((D411+E411)*C411)<='Assumptions and Catalog'!$C$53,((D411+E411)*C411)*'Assumptions and Catalog'!$H$53+'Assumptions and Catalog'!$E$53+'Assumptions and Catalog'!$F$53,IF(((D411+E411)*C411)<='Assumptions and Catalog'!$C$54,((D411+E411)*C411)*'Assumptions and Catalog'!$H$54+'Assumptions and Catalog'!$E$54+'Assumptions and Catalog'!$F$54,IF(((D411+E411)*C411)<='Assumptions and Catalog'!$C$55,((D411+E411)*C411)*'Assumptions and Catalog'!$H$55+'Assumptions and Catalog'!$E$55+'Assumptions and Catalog'!$F$55,IF(((D411+E411)*C411)<='Assumptions and Catalog'!$C$56,((D411+E411)*C411)*'Assumptions and Catalog'!$H$56+'Assumptions and Catalog'!$E$56+'Assumptions and Catalog'!$F$56,IF(((D411+E411)*C411)<='Assumptions and Catalog'!$C$57,((D411+E411)*C411)*'Assumptions and Catalog'!$H$57+'Assumptions and Catalog'!$E$57+'Assumptions and Catalog'!$F$57,"Out of range")))))))),IF(((D411+E411)*C411)<='Assumptions and Catalog'!$C$60,((D411+E411)*C411)*'Assumptions and Catalog'!$H$60+'Assumptions and Catalog'!$E$60+'Assumptions and Catalog'!$F$60,IF(((D411+E411)*C411)<='Assumptions and Catalog'!$C$61,((D411+E411)*C411)*'Assumptions and Catalog'!$H$61+'Assumptions and Catalog'!$E$61+'Assumptions and Catalog'!$F$61,IF(((D411+E411)*C411)<='Assumptions and Catalog'!$C$62,((D411+E411)*C411)*'Assumptions and Catalog'!$H$62+'Assumptions and Catalog'!$E$62+'Assumptions and Catalog'!$F$62,IF(((D411+E411)*C411)<='Assumptions and Catalog'!$C$63,((D411+E411)*C411)*'Assumptions and Catalog'!$H$63+'Assumptions and Catalog'!$E$63+'Assumptions and Catalog'!$F$63,IF(((D411+E411)*C411)<='Assumptions and Catalog'!$C$64,((D411+E411)*C411)*'Assumptions and Catalog'!$H$64+'Assumptions and Catalog'!$E$64+'Assumptions and Catalog'!$F$64,IF(((D411+E411)*C411)<='Assumptions and Catalog'!$C$65,((D411+E411)*C411)*'Assumptions and Catalog'!$H$65+'Assumptions and Catalog'!$E$65+'Assumptions and Catalog'!$F$65,"Out of range")))))))))*(1+'Assumptions and Catalog'!$C$8)^(A411-1),0) -> 8554.9667 | N411: =IF(ISNUMBER(Inputs!$L$5),(IF(Inputs!$L$9="Actual flat rate",L411*Inputs!$L$10,IF(Inputs!$C$9="Residential",IF(L411<='Assumptions and Catalog'!$C$50,L411*'Assumptions and Catalog'!$H$50+'Assumptions and Catalog'!$E$50+'Assumptions and Catalog'!$F$50,IF(L411<='Assumptions and Catalog'!$C$51,L411*'Assumptions and Catalog'!$H$51+'Assumptions and Catalog'!$E$51+'Assumptions and Catalog'!$F$51,IF(L411<='Assumptions and Catalog'!$C$52,L411*'Assumptions and Catalog'!$H$52+'Assumptions and Catalog'!$E$52+'Assumptions and Catalog'!$F$52,IF(L411<='Assumptions and Catalog'!$C$53,L411*'Assumptions and Catalog'!$H$53+'Assumptions and Catalog'!$E$53+'Assumptions and Catalog'!$F$53,IF(L411<='Assumptions and Catalog'!$C$54,L411*'Assumptions and Catalog'!$H$54+'Assumptions and Catalog'!$E$54+'Assumptions and Catalog'!$F$54,IF(L411<='Assumptions and Catalog'!$C$55,L411*'Assumptions and Catalog'!$H$55+'Assumptions and Catalog'!$E$55+'Assumptions and Catalog'!$F$55,IF(L411<='Assumptions and Catalog'!$C$56,L411*'Assumptions and Catalog'!$H$56+'Assumptions and Catalog'!$E$56+'Assumptions and Catalog'!$F$56,IF(L411<='Assumptions and Catalog'!$C$57,L411*'Assumptions and Catalog'!$H$57+'Assumptions and Catalog'!$E$57+'Assumptions and Catalog'!$F$57,"Out of range")))))))),IF(L411<='Assumptions and Catalog'!$C$60,L411*'Assumptions and Catalog'!$H$60+'Assumptions and Catalog'!$E$60+'Assumptions and Catalog'!$F$60,IF(L411<='Assumptions and Catalog'!$C$61,L411*'Assumptions and Catalog'!$H$61+'Assumptions and Catalog'!$E$61+'Assumptions and Catalog'!$F$61,IF(L411<='Assumptions and Catalog'!$C$62,L411*'Assumptions and Catalog'!$H$62+'Assumptions and Catalog'!$E$62+'Assumptions and Catalog'!$F$62,IF(L411<='Assumptions and Catalog'!$C$63,L411*'Assumptions and Catalog'!$H$63+'Assumptions and Catalog'!$E$63+'Assumptions and Catalog'!$F$63,IF(L411<='Assumptions and Catalog'!$C$64,L411*'Assumptions and Catalog'!$H$64+'Assumptions and Catalog'!$E$64+'Assumptions and Catalog'!$F$64,IF(L411<='Assumptions and Catalog'!$C$65,L411*'Assumptions and Catalog'!$H$65+'Assumptions and Catalog'!$E$65+'Assumptions and Catalog'!$F$65,"Out of range")))))))))*(1+'Assumptions and Catalog'!$C$8)^(A411-1),0) -> 8554.9667 | O411: =M411-N411 -> 0 | P411: =D$55*(1-K$14)*(1-'Assumptions and Catalog'!$C$23)^R411 -> 0 | Q411: =IF(ISNUMBER(Inputs!$L$5),(IF(Inputs!$L$9="Actual flat rate",((D411+E411)*C411-G411)*Inputs!$L$10,IF(Inputs!$C$9="Residential",IF(((D411+E411)*C411-G411)<='Assumptions and Catalog'!$C$50,((D411+E411)*C411-G411)*'Assumptions and Catalog'!$H$50+'Assumptions and Catalog'!$E$50+'Assumptions and Catalog'!$F$50,IF(((D411+E411)*C411-G411)<='Assumptions and Catalog'!$C$51,((D411+E411)*C411-G411)*'Assumptions and Catalog'!$H$51+'Assumptions and Catalog'!$E$51+'Assumptions and Catalog'!$F$51,IF(((D411+E411)*C411-G411)<='Assumptions and Catalog'!$C$52,((D411+E411)*C411-G411)*'Assumptions and Catalog'!$H$52+'Assumptions and Catalog'!$E$52+'Assumptions and Catalog'!$F$52,IF(((D411+E411)*C411-G411)<='Assumptions and Catalog'!$C$53,((D411+E411)*C411-G411)*'Assumptions and Catalog'!$H$53+'Assumptions and Catalog'!$E$53+'Assumptions and Catalog'!$F$53,IF(((D411+E411)*C411-G411)<='Assumptions and Catalog'!$C$54,((D411+E411)*C411-G411)*'Assumptions and Catalog'!$H$54+'Assumptions and Catalog'!$E$54+'Assumptions and Catalog'!$F$54,IF(((D411+E411)*C411-G411)<='Assumptions and Catalog'!$C$55,((D411+E411)*C411-G411)*'Assumptions and Catalog'!$H$55+'Assumptions and Catalog'!$E$55+'Assumptions and Catalog'!$F$55,IF(((D411+E411)*C411-G411)<='Assumptions and Catalog'!$C$56,((D411+E411)*C411-G411)*'Assumptions and Catalog'!$H$56+'Assumptions and Catalog'!$E$56+'Assumptions and Catalog'!$F$56,IF(((D411+E411)*C411-G411)<='Assumptions and Catalog'!$C$57,((D411+E411)*C411-G411)*'Assumptions and Catalog'!$H$57+'Assumptions and Catalog'!$E$57+'Assumptions and Catalog'!$F$57,"Out of range")))))))),IF(((D411+E411)*C411-G411)<='Assumptions and Catalog'!$C$60,((D411+E411)*C411-G411)*'Assumptions and Catalog'!$H$60+'Assumptions and Catalog'!$E$60+'Assumptions and Catalog'!$F$60,IF(((D411+E411)*C411-G411)<='Assumptions and Catalog'!$C$61,((D411+E411)*C411-G411)*'Assumptions and Catalog'!$H$61+'Assumptions and Catalog'!$E$61+'Assumptions and Catalog'!$F$61,IF(((D411+E411)*C411-G411)<='Assumptions and Catalog'!$C$62,((D411+E411)*C411-G411)*'Assumptions and Catalog'!$H$62+'Assumptions and Catalog'!$E$62+'Assumptions and Catalog'!$F$62,IF(((D411+E411)*C411-G411)<='Assumptions and Catalog'!$C$63,((D411+E411)*C411-G411)*'Assumptions and Catalog'!$H$63+'Assumptions and Catalog'!$E$63+'Assumptions and Catalog'!$F$63,IF(((D411+E411)*C411-G411)<='Assumptions and Catalog'!$C$64,((D411+E411)*C411-G411)*'Assumptions and Catalog'!$H$64+'Assumptions and Catalog'!$E$64+'Assumptions and Catalog'!$F$64,IF(((D411+E411)*C411-G411)<='Assumptions and Catalog'!$C$65,((D411+E411)*C411-G411)*'Assumptions and Catalog'!$H$65+'Assumptions and Catalog'!$E$65+'Assumptions and Catalog'!$F$65,"Out of range")))))))))*(1+'Assumptions and Catalog'!$C$8)^(A411-1),0) -> 8554.9667 | R411: =IF(AND('Assumptions and Catalog'!$C$19>0,A411>='Assumptions and Catalog'!$C$19),A411-'Assumptions and Catalog'!$C$19,A411-1) -> 0 | S411: =F411+L411-(D411+E411)*C411-J411-K411-IF(D$52>0,'Assumptions and Catalog'!$C$26*C411,0) -> 0
